Workbook

Sheet LISEZMOI
A1: BASE DE DONNÉES – RÉSILIENCE DES FILIÈRES AGRICOLES IVOIRIENNES AUX CHOCS DE PRIX INTERNATIONAUX
A2: MINADERPV – Cellule d'études – version du 1er octobre 2026
A4: Onglets :
A5: SERIES : séries annuelles par filière/pays (données brutes en bleu, calculs en noir).
A6: EPISODES : épisodes de choc T0 -> T2 ; transmission, amortissement, recette, délais.
A7: INDICATEURS : batterie harmonisée (volatilité, beta baisse/hausse, drawdown, décomposition prix/volume de la recette).
A8: STRESS_PARAM / STRESS_TEST : test de stress standardisé (5 scénarios x 6 filières).
A9: MECANISMES : benchmark international des instruments.
A10: LITTERATURE : revue scientifique (tableau interne).
A11: CARTE_QUALI : filières non quantifiées.
A13: Conventions :
A14: Transmission = variation prix producteur / variation prix international (même monnaie locale, même période).
... A19: Voir AUDIT_DONNEES.md pour les limites et les points à valider.

Sheet SERIES
A1: filiere | B1: pays | C1: campagne | D1: annee | E1: prix_int | F1: unite_int | G1: fx | H1: conv | I1: prix_prod | J1: monnaie | K1: prod_kt | L1: mecanisme | M1: qualite | N1: source | O1: url | P1: commentaire | Q1: prix_int_local_kg | R1: part_producteur | S1: recette_mds | T1: var_int | U1: var_prod | V1: var_recette | W1: transmission_annuelle | X1: max_prod_cumul | Y1: drawdown_prod | Z1: dlnP | AA1: dlnQ | AB1: dlnR
A2: Cacao | B2: Côte d'Ivoire | C2: 2012/13 | D2: 2013 | E2: 2340 | F2: USD/t | G2: 500 | H2: 0.001 | I2: 725 | J2: FCFA | K2: 1449 | L2: Prix minimum garanti (>= 60 % CAF), ventes anticipées à la moyenne, FRP | M2: prix prod. A ; prix int. B | N2: CCC (prix, production) ; ICCO (prix int.) | O2: https://www.conseilcafecacao.ci/ ; https://www.icco.org/statistics/ | P2: 1re campagne de la réforme (prix minimum garanti, ventes anticipées) | Q2: =E2*G2*H2 -> 1170 | R2: =I2/Q2 -> 0.61965812 | S2: =I2*K2/1000 -> 1050.525 | X2: =MAX(I$2:I2) -> 725 | Y2: =I2/X2-1 -> 0
A3: Cacao | B3: Côte d'Ivoire | C3: 2013/14 | D3: 2014 | E3: 2920 | F3: USD/t | G3: 490 | H3: 0.001 | I3: 750 | J3: FCFA | K3: 1746 | L3: Prix minimum garanti (>= 60 % CAF), ventes anticipées à la moyenne, FRP | M3: prix prod. A ; prix int. B | N3: CCC (prix, production) ; ICCO (prix int.) | O3: https://www.conseilcafecacao.ci/ ; https://www.icco.org/statistics/ | Q3: =E3*G3*H3 -> 1430.8 | R3: =I3/Q3 -> 0.52418228 | S3: =I3*K3/1000 -> 1309.5 | T3: =Q3/Q2-1 -> 0.22290598 | U3: =I3/I2-1 -> 0.034482759 | V3: =S3/S2-1 -> 0.2465196 | W3: =IF(ABS(T3)>=0.05,U3/T3,"") -> 0.15469642 | X3: =MAX(I$2:I3) -> 750 | Y3: =I3/X3-1 -> 0 | Z3: =LN(I3/I2) -> 0.033901552 | AA3: =LN(K3/K2) -> 0.18645379 | AB3: =LN(S3/S2) -> 0.22035535
A4: Cacao | B4: Côte d'Ivoire | C4: 2014/15 | D4: 2015 | E4: 3080 | F4: USD/t | G4: 560 | H4: 0.001 | I4: 850 | J4: FCFA | K4: 1796 | L4: Prix minimum garanti (>= 60 % CAF), ventes anticipées à la moyenne, FRP | M4: prix prod. A ; prix int. B | N4: CCC (prix, production) ; ICCO (prix int.) | O4: https://www.conseilcafecacao.ci/ ; https://www.icco.org/statistics/ | Q4: =E4*G4*H4 -> 1724.8 | R4: =I4/Q4 -> 0.49281076 | S4: =I4*K4/1000 -> 1526.6 | T4: =Q4/Q3-1 -> 0.20547945 | U4: =I4/I3-1 -> 0.13333333 | V4: =S4/S3-1 -> 0.16578847 | W4: =IF(ABS(T4)>=0.05,U4/T4,"") -> 0.64888889 | X4: =MAX(I$2:I4) -> 850 | Y4: =I4/X4-1 -> 0 | Z4: =LN(I4/I3) -> 0.12516314 | AA4: =LN(K4/K3) -> 0.028234512 | AB4: =LN(S4/S3) -> 0.15339766
A5: Cacao | B5: Côte d'Ivoire | C5: 2015/16 | D5: 2016 | E5: 3000 | F5: USD/t | G5: 590 | H5: 0.001 | I5: 1000 | J5: FCFA | K5: 1581 | L5: Prix minimum garanti (>= 60 % CAF), ventes anticipées à la moyenne, FRP | M5: prix prod. A ; prix int. B | N5: CCC (prix, production) ; ICCO (prix int.) | O5: https://www.conseilcafecacao.ci/ ; https://www.icco.org/statistics/ | Q5: =E5*G5*H5 -> 1770 | R5: =I5/Q5 -> 0.56497175 | S5: =I5*K5/1000 -> 1581 | T5: =Q5/Q4-1 -> 0.026205937 | U5: =I5/I4-1 -> 0.17647059 | V5: =S5/S4-1 -> 0.035634744 | W5: =IF(ABS(T5)>=0.05,U5/T5,"") | X5: =MAX(I$2:I5) -> 1000 | Y5: =I5/X5-1 -> 0 | Z5: =LN(I5/I4) -> 0.16251893 | AA5: =LN(K5/K4) -> -0.12750441 | AB5: =LN(S5/S4) -> 0.035014518
A6: Cacao | B6: Côte d'Ivoire | C6: 2016/17 | D6: 2017 | E6: 2180 | F6: USD/t | G6: 600 | H6: 0.001 | I6: 1020 | J6: FCFA | K6: 2020 | L6: Prix minimum garanti (>= 60 % CAF), ventes anticipées à la moyenne, FRP | M6: prix prod. A ; prix int. B | N6: CCC (prix, production) ; ICCO (prix int.) | O6: https://www.conseilcafecacao.ci/ ; https://www.icco.org/statistics/ | P6: Principale 1 100 ; intermédiaire 700 (avr. 2017) ; pondération 80/20 | Q6: =E6*G6*H6 -> 1308 | R6: =I6/Q6 -> 0.77981651 | S6: =I6*K6/1000 -> 2060.4 | T6: =Q6/Q5-1 -> -0.26101695 | U6: =I6/I5-1 -> 0.02 | V6: =S6/S5-1 -> 0.30322581 | W6: =IF(ABS(T6)>=0.05,U6/T6,"") -> -0.076623377 | X6: =MAX(I$2:I6) -> 1020 | Y6: =I6/X6-1 -> 0 | Z6: =LN(I6/I5) -> 0.019802627 | AA6: =LN(K6/K5) -> 0.24503995 | AB6: =LN(S6/S5) -> 0.26484258
A7: Cacao | B7: Côte d'Ivoire | C7: 2017/18 | D7: 2018 | E7: 2200 | F7: USD/t | G7: 555 | H7: 0.001 | I7: 710 | J7: FCFA | K7: 1964 | L7: Prix minimum garanti (>= 60 % CAF), ventes anticipées à la moyenne, FRP | M7: prix prod. A ; prix int. B | N7: CCC (prix, production) ; ICCO (prix int.) | O7: https://www.conseilcafecacao.ci/ ; https://www.icco.org/statistics/ | P7: Principale 700 ; intermédiaire 750 | Q7: =E7*G7*H7 -> 1221 | R7: =I7/Q7 -> 0.58149058 | S7: =I7*K7/1000 -> 1394.44 | T7: =Q7/Q6-1 -> -0.066513761 | U7: =I7/I6-1 -> -0.30392157 | V7: =S7/S6-1 -> -0.32321879 | W7: =IF(ABS(T7)>=0.05,U7/T7,"") -> 4.5693036 | X7: =MAX(I$2:I7) -> 1020 | Y7: =I7/X7-1 -> -0.30392157 | Z7: =LN(I7/I6) -> -0.36229294 | AA7: =LN(K7/K6) -> -0.028114301 | AB7: =LN(S7/S6) -> -0.39040724
A8: Cacao | B8: Côte d'Ivoire | C8: 2018/19 | D8: 2019 | E8: 2300 | F8: USD/t | G8: 575 | H8: 0.001 | I8: 750 | J8: FCFA | K8: 2154 | L8: Prix minimum garanti (>= 60 % CAF), ventes anticipées à la moyenne, FRP | M8: prix prod. A ; prix int. B | N8: CCC (prix, production) ; ICCO (prix int.) | O8: https://www.conseilcafecacao.ci/ ; https://www.icco.org/statistics/ | Q8: =E8*G8*H8 -> 1322.5 | R8: =I8/Q8 -> 0.56710775 | S8: =I8*K8/1000 -> 1615.5 | T8: =Q8/Q7-1 -> 0.083128583 | U8: =I8/I7-1 -> 0.056338028 | V8: =S8/S7-1 -> 0.15852959 | W8: =IF(ABS(T8)>=0.05,U8/T8,"") -> 0.6777215 | X8: =MAX(I$2:I8) -> 1020 | Y8: =I8/X8-1 -> -0.26470588 | Z8: =LN(I8/I7) -> 0.054808236 | AA8: =LN(K8/K7) -> 0.092343369 | AB8: =LN(S8/S7) -> 0.14715161
A9: Cacao | B9: Côte d'Ivoire | C9: 2019/20 | D9: 2020 | E9: 2450 | F9: USD/t | G9: 590 | H9: 0.001 | I9: 825 | J9: FCFA | K9: 2105 | L9: Prix minimum garanti (>= 60 % CAF), ventes anticipées à la moyenne, FRP | M9: prix prod. A ; prix int. B | N9: CCC (prix, production) ; ICCO (prix int.) | O9: https://www.conseilcafecacao.ci/ ; https://www.icco.org/statistics/ | Q9: =E9*G9*H9 -> 1445.5 | R9: =I9/Q9 -> 0.57073677 | S9: =I9*K9/1000 -> 1736.625 | T9: =Q9/Q8-1 -> 0.093005671 | U9: =I9/I8-1 -> 0.1 | V9: =S9/S8-1 -> 0.074976787 | W9: =IF(ABS(T9)>=0.05,U9/T9,"") -> 1.0752033 | X9: =MAX(I$2:I9) -> 1020 | Y9: =I9/X9-1 -> -0.19117647 | Z9: =LN(I9/I8) -> 0.09531018 | AA9: =LN(K9/K8) -> -0.023011112 | AB9: =LN(S9/S8) -> 0.072299068
A10: Cacao | B10: Côte d'Ivoire | C10: 2020/21 | D10: 2021 | E10: 2420 | F10: USD/t | G10: 550 | H10: 0.001 | I10: 950 | J10: FCFA | K10: 2248 | L10: Prix minimum garanti (>= 60 % CAF), ventes anticipées à la moyenne, FRP | M10: prix prod. A ; prix int. B | N10: CCC (prix, production) ; ICCO (prix int.) | O10: https://www.conseilcafecacao.ci/ ; https://www.icco.org/statistics/ | P10: Principale 1 000 ; intermédiaire 750 ; début du DRD/LID (400 USD/t) | Q10: =E10*G10*H10 -> 1331 | R10: =I10/Q10 -> 0.71374906 | S10: =I10*K10/1000 -> 2135.6 | T10: =Q10/Q9-1 -> -0.079211346 | U10: =I10/I9-1 -> 0.15151515 | V10: =S10/S9-1 -> 0.2297416 | W10: =IF(ABS(T10)>=0.05,U10/T10,"") -> -1.9127961 | X10: =MAX(I$2:I10) -> 1020 | Y10: =I10/X10-1 -> -0.068627451 | Z10: =LN(I10/I9) -> 0.1410786 | AA10: =LN(K10/K9) -> 0.065725465 | AB10: =LN(S10/S9) -> 0.20680406
A11: Cacao | B11: Côte d'Ivoire | C11: 2021/22 | D11: 2022 | E11: 2450 | F11: USD/t | G11: 590 | H11: 0.001 | I11: 825 | J11: FCFA | K11: 2121 | L11: Prix minimum garanti (>= 60 % CAF), ventes anticipées à la moyenne, FRP | M11: prix prod. A ; prix int. B | N11: CCC (prix, production) ; ICCO (prix int.) | O11: https://www.conseilcafecacao.ci/ ; https://www.icco.org/statistics/ | Q11: =E11*G11*H11 -> 1445.5 | R11: =I11/Q11 -> 0.57073677 | S11: =I11*K11/1000 -> 1749.825 | T11: =Q11/Q10-1 -> 0.086025545 | U11: =I11/I10-1 -> -0.13157895 | V11: =S11/S10-1 -> -0.1806401 | W11: =IF(ABS(T11)>=0.05,U11/T11,"") -> -1.5295334 | X11: =MAX(I$2:I11) -> 1020 | Y11: =I11/X11-1 -> -0.19117647 | Z11: =LN(I11/I10) -> -0.1410786 | AA11: =LN(K11/K10) -> -0.058153256 | AB11: =LN(S11/S10) -> -0.19923185
A12: Cacao | B12: Côte d'Ivoire | C12: 2022/23 | D12: 2023 | E12: 2750 | F12: USD/t | G12: 615 | H12: 0.001 | I12: 904 | J12: FCFA | K12: 2241 | L12: Prix minimum garanti (>= 60 % CAF), ventes anticipées à la moyenne, FRP | M12: prix prod. A ; prix int. B | N12: CCC (prix, production) ; ICCO (prix int.) | O12: https://www.conseilcafecacao.ci/ ; https://www.icco.org/statistics/ | P12: Principale 900 ; intermédiaire 920 | Q12: =E12*G12*H12 -> 1691.25 | R12: =I12/Q12 -> 0.53451589 | S12: =I12*K12/1000 -> 2025.864 | T12: =Q12/Q11-1 -> 0.17001038 | U12: =I12/I11-1 -> 0.095757576 | V12: =S12/S11-1 -> 0.15775235 | W12: =IF(ABS(T12)>=0.05,U12/T12,"") -> 0.56324548 | X12: =MAX(I$2:I12) -> 1020 | Y12: =I12/X12-1 -> -0.11372549 | Z12: =LN(I12/I11) -> 0.091445974 | AA12: =LN(K12/K11) -> 0.055034519 | AB12: =LN(S12/S11) -> 0.14648049
A13: Cacao | B13: Côte d'Ivoire | C13: 2023/24 | D13: 2024 | E13: 6550 | F13: USD/t | G13: 605 | H13: 0.001 | I13: 1100 | J13: FCFA | K13: 1755 | L13: Prix minimum garanti (>= 60 % CAF), ventes anticipées à la moyenne, FRP | M13: prix prod. A ; prix int. B | N13: CCC (prix, production) ; ICCO (prix int.) | O13: https://www.conseilcafecacao.ci/ ; https://www.icco.org/statistics/ | P13: Principale 1 000 ; intermédiaire 1 500 ; production -22 % | Q13: =E13*G13*H13 -> 3962.75 | R13: =I13/Q13 -> 0.27758501 | S13: =I13*K13/1000 -> 1930.5 | T13: =Q13/Q12-1 -> 1.3430894 | U13: =I13/I12-1 -> 0.21681416 | V13: =S13/S12-1 -> -0.047073249 | W13: =IF(ABS(T13)>=0.05,U13/T13,"") -> 0.16142943 | X13: =MAX(I$2:I13) -> 1100 | Y13: =I13/X13-1 -> 0 | Z13: =LN(I13/I12) -> 0.1962361 | AA13: =LN(K13/K12) -> -0.24445334 | AB13: =LN(S13/S12) -> -0.04821724
A14: Cacao | B14: Côte d'Ivoire | C14: 2024/25 | D14: 2025 | E14: 8000 | F14: USD/t | G14: 580 | H14: 0.001 | I14: 1880 | J14: FCFA | K14: 1850 | L14: Prix minimum garanti (>= 60 % CAF), ventes anticipées à la moyenne, FRP | M14: prix prod. A ; prix int. B | N14: CCC (prix, production) ; ICCO (prix int.) | O14: https://www.conseilcafecacao.ci/ ; https://www.icco.org/statistics/ | P14: Principale 1 800 ; intermédiaire 2 200 | Q14: =E14*G14*H14 -> 4640 | R14: =I14/Q14 -> 0.40517241 | S14: =I14*K14/1000 -> 3478 | T14: =Q14/Q13-1 -> 0.17090404 | U14: =I14/I13-1 -> 0.70909091 | V14: =S14/S13-1 -> 0.8016058 | W14: =IF(ABS(T14)>=0.05,U14/T14,"") -> 4.1490587 | X14: =MAX(I$2:I14) -> 1880 | Y14: =I14/X14-1 -> 0 | Z14: =LN(I14/I13) -> 0.5359616 | AA14: =LN(K14/K13) -> 0.052716782 | AB14: =LN(S14/S13) -> 0.58867838
A15: Cacao | B15: Côte d'Ivoire | C15: 2025/26 | D15: 2026 | E15: 4700 | F15: USD/t | G15: 565 | H15: 0.001 | I15: 2480 | J15: FCFA | K15: 1850 | L15: Prix minimum garanti (>= 60 % CAF), ventes anticipées à la moyenne, FRP | M15: prix prod. A/C ; prix int. B | N15: CCC (prix, production) ; ICCO (prix int.) | O15: https://www.conseilcafecacao.ci/ ; https://www.icco.org/statistics/ | P15: Principale 2 800 ; intermédiaire 1 200 (4 mars 2026) ; prix int. et prod. provisoires | Q15: =E15*G15*H15 -> 2655.5 | R15: =I15/Q15 -> 0.93391075 | S15: =I15*K15/1000 -> 4588 | T15: =Q15/Q14-1 -> -0.42769397 | U15: =I15/I14-1 -> 0.31914894 | V15: =S15/S14-1 -> 0.31914894 | W15: =IF(ABS(T15)>=0.05,U15/T15,"") -> -0.74620865 | X15: =MAX(I$2:I15) -> 2480 | Y15: =I15/X15-1 -> 0 | Z15: =LN(I15/I14) -> 0.27698678 | AA15: =LN(K15/K14) -> 0 | AB15: =LN(S15/S14) -> 0.27698678
A16: Cacao | B16: Ghana | C16: 2012/13 | D16: 2013 | E16: 2340 | F16: USD/t | G16: 1.95 | H16: 0.001 | I16: 3.392 | J16: GHS | K16: 835 | L16: Prix fixé par Cocobod (>= 70 % FOB depuis Act 1182 de 2026), ventes à terme, prêts syndiqués | M16: prix prod. B ; prix int. B | N16: Cocobod ; ICCO ; Banque du Ghana (change) | O16: https://cocobod.gh/ ; https://www.icco.org/statistics/ | Q16: =E16*G16*H16 -> 4.563 | R16: =I16/Q16 -> 0.74337059 | S16: =I16*K16/1000 -> 2.83232 | X16: =MAX(I$16:I16) -> 3.392 | Y16: =I16/X16-1 -> 0
A17: Cacao | B17: Ghana | C17: 2013/14 | D17: 2014 | E17: 2920 | F17: USD/t | G17: 2.5 | H17: 0.001 | I17: 3.392 | J17: GHS | K17: 897 | L17: Prix fixé par Cocobod (>= 70 % FOB depuis Act 1182 de 2026), ventes à terme, prêts syndiqués | M17: prix prod. B ; prix int. B | N17: Cocobod ; ICCO ; Banque du Ghana (change) | O17: https://cocobod.gh/ ; https://www.icco.org/statistics/ | Q17: =E17*G17*H17 -> 7.3 | R17: =I17/Q17 -> 0.46465753 | S17: =I17*K17/1000 -> 3.042624 | T17: =Q17/Q16-1 -> 0.59982468 | U17: =I17/I16-1 -> 0 | V17: =S17/S16-1 -> 0.074251497 | W17: =IF(ABS(T17)>=0.05,U17/T17,"") -> 0 | X17: =MAX(I$16:I17) -> 3.392 | Y17: =I17/X17-1 -> 0 | Z17: =LN(I17/I16) -> 0 | AA17: =LN(K17/K16) -> 0.071624137 | AB17: =LN(S17/S16) -> 0.071624137
A18: Cacao | B18: Ghana | C18: 2014/15 | D18: 2015 | E18: 3080 | F18: USD/t | G18: 3.3 | H18: 0.001 | I18: 5.2 | J18: GHS | K18: 740 | L18: Prix fixé par Cocobod (>= 70 % FOB depuis Act 1182 de 2026), ventes à terme, prêts syndiqués | M18: prix prod. B ; prix int. B | N18: Cocobod ; ICCO ; Banque du Ghana (change) | O18: https://cocobod.gh/ ; https://www.icco.org/statistics/ | Q18: =E18*G18*H18 -> 10.164 | R18: =I18/Q18 -> 0.5116096 | S18: =I18*K18/1000 -> 3.848 | T18: =Q18/Q17-1 -> 0.39232877 | U18: =I18/I17-1 -> 0.53301887 | V18: =S18/S17-1 -> 0.26469784 | W18: =IF(ABS(T18)>=0.05,U18/T18,"") -> 1.3586026 | X18: =MAX(I$16:I18) -> 5.2 | Y18: =I18/X18-1 -> 0 | Z18: =LN(I18/I17) -> 0.42723891 | AA18: =LN(K18/K17) -> -0.19240568 | AB18: =LN(S18/S17) -> 0.23483323
A19: Cacao | B19: Ghana | C19: 2015/16 | D19: 2016 | E19: 3000 | F19: USD/t | G19: 3.85 | H19: 0.001 | I19: 6.72 | J19: GHS | K19: 778 | L19: Prix fixé par Cocobod (>= 70 % FOB depuis Act 1182 de 2026), ventes à terme, prêts syndiqués | M19: prix prod. B ; prix int. B | N19: Cocobod ; ICCO ; Banque du Ghana (change) | O19: https://cocobod.gh/ ; https://www.icco.org/statistics/ | Q19: =E19*G19*H19 -> 11.55 | R19: =I19/Q19 -> 0.58181818 | S19: =I19*K19/1000 -> 5.22816 | T19: =Q19/Q18-1 -> 0.13636364 | U19: =I19/I18-1 -> 0.29230769 | V19: =S19/S18-1 -> 0.35866944 | W19: =IF(ABS(T19)>=0.05,U19/T19,"") -> 2.1435897 | X19: =MAX(I$16:I19) -> 6.72 | Y19: =I19/X19-1 -> 0 | Z19: =LN(I19/I18) -> 0.25642953 | AA19: =LN(K19/K18) -> 0.050076338 | AB19: =LN(S19/S18) -> 0.30650587
A20: Cacao | B20: Ghana | C20: 2016/17 | D20: 2017 | E20: 2180 | F20: USD/t | G20: 4.25 | H20: 0.001 | I20: 7.6 | J20: GHS | K20: 969 | L20: Prix fixé par Cocobod (>= 70 % FOB depuis Act 1182 de 2026), ventes à terme, prêts syndiqués | M20: prix prod. B ; prix int. B | N20: Cocobod ; ICCO ; Banque du Ghana (change) | O20: https://cocobod.gh/ ; https://www.icco.org/statistics/ | P20: Prix nominal maintenu malgré la chute des cours | Q20: =E20*G20*H20 -> 9.265 | R20: =I20/Q20 -> 0.82029142 | S20: =I20*K20/1000 -> 7.3644 | T20: =Q20/Q19-1 -> -0.1978355 | U20: =I20/I19-1 -> 0.13095238 | V20: =S20/S19-1 -> 0.40860264 | W20: =IF(ABS(T20)>=0.05,U20/T20,"") -> -0.6619256 | X20: =MAX(I$16:I20) -> 7.6 | Y20: =I20/X20-1 -> 0 | Z20: =LN(I20/I19) -> 0.12306009 | AA20: =LN(K20/K19) -> 0.21953809 | AB20: =LN(S20/S19) -> 0.34259818
A21: Cacao | B21: Ghana | C21: 2017/18 | D21: 2018 | E21: 2200 | F21: USD/t | G21: 4.45 | H21: 0.001 | I21: 7.6 | J21: GHS | K21: 905 | L21: Prix fixé par Cocobod (>= 70 % FOB depuis Act 1182 de 2026), ventes à terme, prêts syndiqués | M21: prix prod. B ; prix int. B | N21: Cocobod ; ICCO ; Banque du Ghana (change) | O21: https://cocobod.gh/ ; https://www.icco.org/statistics/ | Q21: =E21*G21*H21 -> 9.79 | R21: =I21/Q21 -> 0.77630235 | S21: =I21*K21/1000 -> 6.878 | T21: =Q21/Q20-1 -> 0.056664868 | U21: =I21/I20-1 -> 0 | V21: =S21/S20-1 -> -0.066047472 | W21: =IF(ABS(T21)>=0.05,U21/T21,"") -> 0 | X21: =MAX(I$16:I21) -> 7.6 | Y21: =I21/X21-1 -> 0 | Z21: =LN(I21/I20) -> 0 | AA21: =LN(K21/K20) -> -0.068329668 | AB21: =LN(S21/S20) -> -0.068329668
A22: Cacao | B22: Ghana | C22: 2018/19 | D22: 2019 | E22: 2300 | F22: USD/t | G22: 5 | H22: 0.001 | I22: 7.6 | J22: GHS | K22: 812 | L22: Prix fixé par Cocobod (>= 70 % FOB depuis Act 1182 de 2026), ventes à terme, prêts syndiqués | M22: prix prod. B ; prix int. B | N22: Cocobod ; ICCO ; Banque du Ghana (change) | O22: https://cocobod.gh/ ; https://www.icco.org/statistics/ | Q22: =E22*G22*H22 -> 11.5 | R22: =I22/Q22 -> 0.66086957 | S22: =I22*K22/1000 -> 6.1712 | T22: =Q22/Q21-1 -> 0.17466803 | U22: =I22/I21-1 -> 0 | V22: =S22/S21-1 -> -0.10276243 | W22: =IF(ABS(T22)>=0.05,U22/T22,"") -> 0 | X22: =MAX(I$16:I22) -> 7.6 | Y22: =I22/X22-1 -> 0 | Z22: =LN(I22/I21) -> 0 | AA22: =LN(K22/K21) -> -0.1084346 | AB22: =LN(S22/S21) -> -0.1084346
A23: Cacao | B23: Ghana | C23: 2019/20 | D23: 2020 | E23: 2450 | F23: USD/t | G23: 5.6 | H23: 0.001 | I23: 8.24 | J23: GHS | K23: 771 | L23: Prix fixé par Cocobod (>= 70 % FOB depuis Act 1182 de 2026), ventes à terme, prêts syndiqués | M23: prix prod. B ; prix int. B | N23: Cocobod ; ICCO ; Banque du Ghana (change) | O23: https://cocobod.gh/ ; https://www.icco.org/statistics/ | Q23: =E23*G23*H23 -> 13.72 | R23: =I23/Q23 -> 0.60058309 | S23: =I23*K23/1000 -> 6.35304 | T23: =Q23/Q22-1 -> 0.19304348 | U23: =I23/I22-1 -> 0.084210526 | V23: =S23/S22-1 -> 0.029465906 | W23: =IF(ABS(T23)>=0.05,U23/T23,"") -> 0.4362257 | X23: =MAX(I$16:I23) -> 8.24 | Y23: =I23/X23-1 -> 0 | Z23: =LN(I23/I22) -> 0.080852097 | AA23: =LN(K23/K22) -> -0.051811967 | AB23: =LN(S23/S22) -> 0.02904013
A24: Cacao | B24: Ghana | C24: 2020/21 | D24: 2021 | E24: 2420 | F24: USD/t | G24: 5.75 | H24: 0.001 | I24: 10.56 | J24: GHS | K24: 1047 | L24: Prix fixé par Cocobod (>= 70 % FOB depuis Act 1182 de 2026), ventes à terme, prêts syndiqués | M24: prix prod. B ; prix int. B | N24: Cocobod ; ICCO ; Banque du Ghana (change) | O24: https://cocobod.gh/ ; https://www.icco.org/statistics/ | Q24: =E24*G24*H24 -> 13.915 | R24: =I24/Q24 -> 0.75889328 | S24: =I24*K24/1000 -> 11.05632 | T24: =Q24/Q23-1 -> 0.014212828 | U24: =I24/I23-1 -> 0.2815534 | V24: =S24/S23-1 -> 0.7403196 | W24: =IF(ABS(T24)>=0.05,U24/T24,"") | X24: =MAX(I$16:I24) -> 10.56 | Y24: =I24/X24-1 -> 0 | Z24: =LN(I24/I23) -> 0.24807293 | AA24: =LN(K24/K23) -> 0.30599584 | AB24: =LN(S24/S23) -> 0.55406877
A25: Cacao | B25: Ghana | C25: 2021/22 | D25: 2022 | E25: 2450 | F25: USD/t | G25: 6.8 | H25: 0.001 | I25: 10.56 | J25: GHS | K25: 683 | L25: Prix fixé par Cocobod (>= 70 % FOB depuis Act 1182 de 2026), ventes à terme, prêts syndiqués | M25: prix prod. B ; prix int. B | N25: Cocobod ; ICCO ; Banque du Ghana (change) | O25: https://cocobod.gh/ ; https://www.icco.org/statistics/ | Q25: =E25*G25*H25 -> 16.66 | R25: =I25/Q25 -> 0.63385354 | S25: =I25*K25/1000 -> 7.21248 | T25: =Q25/Q24-1 -> 0.19726913 | U25: =I25/I24-1 -> 0 | V25: =S25/S24-1 -> -0.34765998 | W25: =IF(ABS(T25)>=0.05,U25/T25,"") -> 0 | X25: =MAX(I$16:I25) -> 10.56 | Y25: =I25/X25-1 -> 0 | Z25: =LN(I25/I24) -> 0 | AA25: =LN(K25/K24) -> -0.42718935 | AB25: =LN(S25/S24) -> -0.42718935
A26: Cacao | B26: Ghana | C26: 2022/23 | D26: 2023 | E26: 2750 | F26: USD/t | G26: 11 | H26: 0.001 | I26: 12.8 | J26: GHS | K26: 654 | L26: Prix fixé par Cocobod (>= 70 % FOB depuis Act 1182 de 2026), ventes à terme, prêts syndiqués | M26: prix prod. B ; prix int. B | N26: Cocobod ; ICCO ; Banque du Ghana (change) | O26: https://cocobod.gh/ ; https://www.icco.org/statistics/ | Q26: =E26*G26*H26 -> 30.25 | R26: =I26/Q26 -> 0.4231405 | S26: =I26*K26/1000 -> 8.3712 | T26: =Q26/Q25-1 -> 0.81572629 | U26: =I26/I25-1 -> 0.21212121 | V26: =S26/S25-1 -> 0.16065486 | W26: =IF(ABS(T26)>=0.05,U26/T26,"") -> 0.26003969 | X26: =MAX(I$16:I26) -> 12.8 | Y26: =I26/X26-1 -> 0 | Z26: =LN(I26/I25) -> 0.19237189 | AA26: =LN(K26/K25) -> -0.043387508 | AB26: =LN(S26/S25) -> 0.14898438
A27: Cacao | B27: Ghana | C27: 2023/24 | D27: 2024 | E27: 6550 | F27: USD/t | G27: 12 | H27: 0.001 | I27: 22.7 | J27: GHS | K27: 432 | L27: Prix fixé par Cocobod (>= 70 % FOB depuis Act 1182 de 2026), ventes à terme, prêts syndiqués | M27: prix prod. B ; prix int. B | N27: Cocobod ; ICCO ; Banque du Ghana (change) | O27: https://cocobod.gh/ ; https://www.icco.org/statistics/ | P27: 20 128 puis 33 120 GHS/t (avr. 2024) ; production 432 kt (vs 800 kt prévues) | Q27: =E27*G27*H27 -> 78.6 | R27: =I27/Q27 -> 0.28880407 | S27: =I27*K27/1000 -> 9.8064 | T27: =Q27/Q26-1 -> 1.5983471 | U27: =I27/I26-1 -> 0.7734375 | V27: =S27/S26-1 -> 0.17144495 | W27: =IF(ABS(T27)>=0.05,U27/T27,"") -> 0.48389833 | X27: =MAX(I$16:I27) -> 22.7 | Y27: =I27/X27-1 -> 0 | Z27: =LN(I27/I26) -> 0.57291975 | AA27: =LN(K27/K26) -> -0.41468176 | AB27: =LN(S27/S26) -> 0.15823799
A28: Cacao | B28: Ghana | C28: 2024/25 | D28: 2025 | E28: 8000 | F28: USD/t | G28: 15 | H28: 0.001 | I28: 49.9 | J28: GHS | K28: 600 | L28: Prix fixé par Cocobod (>= 70 % FOB depuis Act 1182 de 2026), ventes à terme, prêts syndiqués | M28: prix prod. B ; prix int. B | N28: Cocobod ; ICCO ; Banque du Ghana (change) | O28: https://cocobod.gh/ ; https://www.icco.org/statistics/ | P28: 49 600 puis 51 660 GHS/t | Q28: =E28*G28*H28 -> 120 | R28: =I28/Q28 -> 0.41583333 | S28: =I28*K28/1000 -> 29.94 | T28: =Q28/Q27-1 -> 0.52671756 | U28: =I28/I27-1 -> 1.1982379 | V28: =S28/S27-1 -> 2.0531082 | W28: =IF(ABS(T28)>=0.05,U28/T28,"") -> 2.2749154 | X28: =MAX(I$16:I28) -> 49.9 | Y28: =I28/X28-1 -> 0 | Z28: =LN(I28/I27) -> 0.78765608 | AA28: =LN(K28/K27) -> 0.32850407 | AB28: =LN(S28/S27) -> 1.1161601
A29: Cacao | B29: Ghana | C29: 2025/26 | D29: 2026 | E29: 4700 | F29: USD/t | G29: 11.5 | H29: 0.001 | I29: 49.7 | J29: GHS | K29: 650 | L29: Prix fixé par Cocobod (>= 70 % FOB depuis Act 1182 de 2026), ventes à terme, prêts syndiqués | M29: prix prod. A/C ; prix int. B | N29: Cocobod ; ICCO ; Banque du Ghana (change) | O29: https://cocobod.gh/ ; https://www.icco.org/statistics/ | P29: 58 000 GHS/t (oct. 2025) puis 41 392 (12 fév. 2026) | Q29: =E29*G29*H29 -> 54.05 | R29: =I29/Q29 -> 0.91951896 | S29: =I29*K29/1000 -> 32.305 | T29: =Q29/Q28-1 -> -0.54958333 | U29: =I29/I28-1 -> -0.004008016 | V29: =S29/S28-1 -> 0.078991316 | W29: =IF(ABS(T29)>=0.05,U29/T29,"") -> 0.0072928267 | X29: =MAX(I$16:I29) -> 49.9 | Y29: =I29/X29-1 -> -0.004008016 | Z29: =LN(I29/I28) -> -0.0040160697 | AA29: =LN(K29/K28) -> 0.080042708 | AB29: =LN(S29/S28) -> 0.076026638
A30: Coton | B30: Côte d'Ivoire | C30: 2014/15 | D30: 2015 | E30: 0.71 | F30: USD/lb | G30: 560 | H30: 2.20462 | I30: 250 | J30: FCFA | K30: 450 | L30: Prix administré avant semis (Interprofession/État) ; subventions intrants | M30: prix prod. B ; prix int. B | N30: Conseil du Coton et de l'Anacarde ; ICAC/Cotlook A | O30: https://www.conseilcotonanacarde.ci/ ; https://www.icac.org/ | Q30: =E30*G30*H30 -> 876.55691 | R30: =I30/Q30 -> 0.28520681 | S30: =I30*K30/1000 -> 112.5 | X30: =MAX(I$30:I30) -> 250 | Y30: =I30/X30-1 -> 0
A31: Coton | B31: Côte d'Ivoire | C31: 2015/16 | D31: 2016 | E31: 0.7 | F31: USD/lb | G31: 590 | H31: 2.20462 | I31: 250 | J31: FCFA | K31: 400 | L31: Prix administré avant semis (Interprofession/État) ; subventions intrants | M31: prix prod. B ; prix int. B | N31: Conseil du Coton et de l'Anacarde ; ICAC/Cotlook A | O31: https://www.conseilcotonanacarde.ci/ ; https://www.icac.org/ | Q31: =E31*G31*H31 -> 910.50806 | R31: =I31/Q31 -> 0.27457198 | S31: =I31*K31/1000 -> 100 | T31: =Q31/Q30-1 -> 0.038732394 | U31: =I31/I30-1 -> 0 | V31: =S31/S30-1 -> -0.11111111 | W31: =IF(ABS(T31)>=0.05,U31/T31,"") | X31: =MAX(I$30:I31) -> 250 | Y31: =I31/X31-1 -> 0 | Z31: =LN(I31/I30) -> 0 | AA31: =LN(K31/K30) -> -0.11778304 | AB31: =LN(S31/S30) -> -0.11778304
A32: Coton | B32: Côte d'Ivoire | C32: 2016/17 | D32: 2017 | E32: 0.83 | F32: USD/lb | G32: 600 | H32: 2.20462 | I32: 265 | J32: FCFA | K32: 328 | L32: Prix administré avant semis (Interprofession/État) ; subventions intrants | M32: prix prod. B ; prix int. B | N32: Conseil du Coton et de l'Anacarde ; ICAC/Cotlook A | O32: https://www.conseilcotonanacarde.ci/ ; https://www.icac.org/ | Q32: =E32*G32*H32 -> 1097.9008 | R32: =I32/Q32 -> 0.24136972 | S32: =I32*K32/1000 -> 86.92 | T32: =Q32/Q31-1 -> 0.20581114 | U32: =I32/I31-1 -> 0.06 | V32: =S32/S31-1 -> -0.1308 | W32: =IF(ABS(T32)>=0.05,U32/T32,"") -> 0.29152941 | X32: =MAX(I$30:I32) -> 265 | Y32: =I32/X32-1 -> 0 | Z32: =LN(I32/I31) -> 0.058268908 | AA32: =LN(K32/K31) -> -0.19845094 | AB32: =LN(S32/S31) -> -0.14018203
A33: Coton | B33: Côte d'Ivoire | C33: 2017/18 | D33: 2018 | E33: 0.88 | F33: USD/lb | G33: 555 | H33: 2.20462 | I33: 265 | J33: FCFA | K33: 413 | L33: Prix administré avant semis (Interprofession/État) ; subventions intrants | M33: prix prod. B ; prix int. B | N33: Conseil du Coton et de l'Anacarde ; ICAC/Cotlook A | O33: https://www.conseilcotonanacarde.ci/ ; https://www.icac.org/ | Q33: =E33*G33*H33 -> 1076.7364 | R33: =I33/Q33 -> 0.24611409 | S33: =I33*K33/1000 -> 109.445 | T33: =Q33/Q32-1 -> -0.019277108 | U33: =I33/I32-1 -> 0 | V33: =S33/S32-1 -> 0.25914634 | W33: =IF(ABS(T33)>=0.05,U33/T33,"") | X33: =MAX(I$30:I33) -> 265 | Y33: =I33/X33-1 -> 0 | Z33: =LN(I33/I32) -> 0 | AA33: =LN(K33/K32) -> 0.23043398 | AB33: =LN(S33/S32) -> 0.23043398
A34: Coton | B34: Côte d'Ivoire | C34: 2018/19 | D34: 2019 | E34: 0.84 | F34: USD/lb | G34: 575 | H34: 2.20462 | I34: 265 | J34: FCFA | K34: 482 | L34: Prix administré avant semis (Interprofession/État) ; subventions intrants | M34: prix prod. B ; prix int. B | N34: Conseil du Coton et de l'Anacarde ; ICAC/Cotlook A | O34: https://www.conseilcotonanacarde.ci/ ; https://www.icac.org/ | Q34: =E34*G34*H34 -> 1064.8315 | R34: =I34/Q34 -> 0.24886567 | S34: =I34*K34/1000 -> 127.73 | T34: =Q34/Q33-1 -> -0.011056511 | U34: =I34/I33-1 -> 0 | V34: =S34/S33-1 -> 0.16707022 | W34: =IF(ABS(T34)>=0.05,U34/T34,"") | X34: =MAX(I$30:I34) -> 265 | Y34: =I34/X34-1 -> 0 | Z34: =LN(I34/I33) -> 0 | AA34: =LN(K34/K33) -> 0.15449652 | AB34: =LN(S34/S33) -> 0.15449652
A35: Coton | B35: Côte d'Ivoire | C35: 2019/20 | D35: 2020 | E35: 0.72 | F35: USD/lb | G35: 590 | H35: 2.20462 | I35: 300 | J35: FCFA | K35: 490 | L35: Prix administré avant semis (Interprofession/État) ; subventions intrants | M35: prix prod. B ; prix int. B | N35: Conseil du Coton et de l'Anacarde ; ICAC/Cotlook A | O35: https://www.conseilcotonanacarde.ci/ ; https://www.icac.org/ | Q35: =E35*G35*H35 -> 936.52258 | R35: =I35/Q35 -> 0.32033398 | S35: =I35*K35/1000 -> 147 | T35: =Q35/Q34-1 -> -0.12049689 | U35: =I35/I34-1 -> 0.13207547 | V35: =S35/S34-1 -> 0.15086511 | W35: =IF(ABS(T35)>=0.05,U35/T35,"") -> -1.0960903 | X35: =MAX(I$30:I35) -> 300 | Y35: =I35/X35-1 -> 0 | Z35: =LN(I35/I34) -> 0.12405265 | AA35: =LN(K35/K34) -> 0.016461277 | AB35: =LN(S35/S34) -> 0.14051393
A36: Coton | B36: Côte d'Ivoire | C36: 2020/21 | D36: 2021 | E36: 0.87 | F36: USD/lb | G36: 550 | H36: 2.20462 | I36: 300 | J36: FCFA | K36: 560 | L36: Prix administré avant semis (Interprofession/État) ; subventions intrants | M36: prix prod. B ; prix int. B | N36: Conseil du Coton et de l'Anacarde ; ICAC/Cotlook A | O36: https://www.conseilcotonanacarde.ci/ ; https://www.icac.org/ | P36: Prix maintenu en pleine crise COVID grâce à un soutien public | Q36: =E36*G36*H36 -> 1054.9107 | R36: =I36/Q36 -> 0.28438427 | S36: =I36*K36/1000 -> 168 | T36: =Q36/Q35-1 -> 0.12641243 | U36: =I36/I35-1 -> 0 | V36: =S36/S35-1 -> 0.14285714 | W36: =IF(ABS(T36)>=0.05,U36/T36,"") -> 0 | X36: =MAX(I$30:I36) -> 300 | Y36: =I36/X36-1 -> 0 | Z36: =LN(I36/I35) -> 0 | AA36: =LN(K36/K35) -> 0.13353139 | AB36: =LN(S36/S35) -> 0.13353139
A37: Coton | B37: Côte d'Ivoire | C37: 2021/22 | D37: 2022 | E37: 1.3 | F37: USD/lb | G37: 590 | H37: 2.20462 | I37: 300 | J37: FCFA | K37: 560 | L37: Prix administré avant semis (Interprofession/État) ; subventions intrants | M37: prix prod. B ; prix int. B | N37: Conseil du Coton et de l'Anacarde ; ICAC/Cotlook A | O37: https://www.conseilcotonanacarde.ci/ ; https://www.icac.org/ | P37: Envolée des cours (+80 %) non transmise | Q37: =E37*G37*H37 -> 1690.9435 | R37: =I37/Q37 -> 0.17741574 | S37: =I37*K37/1000 -> 168 | T37: =Q37/Q36-1 -> 0.60292581 | U37: =I37/I36-1 -> 0 | V37: =S37/S36-1 -> 0 | W37: =IF(ABS(T37)>=0.05,U37/T37,"") -> 0 | X37: =MAX(I$30:I37) -> 300 | Y37: =I37/X37-1 -> 0 | Z37: =LN(I37/I36) -> 0 | AA37: =LN(K37/K36) -> 0 | AB37: =LN(S37/S36) -> 0
A38: Coton | B38: Côte d'Ivoire | C38: 2022/23 | D38: 2023 | E38: 1 | F38: USD/lb | G38: 615 | H38: 2.20462 | I38: 310 | J38: FCFA | K38: 236 | L38: Prix administré avant semis (Interprofession/État) ; subventions intrants | M38: prix prod. B ; prix int. B | N38: Conseil du Coton et de l'Anacarde ; ICAC/Cotlook A | O38: https://www.conseilcotonanacarde.ci/ ; https://www.icac.org/ | P38: Attaque de jassides : production -58 % | Q38: =E38*G38*H38 -> 1355.8413 | R38: =I38/Q38 -> 0.22864033 | S38: =I38*K38/1000 -> 73.16 | T38: =Q38/Q37-1 -> -0.19817471 | U38: =I38/I37-1 -> 0.033333333 | V38: =S38/S37-1 -> -0.56452381 | W38: =IF(ABS(T38)>=0.05,U38/T38,"") -> -0.16820175 | X38: =MAX(I$30:I38) -> 310 | Y38: =I38/X38-1 -> 0 | Z38: =LN(I38/I37) -> 0.032789823 | AA38: =LN(K38/K37) -> -0.86410498 | AB38: =LN(S38/S37) -> -0.83131516
A39: Coton | B39: Côte d'Ivoire | C39: 2023/24 | D39: 2024 | E39: 0.92 | F39: USD/lb | G39: 605 | H39: 2.20462 | I39: 310 | J39: FCFA | K39: 340 | L39: Prix administré avant semis (Interprofession/État) ; subventions intrants | M39: prix prod. B ; prix int. B | N39: Conseil du Coton et de l'Anacarde ; ICAC/Cotlook A | O39: https://www.conseilcotonanacarde.ci/ ; https://www.icac.org/ | Q39: =E39*G39*H39 -> 1227.0915 | R39: =I39/Q39 -> 0.2526299 | S39: =I39*K39/1000 -> 105.4 | T39: =Q39/Q38-1 -> -0.09495935 | U39: =I39/I38-1 -> 0 | V39: =S39/S38-1 -> 0.44067797 | W39: =IF(ABS(T39)>=0.05,U39/T39,"") -> 0 | X39: =MAX(I$30:I39) -> 310 | Y39: =I39/X39-1 -> 0 | Z39: =LN(I39/I38) -> 0 | AA39: =LN(K39/K38) -> 0.36511381 | AB39: =LN(S39/S38) -> 0.36511381
A40: Coton | B40: Côte d'Ivoire | C40: 2024/25 | D40: 2025 | E40: 0.8 | F40: USD/lb | G40: 580 | H40: 2.20462 | I40: 310 | J40: FCFA | K40: 470 | L40: Prix administré avant semis (Interprofession/État) ; subventions intrants | M40: prix prod. B ; prix int. B | N40: Conseil du Coton et de l'Anacarde ; ICAC/Cotlook A | O40: https://www.conseilcotonanacarde.ci/ ; https://www.icac.org/ | Q40: =E40*G40*H40 -> 1022.9437 | R40: =I40/Q40 -> 0.30304699 | S40: =I40*K40/1000 -> 145.7 | T40: =Q40/Q39-1 -> -0.16636723 | U40: =I40/I39-1 -> 0 | V40: =S40/S39-1 -> 0.38235294 | W40: =IF(ABS(T40)>=0.05,U40/T40,"") -> 0 | X40: =MAX(I$30:I40) -> 310 | Y40: =I40/X40-1 -> 0 | Z40: =LN(I40/I39) -> 0 | AA40: =LN(K40/K39) -> 0.32378708 | AB40: =LN(S40/S39) -> 0.32378708
A41: Coton | B41: Côte d'Ivoire | C41: 2025/26 | D41: 2026 | E41: 0.77 | F41: USD/lb | G41: 565 | H41: 2.20462 | I41: 310 | J41: FCFA | K41: 575 | L41: Prix administré avant semis (Interprofession/État) ; subventions intrants | M41: prix prod. A/C ; prix int. B | N41: Conseil du Coton et de l'Anacarde ; ICAC/Cotlook A | O41: https://www.conseilcotonanacarde.ci/ ; https://www.icac.org/ | P41: Subvention exceptionnelle 25,3 Mds FCFA (44 FCFA/kg) ; production prévisionnelle | Q41: =E41*G41*H41 -> 959.11993 | R41: =I41/Q41 -> 0.32321297 | S41: =I41*K41/1000 -> 178.25 | T41: =Q41/Q40-1 -> -0.062392241 | U41: =I41/I40-1 -> 0 | V41: =S41/S40-1 -> 0.22340426 | W41: =IF(ABS(T41)>=0.05,U41/T41,"") -> 0 | X41: =MAX(I$30:I41) -> 310 | Y41: =I41/X41-1 -> 0 | Z41: =LN(I41/I40) -> 0 | AA41: =LN(K41/K40) -> 0.20163735 | AB41: =LN(S41/S40) -> 0.20163735
A42: Anacarde | B42: Côte d'Ivoire | C42: 2016 | D42: 2016 | E42: 1350 | F42: USD/t | G42: 593 | H42: 0.001 | I42: 350 | J42: FCFA | K42: 650 | L42: Prix plancher bord champ indicatif-obligatoire ; pas de fonds de stabilisation | M42: prix prod. A ; prix int. C | N42: Conseil du Coton et de l'Anacarde ; cotations noix brute CIF Inde (presse spécialisée) | O42: https://www.conseilcotonanacarde.ci/ | Q42: =E42*G42*H42 -> 800.55 | R42: =I42/Q42 -> 0.43719943 | S42: =I42*K42/1000 -> 227.5 | X42: =MAX(I$42:I42) -> 350 | Y42: =I42/X42-1 -> 0
A43: Anacarde | B43: Côte d'Ivoire | C43: 2017 | D43: 2017 | E43: 1800 | F43: USD/t | G43: 582 | H43: 0.001 | I43: 440 | J43: FCFA | K43: 711 | L43: Prix plancher bord champ indicatif-obligatoire ; pas de fonds de stabilisation | M43: prix prod. A ; prix int. C | N43: Conseil du Coton et de l'Anacarde ; cotations noix brute CIF Inde (presse spécialisée) | O43: https://www.conseilcotonanacarde.ci/ | Q43: =E43*G43*H43 -> 1047.6 | R43: =I43/Q43 -> 0.42000764 | S43: =I43*K43/1000 -> 312.84 | T43: =Q43/Q42-1 -> 0.30860034 | U43: =I43/I42-1 -> 0.25714286 | V43: =S43/S42-1 -> 0.37512088 | W43: =IF(ABS(T43)>=0.05,U43/T43,"") -> 0.83325527 | X43: =MAX(I$42:I43) -> 440 | Y43: =I43/X43-1 -> 0 | Z43: =LN(I43/I42) -> 0.22884157 | AA43: =LN(K43/K42) -> 0.089700067 | AB43: =LN(S43/S42) -> 0.31854164
A44: Anacarde | B44: Côte d'Ivoire | C44: 2018 | D44: 2018 | E44: 1600 | F44: USD/t | G44: 555 | H44: 0.001 | I44: 500 | J44: FCFA | K44: 761 | L44: Prix plancher bord champ indicatif-obligatoire ; pas de fonds de stabilisation | M44: prix prod. A ; prix int. C | N44: Conseil du Coton et de l'Anacarde ; cotations noix brute CIF Inde (presse spécialisée) | O44: https://www.conseilcotonanacarde.ci/ | P44: Plancher 500 non respecté : prix réels 250-300 en fin de campagne | Q44: =E44*G44*H44 -> 888 | R44: =I44/Q44 -> 0.56306306 | S44: =I44*K44/1000 -> 380.5 | T44: =Q44/Q43-1 -> -0.15234822 | U44: =I44/I43-1 -> 0.13636364 | V44: =S44/S43-1 -> 0.21627669 | W44: =IF(ABS(T44)>=0.05,U44/T44,"") -> -0.89507861 | X44: =MAX(I$42:I44) -> 500 | Y44: =I44/X44-1 -> 0 | Z44: =LN(I44/I43) -> 0.12783337 | AA44: =LN(K44/K43) -> 0.067960928 | AB44: =LN(S44/S43) -> 0.1957943
A45: Anacarde | B45: Côte d'Ivoire | C45: 2019 | D45: 2019 | E45: 1150 | F45: USD/t | G45: 586 | H45: 0.001 | I45: 375 | J45: FCFA | K45: 634 | L45: Prix plancher bord champ indicatif-obligatoire ; pas de fonds de stabilisation | M45: prix prod. A ; prix int. C | N45: Conseil du Coton et de l'Anacarde ; cotations noix brute CIF Inde (presse spécialisée) | O45: https://www.conseilcotonanacarde.ci/ | Q45: =E45*G45*H45 -> 673.9 | R45: =I45/Q45 -> 0.55646238 | S45: =I45*K45/1000 -> 237.75 | T45: =Q45/Q44-1 -> -0.2411036 | U45: =I45/I44-1 -> -0.25 | V45: =S45/S44-1 -> -0.37516426 | W45: =IF(ABS(T45)>=0.05,U45/T45,"") -> 1.0368986 | X45: =MAX(I$42:I45) -> 500 | Y45: =I45/X45-1 -> -0.25 | Z45: =LN(I45/I44) -> -0.28768207 | AA45: =LN(K45/K44) -> -0.1825844 | AB45: =LN(S45/S44) -> -0.47026648
A46: Anacarde | B46: Côte d'Ivoire | C46: 2020 | D46: 2020 | E46: 1000 | F46: USD/t | G46: 575 | H46: 0.001 | I46: 400 | J46: FCFA | K46: 848 | L46: Prix plancher bord champ indicatif-obligatoire ; pas de fonds de stabilisation | M46: prix prod. A ; prix int. C | N46: Conseil du Coton et de l'Anacarde ; cotations noix brute CIF Inde (presse spécialisée) | O46: https://www.conseilcotonanacarde.ci/ | Q46: =E46*G46*H46 -> 575 | R46: =I46/Q46 -> 0.69565217 | S46: =I46*K46/1000 -> 339.2 | T46: =Q46/Q45-1 -> -0.14675768 | U46: =I46/I45-1 -> 0.066666667 | V46: =S46/S45-1 -> 0.42670873 | W46: =IF(ABS(T46)>=0.05,U46/T46,"") -> -0.45426357 | X46: =MAX(I$42:I46) -> 500 | Y46: =I46/X46-1 -> -0.2 | Z46: =LN(I46/I45) -> 0.064538521 | AA46: =LN(K46/K45) -> 0.29083168 | AB46: =LN(S46/S45) -> 0.3553702
A47: Anacarde | B47: Côte d'Ivoire | C47: 2021 | D47: 2021 | E47: 1100 | F47: USD/t | G47: 554 | H47: 0.001 | I47: 305 | J47: FCFA | K47: 968 | L47: Prix plancher bord champ indicatif-obligatoire ; pas de fonds de stabilisation | M47: prix prod. A ; prix int. C | N47: Conseil du Coton et de l'Anacarde ; cotations noix brute CIF Inde (presse spécialisée) | O47: https://www.conseilcotonanacarde.ci/ | Q47: =E47*G47*H47 -> 609.4 | R47: =I47/Q47 -> 0.50049229 | S47: =I47*K47/1000 -> 295.24 | T47: =Q47/Q46-1 -> 0.059826087 | U47: =I47/I46-1 -> -0.2375 | V47: =S47/S46-1 -> -0.12959906 | W47: =IF(ABS(T47)>=0.05,U47/T47,"") -> -3.9698401 | X47: =MAX(I$42:I47) -> 500 | Y47: =I47/X47-1 -> -0.39 | Z47: =LN(I47/I46) -> -0.27115277 | AA47: =LN(K47/K46) -> 0.13235145 | AB47: =LN(S47/S46) -> -0.13880132
A48: Anacarde | B48: Côte d'Ivoire | C48: 2022 | D48: 2022 | E48: 1050 | F48: USD/t | G48: 623 | H48: 0.001 | I48: 305 | J48: FCFA | K48: 1028 | L48: Prix plancher bord champ indicatif-obligatoire ; pas de fonds de stabilisation | M48: prix prod. A ; prix int. C | N48: Conseil du Coton et de l'Anacarde ; cotations noix brute CIF Inde (presse spécialisée) | O48: https://www.conseilcotonanacarde.ci/ | Q48: =E48*G48*H48 -> 654.15 | R48: =I48/Q48 -> 0.46625392 | S48: =I48*K48/1000 -> 313.54 | T48: =Q48/Q47-1 -> 0.073432885 | U48: =I48/I47-1 -> 0 | V48: =S48/S47-1 -> 0.061983471 | W48: =IF(ABS(T48)>=0.05,U48/T48,"") -> 0 | X48: =MAX(I$42:I48) -> 500 | Y48: =I48/X48-1 -> -0.39 | Z48: =LN(I48/I47) -> 0 | AA48: =LN(K48/K47) -> 0.060138359 | AB48: =LN(S48/S47) -> 0.060138359
A49: Anacarde | B49: Côte d'Ivoire | C49: 2023 | D49: 2023 | E49: 1000 | F49: USD/t | G49: 607 | H49: 0.001 | I49: 315 | J49: FCFA | K49: 1200 | L49: Prix plancher bord champ indicatif-obligatoire ; pas de fonds de stabilisation | M49: prix prod. A ; prix int. C | N49: Conseil du Coton et de l'Anacarde ; cotations noix brute CIF Inde (presse spécialisée) | O49: https://www.conseilcotonanacarde.ci/ | Q49: =E49*G49*H49 -> 607 | R49: =I49/Q49 -> 0.51894563 | S49: =I49*K49/1000 -> 378 | T49: =Q49/Q48-1 -> -0.07207827 | U49: =I49/I48-1 -> 0.032786885 | V49: =S49/S48-1 -> 0.2055878 | W49: =IF(ABS(T49)>=0.05,U49/T49,"") -> -0.45487892 | X49: =MAX(I$42:I49) -> 500 | Y49: =I49/X49-1 -> -0.37 | Z49: =LN(I49/I48) -> 0.032260862 | AA49: =LN(K49/K48) -> 0.15470639 | AB49: =LN(S49/S48) -> 0.18696725
A50: Anacarde | B50: Côte d'Ivoire | C50: 2024 | D50: 2024 | E50: 1350 | F50: USD/t | G50: 607 | H50: 0.001 | I50: 275 | J50: FCFA | K50: 1100 | L50: Prix plancher bord champ indicatif-obligatoire ; pas de fonds de stabilisation | M50: prix prod. A ; prix int. C | N50: Conseil du Coton et de l'Anacarde ; cotations noix brute CIF Inde (presse spécialisée) | O50: https://www.conseilcotonanacarde.ci/ | P50: Prix réels 500-700 en fin de campagne, bien au-dessus du plancher | Q50: =E50*G50*H50 -> 819.45 | R50: =I50/Q50 -> 0.33559095 | S50: =I50*K50/1000 -> 302.5 | T50: =Q50/Q49-1 -> 0.35 | U50: =I50/I49-1 -> -0.12698413 | V50: =S50/S49-1 -> -0.19973545 | W50: =IF(ABS(T50)>=0.05,U50/T50,"") -> -0.36281179 | X50: =MAX(I$42:I50) -> 500 | Y50: =I50/X50-1 -> -0.45 | Z50: =LN(I50/I49) -> -0.13580154 | AA50: =LN(K50/K49) -> -0.087011377 | AB50: =LN(S50/S49) -> -0.22281292
A51: Anacarde | B51: Côte d'Ivoire | C51: 2025 | D51: 2025 | E51: 1450 | F51: USD/t | G51: 580 | H51: 0.001 | I51: 425 | J51: FCFA | K51: 1200 | L51: Prix plancher bord champ indicatif-obligatoire ; pas de fonds de stabilisation | M51: prix prod. A ; prix int. C | N51: Conseil du Coton et de l'Anacarde ; cotations noix brute CIF Inde (presse spécialisée) | O51: https://www.conseilcotonanacarde.ci/ | Q51: =E51*G51*H51 -> 841 | R51: =I51/Q51 -> 0.50535077 | S51: =I51*K51/1000 -> 510 | T51: =Q51/Q50-1 -> 0.026298127 | U51: =I51/I50-1 -> 0.54545455 | V51: =S51/S50-1 -> 0.68595041 | W51: =IF(ABS(T51)>=0.05,U51/T51,"") | X51: =MAX(I$42:I51) -> 500 | Y51: =I51/X51-1 -> -0.15 | Z51: =LN(I51/I50) -> 0.43531807 | AA51: =LN(K51/K50) -> 0.087011377 | AB51: =LN(S51/S50) -> 0.52232945
A52: Anacarde | B52: Côte d'Ivoire | C52: 2026 | D52: 2026 | E52: 1300 | F52: USD/t | G52: 560 | H52: 0.001 | I52: 400 | J52: FCFA | K52: 1200 | L52: Prix plancher bord champ indicatif-obligatoire ; pas de fonds de stabilisation | M52: prix prod. A/C ; prix int. C | N52: Conseil du Coton et de l'Anacarde ; cotations noix brute CIF Inde (presse spécialisée) | O52: https://www.conseilcotonanacarde.ci/ | P52: Plancher 400 bord champ / 425 magasin intérieur / 484 portuaire | Q52: =E52*G52*H52 -> 728 | R52: =I52/Q52 -> 0.54945055 | S52: =I52*K52/1000 -> 480 | T52: =Q52/Q51-1 -> -0.13436385 | U52: =I52/I51-1 -> -0.058823529 | V52: =S52/S51-1 -> -0.058823529 | W52: =IF(ABS(T52)>=0.05,U52/T52,"") -> 0.43779282 | X52: =MAX(I$42:I52) -> 500 | Y52: =I52/X52-1 -> -0.2 | Z52: =LN(I52/I51) -> -0.060624622 | AA52: =LN(K52/K51) -> 0 | AB52: =LN(S52/S51) -> -0.060624622
A53: Hévéa | B53: Côte d'Ivoire | C53: 2011 | D53: 2011 | E53: 4.52 | F53: USD/kg | G53: 471 | H53: 1 | I53: 950 | J53: FCFA | K53: 235 | L53: Prix bord champ mensuel = part fixe (66 % depuis mai 2026) du prix de référence net SICOM | M53: prix prod. C ; prix int. B | N53: APROMAC / CHPC ; Banque mondiale Pink Sheet (TSR20) | O53: https://www.worldbank.org/en/research/commodity-markets | P53: Pic historique des cours | Q53: =E53*G53*H53 -> 2128.92 | R53: =I53/Q53 -> 0.44623565 | S53: =I53*K53/1000 -> 223.25 | X53: =MAX(I$53:I53) -> 950 | Y53: =I53/X53-1 -> 0
A54: Hévéa | B54: Côte d'Ivoire | C54: 2012 | D54: 2012 | E54: 3.16 | F54: USD/kg | G54: 510 | H54: 1 | I54: 650 | J54: FCFA | K54: 256 | L54: Prix bord champ mensuel = part fixe (66 % depuis mai 2026) du prix de référence net SICOM | M54: prix prod. C ; prix int. B | N54: APROMAC / CHPC ; Banque mondiale Pink Sheet (TSR20) | O54: https://www.worldbank.org/en/research/commodity-markets | Q54: =E54*G54*H54 -> 1611.6 | R54: =I54/Q54 -> 0.40332589 | S54: =I54*K54/1000 -> 166.4 | T54: =Q54/Q53-1 -> -0.24299645 | U54: =I54/I53-1 -> -0.31578947 | V54: =S54/S53-1 -> -0.25464726 | W54: =IF(ABS(T54)>=0.05,U54/T54,"") -> 1.2995642 | X54: =MAX(I$53:I54) -> 950 | Y54: =I54/X54-1 -> -0.31578947 | Z54: =LN(I54/I53) -> -0.37948962 | AA54: =LN(K54/K53) -> 0.08559193 | AB54: =LN(S54/S53) -> -0.29389769
A55: Hévéa | B55: Côte d'Ivoire | C55: 2013 | D55: 2013 | E55: 2.52 | F55: USD/kg | G55: 494 | H55: 1 | I55: 500 | J55: FCFA | K55: 290 | L55: Prix bord champ mensuel = part fixe (66 % depuis mai 2026) du prix de référence net SICOM | M55: prix prod. C ; prix int. B | N55: APROMAC / CHPC ; Banque mondiale Pink Sheet (TSR20) | O55: https://www.worldbank.org/en/research/commodity-markets | Q55: =E55*G55*H55 -> 1244.88 | R55: =I55/Q55 -> 0.40164514 | S55: =I55*K55/1000 -> 145 | T55: =Q55/Q54-1 -> -0.22755026 | U55: =I55/I54-1 -> -0.23076923 | V55: =S55/S54-1 -> -0.12860577 | W55: =IF(ABS(T55)>=0.05,U55/T55,"") -> 1.0141462 | X55: =MAX(I$53:I55) -> 950 | Y55: =I55/X55-1 -> -0.47368421 | Z55: =LN(I55/I54) -> -0.26236426 | AA55: =LN(K55/K54) -> 0.12470348 | AB55: =LN(S55/S54) -> -0.13766079
A56: Hévéa | B56: Côte d'Ivoire | C56: 2014 | D56: 2014 | E56: 1.66 | F56: USD/kg | G56: 494 | H56: 1 | I56: 330 | J56: FCFA | K56: 312 | L56: Prix bord champ mensuel = part fixe (66 % depuis mai 2026) du prix de référence net SICOM | M56: prix prod. C ; prix int. B | N56: APROMAC / CHPC ; Banque mondiale Pink Sheet (TSR20) | O56: https://www.worldbank.org/en/research/commodity-markets | Q56: =E56*G56*H56 -> 820.04 | R56: =I56/Q56 -> 0.40241939 | S56: =I56*K56/1000 -> 102.96 | T56: =Q56/Q55-1 -> -0.34126984 | U56: =I56/I55-1 -> -0.34 | V56: =S56/S55-1 -> -0.28993103 | W56: =IF(ABS(T56)>=0.05,U56/T56,"") -> 0.99627907 | X56: =MAX(I$53:I56) -> 950 | Y56: =I56/X56-1 -> -0.65263158 | Z56: =LN(I56/I55) -> -0.41551544 | AA56: =LN(K56/K55) -> 0.073122265 | AB56: =LN(S56/S55) -> -0.34239318
A57: Hévéa | B57: Côte d'Ivoire | C57: 2015 | D57: 2015 | E57: 1.37 | F57: USD/kg | G57: 592 | H57: 1 | I57: 280 | J57: FCFA | K57: 400 | L57: Prix bord champ mensuel = part fixe (66 % depuis mai 2026) du prix de référence net SICOM | M57: prix prod. C ; prix int. B | N57: APROMAC / CHPC ; Banque mondiale Pink Sheet (TSR20) | O57: https://www.worldbank.org/en/research/commodity-markets | Q57: =E57*G57*H57 -> 811.04 | R57: =I57/Q57 -> 0.34523575 | S57: =I57*K57/1000 -> 112 | T57: =Q57/Q56-1 -> -0.010975074 | U57: =I57/I56-1 -> -0.15151515 | V57: =S57/S56-1 -> 0.087801088 | W57: =IF(ABS(T57)>=0.05,U57/T57,"") | X57: =MAX(I$53:I57) -> 950 | Y57: =I57/X57-1 -> -0.70526316 | Z57: =LN(I57/I56) -> -0.16430305 | AA57: =LN(K57/K56) -> 0.24846136 | AB57: =LN(S57/S56) -> 0.084158308
A58: Hévéa | B58: Côte d'Ivoire | C58: 2016 | D58: 2016 | E58: 1.37 | F58: USD/kg | G58: 593 | H58: 1 | I58: 260 | J58: FCFA | K58: 453 | L58: Prix bord champ mensuel = part fixe (66 % depuis mai 2026) du prix de référence net SICOM | M58: prix prod. C ; prix int. B | N58: APROMAC / CHPC ; Banque mondiale Pink Sheet (TSR20) | O58: https://www.worldbank.org/en/research/commodity-markets | P58: Point bas (≈ 230 FCFA/kg début 2016) | Q58: =E58*G58*H58 -> 812.41 | R58: =I58/Q58 -> 0.32003545 | S58: =I58*K58/1000 -> 117.78 | T58: =Q58/Q57-1 -> 0.0016891892 | U58: =I58/I57-1 -> -0.071428571 | V58: =S58/S57-1 -> 0.051607143 | W58: =IF(ABS(T58)>=0.05,U58/T58,"") | X58: =MAX(I$53:I58) -> 950 | Y58: =I58/X58-1 -> -0.72631579 | Z58: =LN(I58/I57) -> -0.074107972 | AA58: =LN(K58/K57) -> 0.12442758 | AB58: =LN(S58/S57) -> 0.050319606
A59: Hévéa | B59: Côte d'Ivoire | C59: 2017 | D59: 2017 | E59: 1.65 | F59: USD/kg | G59: 582 | H59: 1 | I59: 380 | J59: FCFA | K59: 580 | L59: Prix bord champ mensuel = part fixe (66 % depuis mai 2026) du prix de référence net SICOM | M59: prix prod. C ; prix int. B | N59: APROMAC / CHPC ; Banque mondiale Pink Sheet (TSR20) | O59: https://www.worldbank.org/en/research/commodity-markets | Q59: =E59*G59*H59 -> 960.3 | R59: =I59/Q59 -> 0.39570967 | S59: =I59*K59/1000 -> 220.4 | T59: =Q59/Q58-1 -> 0.18203863 | U59: =I59/I58-1 -> 0.46153846 | V59: =S59/S58-1 -> 0.87128545 | W59: =IF(ABS(T59)>=0.05,U59/T59,"") -> 2.5353875 | X59: =MAX(I$53:I59) -> 950 | Y59: =I59/X59-1 -> -0.6 | Z59: =LN(I59/I58) -> 0.37948962 | AA59: =LN(K59/K58) -> 0.24713598 | AB59: =LN(S59/S58) -> 0.6266256
A60: Hévéa | B60: Côte d'Ivoire | C60: 2018 | D60: 2018 | E60: 1.37 | F60: USD/kg | G60: 555 | H60: 1 | I60: 300 | J60: FCFA | K60: 624 | L60: Prix bord champ mensuel = part fixe (66 % depuis mai 2026) du prix de référence net SICOM | M60: prix prod. C ; prix int. B | N60: APROMAC / CHPC ; Banque mondiale Pink Sheet (TSR20) | O60: https://www.worldbank.org/en/research/commodity-markets | Q60: =E60*G60*H60 -> 760.35 | R60: =I60/Q60 -> 0.39455514 | S60: =I60*K60/1000 -> 187.2 | T60: =Q60/Q59-1 -> -0.20821618 | U60: =I60/I59-1 -> -0.21052632 | V60: =S60/S59-1 -> -0.15063521 | W60: =IF(ABS(T60)>=0.05,U60/T60,"") -> 1.0110949 | X60: =MAX(I$53:I60) -> 950 | Y60: =I60/X60-1 -> -0.68421053 | Z60: =LN(I60/I59) -> -0.23638878 | AA60: =LN(K60/K59) -> 0.073122265 | AB60: =LN(S60/S59) -> -0.16326651
A61: Hévéa | B61: Côte d'Ivoire | C61: 2019 | D61: 2019 | E61: 1.41 | F61: USD/kg | G61: 586 | H61: 1 | I61: 300 | J61: FCFA | K61: 780 | L61: Prix bord champ mensuel = part fixe (66 % depuis mai 2026) du prix de référence net SICOM | M61: prix prod. C ; prix int. B | N61: APROMAC / CHPC ; Banque mondiale Pink Sheet (TSR20) | O61: https://www.worldbank.org/en/research/commodity-markets | Q61: =E61*G61*H61 -> 826.26 | R61: =I61/Q61 -> 0.36308184 | S61: =I61*K61/1000 -> 234 | T61: =Q61/Q60-1 -> 0.086683764 | U61: =I61/I60-1 -> 0 | V61: =S61/S60-1 -> 0.25 | W61: =IF(ABS(T61)>=0.05,U61/T61,"") -> 0 | X61: =MAX(I$53:I61) -> 950 | Y61: =I61/X61-1 -> -0.68421053 | Z61: =LN(I61/I60) -> 0 | AA61: =LN(K61/K60) -> 0.22314355 | AB61: =LN(S61/S60) -> 0.22314355
A62: Hévéa | B62: Côte d'Ivoire | C62: 2020 | D62: 2020 | E62: 1.33 | F62: USD/kg | G62: 575 | H62: 1 | I62: 290 | J62: FCFA | K62: 936 | L62: Prix bord champ mensuel = part fixe (66 % depuis mai 2026) du prix de référence net SICOM | M62: prix prod. C ; prix int. B | N62: APROMAC / CHPC ; Banque mondiale Pink Sheet (TSR20) | O62: https://www.worldbank.org/en/research/commodity-markets | Q62: =E62*G62*H62 -> 764.75 | R62: =I62/Q62 -> 0.37920889 | S62: =I62*K62/1000 -> 271.44 | T62: =Q62/Q61-1 -> -0.07444388 | U62: =I62/I61-1 -> -0.033333333 | V62: =S62/S61-1 -> 0.16 | W62: =IF(ABS(T62)>=0.05,U62/T62,"") -> 0.44776459 | X62: =MAX(I$53:I62) -> 950 | Y62: =I62/X62-1 -> -0.69473684 | Z62: =LN(I62/I61) -> -0.033901552 | AA62: =LN(K62/K61) -> 0.18232156 | AB62: =LN(S62/S61) -> 0.14842001
A63: Hévéa | B63: Côte d'Ivoire | C63: 2021 | D63: 2021 | E63: 1.75 | F63: USD/kg | G63: 554 | H63: 1 | I63: 400 | J63: FCFA | K63: 1100 | L63: Prix bord champ mensuel = part fixe (66 % depuis mai 2026) du prix de référence net SICOM | M63: prix prod. C ; prix int. B | N63: APROMAC / CHPC ; Banque mondiale Pink Sheet (TSR20) | O63: https://www.worldbank.org/en/research/commodity-markets | Q63: =E63*G63*H63 -> 969.5 | R63: =I63/Q63 -> 0.41258381 | S63: =I63*K63/1000 -> 440 | T63: =Q63/Q62-1 -> 0.26773455 | U63: =I63/I62-1 -> 0.37931034 | V63: =S63/S62-1 -> 0.62098438 | W63: =IF(ABS(T63)>=0.05,U63/T63,"") -> 1.4167403 | X63: =MAX(I$53:I63) -> 950 | Y63: =I63/X63-1 -> -0.57894737 | Z63: =LN(I63/I62) -> 0.32158362 | AA63: =LN(K63/K62) -> 0.16144998 | AB63: =LN(S63/S62) -> 0.48303361
A64: Hévéa | B64: Côte d'Ivoire | C64: 2022 | D64: 2022 | E64: 1.55 | F64: USD/kg | G64: 623 | H64: 1 | I64: 370 | J64: FCFA | K64: 1280 | L64: Prix bord champ mensuel = part fixe (66 % depuis mai 2026) du prix de référence net SICOM | M64: prix prod. C ; prix int. B | N64: APROMAC / CHPC ; Banque mondiale Pink Sheet (TSR20) | O64: https://www.worldbank.org/en/research/commodity-markets | Q64: =E64*G64*H64 -> 965.65 | R64: =I64/Q64 -> 0.3831616 | S64: =I64*K64/1000 -> 473.6 | T64: =Q64/Q63-1 -> -0.0039711191 | U64: =I64/I63-1 -> -0.075 | V64: =S64/S63-1 -> 0.076363636 | W64: =IF(ABS(T64)>=0.05,U64/T64,"") | X64: =MAX(I$53:I64) -> 950 | Y64: =I64/X64-1 -> -0.61052632 | Z64: =LN(I64/I63) -> -0.077961541 | AA64: =LN(K64/K63) -> 0.1515499 | AB64: =LN(S64/S63) -> 0.073588357
A65: Hévéa | B65: Côte d'Ivoire | C65: 2023 | D65: 2023 | E65: 1.4 | F65: USD/kg | G65: 607 | H65: 1 | I65: 330 | J65: FCFA | K65: 1450 | L65: Prix bord champ mensuel = part fixe (66 % depuis mai 2026) du prix de référence net SICOM | M65: prix prod. C ; prix int. B | N65: APROMAC / CHPC ; Banque mondiale Pink Sheet (TSR20) | O65: https://www.worldbank.org/en/research/commodity-markets | Q65: =E65*G65*H65 -> 849.8 | R65: =I65/Q65 -> 0.38832667 | S65: =I65*K65/1000 -> 478.5 | T65: =Q65/Q64-1 -> -0.119971 | U65: =I65/I64-1 -> -0.10810811 | V65: =S65/S64-1 -> 0.010346284 | W65: =IF(ABS(T65)>=0.05,U65/T65,"") -> 0.90111864 | X65: =MAX(I$53:I65) -> 950 | Y65: =I65/X65-1 -> -0.65263158 | Z65: =LN(I65/I64) -> -0.11441035 | AA65: =LN(K65/K64) -> 0.12470348 | AB65: =LN(S65/S64) -> 0.010293127
A66: Hévéa | B66: Côte d'Ivoire | C66: 2024 | D66: 2024 | E66: 1.7 | F66: USD/kg | G66: 607 | H66: 1 | I66: 380 | J66: FCFA | K66: 1550 | L66: Prix bord champ mensuel = part fixe (66 % depuis mai 2026) du prix de référence net SICOM | M66: prix prod. C ; prix int. B | N66: APROMAC / CHPC ; Banque mondiale Pink Sheet (TSR20) | O66: https://www.worldbank.org/en/research/commodity-markets | Q66: =E66*G66*H66 -> 1031.9 | R66: =I66/Q66 -> 0.36825274 | S66: =I66*K66/1000 -> 589 | T66: =Q66/Q65-1 -> 0.21428571 | U66: =I66/I65-1 -> 0.15151515 | V66: =S66/S65-1 -> 0.23092999 | W66: =IF(ABS(T66)>=0.05,U66/T66,"") -> 0.70707071 | X66: =MAX(I$53:I66) -> 950 | Y66: =I66/X66-1 -> -0.6 | Z66: =LN(I66/I65) -> 0.1410786 | AA66: =LN(K66/K65) -> 0.066691374 | AB66: =LN(S66/S65) -> 0.20776997
A67: Hévéa | B67: Côte d'Ivoire | C67: 2025 | D67: 2025 | E67: 1.75 | F67: USD/kg | G67: 580 | H67: 1 | I67: 420 | J67: FCFA | K67: 1600 | L67: Prix bord champ mensuel = part fixe (66 % depuis mai 2026) du prix de référence net SICOM | M67: prix prod. C ; prix int. B | N67: APROMAC / CHPC ; Banque mondiale Pink Sheet (TSR20) | O67: https://www.worldbank.org/en/research/commodity-markets | Q67: =E67*G67*H67 -> 1015 | R67: =I67/Q67 -> 0.4137931 | S67: =I67*K67/1000 -> 672 | T67: =Q67/Q66-1 -> -0.016377556 | U67: =I67/I66-1 -> 0.10526316 | V67: =S67/S66-1 -> 0.14091681 | W67: =IF(ABS(T67)>=0.05,U67/T67,"") | X67: =MAX(I$53:I67) -> 950 | Y67: =I67/X67-1 -> -0.55789474 | Z67: =LN(I67/I66) -> 0.10008346 | AA67: =LN(K67/K66) -> 0.031748698 | AB67: =LN(S67/S66) -> 0.13183216
A68: Hévéa | B68: Côte d'Ivoire | C68: 2026 | D68: 2026 | E68: 1.8 | F68: USD/kg | G68: 560 | H68: 1 | I68: 450 | J68: FCFA | K68: 1600 | L68: Prix bord champ mensuel = part fixe (66 % depuis mai 2026) du prix de référence net SICOM | M68: prix prod. A/C ; prix int. B | N68: APROMAC / CHPC ; Banque mondiale Pink Sheet (TSR20) | O68: https://www.worldbank.org/en/research/commodity-markets | P68: Nouveau mécanisme au 1er mai 2026 : part producteur 63 % -> 66 % ; 401 (avr.) -> 493 (juil.) | Q68: =E68*G68*H68 -> 1008 | R68: =I68/Q68 -> 0.44642857 | S68: =I68*K68/1000 -> 720 | T68: =Q68/Q67-1 -> -0.0068965517 | U68: =I68/I67-1 -> 0.071428571 | V68: =S68/S67-1 -> 0.071428571 | W68: =IF(ABS(T68)>=0.05,U68/T68,"") | X68: =MAX(I$53:I68) -> 950 | Y68: =I68/X68-1 -> -0.52631579 | Z68: =LN(I68/I67) -> 0.068992871 | AA68: =LN(K68/K67) -> 0 | AB68: =LN(S68/S67) -> 0.068992871

Sheet EPISODES
A1: id | B1: filiere | C1: pays | D1: sens | E1: episode | F1: t0 | G1: t2 | H1: int_t0 | I1: int_t2 | J1: unite_int | K1: fx_t0 | L1: fx_t2 | M1: conv | N1: prod_t0 | O1: prod_t2 | P1: monnaie | Q1: q_t0 | R1: q_t2 | S1: delai_reaction_mois | T1: delai_recup_mois | U1: recup_statut | V1: absorbeur | W1: cout_mds_fcfa | X1: mecanisme | Y1: qualite | Z1: source | AA1: url | AB1: commentaire | AC1: int_local_t0 | AD1: int_local_t2 | AE1: choc_int_usd | AF1: choc_int | AG1: choc_prod | AH1: transmission | AI1: amortissement | AJ1: recette_t0 | AK1: recette_t2 | AL1: var_recette | AM1: part_prod_t0 | AN1: part_prod_t2
A2: CAC-CI-16 | B2: Cacao | C2: Côte d'Ivoire | D2: baisse | E2: Chute des cours 2016-17 | F2: 2016-07 | G2: 2017-02 | H2: 3050 | I2: 1950 | J2: USD/t | K2: 590 | L2: 620 | M2: 0.001 | N2: 1100 | O2: 700 | P2: FCFA | Q2: 2020 | R2: 1964 | S2: 8 | T2: 42 | U2: partielle (1 000 FCFA en oct. 2020 = 91 % du niveau pré-choc) | V2: Acheteurs à terme pendant la campagne, puis producteurs ; défauts d'exportateurs absorbés par le CCC | X2: Ventes anticipées + prix garanti | Y2: B | Z2: CCC ; ICCO ; FMI (rapports art. IV 2017) | AA2: https://www.conseilcafecacao.ci/ | AB2: Prix principal maintenu 6 mois grâce aux ventes anticipées ; baisse de 36 % à la campagne intermédiaire | AC2: =H2*K2*M2 -> 1799.5 | AD2: =I2*L2*M2 -> 1209 | AE2: =I2/H2-1 -> -0.36065574 | AF2: =AD2/AC2-1 -> -0.32814671 | AG2: =O2/N2-1 -> -0.36363636 | AH2: =AG2/AF2 -> 1.1081518 | AI2: =1-AH2 -> -0.1081518 | AJ2: =N2*Q2/1000 -> 2222 | AK2: =O2*R2/1000 -> 1374.8 | AL2: =AK2/AJ2-1 -> -0.38127813 | AM2: =N2/AC2 -> 0.61128091 | AN2: =O2/AD2 -> 0.5789909
A3: CAC-GH-16 | B3: Cacao | C3: Ghana | D3: baisse | E3: Chute des cours 2016-17 | F3: 2016-07 | G3: 2017-02 | H3: 3050 | I3: 1950 | J3: USD/t | K3: 4 | L3: 4.4 | M3: 0.001 | N3: 7.6 | O3: 7.6 | P3: GHS | Q3: 969 | R3: 905 | T3: 0 | U3: sans objet (prix nominal maintenu) | V3: Cocobod (endettement) ; inflation/dépréciation du cedi pour le producteur | X3: Prix fixé + emprunts syndiqués | Y3: B | Z3: Cocobod ; Banque mondiale | AA3: https://cocobod.gh/ | AB3: Stabilité nominale ; le prix réel producteur baisse via l'inflation (~12 %/an) | AC3: =H3*K3*M3 -> 12.2 | AD3: =I3*L3*M3 -> 8.58 | AE3: =I3/H3-1 -> -0.36065574 | AF3: =AD3/AC3-1 -> -0.29672131 | AG3: =O3/N3-1 -> 0 | AH3: =AG3/AF3 -> 0 | AI3: =1-AH3 -> 1 | AJ3: =N3*Q3/1000 -> 7.3644 | AK3: =O3*R3/1000 -> 6.878 | AL3: =AK3/AJ3-1 -> -0.066047472 | AM3: =N3/AC3 -> 0.62295082 | AN3: =O3/AD3 -> 0.88578089
A4: CAC-CM-16 | B4: Cacao | C4: Cameroun | D4: baisse | E4: Chute des cours 2016-17 | F4: 2016-07 | G4: 2017-02 | H4: 3050 | I4: 1950 | J4: USD/t | K4: 590 | L4: 620 | M4: 0.001 | N4: 1450 | O4: 950 | P4: FCFA | Q4: 290 | R4: 280 | S4: 1 | U4: à documenter (ONCC) | V4: Producteurs (marché libéralisé) | X4: Marché libre, information prix ONCC | Y4: C | Z4: ONCC Cameroun (bulletins de prix) | AA4: https://www.oncc.cm/ | AB4: Ordres de grandeur ; transmission quasi immédiate | AC4: =H4*K4*M4 -> 1799.5 | AD4: =I4*L4*M4 -> 1209 | AE4: =I4/H4-1 -> -0.36065574 | AF4: =AD4/AC4-1 -> -0.32814671 | AG4: =O4/N4-1 -> -0.34482759 | AH4: =AG4/AF4 -> 1.0508336 | AI4: =1-AH4 -> -0.050833601 | AJ4: =N4*Q4/1000 -> 420.5 | AK4: =O4*R4/1000 -> 266 | AL4: =AK4/AJ4-1 -> -0.36741974 | AM4: =N4/AC4 -> 0.80577938 | AN4: =O4/AD4 -> 0.78577337
A5: CAC-EC-16 | B5: Cacao | C5: Équateur | D5: baisse | E5: Chute des cours 2016-17 | F5: 2016-07 | G5: 2017-02 | H5: 3050 | I5: 1950 | J5: USD/t | K5: 1 | L5: 1 | M5: 0.001 | N5: 2.6 | O5: 1.7 | P5: USD | Q5: 250 | R5: 290 | S5: 1 | U5: à documenter (MAG/Anecacao) | V5: Producteurs (marché libre) | X5: Marché libre, économie dollarisée | Y5: C | Z5: Anecacao ; MAG Équateur | AA5: https://anecacao.com/ | AB5: Production en hausse malgré la baisse des prix (productivité CCN-51) | AC5: =H5*K5*M5 -> 3.05 | AD5: =I5*L5*M5 -> 1.95 | AE5: =I5/H5-1 -> -0.36065574 | AF5: =AD5/AC5-1 -> -0.36065574 | AG5: =O5/N5-1 -> -0.34615385 | AH5: =AG5/AF5 -> 0.95979021 | AI5: =1-AH5 -> 0.04020979 | AJ5: =N5*Q5/1000 -> 0.65 | AK5: =O5*R5/1000 -> 0.493 | AL5: =AK5/AJ5-1 -> -0.24153846 | AM5: =N5/AC5 -> 0.85245902 | AN5: =O5/AD5 -> 0.87179487
A6: CAC-CI-24 | B6: Cacao | C6: Côte d'Ivoire | D6: hausse | E6: Envolée 2023-25 | F6: 2022/23 | G6: 2024/25 | H6: 2750 | I6: 8000 | J6: USD/t | K6: 615 | L6: 580 | M6: 0.001 | N6: 900 | O6: 1800 | P6: FCFA | Q6: 2241 | R6: 1850 | S6: 7 | V6: Hausse captée par les acheteurs à terme (ventes 2023-24 conclues avant l'envolée) puis CCC/État | X6: Ventes anticipées | Y6: B | Z6: CCC ; ICCO | AA6: https://www.conseilcafecacao.ci/ | AB6: Prix principal à prix principal ; part producteur tombée à ~40 % du prix mondial | AC6: =H6*K6*M6 -> 1691.25 | AD6: =I6*L6*M6 -> 4640 | AE6: =I6/H6-1 -> 1.9090909 | AF6: =AD6/AC6-1 -> 1.7435329 | AG6: =O6/N6-1 -> 1 | AH6: =AG6/AF6 -> 0.57354811 | AI6: =1-AH6 -> 0.42645189 | AJ6: =N6*Q6/1000 -> 2016.9 | AK6: =O6*R6/1000 -> 3330 | AL6: =AK6/AJ6-1 -> 0.65104864 | AM6: =N6/AC6 -> 0.53215078 | AN6: =O6/AD6 -> 0.38793103
A7: CAC-GH-24 | B7: Cacao | C7: Ghana | D7: hausse | E7: Envolée 2023-25 | F7: 2022/23 | G7: 2024/25 | H7: 2750 | I7: 8000 | J7: USD/t | K7: 11 | L7: 15 | M7: 0.001 | N7: 12.8 | O7: 49.6 | P7: GHS | Q7: 654 | R7: 600 | S7: 6 | V7: Cocobod (contrats reportés de 2023/24, pertes > 1 Md USD) | X7: Ventes à terme | Y7: B | Z7: Cocobod ; Ministère des Finances du Ghana | AA7: https://www.isd.gov.gh/?p=8702 | AB7: Production 2023/24 de 432 kt vs 800 kt prévues : contrats non honorés | AC7: =H7*K7*M7 -> 30.25 | AD7: =I7*L7*M7 -> 120 | AE7: =I7/H7-1 -> 1.9090909 | AF7: =AD7/AC7-1 -> 2.9669421 | AG7: =O7/N7-1 -> 2.875 | AH7: =AG7/AF7 -> 0.96901114 | AI7: =1-AH7 -> 0.030988858 | AJ7: =N7*Q7/1000 -> 8.3712 | AK7: =O7*R7/1000 -> 29.76 | AL7: =AK7/AJ7-1 -> 2.5550459 | AM7: =N7/AC7 -> 0.4231405 | AN7: =O7/AD7 -> 0.41333333
A8: CAC-CM-24 | B8: Cacao | C8: Cameroun | D8: hausse | E8: Envolée 2023-25 | F8: 2022/23 | G8: 2024/25 | H8: 2750 | I8: 8000 | J8: USD/t | K8: 615 | L8: 580 | M8: 0.001 | N8: 1350 | O8: 4500 | P8: FCFA | Q8: 295 | R8: 300 | S8: 1 | V8: Producteurs bénéficiaires (marché libre) | X8: Marché libre | Y8: C | Z8: ONCC Cameroun | AA8: https://www.oncc.cm/ | AB8: Prix bord champ ayant dépassé 5 000 FCFA/kg au pic | AC8: =H8*K8*M8 -> 1691.25 | AD8: =I8*L8*M8 -> 4640 | AE8: =I8/H8-1 -> 1.9090909 | AF8: =AD8/AC8-1 -> 1.7435329 | AG8: =O8/N8-1 -> 2.3333333 | AH8: =AG8/AF8 -> 1.3382789 | AI8: =1-AH8 -> -0.33827893 | AJ8: =N8*Q8/1000 -> 398.25 | AK8: =O8*R8/1000 -> 1350 | AL8: =AK8/AJ8-1 -> 2.3898305 | AM8: =N8/AC8 -> 0.79822616 | AN8: =O8/AD8 -> 0.96982759
A9: CAC-CI-26 | B9: Cacao | C9: Côte d'Ivoire | D9: baisse | E9: Retournement 2025-26 | F9: 2024/25 | G9: 2026-03 | H9: 8000 | I9: 2860 | J9: USD/t | K9: 580 | L9: 565 | M9: 0.001 | N9: 2800 | O9: 1200 | P9: FCFA | Q9: 1850 | R9: 1800 | S9: 15 | U9: en cours (1 200 FCFA reconduit pour 2026/27) | V9: CCC/État (rachat d'invendus ~200 kt au prix garanti), puis producteurs (-57 %) | W9: 240 | X9: Ventes anticipées + prix garanti + rachat public | Y9: A (prix) / C (coût) | Z9: Gouvernement CI ; Jeune Afrique ; AllAfrica (invendus) | AA9: https://www.jeuneafrique.com/1771206/economie-entreprises/crise-du-cacao-la-cote-divoire-reduit-de-pres-de-60-le-prix-dachat-aux-producteurs/ ; https://www.gouv.ci/actualite/campagne-principale-2026-2027-le-prix-bord-champ-du-cacao-est-fixe-a-1200-fcfa-le-kg-le-prix-du-cafe-setablit-a-1300-fcfa-le-kg-8771 ; https://fr.allafrica.com/stories/202602280103.html | AB9: Coût = estimation : 200 kt x (2 800 - ~1 600 FCFA/kg de valeur de revente). Prix relevé à contre-courant en oct. 2025 | AC9: =H9*K9*M9 -> 4640 | AD9: =I9*L9*M9 -> 1615.9 | AE9: =I9/H9-1 -> -0.6425 | AF9: =AD9/AC9-1 -> -0.65174569 | AG9: =O9/N9-1 -> -0.57142857 | AH9: =AG9/AF9 -> 0.87676617 | AI9: =1-AH9 -> 0.12323383 | AJ9: =N9*Q9/1000 -> 5180 | AK9: =O9*R9/1000 -> 2160 | AL9: =AK9/AJ9-1 -> -0.58301158 | AM9: =N9/AC9 -> 0.60344828 | AN9: =O9/AD9 -> 0.74262021
A10: CAC-GH-26 | B10: Cacao | C10: Ghana | D10: baisse | E10: Retournement 2025-26 | F10: 2025-10 | G10: 2026-02 | H10: 6000 | I10: 4100 | J10: USD/t | K10: 11.5 | L10: 11 | M10: 0.001 | N10: 58 | O10: 41.392 | P10: GHS | Q10: 600 | R10: 650 | S10: 4 | U10: 42 400 GHS/t en sept. 2026 | V10: Cocobod (défaut sur facilité relais 70 M USD ; dette héritée 5,8 Mds GHS) puis producteurs | X10: Prix fixé ; Act 1182 (2026) : >= 70 % FOB | Y10: A | Z10: Gouvernement du Ghana (ISD) ; GNA | AA10: https://www.isd.gov.gh/?p=8702 ; https://gna.org.gh/2026/09/ghana-opens-2026-27-cocoa-season-with-producer-price-of-ghc-42400-per-tonne/ | AB10: Nouveau prix = 90 % du FOB brut à 4 200 USD/t | AC10: =H10*K10*M10 -> 69 | AD10: =I10*L10*M10 -> 45.1 | AE10: =I10/H10-1 -> -0.31666667 | AF10: =AD10/AC10-1 -> -0.34637681 | AG10: =O10/N10-1 -> -0.28634483 | AH10: =AG10/AF10 -> 0.8266859 | AI10: =1-AH10 -> 0.1733141 | AJ10: =N10*Q10/1000 -> 34.8 | AK10: =O10*R10/1000 -> 26.9048 | AL10: =AK10/AJ10-1 -> -0.22687356 | AM10: =N10/AC10 -> 0.84057971 | AN10: =O10/AD10 -> 0.91778271
A11: CAF-CI-24 | B11: Café | C11: Côte d'Ivoire | D11: hausse | E11: Envolée robusta 2023-25 | F11: 2022/23 | G11: 2024/25 | H11: 2.25 | I11: 4.8 | J11: USD/kg | K11: 615 | L11: 580 | M11: 1 | N11: 900 | O11: 1500 | P11: FCFA | Q11: 80 | R11: 60 | S11: 12 | V11: CCC / acheteurs à terme | X11: Prix minimum garanti (campagne unique) | Y11: B/C | Z11: CCC ; Banque mondiale (robusta) | AA11: https://www.fratmat.info/article/2637237/economie/cafe-cacao/agriculture-les-prix-bord-champs-du-cafe-et-du-cacao-respectivement-fixes-a-1700-fcfa-et-2800-fcfa-pour-la-campagne-2025-2026 | AB11: Volumes ivoiriens marginaux et en déclin structurel | AC11: =H11*K11*M11 -> 1383.75 | AD11: =I11*L11*M11 -> 2784 | AE11: =I11/H11-1 -> 1.1333333 | AF11: =AD11/AC11-1 -> 1.0119241 | AG11: =O11/N11-1 -> 0.66666667 | AH11: =AG11/AF11 -> 0.65881093 | AI11: =1-AH11 -> 0.34118907 | AJ11: =N11*Q11/1000 -> 72 | AK11: =O11*R11/1000 -> 90 | AL11: =AK11/AJ11-1 -> 0.25 | AM11: =N11/AC11 -> 0.6504065 | AN11: =O11/AD11 -> 0.5387931
A12: CAF-CI-26 | B12: Café | C12: Côte d'Ivoire | D12: baisse | E12: Repli robusta 2025-26 | F12: 2025/26 | G12: 2026-07 | H12: 4.6 | I12: 3.7 | J12: USD/kg | K12: 570 | L12: 560 | M12: 1 | N12: 1700 | O12: 1300 | P12: FCFA | Q12: 60 | R12: 60 | S12: 10 | U12: en cours | V12: Producteurs (à la campagne suivante) | X12: Prix minimum garanti | Y12: A (prix prod.) / C (prix int.) | Z12: Gouvernement CI | AA12: https://www.gouv.ci/actualite/campagne-principale-2026-2027-le-prix-bord-champ-du-cacao-est-fixe-a-1200-fcfa-le-kg-le-prix-du-cafe-setablit-a-1300-fcfa-le-kg-8771 | AC12: =H12*K12*M12 -> 2622 | AD12: =I12*L12*M12 -> 2072 | AE12: =I12/H12-1 -> -0.19565217 | AF12: =AD12/AC12-1 -> -0.20976354 | AG12: =O12/N12-1 -> -0.23529412 | AH12: =AG12/AF12 -> 1.1217112 | AI12: =1-AH12 -> -0.12171123 | AJ12: =N12*Q12/1000 -> 102 | AK12: =O12*R12/1000 -> 78 | AL12: =AK12/AJ12-1 -> -0.23529412 | AM12: =N12/AC12 -> 0.64836003 | AN12: =O12/AD12 -> 0.62741313
A13: CAF-VN-24 | B13: Café | C13: Vietnam | D13: hausse | E13: Envolée robusta 2023-25 | F13: 2022/23 | G13: 2024/25 | H13: 2.25 | I13: 4.8 | J13: USD/kg | K13: 23500 | L13: 25300 | M13: 1 | N13: 41000 | O13: 120000 | P13: VND | Q13: 1800 | R13: 1700 | S13: 0 | V13: Producteurs bénéficiaires | X13: Marché libre ; diversification (durian, poivre) | Y13: B/C | Z13: USDA FAS (GAIN Vietnam Coffee Annual) | AA13: https://fas.usda.gov/data | AC13: =H13*K13*M13 -> 52875 | AD13: =I13*L13*M13 -> 121440 | AE13: =I13/H13-1 -> 1.1333333 | AF13: =AD13/AC13-1 -> 1.2967376 | AG13: =O13/N13-1 -> 1.9268293 | AH13: =AG13/AF13 -> 1.4859053 | AI13: =1-AH13 -> -0.48590531 | AJ13: =N13*Q13/1000 -> 73800 | AK13: =O13*R13/1000 -> 204000 | AL13: =AK13/AJ13-1 -> 1.7642276 | AM13: =N13/AC13 -> 0.77541371 | AN13: =O13/AD13 -> 0.98814229
A14: COT-CI-20 | B14: Coton | C14: Côte d'Ivoire | D14: baisse | E14: Choc COVID 2020 | F14: 2020-01 | G14: 2020-04 | H14: 0.79 | I14: 0.66 | J14: USD/lb | K14: 590 | L14: 605 | M14: 2.20462 | N14: 300 | O14: 300 | P14: FCFA | Q14: 490 | R14: 560 | T14: 0 | U14: sans objet (prix maintenu) | V14: État (soutien budgétaire) et sociétés cotonnières | X14: Prix administré + soutien public | Y14: B | Z14: CCA ; ICAC | AA14: https://www.conseilcotonanacarde.ci/ | AB14: Montant du soutien 2020/21 à confirmer auprès du Ministère du Budget | AC14: =H14*K14*M14 -> 1027.5734 | AD14: =I14*L14*M14 -> 880.30477 | AE14: =I14/H14-1 -> -0.16455696 | AF14: =AD14/AC14-1 -> -0.14331688 | AG14: =O14/N14-1 -> 0 | AH14: =AG14/AF14 -> 0 | AI14: =1-AH14 -> 1 | AJ14: =N14*Q14/1000 -> 147 | AK14: =O14*R14/1000 -> 168 | AL14: =AK14/AJ14-1 -> 0.14285714 | AM14: =N14/AC14 -> 0.29194995 | AN14: =O14/AD14 -> 0.34079107
A15: COT-ML-20 | B15: Coton | C15: Mali | D15: baisse | E15: Choc COVID 2020 | F15: 2020-01 | G15: 2020-04 | H15: 0.79 | I15: 0.66 | J15: USD/lb | K15: 590 | L15: 605 | M15: 2.20462 | N15: 275 | O15: 200 | P15: FCFA | Q15: 717 | R15: 147 | S15: 3 | T15: 12 | U15: 280 FCFA et ~760 kt en 2021/22 | V15: Producteurs (boycott des semis) | X15: Prix administré CMDT | Y15: B | Z15: CMDT ; ICAC ; USDA | AA15: https://www.icac.org/ | AB15: Baisse annoncée avant semis : réaction d'offre extrême (-80 %) | AC15: =H15*K15*M15 -> 1027.5734 | AD15: =I15*L15*M15 -> 880.30477 | AE15: =I15/H15-1 -> -0.16455696 | AF15: =AD15/AC15-1 -> -0.14331688 | AG15: =O15/N15-1 -> -0.27272727 | AH15: =AG15/AF15 -> 1.9029668 | AI15: =1-AH15 -> -0.90296679 | AJ15: =N15*Q15/1000 -> 197.175 | AK15: =O15*R15/1000 -> 29.4 | AL15: =AK15/AJ15-1 -> -0.85089388 | AM15: =N15/AC15 -> 0.26762079 | AN15: =O15/AD15 -> 0.22719404
A16: COT-BF-20 | B16: Coton | C16: Burkina Faso | D16: baisse | E16: Choc COVID 2020 | F16: 2020-01 | G16: 2020-04 | H16: 0.79 | I16: 0.66 | J16: USD/lb | K16: 590 | L16: 605 | M16: 2.20462 | N16: 265 | O16: 250 | P16: FCFA | Q16: 637 | R16: 470 | S16: 3 | U16: à documenter (AICB) | V16: Fonds de lissage AICB + État | X16: Fonds de lissage (prix plancher + moyenne mobile) | Y16: C | Z16: AICB ; Kaminski et al. (IFPRI) | AA16: https://www.ifpri.org/ | AC16: =H16*K16*M16 -> 1027.5734 | AD16: =I16*L16*M16 -> 880.30477 | AE16: =I16/H16-1 -> -0.16455696 | AF16: =AD16/AC16-1 -> -0.14331688 | AG16: =O16/N16-1 -> -0.056603774 | AH16: =AG16/AF16 -> 0.39495537 | AI16: =1-AH16 -> 0.60504463 | AJ16: =N16*Q16/1000 -> 168.805 | AK16: =O16*R16/1000 -> 117.5 | AL16: =AK16/AJ16-1 -> -0.30393057 | AM16: =N16/AC16 -> 0.25788912 | AN16: =O16/AD16 -> 0.28399256
A17: COT-CI-22 | B17: Coton | C17: Côte d'Ivoire | D17: hausse | E17: Envolée 2021-22 | F17: 2019/20 | G17: 2021/22 | H17: 0.72 | I17: 1.3 | J17: USD/lb | K17: 590 | L17: 590 | M17: 2.20462 | N17: 300 | O17: 300 | P17: FCFA | Q17: 490 | R17: 560 | V17: Sociétés cotonnières (marge) ; pas de réserve constituée | X17: Prix administré | Y17: B | Z17: CCA ; ICAC | AA17: https://www.conseilcotonanacarde.ci/ | AB17: Hausse quasi non transmise et non mise en réserve | AC17: =H17*K17*M17 -> 936.52258 | AD17: =I17*L17*M17 -> 1690.9435 | AE17: =I17/H17-1 -> 0.80555556 | AF17: =AD17/AC17-1 -> 0.80555556 | AG17: =O17/N17-1 -> 0 | AH17: =AG17/AF17 -> 0 | AI17: =1-AH17 -> 1 | AJ17: =N17*Q17/1000 -> 147 | AK17: =O17*R17/1000 -> 168 | AL17: =AK17/AJ17-1 -> 0.14285714 | AM17: =N17/AC17 -> 0.32033398 | AN17: =O17/AD17 -> 0.17741574
A18: ANA-CI-19 | B18: Anacarde | C18: Côte d'Ivoire | D18: baisse | E18: Effondrement 2018-19 | F18: 2018-S1 | G18: 2019 | H18: 1700 | I18: 1150 | J18: USD/t | K18: 555 | L18: 586 | M18: 0.001 | N18: 550 | O18: 330 | P18: FCFA | Q18: 761 | R18: 634 | S18: 2 | T18: 72 | U18: prix de marché > 550 FCFA seulement fin 2024 | V18: Producteurs (plancher non respecté) | X18: Prix plancher sans fonds | Y18: C | Z18: CCA ; RONGEAD/N'kalô | AA18: https://www.conseilcotonanacarde.ci/ | AB18: Prix effectivement payés ; plancher officiel 500 -> 375 | AC18: =H18*K18*M18 -> 943.5 | AD18: =I18*L18*M18 -> 673.9 | AE18: =I18/H18-1 -> -0.32352941 | AF18: =AD18/AC18-1 -> -0.28574457 | AG18: =O18/N18-1 -> -0.4 | AH18: =AG18/AF18 -> 1.3998516 | AI18: =1-AH18 -> -0.39985163 | AJ18: =N18*Q18/1000 -> 418.55 | AK18: =O18*R18/1000 -> 209.22 | AL18: =AK18/AJ18-1 -> -0.50013141 | AM18: =N18/AC18 -> 0.58293588 | AN18: =O18/AD18 -> 0.4896869
A19: ANA-TZ-19 | B19: Anacarde | C19: Tanzanie | D19: baisse | E19: Effondrement 2018-19 | F19: 2017/18 | G19: 2019/20 | H19: 1700 | I19: 1150 | J19: USD/t | K19: 2250 | L19: 2300 | M19: 0.001 | N19: 3.5 | O19: 2.6 | P19: TZS (milliers) | Q19: 313 | R19: 225 | S19: 1 | U19: à documenter (CBT) | V19: Producteurs ; intervention publique coûteuse en 2018 (achat par l'État) | X19: Récépissés d'entrepôt + enchères | Y19: C | Z19: Cashewnut Board of Tanzania | AA19: https://www.cashewnut.go.tz/ | AB19: Enchères : transmission rapide mais transparente | AC19: =H19*K19*M19 -> 3825 | AD19: =I19*L19*M19 -> 2645 | AE19: =I19/H19-1 -> -0.32352941 | AF19: =AD19/AC19-1 -> -0.30849673 | AG19: =O19/N19-1 -> -0.25714286 | AH19: =AG19/AF19 -> 0.83353511 | AI19: =1-AH19 -> 0.16646489 | AJ19: =N19*Q19/1000 -> 1.0955 | AK19: =O19*R19/1000 -> 0.585 | AL19: =AK19/AJ19-1 -> -0.46599726 | AM19: =N19/AC19 -> 0.00091503268 | AN19: =O19/AD19 -> 0.00098298677
A20: ANA-CI-24 | B20: Anacarde | C20: Côte d'Ivoire | D20: hausse | E20: Rebond 2024 | F20: 2024-T1 | G20: 2024-T4 | H20: 1050 | I20: 1650 | J20: USD/t | K20: 605 | L20: 605 | M20: 0.001 | N20: 300 | O20: 600 | P20: FCFA | Q20: 1100 | R20: 1100 | S20: 1 | V20: Producteurs bénéficiaires | X20: Marché (plancher non contraignant à la hausse) | Y20: C | Z20: CCA ; presse spécialisée | AA20: https://www.conseilcotonanacarde.ci/ | AB20: Plancher 275 ; prix de marché 500-700 | AC20: =H20*K20*M20 -> 635.25 | AD20: =I20*L20*M20 -> 998.25 | AE20: =I20/H20-1 -> 0.57142857 | AF20: =AD20/AC20-1 -> 0.57142857 | AG20: =O20/N20-1 -> 1 | AH20: =AG20/AF20 -> 1.75 | AI20: =1-AH20 -> -0.75 | AJ20: =N20*Q20/1000 -> 330 | AK20: =O20*R20/1000 -> 660 | AL20: =AK20/AJ20-1 -> 1 | AM20: =N20/AC20 -> 0.47225502 | AN20: =O20/AD20 -> 0.60105184
A21: HEV-CI-16 | B21: Hévéa | C21: Côte d'Ivoire | D21: baisse | E21: Super-cycle baissier 2011-16 | F21: 2011 | G21: 2016 | H21: 4.52 | I21: 1.37 | J21: USD/kg | K21: 471 | L21: 593 | M21: 1 | N21: 950 | O21: 260 | P21: FCFA | Q21: 235 | R21: 453 | S21: 1 | U21: non récupéré (493 FCFA en juil. 2026) | V21: Producteurs ; amortisseur de change (dépréciation EUR/USD) | X21: Prix mensuel indexé SICOM | Y21: C (prix prod.) / B (int.) | Z21: APROMAC ; Banque mondiale | AA21: https://www.worldbank.org/en/research/commodity-markets | AB21: Volumes en forte hausse (jeunes plantations) : recette moins touchée que le prix | AC21: =H21*K21*M21 -> 2128.92 | AD21: =I21*L21*M21 -> 812.41 | AE21: =I21/H21-1 -> -0.69690265 | AF21: =AD21/AC21-1 -> -0.61839336 | AG21: =O21/N21-1 -> -0.72631579 | AH21: =AG21/AF21 -> 1.1745207 | AI21: =1-AH21 -> -0.17452067 | AJ21: =N21*Q21/1000 -> 223.25 | AK21: =O21*R21/1000 -> 117.78 | AL21: =AK21/AJ21-1 -> -0.47243001 | AM21: =N21/AC21 -> 0.44623565 | AN21: =O21/AD21 -> 0.32003545
A22: HEV-TH-16 | B22: Hévéa | C22: Thaïlande | D22: baisse | E22: Super-cycle baissier 2011-16 | F22: 2011 | G22: 2016 | H22: 4.52 | I22: 1.37 | J22: USD/kg | K22: 30.5 | L22: 35.3 | M22: 1 | N22: 140 | O22: 45 | P22: THB | Q22: 3570 | R22: 4470 | S22: 0 | U22: non récupéré | V22: Producteurs puis État (achats publics 2012-13, aides à la surface, garantie de revenu 2019-22) | X22: Rubber Authority of Thailand ; cess à l'export | Y22: B/C | Z22: Rubber Authority of Thailand ; IRSG | AA22: https://www.raot.co.th/ | AC22: =H22*K22*M22 -> 137.86 | AD22: =I22*L22*M22 -> 48.361 | AE22: =I22/H22-1 -> -0.69690265 | AF22: =AD22/AC22-1 -> -0.64920209 | AG22: =O22/N22-1 -> -0.67857143 | AH22: =AG22/AF22 -> 1.0452391 | AI22: =1-AH22 -> -0.045239133 | AJ22: =N22*Q22/1000 -> 499.8 | AK22: =O22*R22/1000 -> 201.15 | AL22: =AK22/AJ22-1 -> -0.59753902 | AM22: =N22/AC22 -> 1.015523 | AN22: =O22/AD22 -> 0.93050185
A23: HEV-CI-26 | B23: Hévéa | C23: Côte d'Ivoire | D23: hausse | E23: Remontée 2026 | F23: 2026-04 | G23: 2026-07 | H23: 1.65 | I23: 1.85 | J23: USD/kg | K23: 560 | L23: 560 | M23: 1 | N23: 401 | O23: 493 | P23: FCFA | Q23: 1600 | R23: 1600 | S23: 1 | V23: Producteurs bénéficiaires | X23: Nouveau mécanisme (66 % du prix net) | Y23: A (prix prod.) / C (int.) | Z23: Sika Finance ; AIP | AA23: https://www.sikafinance.com/marches/cote-d-ivoire-fin-de-la-decote-et-meilleure-remuneration-des-planteurs-la-campagne-heveicole-2026-demarre-sous-de-bons-auspices_62460 | AB23: Effet combiné hausse des cours + hausse de la part producteur | AC23: =H23*K23*M23 -> 924 | AD23: =I23*L23*M23 -> 1036 | AE23: =I23/H23-1 -> 0.12121212 | AF23: =AD23/AC23-1 -> 0.12121212 | AG23: =O23/N23-1 -> 0.22942643 | AH23: =AG23/AF23 -> 1.8927681 | AI23: =1-AH23 -> -0.89276808 | AJ23: =N23*Q23/1000 -> 641.6 | AK23: =O23*R23/1000 -> 788.8 | AL23: =AK23/AJ23-1 -> 0.22942643 | AM23: =N23/AC23 -> 0.43398268 | AN23: =O23/AD23 -> 0.47586873
A24: PAL-CI-22 | B24: Palmier à huile | C24: Côte d'Ivoire | D24: baisse | E24: Retournement 2022 | F24: 2022-03 | G24: 2022-10 | H24: 1780 | I24: 890 | J24: USD/t | K24: 595 | L24: 655 | M24: 0.001 | N24: 120 | O24: 80 | P24: FCFA | Q24: 2500 | R24: 2500 | S24: 1 | U24: à documenter (AIPH/CHPC) | V24: Producteurs de régimes et huileries ; marché régional partiellement protégé (TEC UEMOA) | X24: Prix mensuel des régimes indexé sur l'huile brute | Y24: C | Z24: AIPH ; Banque mondiale | AA24: https://www.worldbank.org/en/research/commodity-markets | AB24: Prix régimes (FCFA/kg) à valider auprès de l'AIPH/CHPC | AC24: =H24*K24*M24 -> 1059.1 | AD24: =I24*L24*M24 -> 582.95 | AE24: =I24/H24-1 -> -0.5 | AF24: =AD24/AC24-1 -> -0.44957983 | AG24: =O24/N24-1 -> -0.33333333 | AH24: =AG24/AF24 -> 0.74143302 | AI24: =1-AH24 -> 0.25856698 | AJ24: =N24*Q24/1000 -> 300 | AK24: =O24*R24/1000 -> 200 | AL24: =AK24/AJ24-1 -> -0.33333333 | AM24: =N24/AC24 -> 0.11330375 | AN24: =O24/AD24 -> 0.13723304
A25: PAL-ID-22 | B25: Palmier à huile | C25: Indonésie | D25: baisse | E25: Retournement 2022 | F25: 2022-03 | G25: 2022-07 | H25: 1780 | I25: 1050 | J25: USD/t | K25: 14350 | L25: 14950 | M25: 0.001 | N25: 3800 | O25: 1600 | P25: IDR | Q25: 46000 | R25: 46000 | S25: 1 | T25: 4 | U25: partielle après levée de l'interdiction et du prélèvement | V25: Petits planteurs (interdiction d'exporter avr.-mai 2022) | X25: Fonds BPDPKS (prélèvement export progressif) | Y25: C | Z25: BPDPKS ; USDA | AA25: https://www.bpdp.or.id/ | AB25: Choc amplifié par une mesure commerciale nationale | AC25: =H25*K25*M25 -> 25543 | AD25: =I25*L25*M25 -> 15697.5 | AE25: =I25/H25-1 -> -0.41011236 | AF25: =AD25/AC25-1 -> -0.38544807 | AG25: =O25/N25-1 -> -0.57894737 | AH25: =AG25/AF25 -> 1.5020113 | AI25: =1-AH25 -> -0.50201134 | AJ25: =N25*Q25/1000 -> 174800 | AK25: =O25*R25/1000 -> 73600 | AL25: =AK25/AJ25-1 -> -0.57894737 | AM25: =N25/AC25 -> 0.14876874 | AN25: =O25/AD25 -> 0.10192706
A26: RIZ-CI-23 | B26: Riz (importé) | C26: Côte d'Ivoire | D26: hausse | E26: Restrictions indiennes 2023 | F26: 2023-06 | G26: 2024-01 | H26: 515 | I26: 660 | J26: USD/t | K26: 605 | L26: 605 | M26: 0.001 | N26: 425 | O26: 475 | P26: FCFA | Q26: 1500 | R26: 1500 | S26: 2 | V26: Importateurs et État (plafonnement, mesures fiscales) | X26: Prix plafonnés ; régime fiscal à l'importation | Y26: C | Z26: FAO GIEWS FPMA ; Conseil national de lutte contre la vie chère | AA26: https://fpma.fao.org/ | AB26: Prix consommateur (riz brisé importé) ; Q = importations | AC26: =H26*K26*M26 -> 311.575 | AD26: =I26*L26*M26 -> 399.3 | AE26: =I26/H26-1 -> 0.2815534 | AF26: =AD26/AC26-1 -> 0.2815534 | AG26: =O26/N26-1 -> 0.11764706 | AH26: =AG26/AF26 -> 0.4178499 | AI26: =1-AH26 -> 0.5821501 | AJ26: =N26*Q26/1000 -> 637.5 | AK26: =O26*R26/1000 -> 712.5 | AL26: =AK26/AJ26-1 -> 0.11764706 | AM26: =N26/AC26 -> 1.3640376 | AN26: =O26/AD26 -> 1.1895818

Sheet INDICATEURS
A1: filiere | B1: pays | C1: periode | D1: n_obs | E1: I1_CV_prix_int | F1: I2_CV_prix_prod | G1: CV_recette | H1: I3_beta_baisse_annuel | I1: I4_beta_hausse_annuel | J1: I3b_beta_baisse_episodes | K1: I4b_beta_hausse_episodes | L1: I5_amortissement_baisses | M1: I6_drawdown_max_prod | N1: I7_baisse_max_recette | O1: part_variance_recette_due_Q | P1: correl_dlnP_dlnQ | Q1: I8_recup_max_mois | R1: I9_cout_observe_mds | S1: nb_chocs_int_15pct | T1: nb_chocs_int_20pct
A2: Cacao | B2: Côte d'Ivoire | C2: =SERIES!C2:C2&" – "&SERIES!C15:C15 -> 2012/13 – 2025/26 | D2: 14 | E2: =STDEV(SERIES!Q2:Q15)/AVERAGE(SERIES!Q2:Q15) -> 0.55528569 | F2: =STDEV(SERIES!I2:I15)/AVERAGE(SERIES!I2:I15) -> 0.47854841 | G2: =STDEV(SERIES!S2:S15)/AVERAGE(SERIES!S2:S15) -> 0.46379817 | H2: =IFERROR(AVERAGEIFS(SERIES!W3:W15,SERIES!T3:T15,"<-0.05"),"") -> 0.45841887 | I2: =IFERROR(AVERAGEIFS(SERIES!W3:W15,SERIES!T3:T15,">0.05"),"") -> 0.73758878 | J2: =IFERROR(AVERAGEIFS(EPISODES!$AH$2:$AH$26,EPISODES!$B$2:$B$26,A2,EPISODES!$C$2:$C$26,B2,EPISODES!$D$2:$D$26,"baisse"),"") -> 0.99245898 | K2: =IFERROR(AVERAGEIFS(EPISODES!$AH$2:$AH$26,EPISODES!$B$2:$B$26,A2,EPISODES!$C$2:$C$26,B2,EPISODES!$D$2:$D$26,"hausse"),"") -> 0.57354811 | L2: =IF(ISNUMBER(H2),1-H2,"") -> 0.54158113 | M2: =MIN(SERIES!Y2:Y15) -> -0.30392157 | N2: =MIN(SERIES!V3:V15) -> -0.32321879 | O2: =VAR(SERIES!AA3:AA15)/(VAR(SERIES!Z3:Z15)+VAR(SERIES!AA3:AA15)) -> 0.26752603 | P2: =CORREL(SERIES!Z3:Z15,SERIES!AA3:AA15) -> -0.042156913 | Q2: =IFERROR(_xlfn.MAXIFS(EPISODES!$T$2:$T$26,EPISODES!$B$2:$B$26,A2,EPISODES!$C$2:$C$26,B2),"") -> 42 | R2: =SUMIFS(EPISODES!$W$2:$W$26,EPISODES!$B$2:$B$26,A2,EPISODES!$C$2:$C$26,B2) -> 240 | S2: =COUNTIF(SERIES!T3:T15,"<=-0.15") -> 2 | T2: =COUNTIF(SERIES!T3:T15,"<=-0.2") -> 2
A3: Cacao | B3: Ghana | C3: =SERIES!C16:C16&" – "&SERIES!C29:C29 -> 2012/13 – 2025/26 | D3: 14 | E3: =STDEV(SERIES!Q16:Q29)/AVERAGE(SERIES!Q16:Q29) -> 1.2054897 | F3: =STDEV(SERIES!I16:I29)/AVERAGE(SERIES!I16:I29) -> 1.0611972 | G3: =STDEV(SERIES!S16:S29)/AVERAGE(SERIES!S16:S29) -> 0.92206423 | H3: =IFERROR(AVERAGEIFS(SERIES!W17:W29,SERIES!T17:T29,"<-0.05"),"") -> -0.32731639 | I3: =IFERROR(AVERAGEIFS(SERIES!W17:W29,SERIES!T17:T29,">0.05"),"") -> 0.69572714 | J3: =IFERROR(AVERAGEIFS(EPISODES!$AH$2:$AH$26,EPISODES!$B$2:$B$26,A3,EPISODES!$C$2:$C$26,B3,EPISODES!$D$2:$D$26,"baisse"),"") -> 0.41334295 | K3: =IFERROR(AVERAGEIFS(EPISODES!$AH$2:$AH$26,EPISODES!$B$2:$B$26,A3,EPISODES!$C$2:$C$26,B3,EPISODES!$D$2:$D$26,"hausse"),"") -> 0.96901114 | L3: =IF(ISNUMBER(H3),1-H3,"") -> 1.3273164 | M3: =MIN(SERIES!Y16:Y29) -> -0.004008016 | N3: =MIN(SERIES!V17:V29) -> -0.34765998 | O3: =VAR(SERIES!AA17:AA29)/(VAR(SERIES!Z17:Z29)+VAR(SERIES!AA17:AA29)) -> 0.46815062 | P3: =CORREL(SERIES!Z17:Z29,SERIES!AA17:AA29) -> 0.13078519 | Q3: =IFERROR(_xlfn.MAXIFS(EPISODES!$T$2:$T$26,EPISODES!$B$2:$B$26,A3,EPISODES!$C$2:$C$26,B3),"") -> 0 | R3: =SUMIFS(EPISODES!$W$2:$W$26,EPISODES!$B$2:$B$26,A3,EPISODES!$C$2:$C$26,B3) -> 0 | S3: =COUNTIF(SERIES!T17:T29,"<=-0.15") -> 2 | T3: =COUNTIF(SERIES!T17:T29,"<=-0.2") -> 1
A4: Coton | B4: Côte d'Ivoire | C4: =SERIES!C30:C30&" – "&SERIES!C41:C41 -> 2014/15 – 2025/26 | D4: 12 | E4: =STDEV(SERIES!Q30:Q41)/AVERAGE(SERIES!Q30:Q41) -> 0.20624503 | F4: =STDEV(SERIES!I30:I41)/AVERAGE(SERIES!I30:I41) -> 0.086898466 | G4: =STDEV(SERIES!S30:S41)/AVERAGE(SERIES!S30:S41) -> 0.27058456 | H4: =IFERROR(AVERAGEIFS(SERIES!W31:W41,SERIES!T31:T41,"<-0.05"),"") -> -0.2528584 | I4: =IFERROR(AVERAGEIFS(SERIES!W31:W41,SERIES!T31:T41,">0.05"),"") -> 0.097176471 | J4: =IFERROR(AVERAGEIFS(EPISODES!$AH$2:$AH$26,EPISODES!$B$2:$B$26,A4,EPISODES!$C$2:$C$26,B4,EPISODES!$D$2:$D$26,"baisse"),"") -> 0 | K4: =IFERROR(AVERAGEIFS(EPISODES!$AH$2:$AH$26,EPISODES!$B$2:$B$26,A4,EPISODES!$C$2:$C$26,B4,EPISODES!$D$2:$D$26,"hausse"),"") -> 0 | L4: =IF(ISNUMBER(H4),1-H4,"") -> 1.2528584 | M4: =MIN(SERIES!Y30:Y41) -> 0 | N4: =MIN(SERIES!V31:V41) -> -0.56452381 | O4: =VAR(SERIES!AA31:AA41)/(VAR(SERIES!Z31:Z41)+VAR(SERIES!AA31:AA41)) -> 0.98677965 | P4: =CORREL(SERIES!Z31:Z41,SERIES!AA31:AA41) -> -0.31537292 | Q4: =IFERROR(_xlfn.MAXIFS(EPISODES!$T$2:$T$26,EPISODES!$B$2:$B$26,A4,EPISODES!$C$2:$C$26,B4),"") -> 0 | R4: =SUMIFS(EPISODES!$W$2:$W$26,EPISODES!$B$2:$B$26,A4,EPISODES!$C$2:$C$26,B4) -> 0 | S4: =COUNTIF(SERIES!T31:T41,"<=-0.15") -> 2 | T4: =COUNTIF(SERIES!T31:T41,"<=-0.2") -> 0
A5: Anacarde | B5: Côte d'Ivoire | C5: =SERIES!C42:C42&" – "&SERIES!C52:C52 -> 2016 – 2026 | D5: 11 | E5: =STDEV(SERIES!Q42:Q52)/AVERAGE(SERIES!Q42:Q52) -> 0.19316018 | F5: =STDEV(SERIES!I42:I52)/AVERAGE(SERIES!I42:I52) -> 0.18538667 | G5: =STDEV(SERIES!S42:S52)/AVERAGE(SERIES!S42:S52) -> 0.25953699 | H5: =IFERROR(AVERAGEIFS(SERIES!W43:W52,SERIES!T43:T52,"<-0.05"),"") -> -0.065905926 | I5: =IFERROR(AVERAGEIFS(SERIES!W43:W52,SERIES!T43:T52,">0.05"),"") -> -0.87484916 | J5: =IFERROR(AVERAGEIFS(EPISODES!$AH$2:$AH$26,EPISODES!$B$2:$B$26,A5,EPISODES!$C$2:$C$26,B5,EPISODES!$D$2:$D$26,"baisse"),"") -> 1.3998516 | K5: =IFERROR(AVERAGEIFS(EPISODES!$AH$2:$AH$26,EPISODES!$B$2:$B$26,A5,EPISODES!$C$2:$C$26,B5,EPISODES!$D$2:$D$26,"hausse"),"") -> 1.75 | L5: =IF(ISNUMBER(H5),1-H5,"") -> 1.0659059 | M5: =MIN(SERIES!Y42:Y52) -> -0.45 | N5: =MIN(SERIES!V43:V52) -> -0.37516426 | O5: =VAR(SERIES!AA43:AA52)/(VAR(SERIES!Z43:Z52)+VAR(SERIES!AA43:AA52)) -> 0.25825023 | P5: =CORREL(SERIES!Z43:Z52,SERIES!AA43:AA52) -> 0.42797376 | Q5: =IFERROR(_xlfn.MAXIFS(EPISODES!$T$2:$T$26,EPISODES!$B$2:$B$26,A5,EPISODES!$C$2:$C$26,B5),"") -> 72 | R5: =SUMIFS(EPISODES!$W$2:$W$26,EPISODES!$B$2:$B$26,A5,EPISODES!$C$2:$C$26,B5) -> 0 | S5: =COUNTIF(SERIES!T43:T52,"<=-0.15") -> 2 | T5: =COUNTIF(SERIES!T43:T52,"<=-0.2") -> 1
A6: Hévéa | B6: Côte d'Ivoire | C6: =SERIES!C53:C53&" – "&SERIES!C68:C68 -> 2011 – 2026 | D6: 16 | E6: =STDEV(SERIES!Q53:Q68)/AVERAGE(SERIES!Q53:Q68) -> 0.34893353 | F6: =STDEV(SERIES!I53:I68)/AVERAGE(SERIES!I53:I68) -> 0.4220412 | G6: =STDEV(SERIES!S53:S68)/AVERAGE(SERIES!S53:S68) -> 0.64701453 | H6: =IFERROR(AVERAGEIFS(SERIES!W54:W68,SERIES!T54:T68,"<-0.05"),"") -> 0.94499459 | I6: =IFERROR(AVERAGEIFS(SERIES!W54:W68,SERIES!T54:T68,">0.05"),"") -> 1.1647996 | J6: =IFERROR(AVERAGEIFS(EPISODES!$AH$2:$AH$26,EPISODES!$B$2:$B$26,A6,EPISODES!$C$2:$C$26,B6,EPISODES!$D$2:$D$26,"baisse"),"") -> 1.1745207 | K6: =IFERROR(AVERAGEIFS(EPISODES!$AH$2:$AH$26,EPISODES!$B$2:$B$26,A6,EPISODES!$C$2:$C$26,B6,EPISODES!$D$2:$D$26,"hausse"),"") -> 1.8927681 | L6: =IF(ISNUMBER(H6),1-H6,"") -> 0.055005412 | M6: =MIN(SERIES!Y53:Y68) -> -0.72631579 | N6: =MIN(SERIES!V54:V68) -> -0.28993103 | O6: =VAR(SERIES!AA54:AA68)/(VAR(SERIES!Z54:Z68)+VAR(SERIES!AA54:AA68)) -> 0.097279118 | P6: =CORREL(SERIES!Z54:Z68,SERIES!AA54:AA68) -> 0.24181747 | Q6: =IFERROR(_xlfn.MAXIFS(EPISODES!$T$2:$T$26,EPISODES!$B$2:$B$26,A6,EPISODES!$C$2:$C$26,B6),"") -> 0 | R6: =SUMIFS(EPISODES!$W$2:$W$26,EPISODES!$B$2:$B$26,A6,EPISODES!$C$2:$C$26,B6) -> 0 | S6: =COUNTIF(SERIES!T54:T68,"<=-0.15") -> 4 | T6: =COUNTIF(SERIES!T54:T68,"<=-0.2") -> 4
A8: Transmission par épisode (toutes filières/pays) – lecture directe de l'onglet EPISODES
A9: filiere | B9: pays | C9: sens | D9: nb_episodes | E9: beta_moyen | F9: choc_int_moyen | G9: choc_prod_moyen
A10: Cacao | B10: Côte d'Ivoire | C10: baisse | D10: =COUNTIFS(EPISODES!$B$2:$B$26,A10,EPISODES!$C$2:$C$26,B10,EPISODES!$D$2:$D$26,C10) -> 2 | E10: =AVERAGEIFS(EPISODES!$AH$2:$AH$26,EPISODES!$B$2:$B$26,A10,EPISODES!$C$2:$C$26,B10,EPISODES!$D$2:$D$26,C10) -> 0.99245898 | F10: =AVERAGEIFS(EPISODES!$AF$2:$AF$26,EPISODES!$B$2:$B$26,A10,EPISODES!$C$2:$C$26,B10,EPISODES!$D$2:$D$26,C10) -> -0.4899462 | G10: =AVERAGEIFS(EPISODES!$AG$2:$AG$26,EPISODES!$B$2:$B$26,A10,EPISODES!$C$2:$C$26,B10,EPISODES!$D$2:$D$26,C10) -> -0.46753247
A11: Cacao | B11: Ghana | C11: baisse | D11: =COUNTIFS(EPISODES!$B$2:$B$26,A11,EPISODES!$C$2:$C$26,B11,EPISODES!$D$2:$D$26,C11) -> 2 | E11: =AVERAGEIFS(EPISODES!$AH$2:$AH$26,EPISODES!$B$2:$B$26,A11,EPISODES!$C$2:$C$26,B11,EPISODES!$D$2:$D$26,C11) -> 0.41334295 | F11: =AVERAGEIFS(EPISODES!$AF$2:$AF$26,EPISODES!$B$2:$B$26,A11,EPISODES!$C$2:$C$26,B11,EPISODES!$D$2:$D$26,C11) -> -0.32154906 | G11: =AVERAGEIFS(EPISODES!$AG$2:$AG$26,EPISODES!$B$2:$B$26,A11,EPISODES!$C$2:$C$26,B11,EPISODES!$D$2:$D$26,C11) -> -0.14317241
A12: Cacao | B12: Cameroun | C12: baisse | D12: =COUNTIFS(EPISODES!$B$2:$B$26,A12,EPISODES!$C$2:$C$26,B12,EPISODES!$D$2:$D$26,C12) -> 1 | E12: =AVERAGEIFS(EPISODES!$AH$2:$AH$26,EPISODES!$B$2:$B$26,A12,EPISODES!$C$2:$C$26,B12,EPISODES!$D$2:$D$26,C12) -> 1.0508336 | F12: =AVERAGEIFS(EPISODES!$AF$2:$AF$26,EPISODES!$B$2:$B$26,A12,EPISODES!$C$2:$C$26,B12,EPISODES!$D$2:$D$26,C12) -> -0.32814671 | G12: =AVERAGEIFS(EPISODES!$AG$2:$AG$26,EPISODES!$B$2:$B$26,A12,EPISODES!$C$2:$C$26,B12,EPISODES!$D$2:$D$26,C12) -> -0.34482759
A13: Cacao | B13: Équateur | C13: baisse | D13: =COUNTIFS(EPISODES!$B$2:$B$26,A13,EPISODES!$C$2:$C$26,B13,EPISODES!$D$2:$D$26,C13) -> 1 | E13: =AVERAGEIFS(EPISODES!$AH$2:$AH$26,EPISODES!$B$2:$B$26,A13,EPISODES!$C$2:$C$26,B13,EPISODES!$D$2:$D$26,C13) -> 0.95979021 | F13: =AVERAGEIFS(EPISODES!$AF$2:$AF$26,EPISODES!$B$2:$B$26,A13,EPISODES!$C$2:$C$26,B13,EPISODES!$D$2:$D$26,C13) -> -0.36065574 | G13: =AVERAGEIFS(EPISODES!$AG$2:$AG$26,EPISODES!$B$2:$B$26,A13,EPISODES!$C$2:$C$26,B13,EPISODES!$D$2:$D$26,C13) -> -0.34615385
A14: Cacao | B14: Côte d'Ivoire | C14: hausse | D14: =COUNTIFS(EPISODES!$B$2:$B$26,A14,EPISODES!$C$2:$C$26,B14,EPISODES!$D$2:$D$26,C14) -> 1 | E14: =AVERAGEIFS(EPISODES!$AH$2:$AH$26,EPISODES!$B$2:$B$26,A14,EPISODES!$C$2:$C$26,B14,EPISODES!$D$2:$D$26,C14) -> 0.57354811 | F14: =AVERAGEIFS(EPISODES!$AF$2:$AF$26,EPISODES!$B$2:$B$26,A14,EPISODES!$C$2:$C$26,B14,EPISODES!$D$2:$D$26,C14) -> 1.7435329 | G14: =AVERAGEIFS(EPISODES!$AG$2:$AG$26,EPISODES!$B$2:$B$26,A14,EPISODES!$C$2:$C$26,B14,EPISODES!$D$2:$D$26,C14) -> 1
A15: Cacao | B15: Ghana | C15: hausse | D15: =COUNTIFS(EPISODES!$B$2:$B$26,A15,EPISODES!$C$2:$C$26,B15,EPISODES!$D$2:$D$26,C15) -> 1 | E15: =AVERAGEIFS(EPISODES!$AH$2:$AH$26,EPISODES!$B$2:$B$26,A15,EPISODES!$C$2:$C$26,B15,EPISODES!$D$2:$D$26,C15) -> 0.96901114 | F15: =AVERAGEIFS(EPISODES!$AF$2:$AF$26,EPISODES!$B$2:$B$26,A15,EPISODES!$C$2:$C$26,B15,EPISODES!$D$2:$D$26,C15) -> 2.9669421 | G15: =AVERAGEIFS(EPISODES!$AG$2:$AG$26,EPISODES!$B$2:$B$26,A15,EPISODES!$C$2:$C$26,B15,EPISODES!$D$2:$D$26,C15) -> 2.875
A16: Cacao | B16: Cameroun | C16: hausse | D16: =COUNTIFS(EPISODES!$B$2:$B$26,A16,EPISODES!$C$2:$C$26,B16,EPISODES!$D$2:$D$26,C16) -> 1 | E16: =AVERAGEIFS(EPISODES!$AH$2:$AH$26,EPISODES!$B$2:$B$26,A16,EPISODES!$C$2:$C$26,B16,EPISODES!$D$2:$D$26,C16) -> 1.3382789 | F16: =AVERAGEIFS(EPISODES!$AF$2:$AF$26,EPISODES!$B$2:$B$26,A16,EPISODES!$C$2:$C$26,B16,EPISODES!$D$2:$D$26,C16) -> 1.7435329 | G16: =AVERAGEIFS(EPISODES!$AG$2:$AG$26,EPISODES!$B$2:$B$26,A16,EPISODES!$C$2:$C$26,B16,EPISODES!$D$2:$D$26,C16) -> 2.3333333
A17: Café | B17: Côte d'Ivoire | C17: hausse | D17: =COUNTIFS(EPISODES!$B$2:$B$26,A17,EPISODES!$C$2:$C$26,B17,EPISODES!$D$2:$D$26,C17) -> 1 | E17: =AVERAGEIFS(EPISODES!$AH$2:$AH$26,EPISODES!$B$2:$B$26,A17,EPISODES!$C$2:$C$26,B17,EPISODES!$D$2:$D$26,C17) -> 0.65881093 | F17: =AVERAGEIFS(EPISODES!$AF$2:$AF$26,EPISODES!$B$2:$B$26,A17,EPISODES!$C$2:$C$26,B17,EPISODES!$D$2:$D$26,C17) -> 1.0119241 | G17: =AVERAGEIFS(EPISODES!$AG$2:$AG$26,EPISODES!$B$2:$B$26,A17,EPISODES!$C$2:$C$26,B17,EPISODES!$D$2:$D$26,C17) -> 0.66666667
A18: Café | B18: Côte d'Ivoire | C18: baisse | D18: =COUNTIFS(EPISODES!$B$2:$B$26,A18,EPISODES!$C$2:$C$26,B18,EPISODES!$D$2:$D$26,C18) -> 1 | E18: =AVERAGEIFS(EPISODES!$AH$2:$AH$26,EPISODES!$B$2:$B$26,A18,EPISODES!$C$2:$C$26,B18,EPISODES!$D$2:$D$26,C18) -> 1.1217112 | F18: =AVERAGEIFS(EPISODES!$AF$2:$AF$26,EPISODES!$B$2:$B$26,A18,EPISODES!$C$2:$C$26,B18,EPISODES!$D$2:$D$26,C18) -> -0.20976354 | G18: =AVERAGEIFS(EPISODES!$AG$2:$AG$26,EPISODES!$B$2:$B$26,A18,EPISODES!$C$2:$C$26,B18,EPISODES!$D$2:$D$26,C18) -> -0.23529412
A19: Café | B19: Vietnam | C19: hausse | D19: =COUNTIFS(EPISODES!$B$2:$B$26,A19,EPISODES!$C$2:$C$26,B19,EPISODES!$D$2:$D$26,C19) -> 1 | E19: =AVERAGEIFS(EPISODES!$AH$2:$AH$26,EPISODES!$B$2:$B$26,A19,EPISODES!$C$2:$C$26,B19,EPISODES!$D$2:$D$26,C19) -> 1.4859053 | F19: =AVERAGEIFS(EPISODES!$AF$2:$AF$26,EPISODES!$B$2:$B$26,A19,EPISODES!$C$2:$C$26,B19,EPISODES!$D$2:$D$26,C19) -> 1.2967376 | G19: =AVERAGEIFS(EPISODES!$AG$2:$AG$26,EPISODES!$B$2:$B$26,A19,EPISODES!$C$2:$C$26,B19,EPISODES!$D$2:$D$26,C19) -> 1.9268293
A20: Coton | B20: Côte d'Ivoire | C20: baisse | D20: =COUNTIFS(EPISODES!$B$2:$B$26,A20,EPISODES!$C$2:$C$26,B20,EPISODES!$D$2:$D$26,C20) -> 1 | E20: =AVERAGEIFS(EPISODES!$AH$2:$AH$26,EPISODES!$B$2:$B$26,A20,EPISODES!$C$2:$C$26,B20,EPISODES!$D$2:$D$26,C20) -> 0 | F20: =AVERAGEIFS(EPISODES!$AF$2:$AF$26,EPISODES!$B$2:$B$26,A20,EPISODES!$C$2:$C$26,B20,EPISODES!$D$2:$D$26,C20) -> -0.14331688 | G20: =AVERAGEIFS(EPISODES!$AG$2:$AG$26,EPISODES!$B$2:$B$26,A20,EPISODES!$C$2:$C$26,B20,EPISODES!$D$2:$D$26,C20) -> 0
A21: Coton | B21: Mali | C21: baisse | D21: =COUNTIFS(EPISODES!$B$2:$B$26,A21,EPISODES!$C$2:$C$26,B21,EPISODES!$D$2:$D$26,C21) -> 1 | E21: =AVERAGEIFS(EPISODES!$AH$2:$AH$26,EPISODES!$B$2:$B$26,A21,EPISODES!$C$2:$C$26,B21,EPISODES!$D$2:$D$26,C21) -> 1.9029668 | F21: =AVERAGEIFS(EPISODES!$AF$2:$AF$26,EPISODES!$B$2:$B$26,A21,EPISODES!$C$2:$C$26,B21,EPISODES!$D$2:$D$26,C21) -> -0.14331688 | G21: =AVERAGEIFS(EPISODES!$AG$2:$AG$26,EPISODES!$B$2:$B$26,A21,EPISODES!$C$2:$C$26,B21,EPISODES!$D$2:$D$26,C21) -> -0.27272727
... A32: Riz (importé) | B32: Côte d'Ivoire | C32: hausse | D32: =COUNTIFS(EPISODES!$B$2:$B$26,A32,EPISODES!$C$2:$C$26,B32,EPISODES!$D$2:$D$26,C32) -> 1 | E32: =AVERAGEIFS(EPISODES!$AH$2:$AH$26,EPISODES!$B$2:$B$26,A32,EPISODES!$C$2:$C$26,B32,EPISODES!$D$2:$D$26,C32) -> 0.4178499 | F32: =AVERAGEIFS(EPISODES!$AF$2:$AF$26,EPISODES!$B$2:$B$26,A32,EPISODES!$C$2:$C$26,B32,EPISODES!$D$2:$D$26,C32) -> 0.2815534 | G32: =AVERAGEIFS(EPISODES!$AG$2:$AG$26,EPISODES!$B$2:$B$26,A32,EPISODES!$C$2:$C$26,B32,EPISODES!$D$2:$D$26,C32) -> 0.11764706

Sheet STRESS_PARAM
A1: filiere | B1: p0 | C1: unite | D1: q0_kt | E1: beta1 | F1: beta2 | G1: part_publique | H1: capacite_mds | I1: protection | J1: justification | K1: valeur_filiere_mds
A2: Cacao | B2: 1200 | C2: FCFA/kg | D2: 1800 | E2: 0.2 | F2: 0.95 | G2: 0.3 | H2: 0 | I2: Prix garanti + ventes anticipées (~70 % de la récolte vendue à terme) | J2: beta1 observé 2016/17 et 2025/26 (~0,2 sur le prix moyen de campagne) ; beta2 = moyenne 2017/18 (1,09) et 2026/27 (0,86) ; part publique = récolte non vendue à terme ; FRP non publié -> capacité 0 par prudence | K2: =B2*D2/1000 -> 2160
A3: Café | B3: 1300 | C3: FCFA/kg | D3: 60 | E3: 0 | F3: 1 | G3: 0.3 | H3: 0 | I3: Prix garanti, une seule campagne/an | J3: Même architecture que le cacao, sans campagne intermédiaire | K3: =B3*D3/1000 -> 78
A4: Coton | B4: 310 | C4: FCFA/kg | D4: 575 | E4: 0 | F4: 0.5 | G4: 0.5 | H4: 0 | I4: Prix fixé avant semis + subventions intrants (25,3 Mds en 2025/26) | J4: Prix intangible en cours de campagne ; beta2 = ajustement partiel (pas de fonds de lissage) ; enveloppe 2025/26 déjà affectée aux intrants ; part publique 0,5 = partage supposé État / sociétés cotonnières (C) | K4: =B4*D4/1000 -> 178.25
A5: Anacarde | B5: 400 | C5: FCFA/kg | D5: 1200 | E5: 1 | F5: 1 | G5: 0 | H5: 0 | I5: Prix plancher sans fonds ni obligation d'achat | J5: 2018-19 : transmission ~1 sur les prix réellement payés | K5: =B5*D5/1000 -> 480
A6: Hévéa | B6: 493 | C6: FCFA/kg humide | D6: 2700 | E6: 1 | F6: 1 | G6: 0 | H6: 0 | I6: Indexation mensuelle (66 % du prix net de référence) | J6: Formule : le pourcentage de baisse est transmis en un mois ; Q0 = ~1 600 kt sec / teneur en caoutchouc sec ~0,6 = ~2 700 kt humide (C) | K6: =B6*D6/1000 -> 1331.1
A7: Palmier à huile | B7: 100 | C7: FCFA/kg régime | D7: 2500 | E7: 0.7 | F7: 0.9 | G7: 0 | H7: 0 | I7: Prix des régimes indexé ; marché régional protégé | J7: 2022 : transmission ~0,7 (estimation C) | K7: =B7*D7/1000 -> 250
A10: Hypothèses : beta1 = transmission pendant la campagne en cours ; beta2 = transmission à la campagne suivante ; part_publique = part de la charge d'amortissement susceptible de revenir à l'État/régulateur ; capacité = réserves mobilisables publiées (0 si non publiées).

Sheet STRESS_TEST
A1: filiere | B1: scenario | C1: libelle | D1: choc_int | E1: dQ | F1: deux_campagnes | G1: valeur_filiere_mds | H1: dP_prod_c1 | I1: dP_prod_c2 | J1: dRecette_c1 | K1: perte_recette_c1_mds | L1: perte_recette_c2_mds | M1: perte_recette_cumulee_mds | N1: charge_absorbee_hors_prod_mds | O1: besoin_public_mds | P1: capacite_mds | Q1: deficit_financement_mds | R1: besoin_public_FCFA_kg | S1: besoin_public_pct_valeur | T1: cout_protection_totale_c1_mds | U1: cout_garantie_recette_90_mds
A2: Cacao | B2: S1 | C2: Prix int. -10 % | D2: -0.1 | E2: 0 | F2: 0 | G2: =STRESS_PARAM!$K$2 -> 2160 | H2: =STRESS_PARAM!$E$2*D2 -> -0.02 | I2: =IF(F2=1,STRESS_PARAM!$F$2*D2,"") | J2: =(1+H2)*(1+E2)-1 -> -0.02 | K2: =-J2*G2 -> 43.2 | L2: =IF(F2=1,-I2*G2,0) -> 0 | M2: =K2+L2 -> 43.2 | N2: =(1-STRESS_PARAM!$E$2)*(-D2)*G2*(1+E2)+IF(F2=1,(1-STRESS_PARAM!$F$2)*(-D2)*G2,0) -> 172.8 | O2: =N2*STRESS_PARAM!$G$2 -> 51.84 | P2: =STRESS_PARAM!$H$2 -> 0 | Q2: =MAX(0,O2-P2) -> 51.84 | R2: =O2*1000/(STRESS_PARAM!$D$2*(1+E2)*(1+F2)) -> 28.8 | S2: =O2/G2 -> 0.024 | T2: =-H2*G2*(1+E2) -> 43.2 | U2: =MAX(0,0.9-(1+J2))*G2 -> 0
A3: Cacao | B3: S2 | C3: Prix int. -20 % | D3: -0.2 | E3: 0 | F3: 0 | G3: =STRESS_PARAM!$K$2 -> 2160 | H3: =STRESS_PARAM!$E$2*D3 -> -0.04 | I3: =IF(F3=1,STRESS_PARAM!$F$2*D3,"") | J3: =(1+H3)*(1+E3)-1 -> -0.04 | K3: =-J3*G3 -> 86.4 | L3: =IF(F3=1,-I3*G3,0) -> 0 | M3: =K3+L3 -> 86.4 | N3: =(1-STRESS_PARAM!$E$2)*(-D3)*G3*(1+E3)+IF(F3=1,(1-STRESS_PARAM!$F$2)*(-D3)*G3,0) -> 345.6 | O3: =N3*STRESS_PARAM!$G$2 -> 103.68 | P3: =STRESS_PARAM!$H$2 -> 0 | Q3: =MAX(0,O3-P3) -> 103.68 | R3: =O3*1000/(STRESS_PARAM!$D$2*(1+E3)*(1+F3)) -> 57.6 | S3: =O3/G3 -> 0.048 | T3: =-H3*G3*(1+E3) -> 86.4 | U3: =MAX(0,0.9-(1+J3))*G3 -> 0
A4: Cacao | B4: S3 | C4: Prix int. -30 % | D4: -0.3 | E4: 0 | F4: 0 | G4: =STRESS_PARAM!$K$2 -> 2160 | H4: =STRESS_PARAM!$E$2*D4 -> -0.06 | I4: =IF(F4=1,STRESS_PARAM!$F$2*D4,"") | J4: =(1+H4)*(1+E4)-1 -> -0.06 | K4: =-J4*G4 -> 129.6 | L4: =IF(F4=1,-I4*G4,0) -> 0 | M4: =K4+L4 -> 129.6 | N4: =(1-STRESS_PARAM!$E$2)*(-D4)*G4*(1+E4)+IF(F4=1,(1-STRESS_PARAM!$F$2)*(-D4)*G4,0) -> 518.4 | O4: =N4*STRESS_PARAM!$G$2 -> 155.52 | P4: =STRESS_PARAM!$H$2 -> 0 | Q4: =MAX(0,O4-P4) -> 155.52 | R4: =O4*1000/(STRESS_PARAM!$D$2*(1+E4)*(1+F4)) -> 86.4 | S4: =O4/G4 -> 0.072 | T4: =-H4*G4*(1+E4) -> 129.6 | U4: =MAX(0,0.9-(1+J4))*G4 -> 0
A5: Cacao | B5: S4 | C5: Prix -30 % et production -10 % | D5: -0.3 | E5: -0.1 | F5: 0 | G5: =STRESS_PARAM!$K$2 -> 2160 | H5: =STRESS_PARAM!$E$2*D5 -> -0.06 | I5: =IF(F5=1,STRESS_PARAM!$F$2*D5,"") | J5: =(1+H5)*(1+E5)-1 -> -0.154 | K5: =-J5*G5 -> 332.64 | L5: =IF(F5=1,-I5*G5,0) -> 0 | M5: =K5+L5 -> 332.64 | N5: =(1-STRESS_PARAM!$E$2)*(-D5)*G5*(1+E5)+IF(F5=1,(1-STRESS_PARAM!$F$2)*(-D5)*G5,0) -> 466.56 | O5: =N5*STRESS_PARAM!$G$2 -> 139.968 | P5: =STRESS_PARAM!$H$2 -> 0 | Q5: =MAX(0,O5-P5) -> 139.968 | R5: =O5*1000/(STRESS_PARAM!$D$2*(1+E5)*(1+F5)) -> 86.4 | S5: =O5/G5 -> 0.0648 | T5: =-H5*G5*(1+E5) -> 116.64 | U5: =MAX(0,0.9-(1+J5))*G5 -> 116.64
A6: Cacao | B6: S5 | C6: Prix -30 % pendant 2 campagnes | D6: -0.3 | E6: 0 | F6: 1 | G6: =STRESS_PARAM!$K$2 -> 2160 | H6: =STRESS_PARAM!$E$2*D6 -> -0.06 | I6: =IF(F6=1,STRESS_PARAM!$F$2*D6,"") -> -0.285 | J6: =(1+H6)*(1+E6)-1 -> -0.06 | K6: =-J6*G6 -> 129.6 | L6: =IF(F6=1,-I6*G6,0) -> 615.6 | M6: =K6+L6 -> 745.2 | N6: =(1-STRESS_PARAM!$E$2)*(-D6)*G6*(1+E6)+IF(F6=1,(1-STRESS_PARAM!$F$2)*(-D6)*G6,0) -> 550.8 | O6: =N6*STRESS_PARAM!$G$2 -> 165.24 | P6: =STRESS_PARAM!$H$2 -> 0 | Q6: =MAX(0,O6-P6) -> 165.24 | R6: =O6*1000/(STRESS_PARAM!$D$2*(1+E6)*(1+F6)) -> 45.9 | S6: =O6/G6 -> 0.0765 | T6: =-H6*G6*(1+E6) -> 129.6 | U6: =MAX(0,0.9-(1+J6))*G6 -> 0
A7: Café | B7: S1 | C7: Prix int. -10 % | D7: -0.1 | E7: 0 | F7: 0 | G7: =STRESS_PARAM!$K$3 -> 78 | H7: =STRESS_PARAM!$E$3*D7 -> 0 | I7: =IF(F7=1,STRESS_PARAM!$F$3*D7,"") | J7: =(1+H7)*(1+E7)-1 -> 0 | K7: =-J7*G7 -> 0 | L7: =IF(F7=1,-I7*G7,0) -> 0 | M7: =K7+L7 -> 0 | N7: =(1-STRESS_PARAM!$E$3)*(-D7)*G7*(1+E7)+IF(F7=1,(1-STRESS_PARAM!$F$3)*(-D7)*G7,0) -> 7.8 | O7: =N7*STRESS_PARAM!$G$3 -> 2.34 | P7: =STRESS_PARAM!$H$3 -> 0 | Q7: =MAX(0,O7-P7) -> 2.34 | R7: =O7*1000/(STRESS_PARAM!$D$3*(1+E7)*(1+F7)) -> 39 | S7: =O7/G7 -> 0.03 | T7: =-H7*G7*(1+E7) -> 0 | U7: =MAX(0,0.9-(1+J7))*G7 -> 0
A8: Café | B8: S2 | C8: Prix int. -20 % | D8: -0.2 | E8: 0 | F8: 0 | G8: =STRESS_PARAM!$K$3 -> 78 | H8: =STRESS_PARAM!$E$3*D8 -> 0 | I8: =IF(F8=1,STRESS_PARAM!$F$3*D8,"") | J8: =(1+H8)*(1+E8)-1 -> 0 | K8: =-J8*G8 -> 0 | L8: =IF(F8=1,-I8*G8,0) -> 0 | M8: =K8+L8 -> 0 | N8: =(1-STRESS_PARAM!$E$3)*(-D8)*G8*(1+E8)+IF(F8=1,(1-STRESS_PARAM!$F$3)*(-D8)*G8,0) -> 15.6 | O8: =N8*STRESS_PARAM!$G$3 -> 4.68 | P8: =STRESS_PARAM!$H$3 -> 0 | Q8: =MAX(0,O8-P8) -> 4.68 | R8: =O8*1000/(STRESS_PARAM!$D$3*(1+E8)*(1+F8)) -> 78 | S8: =O8/G8 -> 0.06 | T8: =-H8*G8*(1+E8) -> 0 | U8: =MAX(0,0.9-(1+J8))*G8 -> 0
A9: Café | B9: S3 | C9: Prix int. -30 % | D9: -0.3 | E9: 0 | F9: 0 | G9: =STRESS_PARAM!$K$3 -> 78 | H9: =STRESS_PARAM!$E$3*D9 -> 0 | I9: =IF(F9=1,STRESS_PARAM!$F$3*D9,"") | J9: =(1+H9)*(1+E9)-1 -> 0 | K9: =-J9*G9 -> 0 | L9: =IF(F9=1,-I9*G9,0) -> 0 | M9: =K9+L9 -> 0 | N9: =(1-STRESS_PARAM!$E$3)*(-D9)*G9*(1+E9)+IF(F9=1,(1-STRESS_PARAM!$F$3)*(-D9)*G9,0) -> 23.4 | O9: =N9*STRESS_PARAM!$G$3 -> 7.02 | P9: =STRESS_PARAM!$H$3 -> 0 | Q9: =MAX(0,O9-P9) -> 7.02 | R9: =O9*1000/(STRESS_PARAM!$D$3*(1+E9)*(1+F9)) -> 117 | S9: =O9/G9 -> 0.09 | T9: =-H9*G9*(1+E9) -> 0 | U9: =MAX(0,0.9-(1+J9))*G9 -> 0
A10: Café | B10: S4 | C10: Prix -30 % et production -10 % | D10: -0.3 | E10: -0.1 | F10: 0 | G10: =STRESS_PARAM!$K$3 -> 78 | H10: =STRESS_PARAM!$E$3*D10 -> 0 | I10: =IF(F10=1,STRESS_PARAM!$F$3*D10,"") | J10: =(1+H10)*(1+E10)-1 -> -0.1 | K10: =-J10*G10 -> 7.8 | L10: =IF(F10=1,-I10*G10,0) -> 0 | M10: =K10+L10 -> 7.8 | N10: =(1-STRESS_PARAM!$E$3)*(-D10)*G10*(1+E10)+IF(F10=1,(1-STRESS_PARAM!$F$3)*(-D10)*G10,0) -> 21.06 | O10: =N10*STRESS_PARAM!$G$3 -> 6.318 | P10: =STRESS_PARAM!$H$3 -> 0 | Q10: =MAX(0,O10-P10) -> 6.318 | R10: =O10*1000/(STRESS_PARAM!$D$3*(1+E10)*(1+F10)) -> 117 | S10: =O10/G10 -> 0.081 | T10: =-H10*G10*(1+E10) -> 0 | U10: =MAX(0,0.9-(1+J10))*G10 -> 0
A11: Café | B11: S5 | C11: Prix -30 % pendant 2 campagnes | D11: -0.3 | E11: 0 | F11: 1 | G11: =STRESS_PARAM!$K$3 -> 78 | H11: =STRESS_PARAM!$E$3*D11 -> 0 | I11: =IF(F11=1,STRESS_PARAM!$F$3*D11,"") -> -0.3 | J11: =(1+H11)*(1+E11)-1 -> 0 | K11: =-J11*G11 -> 0 | L11: =IF(F11=1,-I11*G11,0) -> 23.4 | M11: =K11+L11 -> 23.4 | N11: =(1-STRESS_PARAM!$E$3)*(-D11)*G11*(1+E11)+IF(F11=1,(1-STRESS_PARAM!$F$3)*(-D11)*G11,0) -> 23.4 | O11: =N11*STRESS_PARAM!$G$3 -> 7.02 | P11: =STRESS_PARAM!$H$3 -> 0 | Q11: =MAX(0,O11-P11) -> 7.02 | R11: =O11*1000/(STRESS_PARAM!$D$3*(1+E11)*(1+F11)) -> 58.5 | S11: =O11/G11 -> 0.09 | T11: =-H11*G11*(1+E11) -> 0 | U11: =MAX(0,0.9-(1+J11))*G11 -> 0
A12: Coton | B12: S1 | C12: Prix int. -10 % | D12: -0.1 | E12: 0 | F12: 0 | G12: =STRESS_PARAM!$K$4 -> 178.25 | H12: =STRESS_PARAM!$E$4*D12 -> 0 | I12: =IF(F12=1,STRESS_PARAM!$F$4*D12,"") | J12: =(1+H12)*(1+E12)-1 -> 0 | K12: =-J12*G12 -> 0 | L12: =IF(F12=1,-I12*G12,0) -> 0 | M12: =K12+L12 -> 0 | N12: =(1-STRESS_PARAM!$E$4)*(-D12)*G12*(1+E12)+IF(F12=1,(1-STRESS_PARAM!$F$4)*(-D12)*G12,0) -> 17.825 | O12: =N12*STRESS_PARAM!$G$4 -> 8.9125 | P12: =STRESS_PARAM!$H$4 -> 0 | Q12: =MAX(0,O12-P12) -> 8.9125 | R12: =O12*1000/(STRESS_PARAM!$D$4*(1+E12)*(1+F12)) -> 15.5 | S12: =O12/G12 -> 0.05 | T12: =-H12*G12*(1+E12) -> 0 | U12: =MAX(0,0.9-(1+J12))*G12 -> 0
A13: Coton | B13: S2 | C13: Prix int. -20 % | D13: -0.2 | E13: 0 | F13: 0 | G13: =STRESS_PARAM!$K$4 -> 178.25 | H13: =STRESS_PARAM!$E$4*D13 -> 0 | I13: =IF(F13=1,STRESS_PARAM!$F$4*D13,"") | J13: =(1+H13)*(1+E13)-1 -> 0 | K13: =-J13*G13 -> 0 | L13: =IF(F13=1,-I13*G13,0) -> 0 | M13: =K13+L13 -> 0 | N13: =(1-STRESS_PARAM!$E$4)*(-D13)*G13*(1+E13)+IF(F13=1,(1-STRESS_PARAM!$F$4)*(-D13)*G13,0) -> 35.65 | O13: =N13*STRESS_PARAM!$G$4 -> 17.825 | P13: =STRESS_PARAM!$H$4 -> 0 | Q13: =MAX(0,O13-P13) -> 17.825 | R13: =O13*1000/(STRESS_PARAM!$D$4*(1+E13)*(1+F13)) -> 31 | S13: =O13/G13 -> 0.1 | T13: =-H13*G13*(1+E13) -> 0 | U13: =MAX(0,0.9-(1+J13))*G13 -> 0
A14: Coton | B14: S3 | C14: Prix int. -30 % | D14: -0.3 | E14: 0 | F14: 0 | G14: =STRESS_PARAM!$K$4 -> 178.25 | H14: =STRESS_PARAM!$E$4*D14 -> 0 | I14: =IF(F14=1,STRESS_PARAM!$F$4*D14,"") | J14: =(1+H14)*(1+E14)-1 -> 0 | K14: =-J14*G14 -> 0 | L14: =IF(F14=1,-I14*G14,0) -> 0 | M14: =K14+L14 -> 0 | N14: =(1-STRESS_PARAM!$E$4)*(-D14)*G14*(1+E14)+IF(F14=1,(1-STRESS_PARAM!$F$4)*(-D14)*G14,0) -> 53.475 | O14: =N14*STRESS_PARAM!$G$4 -> 26.7375 | P14: =STRESS_PARAM!$H$4 -> 0 | Q14: =MAX(0,O14-P14) -> 26.7375 | R14: =O14*1000/(STRESS_PARAM!$D$4*(1+E14)*(1+F14)) -> 46.5 | S14: =O14/G14 -> 0.15 | T14: =-H14*G14*(1+E14) -> 0 | U14: =MAX(0,0.9-(1+J14))*G14 -> 0
A15: Coton | B15: S4 | C15: Prix -30 % et production -10 % | D15: -0.3 | E15: -0.1 | F15: 0 | G15: =STRESS_PARAM!$K$4 -> 178.25 | H15: =STRESS_PARAM!$E$4*D15 -> 0 | I15: =IF(F15=1,STRESS_PARAM!$F$4*D15,"") | J15: =(1+H15)*(1+E15)-1 -> -0.1 | K15: =-J15*G15 -> 17.825 | L15: =IF(F15=1,-I15*G15,0) -> 0 | M15: =K15+L15 -> 17.825 | N15: =(1-STRESS_PARAM!$E$4)*(-D15)*G15*(1+E15)+IF(F15=1,(1-STRESS_PARAM!$F$4)*(-D15)*G15,0) -> 48.1275 | O15: =N15*STRESS_PARAM!$G$4 -> 24.06375 | P15: =STRESS_PARAM!$H$4 -> 0 | Q15: =MAX(0,O15-P15) -> 24.06375 | R15: =O15*1000/(STRESS_PARAM!$D$4*(1+E15)*(1+F15)) -> 46.5 | S15: =O15/G15 -> 0.135 | T15: =-H15*G15*(1+E15) -> 0 | U15: =MAX(0,0.9-(1+J15))*G15 -> 0
A16: Coton | B16: S5 | C16: Prix -30 % pendant 2 campagnes | D16: -0.3 | E16: 0 | F16: 1 | G16: =STRESS_PARAM!$K$4 -> 178.25 | H16: =STRESS_PARAM!$E$4*D16 -> 0 | I16: =IF(F16=1,STRESS_PARAM!$F$4*D16,"") -> -0.15 | J16: =(1+H16)*(1+E16)-1 -> 0 | K16: =-J16*G16 -> 0 | L16: =IF(F16=1,-I16*G16,0) -> 26.7375 | M16: =K16+L16 -> 26.7375 | N16: =(1-STRESS_PARAM!$E$4)*(-D16)*G16*(1+E16)+IF(F16=1,(1-STRESS_PARAM!$F$4)*(-D16)*G16,0) -> 80.2125 | O16: =N16*STRESS_PARAM!$G$4 -> 40.10625 | P16: =STRESS_PARAM!$H$4 -> 0 | Q16: =MAX(0,O16-P16) -> 40.10625 | R16: =O16*1000/(STRESS_PARAM!$D$4*(1+E16)*(1+F16)) -> 34.875 | S16: =O16/G16 -> 0.225 | T16: =-H16*G16*(1+E16) -> 0 | U16: =MAX(0,0.9-(1+J16))*G16 -> 0
A17: Anacarde | B17: S1 | C17: Prix int. -10 % | D17: -0.1 | E17: 0 | F17: 0 | G17: =STRESS_PARAM!$K$5 -> 480 | H17: =STRESS_PARAM!$E$5*D17 -> -0.1 | I17: =IF(F17=1,STRESS_PARAM!$F$5*D17,"") | J17: =(1+H17)*(1+E17)-1 -> -0.1 | K17: =-J17*G17 -> 48 | L17: =IF(F17=1,-I17*G17,0) -> 0 | M17: =K17+L17 -> 48 | N17: =(1-STRESS_PARAM!$E$5)*(-D17)*G17*(1+E17)+IF(F17=1,(1-STRESS_PARAM!$F$5)*(-D17)*G17,0) -> 0 | O17: =N17*STRESS_PARAM!$G$5 -> 0 | P17: =STRESS_PARAM!$H$5 -> 0 | Q17: =MAX(0,O17-P17) -> 0 | R17: =O17*1000/(STRESS_PARAM!$D$5*(1+E17)*(1+F17)) -> 0 | S17: =O17/G17 -> 0 | T17: =-H17*G17*(1+E17) -> 48 | U17: =MAX(0,0.9-(1+J17))*G17 -> 0
A18: Anacarde | B18: S2 | C18: Prix int. -20 % | D18: -0.2 | E18: 0 | F18: 0 | G18: =STRESS_PARAM!$K$5 -> 480 | H18: =STRESS_PARAM!$E$5*D18 -> -0.2 | I18: =IF(F18=1,STRESS_PARAM!$F$5*D18,"") | J18: =(1+H18)*(1+E18)-1 -> -0.2 | K18: =-J18*G18 -> 96 | L18: =IF(F18=1,-I18*G18,0) -> 0 | M18: =K18+L18 -> 96 | N18: =(1-STRESS_PARAM!$E$5)*(-D18)*G18*(1+E18)+IF(F18=1,(1-STRESS_PARAM!$F$5)*(-D18)*G18,0) -> 0 | O18: =N18*STRESS_PARAM!$G$5 -> 0 | P18: =STRESS_PARAM!$H$5 -> 0 | Q18: =MAX(0,O18-P18) -> 0 | R18: =O18*1000/(STRESS_PARAM!$D$5*(1+E18)*(1+F18)) -> 0 | S18: =O18/G18 -> 0 | T18: =-H18*G18*(1+E18) -> 96 | U18: =MAX(0,0.9-(1+J18))*G18 -> 48
A19: Anacarde | B19: S3 | C19: Prix int. -30 % | D19: -0.3 | E19: 0 | F19: 0 | G19: =STRESS_PARAM!$K$5 -> 480 | H19: =STRESS_PARAM!$E$5*D19 -> -0.3 | I19: =IF(F19=1,STRESS_PARAM!$F$5*D19,"") | J19: =(1+H19)*(1+E19)-1 -> -0.3 | K19: =-J19*G19 -> 144 | L19: =IF(F19=1,-I19*G19,0) -> 0 | M19: =K19+L19 -> 144 | N19: =(1-STRESS_PARAM!$E$5)*(-D19)*G19*(1+E19)+IF(F19=1,(1-STRESS_PARAM!$F$5)*(-D19)*G19,0) -> 0 | O19: =N19*STRESS_PARAM!$G$5 -> 0 | P19: =STRESS_PARAM!$H$5 -> 0 | Q19: =MAX(0,O19-P19) -> 0 | R19: =O19*1000/(STRESS_PARAM!$D$5*(1+E19)*(1+F19)) -> 0 | S19: =O19/G19 -> 0 | T19: =-H19*G19*(1+E19) -> 144 | U19: =MAX(0,0.9-(1+J19))*G19 -> 96
A20: Anacarde | B20: S4 | C20: Prix -30 % et production -10 % | D20: -0.3 | E20: -0.1 | F20: 0 | G20: =STRESS_PARAM!$K$5 -> 480 | H20: =STRESS_PARAM!$E$5*D20 -> -0.3 | I20: =IF(F20=1,STRESS_PARAM!$F$5*D20,"") | J20: =(1+H20)*(1+E20)-1 -> -0.37 | K20: =-J20*G20 -> 177.6 | L20: =IF(F20=1,-I20*G20,0) -> 0 | M20: =K20+L20 -> 177.6 | N20: =(1-STRESS_PARAM!$E$5)*(-D20)*G20*(1+E20)+IF(F20=1,(1-STRESS_PARAM!$F$5)*(-D20)*G20,0) -> 0 | O20: =N20*STRESS_PARAM!$G$5 -> 0 | P20: =STRESS_PARAM!$H$5 -> 0 | Q20: =MAX(0,O20-P20) -> 0 | R20: =O20*1000/(STRESS_PARAM!$D$5*(1+E20)*(1+F20)) -> 0 | S20: =O20/G20 -> 0 | T20: =-H20*G20*(1+E20) -> 129.6 | U20: =MAX(0,0.9-(1+J20))*G20 -> 129.6
A21: Anacarde | B21: S5 | C21: Prix -30 % pendant 2 campagnes | D21: -0.3 | E21: 0 | F21: 1 | G21: =STRESS_PARAM!$K$5 -> 480 | H21: =STRESS_PARAM!$E$5*D21 -> -0.3 | I21: =IF(F21=1,STRESS_PARAM!$F$5*D21,"") -> -0.3 | J21: =(1+H21)*(1+E21)-1 -> -0.3 | K21: =-J21*G21 -> 144 | L21: =IF(F21=1,-I21*G21,0) -> 144 | M21: =K21+L21 -> 288 | N21: =(1-STRESS_PARAM!$E$5)*(-D21)*G21*(1+E21)+IF(F21=1,(1-STRESS_PARAM!$F$5)*(-D21)*G21,0) -> 0 | O21: =N21*STRESS_PARAM!$G$5 -> 0 | P21: =STRESS_PARAM!$H$5 -> 0 | Q21: =MAX(0,O21-P21) -> 0 | R21: =O21*1000/(STRESS_PARAM!$D$5*(1+E21)*(1+F21)) -> 0 | S21: =O21/G21 -> 0 | T21: =-H21*G21*(1+E21) -> 144 | U21: =MAX(0,0.9-(1+J21))*G21 -> 96
A22: Hévéa | B22: S1 | C22: Prix int. -10 % | D22: -0.1 | E22: 0 | F22: 0 | G22: =STRESS_PARAM!$K$6 -> 1331.1 | H22: =STRESS_PARAM!$E$6*D22 -> -0.1 | I22: =IF(F22=1,STRESS_PARAM!$F$6*D22,"") | J22: =(1+H22)*(1+E22)-1 -> -0.1 | K22: =-J22*G22 -> 133.11 | L22: =IF(F22=1,-I22*G22,0) -> 0 | M22: =K22+L22 -> 133.11 | N22: =(1-STRESS_PARAM!$E$6)*(-D22)*G22*(1+E22)+IF(F22=1,(1-STRESS_PARAM!$F$6)*(-D22)*G22,0) -> 0 | O22: =N22*STRESS_PARAM!$G$6 -> 0 | P22: =STRESS_PARAM!$H$6 -> 0 | Q22: =MAX(0,O22-P22) -> 0 | R22: =O22*1000/(STRESS_PARAM!$D$6*(1+E22)*(1+F22)) -> 0 | S22: =O22/G22 -> 0 | T22: =-H22*G22*(1+E22) -> 133.11 | U22: =MAX(0,0.9-(1+J22))*G22 -> 0
A23: Hévéa | B23: S2 | C23: Prix int. -20 % | D23: -0.2 | E23: 0 | F23: 0 | G23: =STRESS_PARAM!$K$6 -> 1331.1 | H23: =STRESS_PARAM!$E$6*D23 -> -0.2 | I23: =IF(F23=1,STRESS_PARAM!$F$6*D23,"") | J23: =(1+H23)*(1+E23)-1 -> -0.2 | K23: =-J23*G23 -> 266.22 | L23: =IF(F23=1,-I23*G23,0) -> 0 | M23: =K23+L23 -> 266.22 | N23: =(1-STRESS_PARAM!$E$6)*(-D23)*G23*(1+E23)+IF(F23=1,(1-STRESS_PARAM!$F$6)*(-D23)*G23,0) -> 0 | O23: =N23*STRESS_PARAM!$G$6 -> 0 | P23: =STRESS_PARAM!$H$6 -> 0 | Q23: =MAX(0,O23-P23) -> 0 | R23: =O23*1000/(STRESS_PARAM!$D$6*(1+E23)*(1+F23)) -> 0 | S23: =O23/G23 -> 0 | T23: =-H23*G23*(1+E23) -> 266.22 | U23: =MAX(0,0.9-(1+J23))*G23 -> 133.11
A24: Hévéa | B24: S3 | C24: Prix int. -30 % | D24: -0.3 | E24: 0 | F24: 0 | G24: =STRESS_PARAM!$K$6 -> 1331.1 | H24: =STRESS_PARAM!$E$6*D24 -> -0.3 | I24: =IF(F24=1,STRESS_PARAM!$F$6*D24,"") | J24: =(1+H24)*(1+E24)-1 -> -0.3 | K24: =-J24*G24 -> 399.33 | L24: =IF(F24=1,-I24*G24,0) -> 0 | M24: =K24+L24 -> 399.33 | N24: =(1-STRESS_PARAM!$E$6)*(-D24)*G24*(1+E24)+IF(F24=1,(1-STRESS_PARAM!$F$6)*(-D24)*G24,0) -> 0 | O24: =N24*STRESS_PARAM!$G$6 -> 0 | P24: =STRESS_PARAM!$H$6 -> 0 | Q24: =MAX(0,O24-P24) -> 0 | R24: =O24*1000/(STRESS_PARAM!$D$6*(1+E24)*(1+F24)) -> 0 | S24: =O24/G24 -> 0 | T24: =-H24*G24*(1+E24) -> 399.33 | U24: =MAX(0,0.9-(1+J24))*G24 -> 266.22
A25: Hévéa | B25: S4 | C25: Prix -30 % et production -10 % | D25: -0.3 | E25: -0.1 | F25: 0 | G25: =STRESS_PARAM!$K$6 -> 1331.1 | H25: =STRESS_PARAM!$E$6*D25 -> -0.3 | I25: =IF(F25=1,STRESS_PARAM!$F$6*D25,"") | J25: =(1+H25)*(1+E25)-1 -> -0.37 | K25: =-J25*G25 -> 492.507 | L25: =IF(F25=1,-I25*G25,0) -> 0 | M25: =K25+L25 -> 492.507 | N25: =(1-STRESS_PARAM!$E$6)*(-D25)*G25*(1+E25)+IF(F25=1,(1-STRESS_PARAM!$F$6)*(-D25)*G25,0) -> 0 | O25: =N25*STRESS_PARAM!$G$6 -> 0 | P25: =STRESS_PARAM!$H$6 -> 0 | Q25: =MAX(0,O25-P25) -> 0 | R25: =O25*1000/(STRESS_PARAM!$D$6*(1+E25)*(1+F25)) -> 0 | S25: =O25/G25 -> 0 | T25: =-H25*G25*(1+E25) -> 359.397 | U25: =MAX(0,0.9-(1+J25))*G25 -> 359.397
A26: Hévéa | B26: S5 | C26: Prix -30 % pendant 2 campagnes | D26: -0.3 | E26: 0 | F26: 1 | G26: =STRESS_PARAM!$K$6 -> 1331.1 | H26: =STRESS_PARAM!$E$6*D26 -> -0.3 | I26: =IF(F26=1,STRESS_PARAM!$F$6*D26,"") -> -0.3 | J26: =(1+H26)*(1+E26)-1 -> -0.3 | K26: =-J26*G26 -> 399.33 | L26: =IF(F26=1,-I26*G26,0) -> 399.33 | M26: =K26+L26 -> 798.66 | N26: =(1-STRESS_PARAM!$E$6)*(-D26)*G26*(1+E26)+IF(F26=1,(1-STRESS_PARAM!$F$6)*(-D26)*G26,0) -> 0 | O26: =N26*STRESS_PARAM!$G$6 -> 0 | P26: =STRESS_PARAM!$H$6 -> 0 | Q26: =MAX(0,O26-P26) -> 0 | R26: =O26*1000/(STRESS_PARAM!$D$6*(1+E26)*(1+F26)) -> 0 | S26: =O26/G26 -> 0 | T26: =-H26*G26*(1+E26) -> 399.33 | U26: =MAX(0,0.9-(1+J26))*G26 -> 266.22
A27: Palmier à huile | B27: S1 | C27: Prix int. -10 % | D27: -0.1 | E27: 0 | F27: 0 | G27: =STRESS_PARAM!$K$7 -> 250 | H27: =STRESS_PARAM!$E$7*D27 -> -0.07 | I27: =IF(F27=1,STRESS_PARAM!$F$7*D27,"") | J27: =(1+H27)*(1+E27)-1 -> -0.07 | K27: =-J27*G27 -> 17.5 | L27: =IF(F27=1,-I27*G27,0) -> 0 | M27: =K27+L27 -> 17.5 | N27: =(1-STRESS_PARAM!$E$7)*(-D27)*G27*(1+E27)+IF(F27=1,(1-STRESS_PARAM!$F$7)*(-D27)*G27,0) -> 7.5 | O27: =N27*STRESS_PARAM!$G$7 -> 0 | P27: =STRESS_PARAM!$H$7 -> 0 | Q27: =MAX(0,O27-P27) -> 0 | R27: =O27*1000/(STRESS_PARAM!$D$7*(1+E27)*(1+F27)) -> 0 | S27: =O27/G27 -> 0 | T27: =-H27*G27*(1+E27) -> 17.5 | U27: =MAX(0,0.9-(1+J27))*G27 -> 0
A28: Palmier à huile | B28: S2 | C28: Prix int. -20 % | D28: -0.2 | E28: 0 | F28: 0 | G28: =STRESS_PARAM!$K$7 -> 250 | H28: =STRESS_PARAM!$E$7*D28 -> -0.14 | I28: =IF(F28=1,STRESS_PARAM!$F$7*D28,"") | J28: =(1+H28)*(1+E28)-1 -> -0.14 | K28: =-J28*G28 -> 35 | L28: =IF(F28=1,-I28*G28,0) -> 0 | M28: =K28+L28 -> 35 | N28: =(1-STRESS_PARAM!$E$7)*(-D28)*G28*(1+E28)+IF(F28=1,(1-STRESS_PARAM!$F$7)*(-D28)*G28,0) -> 15 | O28: =N28*STRESS_PARAM!$G$7 -> 0 | P28: =STRESS_PARAM!$H$7 -> 0 | Q28: =MAX(0,O28-P28) -> 0 | R28: =O28*1000/(STRESS_PARAM!$D$7*(1+E28)*(1+F28)) -> 0 | S28: =O28/G28 -> 0 | T28: =-H28*G28*(1+E28) -> 35 | U28: =MAX(0,0.9-(1+J28))*G28 -> 10
A29: Palmier à huile | B29: S3 | C29: Prix int. -30 % | D29: -0.3 | E29: 0 | F29: 0 | G29: =STRESS_PARAM!$K$7 -> 250 | H29: =STRESS_PARAM!$E$7*D29 -> -0.21 | I29: =IF(F29=1,STRESS_PARAM!$F$7*D29,"") | J29: =(1+H29)*(1+E29)-1 -> -0.21 | K29: =-J29*G29 -> 52.5 | L29: =IF(F29=1,-I29*G29,0) -> 0 | M29: =K29+L29 -> 52.5 | N29: =(1-STRESS_PARAM!$E$7)*(-D29)*G29*(1+E29)+IF(F29=1,(1-STRESS_PARAM!$F$7)*(-D29)*G29,0) -> 22.5 | O29: =N29*STRESS_PARAM!$G$7 -> 0 | P29: =STRESS_PARAM!$H$7 -> 0 | Q29: =MAX(0,O29-P29) -> 0 | R29: =O29*1000/(STRESS_PARAM!$D$7*(1+E29)*(1+F29)) -> 0 | S29: =O29/G29 -> 0 | T29: =-H29*G29*(1+E29) -> 52.5 | U29: =MAX(0,0.9-(1+J29))*G29 -> 27.5
A30: Palmier à huile | B30: S4 | C30: Prix -30 % et production -10 % | D30: -0.3 | E30: -0.1 | F30: 0 | G30: =STRESS_PARAM!$K$7 -> 250 | H30: =STRESS_PARAM!$E$7*D30 -> -0.21 | I30: =IF(F30=1,STRESS_PARAM!$F$7*D30,"") | J30: =(1+H30)*(1+E30)-1 -> -0.289 | K30: =-J30*G30 -> 72.25 | L30: =IF(F30=1,-I30*G30,0) -> 0 | M30: =K30+L30 -> 72.25 | N30: =(1-STRESS_PARAM!$E$7)*(-D30)*G30*(1+E30)+IF(F30=1,(1-STRESS_PARAM!$F$7)*(-D30)*G30,0) -> 20.25 | O30: =N30*STRESS_PARAM!$G$7 -> 0 | P30: =STRESS_PARAM!$H$7 -> 0 | Q30: =MAX(0,O30-P30) -> 0 | R30: =O30*1000/(STRESS_PARAM!$D$7*(1+E30)*(1+F30)) -> 0 | S30: =O30/G30 -> 0 | T30: =-H30*G30*(1+E30) -> 47.25 | U30: =MAX(0,0.9-(1+J30))*G30 -> 47.25
A31: Palmier à huile | B31: S5 | C31: Prix -30 % pendant 2 campagnes | D31: -0.3 | E31: 0 | F31: 1 | G31: =STRESS_PARAM!$K$7 -> 250 | H31: =STRESS_PARAM!$E$7*D31 -> -0.21 | I31: =IF(F31=1,STRESS_PARAM!$F$7*D31,"") -> -0.27 | J31: =(1+H31)*(1+E31)-1 -> -0.21 | K31: =-J31*G31 -> 52.5 | L31: =IF(F31=1,-I31*G31,0) -> 67.5 | M31: =K31+L31 -> 120 | N31: =(1-STRESS_PARAM!$E$7)*(-D31)*G31*(1+E31)+IF(F31=1,(1-STRESS_PARAM!$F$7)*(-D31)*G31,0) -> 30 | O31: =N31*STRESS_PARAM!$G$7 -> 0 | P31: =STRESS_PARAM!$H$7 -> 0 | Q31: =MAX(0,O31-P31) -> 0 | R31: =O31*1000/(STRESS_PARAM!$D$7*(1+E31)*(1+F31)) -> 0 | S31: =O31/G31 -> 0 | T31: =-H31*G31*(1+E31) -> 52.5 | U31: =MAX(0,0.9-(1+J31))*G31 -> 27.5

Sheet MECANISMES
A1: pays | B1: filiere | C1: categorie | D1: mecanisme | E1: resultat | F1: cout_limite | G1: enseignement | H1: transposable | I1: qualite | J1: source
A2: Ghana | B2: Cacao | C2: A+D | D2: Prix fixé par Cocobod, ventes à terme, prêts syndiqués ; Act 1182 (2026) : >= 70 % du FOB | E2: Prix nominal intact en 2016-18 (transmission 0) | F2: Dette héritée 5,8 Mds GHS ; défaut sur facilité relais 70 M USD ; contrats 2023/24 reportés ; coupe de -29 % en fév. 2026 | G2: Stabiliser par la dette n'est pas soutenable ; une règle de partage explicite (% FOB) rend les ajustements prévisibles | H2: Partiel (règle de partage) | I2: A/B | J2: isd.gov.gh ; gna.org.gh
A3: Équateur | B3: Cacao | C3: E | D3: Marché libre, économie dollarisée, différenciation qualité (fino de aroma, CCN-51) | E3: Producteurs ~85-90 % du FOB ; production presque doublée depuis 2016 | F3: Aucune protection contre les baisses | G3: Transmettre les hausses finance l'investissement et la productivité | H3: Partiel (transmission des hausses) | I3: C | J3: Anecacao
A4: Burkina Faso | B4: Coton | C4: C | D4: Fonds de lissage AICB : prix plancher + ajustement selon moyenne mobile des cours ; abondé en bonnes années | E4: Choc 2020 amorti (transmission estimée ~0,3) | F4: Épuisé lors de chocs longs ; recapitalisations par bailleurs | G4: Règle automatique de dotation/décaissement, plafonnée | H4: Oui (coton, café) | I4: C | J4: Kaminski, Headey & Bernard (IFPRI 2011)
A5: Mali | B5: Coton | C5: A | D5: Prix administré par la CMDT ; baisse brutale avant semis 2020 (275 -> 200 FCFA) | E5: Production -80 % (717 -> 147 kt) ; revenu effondré | F5: Rattrapage en 2021/22 seulement | G5: Un ajustement brutal annoncé avant semis détruit la recette : lisser et pré-annoncer la règle | H5: Contre-exemple | I5: B | J5: CMDT ; USDA
A6: Brésil | B6: Coton, café | C6: A+B+F | D6: PGPM/PEPRO (paiement de l'écart au prix minimum par enchères), FUNCAFÉ (crédit), marchés à terme B3, assurance PSR subventionnée | E6: Revenu stabilisé sans figer le prix de marché | F6: Coût budgétaire annuel voté ; nécessite marchés financiers et données de rendement | G6: Paiements contracycliques ciblés et budgétés ex ante | H6: Partiel (à moyen terme) | I6: B | J6: CONAB ; MAPA
A7: Malaisie | B7: Hévéa | C7: B | D7: Incitation à la production (IPG) : versement automatique quand le prix tombe sous un seuil | E7: Plancher de revenu pour petits planteurs | F7: Financé par le budget ; seuil à ajuster | G7: Déclencheur automatique et plafonné par producteur | H7: Oui (hévéa) | I7: C | J7: RISDA / LGM
A8: Thaïlande | B8: Hévéa | C8: B+D | D8: Achats publics (2012-13), aides à la surface, garantie de revenu (2019-22) plafonnée par exploitation ; cess export | E8: Revenu plancher pour petits planteurs | F8: Coût élevé, stocks publics invendables (2012-13) | G8: Plafonner la garantie ; éviter le stockage public | H8: Partiel | I8: B/C | J8: Rubber Authority of Thailand
A9: Indonésie | B9: Palmier à huile | C9: C+E | D9: Fonds BPDPKS financé par un prélèvement export progressif (replantation, biodiesel) | E9: Fonds de grande taille ; soutien de la demande intérieure | F9: Interdiction d'exporter en 2022 : prix des régimes -55 % | G9: Le prélèvement progressif constitue des réserves en haut de cycle ; éviter les mesures commerciales brutales | H9: Oui (prélèvement progressif) | I9: C | J9: BPDPKS ; USDA
A10: Tanzanie | B10: Anacarde | C10: F | D10: Récépissés d'entrepôt + enchères publiques | E10: Prix transparents, financement de stockage | F10: Intervention 2018 (achat public) coûteuse | G10: Outil de crédit-stockage adapté à l'anacarde | H10: Oui (anacarde) | I10: C | J10: Coulter & Onumah (2002) ; CBT
A11: Vietnam | B11: Café, anacarde | C11: E | D11: Transformation, irrigation, diversification des cultures (durian, poivre) | E11: Volumes stables malgré transmission totale | F11: Pas de protection prix | G11: La productivité et la diversification sont des amortisseurs de revenu | H11: Oui (long terme) | I11: B | J11: USDA FAS

Sheet LITTERATURE
A1: reference | B1: instrument | C1: pays | D1: resultat | E1: limites | F1: enseignement_ci
A2: Newbery & Stiglitz (1981), The Theory of Commodity Price Stabilization, Oxford UP | B2: Stabilisation des prix | C2: Théorie | D2: Gains de bien-être de la stabilisation des prix faibles ; c'est l'instabilité du revenu qui compte | E2: Hypothèses de marchés complets | F2: Cibler la recette/le revenu plutôt que le prix
A3: Deaton & Laroque (1992), Review of Economic Studies 59(1) | B3: Stocks régulateurs | C3: Monde | D3: Les prix des matières premières ont de longues périodes de calme et des pics : les stocks s'épuisent | E3: Modèle de stockage compétitif | F3: Un fonds doit être dimensionné pour des chocs longs
A4: Cashin, Liang & McDermott (2000), IMF Staff Papers 47(2) | B4: Fonds de stabilisation | C4: Monde | D4: Les chocs de prix sont très persistants (plusieurs années) pour de nombreuses matières premières | E4: Échantillon 1957-98 | F4: Une règle de décaissement doit supposer que le choc peut durer >= 2 campagnes
A5: Deaton (1999), Journal of Economic Perspectives 13(3) | B5: Offices de commercialisation | C5: Afrique | D5: Les offices ont souvent capté les hausses et transmis les baisses | E5: Analyse historique | F5: Règle de partage transparente des hausses
A6: Varangis & Larson (1996), WB Policy Research WP 1667 | B6: Couverture (futures/options) | C6: Pays en développement | D6: Les instruments de marché sont moins coûteux que les fonds pour les risques de court terme | E6: Ne couvrent pas les chocs pluriannuels | F6: Options put sur une partie des ventes anticipées
A7: Borensztein, Jeanne & Sandri (2013), Journal of Development Economics 101 | B7: Couverture macro | C7: Exportateurs de matières premières | D7: La couverture réduit fortement le besoin de réserves de précaution | E7: Coût des primes, risque politique en cas de perte | F7: Complément aux ventes anticipées
A8: Gilbert (1996), World Development 24(1) | B8: Accords internationaux de produits | C8: Monde | D8: Échec des accords de stabilisation (stocks, quotas) | E8: — | F8: Éviter les mécanismes de soutien des cours mondiaux (ex. ITRC hévéa)
A9: Baffes & Gardner (2003), Policy Reform 6(3) | B9: Transmission des prix | C9: 10 pays | D9: Transmission faible et lente sous régimes administrés | E9: Données annuelles | F9: Mesurer la transmission séparément par régime
A10: Meyer & von Cramon-Taubadel (2004), Journal of Agricultural Economics 55(3) | B10: Transmission asymétrique | C10: Revue | D10: L'asymétrie est fréquente ; méthodes ECM/seuils | E10: Sensibilité aux méthodes | F10: Tester beta hausse vs beta baisse
A11: Shin, Yu & Greenwood-Nimmo (2014), in Festschrift P. Schmidt, Springer | B11: NARDL | C11: Méthode | D11: Cadre pour estimer des effets de long terme asymétriques | E11: Exige des séries mensuelles longues | F11: Méthode recommandée pour l'annexe économétrique
A12: Minot (2011), IFPRI Discussion Paper 1059 | B12: Transmission prix vivriers | C12: Afrique subsaharienne | D12: Transmission forte pour le riz importé, faible pour le maïs | E12: Données 2007-08 | F12: Riz : surveiller ; maïs : ne pas forcer l'analyse internationale
... A19: OCDE (2011), Managing Risk in Agriculture: Policy Assessment and Design | B19: Gestion des risques | C19: OCDE | D19: Distinguer risques normaux (exploitant), marchands (marché) et catastrophiques (État) | E19: Pays développés | F19: Répartir les couches de risque entre acteurs

Sheet CARTE_QUALI
A1: filiere | B1: exposition | C1: transmission | D1: absorbeur | E1: vulnerabilite
A2: Banane dessert | B2: Forte (UE), contrats en EUR | C2: Faible : contrats annuels intégrés ; pas de risque de change (FCFA arrimé à l'EUR) | D2: Producteurs intégrés (plantations industrielles) | E2: Vulnérabilité d'accès au marché (préférences UE, normes) plus que de prix
A3: Ananas, mangue | B3: Forte (UE) | C3: Non mesurable (prix contractuels, données de prix producteur absentes) | D3: Exportateurs / stations de conditionnement | E3: Choc de compétitivité structurel (ananas MD2) et sanitaire (mouche des fruits), non un choc de prix
A4: Sucre | B4: Faible (marché intérieur protégé) | C4: Faible : protection à l'importation | D4: Consommateur / budget (prix intérieur administré) | E4: Coût de protection pour le consommateur
A5: Riz importé | B5: Forte (importations ~1,5 Mt) | C5: Partielle (~0,4 au consommateur en 2023) | D5: Importateurs, État (fiscalité), consommateurs | E5: Choc de pouvoir d'achat urbain
A6: Maïs | B6: Faible | C6: Non significative | D6: — | E6: Analyse internationale non pertinente
