Workbook

Sheet Lisez-moi
A1: Base de données du benchmark des prix agricoles – Côte d'Ivoire
A3: Objet | B3: Traçabilité complète des prix utilisés dans la note « Les prix agricoles ivoiriens sont-ils compétitifs ? » (octobre 2026).
A4: Date d'arrêté des données | B4: 1er octobre 2026 (dernières annonces : prix cacao/café 2026-27 du 01/09/2026 ; prix COCOBOD du 25/09/2026).
A5: Règle d'or | B5: Aucun graphique ni chiffre de la note n'est produit en dehors de cette base. Toutes les conversions sont des formules visibles.
A6: Codes couleur | B6: Bleu = donnée saisie (prix d'origine, taux) ; noir = formule ; vert = renvoi vers un autre onglet ; fond jaune = paramètre ou hypothèse à valider.
A7: Fiabilité | B7: A = source officielle primaire ; B = presse/agence reprenant une annonce officielle datée ; C = source secondaire, commerciale ou approximation (indicatif).
A8: Observations | B8: Une ligne par prix : produit, qualité, stade, campagne, pays, monnaie, unité, prix d'origine, taux de change de la même période, prix FCFA/kg, référence internationale, taux de transmission, source, URL, date de consultation, remarque.
A9: Change_mensuel / Change_periodes | B9: Taux mensuels (BCE pour l'euro et donc le FCFA ; BRI et banques centrales pour les autres monnaies) et moyennes exactes de chaque période de comparaison.
A10: Cours_mensuels / Cours_periodes | B10: Cours internationaux mensuels (Banque mondiale « Pink Sheet » jusqu'en janvier 2026, compléments FMI/OIC/SGX ensuite) et moyennes par période.
A11: Cacao_transmission | B11: Série 2016/17-2026/27 par demi-campagne : prix CI, prix Ghana, cours mondial, taux de transmission.
A12: Series_CI | B12: Prix officiels ivoiriens sur 10 campagnes, en nominal et en FCFA constants 2025 ; coefficients de variation.
A13: Indicateurs | B13: Comparaisons deux à deux (écart absolu, écart relatif, indice, transmission) et médianes des comparateurs.
A14: Decomposition | B14: Décomposition de la valeur (cacao, anacarde, caoutchouc, palmier).
... A19: Limites d'accès | B19: L'environnement de production n'autorisait pas le téléchargement direct (FAOSTAT, Comtrade, Eurostat, API Banque mondiale). Les fichiers primaires utilisés sont archivés dans SOURCES/donnees_primaires ; les autres chiffres proviennent des pages citées (URL).

Sheet Matrice
A1: Matrice de synthèse – compétitivité-prix des filières ivoiriennes
A3: Filière | B3: Prix CI (FCFA/kg) | C3: Benchmark (pays) | D3: Prix benchmark (FCFA/kg) | E3: Écart CI vs benchmark | F3: Part producteur / transmission | G3: Tendance (10 ans, nominal) | H3: Facteur explicatif principal | I3: Diagnostic | J3: Fiabilité
A4: Cacao | B4: =Indicateurs!E32 -> 1200 | C4: Ghana (ouverture 2026/27) | D4: =Indicateurs!F32 -> 2085.7803 | E4: =Indicateurs!H32 -> -0.42467575 | F4: =Indicateurs!J32 -> 0.35423886 | G4: =Series_CI!E17 -> 1.5454545 | H4: Ventes anticipées conclues au creux du marché (mars-juin 2026) ; règle ≥60 % CAF ; prélèvements ≈22 % du CAF ; Ghana : 70 % du FOB réalisé garanti par la loi | I4: Rémunération inférieure au benchmark ; transmission faible à court terme (décalage des ventes anticipées) | J4: A/B
A5: Café | B5: =Indicateurs!E33 -> 1300 | C5: Vietnam, Ouganda (2026) | D5: =Indicateurs!F33 -> 1916.6382 | E5: =Indicateurs!H33 -> -0.32172906 | F5: =Indicateurs!J33 -> 0.57695765 | G5: =Series_CI!G17 -> 1.2666667 | H5: Prix administré aligné sur ventes anticipées ; productivité très faible (production -70 % en 2024/25) | I5: Rémunération inférieure au benchmark ; problème de productivité plus que de prix | J5: A/B/C
A6: Anacarde | B6: =Indicateurs!E34 -> 400 | C6: Burkina, G.-Bissau, Ghana (2026) | D6: =Indicateurs!F34 -> 410 | E6: =Indicateurs!H34 -> -0.024390244 | F6: =Indicateurs!J34 -> 0.45694742 | G6: =Series_CI!H17 -> 0.21428571 | H6: Plancher aligné sur les voisins UEMOA ; forte valeur captée entre le port et le CFR Asie ; Ghana/Tanzanie mieux transmis (enchères, qualité) | I6: Prix au niveau des voisins UEMOA, nettement inférieur au Ghana ; valeur captée en aval du port | J6: B/C
A7: Coton | B7: =Indicateurs!E35 -> 310 | C7: Burkina, Mali, Bénin, Togo (2025/26) | D7: =Indicateurs!F35 -> 300 | E7: =Indicateurs!H35 -> 0.033333333 | F7: =Indicateurs!J35 -> 0.72795032 | G7: =Series_CI!I17 -> 0.16981132 | H7: Prix administré soutenu par une subvention de 25,3 Mds FCFA (2025/26) ; rendements dans la moyenne régionale | I7: Prix proche de la référence, soutenu par le budget | J7: A/B
A8: Caoutchouc | B8: =Indicateurs!E36 -> 806.66667 | C8: Thaïlande, Indonésie | D8: =Indicateurs!F36 -> 1144.0664 | E8: =Indicateurs!H36 -> -0.29491271 | F8: =Decomposition!B22 -> 0.59875527 | G8: n.d. | H8: Formule : 63-66 % d'un prix de référence net de coûts ; DRC conventionnel 60 % < DRC réel ; pouvoir de négociation des usiniers | I8: Transmission faible ; rémunération inférieure aux producteurs asiatiques | J8: B/C
A9: Palmier à huile | B9: =Indicateurs!E37 -> 80 | C9: Indonésie, Malaisie | D9: =Indicateurs!F37 -> 120.96905 | E9: =Indicateurs!H37 -> -0.33867382 | F9: =Decomposition!B28 -> 0.14347142 | G9: n.d. | H9: Prix du régime ≈14 % du prix mondial de l'huile brute contre ≈21-22 % en Asie (≈13 % du prix intérieur de l'huile), alors que l'huile brute est payée au-dessus du prix mondial sur le marché intérieur | I9: Rémunération inférieure ; partage de la valeur défavorable au planteur | J9: A/B
A10: Riz | B10: =Indicateurs!E38 -> 233 | C10: Sénégal (2025) | D10: =Indicateurs!F38 -> 130 | E10: =Indicateurs!H38 -> 0.79230769 | F10: =Observations!$Y$116 -> 1.5103939 | G10: n.d. | H10: Paddy payé au-dessus de la parité FOB du riz importé (équivalent paddy du riz thaï 5 %, hors fret et droits) : coûts de production et d'usinage élevés, rendements faibles | I10: Rémunération supérieure mais compétitivité faible face aux importations | J10: A/B
A11: Banane dessert | B11: n.d. | C11: Équateur (prix minimum) | D11: =Observations!$S$119 -> 216.93201 | E11: n.d. | F11: n.d. | G11: n.d. | H11: Filière intégrée (plantations exportatrices) : aucun prix producteur public en Côte d'Ivoire | I11: Données insuffisantes pour conclure | J11: B
A12: Mangue | B12: =Observations!$S$120 -> 220 | C12: Burkina Faso | D12: =Observations!$S$121 -> 95 | E12: n.c. | F12: n.d. | G12: n.d. | H12: Prix CI fixé en station (220 FCFA/kg) et à la caisse bord champ (poids non publié) : stades non comparables | I12: Données insuffisantes pour conclure | J12: B
A13: Ananas, maïs, manioc, igname, plantain, tomate, oignon, cola, coco, canne | B13: n.d. | C13: — | D13: n.d. | E13: n.d. | F13: n.d. | G13: n.d. | H13: Pas de prix bord champ public harmonisé (OCPV publie des prix à la consommation) ; FAOSTAT non accessible depuis l'environnement d'étude | I13: Données insuffisantes pour conclure | J13: —
A15: Lecture : écart = prix CI ÷ benchmark − 1 ; part producteur = prix CI ÷ référence internationale (caoutchouc : base sèche ; palmier : prix du régime ÷ prix mondial de l'huile ; riz : ÷ équivalent paddy du riz thaï 5 % FOB). n.d. = non disponible ; n.c. = non comparable.

Sheet Indicateurs
A1: Indicateurs de compétitivité-prix : comparaisons deux à deux (même produit, même stade, même période)
A3: Filière | B3: Comparaison | C3: ID Côte d'Ivoire | D3: ID comparateur | E3: Prix CI (FCFA/kg) | F3: Prix comparateur (FCFA/kg) | G3: I. Écart absolu (FCFA/kg) | H3: II. Écart relatif | I3: Indice CI (comparateur = 100) | J3: IV. Transmission CI | K3: IV. Transmission comparateur | L3: Comparabilité | M3: Commentaire
A4: Cacao | B4: Ghana – ouverture 2026/27 | C4: CAC-CI-2026/27-P | D4: CAC-GH-2026/27-P | E4: =Observations!$S$42 -> 1200 | F4: =Observations!$S$43 -> 2085.7803 | G4: =E4-F4 -> -885.78034 | H4: =E4/F4-1 -> -0.42467575 | I4: =E4/F4*100 -> 57.532425 | J4: =Observations!$Y$42 -> 0.35423886 | K4: =Observations!$Y$43 -> 0.61572037 | L4: Directe | M4: Deux prix administrés, même grade, même date ; Ghana = 71 % du FOB réalisé (Act 1182)
A5: Cacao | B5: Ghana – campagne principale 2025/26 | C5: CAC-CI-2025/26-P | D5: CAC-GH-2025/26-P | E5: =Observations!$S$20 -> 2800 | F5: =Observations!$S$40 -> 2964.4546 | G5: =E5-F5 -> -164.45457 | H5: =E5/F5-1 -> -0.055475489 | I5: =E5/F5*100 -> 94.452451 | J5: =Observations!$Y$20 -> 1.0252265 | K5: =Observations!$Y$40 -> 1.0854419 | L5: Directe | M5: Prix d'ouverture ; Ghana ramené à 41 392 GH¢/t au 12/02/2026
A6: Cacao | B6: Ghana – campagne intermédiaire 2025/26 | C6: CAC-CI-2025/26-I | D6: CAC-GH-2025/26-I | E6: =Observations!$S$21 -> 1200 | F6: =Observations!$S$41 -> 2059.1954 | G6: =E6-F6 -> -859.19544 | H6: =E6/F6-1 -> -0.41724813 | I6: =E6/F6*100 -> 58.275187 | J6: =Observations!$Y$21 -> 0.45005266 | K6: =Observations!$Y$41 -> 0.77228865 | L6: Directe
A7: Cacao | B7: Cameroun – mars-avril 2026 (marché libéralisé) | C7: CAC-CI-2025/26-I | D7: CAC-CM-2026-04 | E7: =Observations!$S$21 -> 1200 | F7: =Observations!$S$45 -> 1325 | G7: =E7-F7 -> -125 | H7: =E7/F7-1 -> -0.094339623 | I7: =E7/F7*100 -> 90.566038 | J7: =Observations!$Y$21 -> 0.45005266 | K7: =Observations!$Y$45 -> 0.70838523 | L7: Indicative | M7: Prix de marché relevé (fourchette) vs prix garanti
A8: Cacao | B8: Cameroun – fin juin 2026 | C8: CAC-CI-2025/26-I | D8: CAC-CM-2026-06 | E8: =Observations!$S$21 -> 1200 | F8: =Observations!$S$47 -> 2175 | G8: =E8-F8 -> -975 | H8: =E8/F8-1 -> -0.44827586 | I8: =E8/F8*100 -> 55.172414 | J8: =Observations!$Y$21 -> 0.45005266 | K8: =Observations!$Y$47 -> 0.86887366 | L8: Indicative | M8: Le marché libéralisé suit le cours mondial avec peu de retard
A9: Cacao | B9: Nigeria – sept. 2026 (source secondaire) | C9: CAC-CI-2026/27-P | D9: CAC-NG-2026-09 | E9: =Observations!$S$42 -> 1200 | F9: =Observations!$S$48 -> 2436.6927 | G9: =E9-F9 -> -1236.6927 | H9: =E9/F9-1 -> -0.5075292 | I9: =E9/F9*100 -> 49.24708 | J9: =Observations!$Y$42 -> 0.35423886 | K9: =Observations!$Y$48 -> 0.71930937 | L9: Indicative | M9: Source C : à confirmer
A10: Cacao | B10: Équateur – février 2026 | C10: CAC-CI-2025/26-P | D10: CAC-EC-2026-02 | E10: =Observations!$S$20 -> 2800 | F10: =Observations!$S$50 -> 1223.059 | G10: =E10-F10 -> 1576.941 | H10: =E10/F10-1 -> 1.2893418 | I10: =E10/F10*100 -> 228.93418 | J10: =Observations!$Y$20 -> 1.0252265 | K10: =Observations!$Y$50 -> 0.61458256 | L10: Indicative | M10: Qualités différentes (CCN-51/Nacional)
A11: Café | B11: Vietnam – fin sept. 2026 | C11: CAF-CI-2026/27 | D11: CAF-VN-2026-09 | E11: =Observations!$S$61 -> 1300 | F11: =Observations!$S$63 -> 2037.167 | G11: =E11-F11 -> -737.16704 | H11: =E11/F11-1 -> -0.36185891 | I11: =E11/F11*100 -> 63.814109 | J11: =Observations!$Y$61 -> 0.57695765 | K11: =Observations!$Y$63 -> 0.9041224 | L11: Directe | M11: Café vert robusta, prix bord champ/collecteur
A12: Café | B12: Ouganda – juillet 2026 | C12: CAF-CI-2025/26 | D12: CAF-UG-2026-07 | E12: =Observations!$S$60 -> 1700 | F12: =Observations!$S$62 -> 1796.1094 | G12: =E12-F12 -> -96.109383 | H12: =E12/F12-1 -> -0.053509761 | I12: =E12/F12*100 -> 94.649024 | J12: =Observations!$Y$60 -> 0.7385801 | K12: =Observations!$Y$62 -> 0.76556593 | L12: Directe | M12: FAQ ≈ café vert non classé ; taux de change de source C
A13: Anacarde | B13: Burkina Faso – 2026 | C13: ANA-CI-2026 | D13: ANA-BF-2026 | E13: =Observations!$S$74 -> 400 | F13: =Observations!$S$77 -> 385 | G13: =E13-F13 -> 15 | H13: =E13/F13-1 -> 0.038961039 | I13: =E13/F13*100 -> 103.8961 | J13: =Observations!$Y$74 -> 0.45694742 | K13: =Observations!$Y$77 -> 0.43981189 | L13: Directe | M13: Deux prix planchers, même devise
A14: Anacarde | B14: Guinée-Bissau – 2026 | C14: ANA-CI-2026 | D14: ANA-GW-2026 | E14: =Observations!$S$74 -> 400 | F14: =Observations!$S$78 -> 410 | G14: =E14-F14 -> -10 | H14: =E14/F14-1 -> -0.024390244 | I14: =E14/F14*100 -> 97.560976 | J14: =Observations!$Y$74 -> 0.45694742 | K14: =Observations!$Y$78 -> 0.4683711 | L14: Directe | M14: Prix de référence producteur
A15: Anacarde | B15: Ghana – 2026 | C15: ANA-CI-2026 | D15: ANA-GH-2026 | E15: =Observations!$S$74 -> 400 | F15: =Observations!$S$80 -> 607.91081 | G15: =E15-F15 -> -207.91081 | H15: =E15/F15-1 -> -0.34200874 | I15: =E15/F15*100 -> 65.799126 | J15: =Observations!$Y$74 -> 0.45694742 | K15: =Observations!$Y$80 -> 0.69445819 | L15: Directe | M15: Prix minimum ; respect effectif non documenté
A16: Anacarde | B16: Tanzanie – 2025/26 (enchères) | C16: ANA-CI-2026 | D16: ANA-TZ-2025/26 | E16: =Observations!$S$74 -> 400 | F16: =Observations!$S$82 -> 691.81801 | G16: =E16-F16 -> -291.81801 | H16: =E16/F16-1 -> -0.42181326 | I16: =E16/F16*100 -> 57.818674 | J16: =Observations!$Y$74 -> 0.45694742 | K16: =Observations!$Y$82 -> 0.79031113 | L16: Indicative | M16: Saison et qualité (KOR) différentes ; prix d'enchère en magasin primaire
A17: Anacarde | B17: Mali – 2025 | C17: ANA-CI-2025 | D17: ANA-ML-2025 | E17: =Observations!$S$73 -> 425 | F17: =Observations!$S$79 -> 390 | G17: =E17-F17 -> 35 | H17: =E17/F17-1 -> 0.08974359 | I17: =E17/F17*100 -> 108.97436 | J17: =Observations!$Y$73 | K17: =Observations!$Y$79 | L17: Directe | M17: Même année (2025)
A18: Coton | B18: Burkina Faso – 2025/26 | C18: COT-CI-2025/26 | D18: COT-BF-2025/26 | E18: =Observations!$S$93 -> 310 | F18: =Observations!$S$94 -> 325 | G18: =E18-F18 -> -15 | H18: =E18/F18-1 -> -0.046153846 | I18: =E18/F18*100 -> 95.384615 | J18: =Observations!$Y$93 -> 0.72795032 | K18: =Observations!$Y$94 | L18: Directe | M18: Prix administrés, même qualité (1er choix)
A19: Coton | B19: Mali – 2025/26 | C19: COT-CI-2025/26 | D19: COT-ML-2025/26 | E19: =Observations!$S$93 -> 310 | F19: =Observations!$S$95 -> 300 | G19: =E19-F19 -> 10 | H19: =E19/F19-1 -> 0.033333333 | I19: =E19/F19*100 -> 103.33333 | J19: =Observations!$Y$93 -> 0.72795032 | K19: =Observations!$Y$95 | L19: Directe
A20: Coton | B20: Bénin – 2025/26 | C20: COT-CI-2025/26 | D20: COT-BJ-2025/26 | E20: =Observations!$S$93 -> 310 | F20: =Observations!$S$96 -> 300 | G20: =E20-F20 -> 10 | H20: =E20/F20-1 -> 0.033333333 | I20: =E20/F20*100 -> 103.33333 | J20: =Observations!$Y$93 -> 0.72795032 | K20: =Observations!$Y$96 | L20: Directe | M20: Coton conventionnel
A21: Coton | B21: Togo – 2025/26 | C21: COT-CI-2025/26 | D21: COT-TG-2025/26 | E21: =Observations!$S$93 -> 310 | F21: =Observations!$S$97 -> 300 | G21: =E21-F21 -> 10 | H21: =E21/F21-1 -> 0.033333333 | I21: =E21/F21*100 -> 103.33333 | J21: =Observations!$Y$93 -> 0.72795032 | K21: =Observations!$Y$97 | L21: Directe | M21: Source C
A22: Coton | B22: Sénégal – 2025/26 | C22: COT-CI-2025/26 | D22: COT-SN-2025/26 | E22: =Observations!$S$93 -> 310 | F22: =Observations!$S$98 -> 350 | G22: =E22-F22 -> -40 | H22: =E22/F22-1 -> -0.11428571 | I22: =E22/F22*100 -> 88.571429 | J22: =Observations!$Y$93 -> 0.72795032 | K22: =Observations!$Y$98 | L22: Indicative | M22: « Jusqu'à 350 FCFA » : source C
A23: Caoutchouc | B23: Thaïlande – mai 2025 (base sèche) | C23: CAO-CI-2025-04 | D23: CAO-TH-2025-05 | E23: =Observations!$V$102 -> 730 | F23: =Observations!$V$109 -> 1004.295 | G23: =E23-F23 -> -274.29498 | H23: =E23/F23-1 -> -0.27312193 | I23: =E23/F23*100 -> 72.687807 | J23: =Observations!$Y$102 -> 0.60691659 | K23: =Observations!$Y$109 -> 1.0060933 | L23: Indicative | M23: CI converti en kg sec (DRC 60 %) ; un mois d'écart
A24: Caoutchouc | B24: Indonésie – août/sept. 2026 (base sèche) | C24: CAO-CI-2026-09 | D24: CAO-ID-2026-08 | E24: =Observations!$V$108 -> 806.66667 | F24: =Observations!$V$110 -> 1283.8378 | G24: =E24-F24 -> -477.17111 | H24: =E24/F24-1 -> -0.37167555 | I24: =E24/F24*100 -> 62.832445 | J24: =Observations!$Y$108 | K24: =Observations!$Y$110 | L24: Indicative | M24: Prix de référence provincial ; un mois d'écart
A25: Palmier à huile | B25: Indonésie (Riau) – janvier 2026 | C25: PAL-CI-FFB-2026-01 | D25: PAL-ID-FFB-2026-01 | E25: =Observations!$S$111 -> 80 | F25: =Observations!$S$114 -> 114.8472 | G25: =E25-F25 -> -34.847202 | H25: =E25/F25-1 -> -0.3034223 | I25: =E25/F25*100 -> 69.65777 | J25: =Observations!$Y$111 -> 0.14347142 | K25: =Observations!$Y$114 -> 0.20596614 | L25: Indicative | M25: Bord champ (CI) vs livraison usine (Riau)
A26: Palmier à huile | B26: Malaisie – 2025 vs CI janv. 2026 | C26: PAL-CI-FFB-2026-01 | D26: PAL-MY-FFB-2025 | E26: =Observations!$S$111 -> 80 | F26: =Observations!$S$115 -> 127.0909 | G26: =E26-F26 -> -47.090897 | H26: =E26/F26-1 -> -0.37052927 | I26: =E26/F26*100 -> 62.947073 | J26: =Observations!$Y$111 -> 0.14347142 | K26: =Observations!$Y$115 -> 0.21688915 | L26: Indicative | M26: Périodes proches mais différentes
A27: Riz | B27: Sénégal – 2025 | C27: RIZ-CI-2025 | D27: RIZ-SN-2025 | E27: =Observations!$S$116 -> 233 | F27: =Observations!$S$117 -> 130 | G27: =E27-F27 -> 103 | H27: =E27/F27-1 -> 0.79230769 | I27: =E27/F27*100 -> 179.23077 | J27: =Observations!$Y$116 -> 1.5103939 | K27: =Observations!$Y$117 -> 0.84270905 | L27: Directe | M27: Prix producteur fixé (130) ; usiniers 160 avec subvention
A28: Riz | B28: Vietnam – fin 2025 (paddy frais) | C28: RIZ-CI-2025 | D28: RIZ-VN-2025 | E28: =Observations!$S$116 -> 233 | F28: =Observations!$S$118 -> 123.69116 | G28: =E28-F28 -> 109.30884 | H28: =E28/F28-1 -> 0.88372396 | I28: =E28/F28*100 -> 188.3724 | J28: =Observations!$Y$116 -> 1.5103939 | K28: =Observations!$Y$118 -> 0.80181277 | L28: Indicative | M28: Paddy frais (humide) vs paddy sec
A30: III. Position relative : médiane des comparateurs directs de la même période (à défaut de comparateur direct : médiane des comparateurs indicatifs, résultat indicatif)
A31: Filière | B31: Période de référence | C31: ID CI | D31: Statut du benchmark | E31: Prix CI (FCFA/kg) | F31: Médiane comparateurs (FCFA/kg) | G31: Écart absolu | H31: Écart relatif | I31: Indice CI (médiane = 100) | J31: Transmission CI | K31: Médiane transmission comparateurs | L31: Nb comparateurs | M31: Comparateurs retenus
A32: Cacao | B32: Ouverture 2026/27 | C32: CAC-CI-2026/27-P | D32: Directs | E32: =Observations!$S$42 -> 1200 | F32: =MEDIAN(Observations!$S$43) -> 2085.7803 | G32: =E32-F32 -> -885.78034 | H32: =E32/F32-1 -> -0.42467575 | I32: =E32/F32*100 -> 57.532425 | J32: =Observations!$Y$42 -> 0.35423886 | K32: =IFERROR(MEDIAN(Observations!$Y$43),"") -> 0.61572037 | L32: 1 | M32: Ghana (seul comparateur direct à la même date ; Nigeria sept. 2026 exclu : source C, comparaison indicative)
A33: Café | B33: Sept. 2026 (CI 2026/27) | C33: CAF-CI-2026/27 | D33: Directs | E33: =Observations!$S$61 -> 1300 | F33: =MEDIAN(Observations!$S$63,Observations!$S$62) -> 1916.6382 | G33: =E33-F33 -> -616.63821 | H33: =E33/F33-1 -> -0.32172906 | I33: =E33/F33*100 -> 67.827094 | J33: =Observations!$Y$61 -> 0.57695765 | K33: =IFERROR(MEDIAN(Observations!$Y$63,Observations!$Y$62),"") -> 0.83484417 | L33: 2 | M33: Vietnam (sept. 2026), Ouganda (juil. 2026)
A34: Anacarde | B34: Campagne 2026 | C34: ANA-CI-2026 | D34: Directs | E34: =Observations!$S$74 -> 400 | F34: =MEDIAN(Observations!$S$77,Observations!$S$78,Observations!$S$80) -> 410 | G34: =E34-F34 -> -10 | H34: =E34/F34-1 -> -0.024390244 | I34: =E34/F34*100 -> 97.560976 | J34: =Observations!$Y$74 -> 0.45694742 | K34: =IFERROR(MEDIAN(Observations!$Y$77,Observations!$Y$78,Observations!$Y$80),"") -> 0.4683711 | L34: 3 | M34: Burkina, Guinée-Bissau, Ghana (Tanzanie exclue : saison, qualité et stade différents, comparaison indicative)
A35: Coton | B35: Campagne 2025/26 | C35: COT-CI-2025/26 | D35: Directs | E35: =Observations!$S$93 -> 310 | F35: =MEDIAN(Observations!$S$94,Observations!$S$95,Observations!$S$96,Observations!$S$97) -> 300 | G35: =E35-F35 -> 10 | H35: =E35/F35-1 -> 0.033333333 | I35: =E35/F35*100 -> 103.33333 | J35: =Observations!$Y$93 -> 0.72795032 | K35: =IFERROR(MEDIAN(Observations!$Y$94,Observations!$Y$95,Observations!$Y$96,Observations!$Y$97),"") | L35: 4 | M35: Burkina, Mali, Bénin, Togo (Sénégal exclu : comparaison indicative)
A36: Caoutchouc | B36: 2025-2026 (base sèche) | C36: CAO-CI-2026-09 | D36: Indicatifs (aucun direct) | E36: =Observations!$V$108 -> 806.66667 | F36: =MEDIAN(Observations!$V$109,Observations!$V$110) -> 1144.0664 | G36: =E36-F36 -> -337.39971 | H36: =E36/F36-1 -> -0.29491271 | I36: =E36/F36*100 -> 70.508729 | J36: =Observations!$Y$108 | K36: =IFERROR(MEDIAN(Observations!$Y$109,Observations!$Y$110),"") -> 1.0060933 | L36: 2 | M36: Thaïlande (mai 2025), Indonésie (août 2026)
A37: Palmier à huile | B37: Janv. 2026 / 2025 | C37: PAL-CI-FFB-2026-01 | D37: Indicatifs (aucun direct) | E37: =Observations!$S$111 -> 80 | F37: =MEDIAN(Observations!$S$114,Observations!$S$115) -> 120.96905 | G37: =E37-F37 -> -40.96905 | H37: =E37/F37-1 -> -0.33867382 | I37: =E37/F37*100 -> 66.132618 | J37: =Observations!$Y$111 -> 0.14347142 | K37: =IFERROR(MEDIAN(Observations!$Y$114,Observations!$Y$115),"") -> 0.21142764 | L37: 2 | M37: Indonésie (Riau), Malaisie
A38: Riz | B38: 2025 | C38: RIZ-CI-2025 | D38: Directs | E38: =Observations!$S$116 -> 233 | F38: =MEDIAN(Observations!$S$117) -> 130 | G38: =E38-F38 -> 103 | H38: =E38/F38-1 -> 0.79230769 | I38: =E38/F38*100 -> 179.23077 | J38: =Observations!$Y$116 -> 1.5103939 | K38: =IFERROR(MEDIAN(Observations!$Y$117),"") -> 0.84270905 | L38: 1 | M38: Sénégal (Vietnam exclu : paddy frais, comparaison indicative)
A40: VI. Transmission moyenne sur la durée (prix CI ÷ cours international de la même campagne)
A41: Filière | B41: Période | E41: Moyenne CI | F41: Moyenne 3 dernières campagnes | M41: Note
A42: Café | B42: 2016/17-2025/26 | E42: =AVERAGE(Observations!$Y$51,Observations!$Y$52,Observations!$Y$53,Observations!$Y$54,Observations!$Y$55,Observations!$Y$56,Observations!$Y$57,Observations!$Y$58,Observations!$Y$59,Observations!$Y$60) -> 0.59434815 | F42: =AVERAGE(Observations!$Y$58,Observations!$Y$59,Observations!$Y$60) -> 0.54392516 | M42: Robusta (indicateur OIC) ; 2025/26 : oct. 2025-août 2026
A43: Coton | B43: 2017/18-2025/26 | E43: =AVERAGE(Observations!$Y$85,Observations!$Y$86,Observations!$Y$87,Observations!$Y$88,Observations!$Y$89,Observations!$Y$90,Observations!$Y$91,Observations!$Y$92,Observations!$Y$93) -> 0.58600087 | F43: =AVERAGE(Observations!$Y$91,Observations!$Y$92,Observations!$Y$93) -> 0.64572195 | M43: Équivalent fibre (rendement à l'égrenage) ÷ indice A ; 2025/26 partiel
A44: Cacao | B44: 2016/17-2025/26 (demi-campagnes) | E44: =Cacao_transmission!F26 -> 0.56393904 | F44: =Cacao_transmission!F27 -> 0.49231981 | M44: Ghana sur la même période : voir onglet Cacao_transmission

Sheet Observations
A1: ID | B1: Filière | C1: Produit exact | D1: Pays | E1: Année / campagne | F1: Période couverte | G1: Type de prix | H1: Stade de commercialisation | I1: Qualité / spécification | J1: Prix original | K1: Monnaie | L1: Unité d'origine | M1: kg par unité | N1: Code période (change) | O1: Taux de change (monnaie / USD) | P1: Source du taux de change | Q1: Taux FCFA / USD (même période) | R1: Prix USD/kg | S1: Prix FCFA/kg | T1: Facteur d'équivalence | U1: Base de comparaison | V1: Prix FCFA/kg (base de comparaison) | W1: ID référence internationale | X1: Prix international de référence (FCFA/kg) | Y1: Taux de transmission | Z1: ID valeur FOB/CAF nationale | AA1: Valeur FOB/CAF (FCFA/kg) | AB1: Part producteur dans FOB/CAF | AC1: Source | AD1: URL | AE1: Date de consultation | AF1: Fiabilité | AG1: Remarque méthodologique
A2: CAC-CI-2016/17-P | B2: Cacao | C2: Fèves de cacao marchandes | D2: Côte d'Ivoire | E2: 2016/17 | F2: Campagne principale (oct.-mars) | G2: Prix minimum garanti (administré) | H2: Bord champ | I2: Bien fermenté, séché, trié (grade marchand) | J2: 1100 | K2: XOF | L2: kg | M2: 1 | N2: 2016-10:2017-03 | O2: =IF(K2="USD",1,INDEX(Change_periodes!$D$1:$N$400,MATCH($N2,Change_periodes!$A$1:$A$400,0),MATCH($K2,Change_periodes!$D$1:$N$1,0))) -> 612.12961 | P2: BCE (parité fixe 655,957 FCFA/EUR) | Q2: =INDEX(Change_periodes!$D$1:$D$400,MATCH($N2,Change_periodes!$A$1:$A$400,0)) -> 612.12961 | R2: =IFERROR(J2/M2/O2,"") -> 1.797005 | S2: =IFERROR(R2*Q2,"") -> 1100 | T2: 1 | U2: FCFA/kg de produit tel que vendu | V2: =IFERROR(S2/T2,"") -> 1100 | W2: INT-CAC-2016/17-P | X2: =IF(W2="","",IFERROR(INDEX($V$1:$V$178,MATCH(W2,$A$1:$A$178,0)),"")) -> 1405.57 | Y2: =IF(OR(X2="",V2=""),"",V2/X2) -> 0.78260066 | AA2: =IF(Z2="","",IFERROR(INDEX($V$1:$V$178,MATCH(Z2,$A$1:$A$178,0)),"")) | AB2: =IF(OR(AA2="",V2=""),"",V2/AA2) | AC2: CCC / Gouvernement (via Connectionivoirienne) – Le kilo de cacao à 1 100 FCFA pour la campagne 2016-2017 | AD2: https://connectionivoirienne.net/2016/09/28/cote-divoire-le-kilo-de-cacao-a-1-100-fcfa-pour-la-campagne-2016-2017 | AE2: 2026-10-01 | AF2: B | AG2: Prix administré par le CCC ; ventes anticipées ; règle ≥60 % du prix CAF de référence
A3: CAC-CI-2016/17-I | B3: Cacao | C3: Fèves de cacao marchandes | D3: Côte d'Ivoire | E3: 2016/17 | F3: Campagne intermédiaire (avr.-sept.) | G3: Prix minimum garanti (administré) | H3: Bord champ | I3: Bien fermenté, séché, trié (grade marchand) | J3: 700 | K3: XOF | L3: kg | M3: 1 | N3: 2017-04:2017-09 | O3: =IF(K3="USD",1,INDEX(Change_periodes!$D$1:$N$400,MATCH($N3,Change_periodes!$A$1:$A$400,0),MATCH($K3,Change_periodes!$D$1:$N$1,0))) -> 577.51424 | P3: BCE (parité fixe 655,957 FCFA/EUR) | Q3: =INDEX(Change_periodes!$D$1:$D$400,MATCH($N3,Change_periodes!$A$1:$A$400,0)) -> 577.51424 | R3: =IFERROR(J3/M3/O3,"") -> 1.2120913 | S3: =IFERROR(R3*Q3,"") -> 700 | T3: 1 | U3: FCFA/kg de produit tel que vendu | V3: =IFERROR(S3/T3,"") -> 700 | W3: INT-CAC-2016/17-I | X3: =IF(W3="","",IFERROR(INDEX($V$1:$V$178,MATCH(W3,$A$1:$A$178,0)),"")) -> 1147.1675 | Y3: =IF(OR(X3="",V3=""),"",V3/X3) -> 0.61019857 | AA3: =IF(Z3="","",IFERROR(INDEX($V$1:$V$178,MATCH(Z3,$A$1:$A$178,0)),"")) | AB3: =IF(OR(AA3="",V3=""),"",V3/AA3) | AC3: CCC (via Connectionivoirienne) – Prix bord champ du cacao pour la campagne intermédiaire fixé à 700 FCFA | AD3: https://connectionivoirienne.net/2017/03/30/cote-divoire-le-prix-bord-champ-du-cacao-pour-la-campagne-intermediaire-fixe-a-700-fcfa-1-euro/ | AE3: 2026-10-01 | AF3: B | AG3: Prix administré par le CCC ; ventes anticipées ; règle ≥60 % du prix CAF de référence
A4: CAC-CI-2017/18-P | B4: Cacao | C4: Fèves de cacao marchandes | D4: Côte d'Ivoire | E4: 2017/18 | F4: Campagne principale (oct.-mars) | G4: Prix minimum garanti (administré) | H4: Bord champ | I4: Bien fermenté, séché, trié (grade marchand) | J4: 700 | K4: XOF | L4: kg | M4: 1 | N4: 2017-10:2018-03 | O4: =IF(K4="USD",1,INDEX(Change_periodes!$D$1:$N$400,MATCH($N4,Change_periodes!$A$1:$A$400,0),MATCH($K4,Change_periodes!$D$1:$N$1,0))) -> 545.27827 | P4: BCE (parité fixe 655,957 FCFA/EUR) | Q4: =INDEX(Change_periodes!$D$1:$D$400,MATCH($N4,Change_periodes!$A$1:$A$400,0)) -> 545.27827 | R4: =IFERROR(J4/M4/O4,"") -> 1.2837482 | S4: =IFERROR(R4*Q4,"") -> 700 | T4: 1 | U4: FCFA/kg de produit tel que vendu | V4: =IFERROR(S4/T4,"") -> 700 | W4: INT-CAC-2017/18-P | X4: =IF(W4="","",IFERROR(INDEX($V$1:$V$178,MATCH(W4,$A$1:$A$178,0)),"")) -> 1156.0999 | Y4: =IF(OR(X4="",V4=""),"",V4/X4) -> 0.60548401 | AA4: =IF(Z4="","",IFERROR(INDEX($V$1:$V$178,MATCH(Z4,$A$1:$A$178,0)),"")) | AB4: =IF(OR(AA4="",V4=""),"",V4/AA4) | AC4: CCC (via Connectionivoirienne) – Le prix d'achat au producteur de cacao maintenu à 700 FCFA (campagne intermédiaire 2017-2018) | AD4: https://connectionivoirienne.net/2018/03/30/le-prix-dachat-au-producteur-de-cacao-en-cote-divoire-maintenu-a-700-francs-cfa | AE4: 2026-10-01 | AF4: B | AG4: Prix administré par le CCC ; ventes anticipées ; règle ≥60 % du prix CAF de référence
A5: CAC-CI-2017/18-I | B5: Cacao | C5: Fèves de cacao marchandes | D5: Côte d'Ivoire | E5: 2017/18 | F5: Campagne intermédiaire (avr.-sept.) | G5: Prix minimum garanti (administré) | H5: Bord champ | I5: Bien fermenté, séché, trié (grade marchand) | J5: 700 | K5: XOF | L5: kg | M5: 1 | N5: 2018-04:2018-09 | O5: =IF(K5="USD",1,INDEX(Change_periodes!$D$1:$N$400,MATCH($N5,Change_periodes!$A$1:$A$400,0),MATCH($K5,Change_periodes!$D$1:$N$1,0))) -> 557.21356 | P5: BCE (parité fixe 655,957 FCFA/EUR) | Q5: =INDEX(Change_periodes!$D$1:$D$400,MATCH($N5,Change_periodes!$A$1:$A$400,0)) -> 557.21356 | R5: =IFERROR(J5/M5/O5,"") -> 1.2562508 | S5: =IFERROR(R5*Q5,"") -> 700 | T5: 1 | U5: FCFA/kg de produit tel que vendu | V5: =IFERROR(S5/T5,"") -> 700 | W5: INT-CAC-2017/18-I | X5: =IF(W5="","",IFERROR(INDEX($V$1:$V$178,MATCH(W5,$A$1:$A$178,0)),"")) -> 1339.0761 | Y5: =IF(OR(X5="",V5=""),"",V5/X5) -> 0.52274847 | AA5: =IF(Z5="","",IFERROR(INDEX($V$1:$V$178,MATCH(Z5,$A$1:$A$178,0)),"")) | AB5: =IF(OR(AA5="",V5=""),"",V5/AA5) | AC5: CCC (via Connectionivoirienne) – Le prix d'achat au producteur de cacao maintenu à 700 FCFA (campagne intermédiaire 2017-2018) | AD5: https://connectionivoirienne.net/2018/03/30/le-prix-dachat-au-producteur-de-cacao-en-cote-divoire-maintenu-a-700-francs-cfa | AE5: 2026-10-01 | AF5: B | AG5: Prix administré par le CCC ; ventes anticipées ; règle ≥60 % du prix CAF de référence
A6: CAC-CI-2018/19-P | B6: Cacao | C6: Fèves de cacao marchandes | D6: Côte d'Ivoire | E6: 2018/19 | F6: Campagne principale (oct.-mars) | G6: Prix minimum garanti (administré) | H6: Bord champ | I6: Bien fermenté, séché, trié (grade marchand) | J6: 750 | K6: XOF | L6: kg | M6: 1 | N6: 2018-10:2019-03 | O6: =IF(K6="USD",1,INDEX(Change_periodes!$D$1:$N$400,MATCH($N6,Change_periodes!$A$1:$A$400,0),MATCH($K6,Change_periodes!$D$1:$N$1,0))) -> 576.214 | P6: BCE (parité fixe 655,957 FCFA/EUR) | Q6: =INDEX(Change_periodes!$D$1:$D$400,MATCH($N6,Change_periodes!$A$1:$A$400,0)) -> 576.214 | R6: =IFERROR(J6/M6/O6,"") -> 1.3015998 | S6: =IFERROR(R6*Q6,"") -> 750 | T6: 1 | U6: FCFA/kg de produit tel que vendu | V6: =IFERROR(S6/T6,"") -> 750 | W6: INT-CAC-2018/19-P | X6: =IF(W6="","",IFERROR(INDEX($V$1:$V$178,MATCH(W6,$A$1:$A$178,0)),"")) -> 1272.2114 | Y6: =IF(OR(X6="",V6=""),"",V6/X6) -> 0.58952468 | AA6: =IF(Z6="","",IFERROR(INDEX($V$1:$V$178,MATCH(Z6,$A$1:$A$178,0)),"")) | AB6: =IF(OR(AA6="",V6=""),"",V6/AA6) | AC6: CCC (via Agence Ecofin) – Cocoa farm-gate price set to CFA750 per kilo for 2018/2019 season | AD6: https://www.ecofinagency.com/agriculture/0210-39023-cote-d-ivoire-cocoa-farm-gate-price-set-to-cfa750-per-kilo-for-2018/2019-season | AE6: 2026-10-01 | AF6: B | AG6: Prix administré par le CCC ; ventes anticipées ; règle ≥60 % du prix CAF de référence
A7: CAC-CI-2018/19-I | B7: Cacao | C7: Fèves de cacao marchandes | D7: Côte d'Ivoire | E7: 2018/19 | F7: Campagne intermédiaire (avr.-sept.) | G7: Prix minimum garanti (administré) | H7: Bord champ | I7: Bien fermenté, séché, trié (grade marchand) | J7: 750 | K7: XOF | L7: kg | M7: 1 | N7: 2019-04:2019-09 | O7: =IF(K7="USD",1,INDEX(Change_periodes!$D$1:$N$400,MATCH($N7,Change_periodes!$A$1:$A$400,0),MATCH($K7,Change_periodes!$D$1:$N$1,0))) -> 586.8976 | P7: BCE (parité fixe 655,957 FCFA/EUR) | Q7: =INDEX(Change_periodes!$D$1:$D$400,MATCH($N7,Change_periodes!$A$1:$A$400,0)) -> 586.8976 | R7: =IFERROR(J7/M7/O7,"") -> 1.2779061 | S7: =IFERROR(R7*Q7,"") -> 750 | T7: 1 | U7: FCFA/kg de produit tel que vendu | V7: =IFERROR(S7/T7,"") -> 750 | W7: INT-CAC-2018/19-I | X7: =IF(W7="","",IFERROR(INDEX($V$1:$V$178,MATCH(W7,$A$1:$A$178,0)),"")) -> 1366.551 | Y7: =IF(OR(X7="",V7=""),"",V7/X7) -> 0.54882695 | AA7: =IF(Z7="","",IFERROR(INDEX($V$1:$V$178,MATCH(Z7,$A$1:$A$178,0)),"")) | AB7: =IF(OR(AA7="",V7=""),"",V7/AA7) | AC7: Gouvernement (via Afrique-sur7) – Le gouvernement maintient le prix du cacao à 750 FCFA pour la campagne intermédiaire | AD7: https://www.afrique-sur7.fr/420663-prix-cacao-750-campagne-intermediaire | AE7: 2026-10-01 | AF7: B | AG7: Prix administré par le CCC ; ventes anticipées ; règle ≥60 % du prix CAF de référence
A8: CAC-CI-2019/20-P | B8: Cacao | C8: Fèves de cacao marchandes | D8: Côte d'Ivoire | E8: 2019/20 | F8: Campagne principale (oct.-mars) | G8: Prix minimum garanti (administré) | H8: Bord champ | I8: Bien fermenté, séché, trié (grade marchand) | J8: 825 | K8: XOF | L8: kg | M8: 1 | N8: 2019-10:2020-03 | O8: =IF(K8="USD",1,INDEX(Change_periodes!$D$1:$N$400,MATCH($N8,Change_periodes!$A$1:$A$400,0),MATCH($K8,Change_periodes!$D$1:$N$1,0))) -> 593.77663 | P8: BCE (parité fixe 655,957 FCFA/EUR) | Q8: =INDEX(Change_periodes!$D$1:$D$400,MATCH($N8,Change_periodes!$A$1:$A$400,0)) -> 593.77663 | R8: =IFERROR(J8/M8/O8,"") -> 1.3894114 | S8: =IFERROR(R8*Q8,"") -> 825 | T8: 1 | U8: FCFA/kg de produit tel que vendu | V8: =IFERROR(S8/T8,"") -> 825 | W8: INT-CAC-2019/20-P | X8: =IF(W8="","",IFERROR(INDEX($V$1:$V$178,MATCH(W8,$A$1:$A$178,0)),"")) -> 1490.121 | Y8: =IF(OR(X8="",V8=""),"",V8/X8) -> 0.5536463 | AA8: =IF(Z8="","",IFERROR(INDEX($V$1:$V$178,MATCH(Z8,$A$1:$A$178,0)),"")) | AB8: =IF(OR(AA8="",V8=""),"",V8/AA8) | AC8: CCC (via Connectionivoirienne) – Le prix du kg de cacao fixé à 825 FCFA pour la campagne 2019-2020 | AD8: https://connectionivoirienne.net/2019/10/01/le-prix-du-kg-de-cacao-fixe-a-825-fcfa-en-cote-divoire-pour-la-campagne-2019-2020/ | AE8: 2026-10-01 | AF8: B | AG8: Prix administré par le CCC ; ventes anticipées ; règle ≥60 % du prix CAF de référence
A9: CAC-CI-2019/20-I | B9: Cacao | C9: Fèves de cacao marchandes | D9: Côte d'Ivoire | E9: 2019/20 | F9: Campagne intermédiaire (avr.-sept.) | G9: Prix minimum garanti (administré) | H9: Bord champ | I9: Bien fermenté, séché, trié (grade marchand) | J9: 825 | K9: XOF | L9: kg | M9: 1 | N9: 2020-04:2020-09 | O9: =IF(K9="USD",1,INDEX(Change_periodes!$D$1:$N$400,MATCH($N9,Change_periodes!$A$1:$A$400,0),MATCH($K9,Change_periodes!$D$1:$N$1,0))) -> 578.5804 | P9: BCE (parité fixe 655,957 FCFA/EUR) | Q9: =INDEX(Change_periodes!$D$1:$D$400,MATCH($N9,Change_periodes!$A$1:$A$400,0)) -> 578.5804 | R9: =IFERROR(J9/M9/O9,"") -> 1.4259038 | S9: =IFERROR(R9*Q9,"") -> 825 | T9: 1 | U9: FCFA/kg de produit tel que vendu | V9: =IFERROR(S9/T9,"") -> 825 | W9: INT-CAC-2019/20-I | X9: =IF(W9="","",IFERROR(INDEX($V$1:$V$178,MATCH(W9,$A$1:$A$178,0)),"")) -> 1323.3272 | Y9: =IF(OR(X9="",V9=""),"",V9/X9) -> 0.6234286 | AA9: =IF(Z9="","",IFERROR(INDEX($V$1:$V$178,MATCH(Z9,$A$1:$A$178,0)),"")) | AB9: =IF(OR(AA9="",V9=""),"",V9/AA9) | AC9: CCC (via Connectionivoirienne) – Le prix bord champ du cacao maintenu à 825 FCFA/kg pour la petite traite (le prix de marché aurait été de 625 FCFA) | AD9: https://connectionivoirienne.net/2020/04/01/le-prix-bord-champ-du-cacao-maintenu-a-825-fcfa-kg-pour-la-petite-traite-en-cote-divoire/ | AE9: 2026-10-01 | AF9: B | AG9: Prix administré par le CCC ; ventes anticipées ; règle ≥60 % du prix CAF de référence
A10: CAC-CI-2020/21-P | B10: Cacao | C10: Fèves de cacao marchandes | D10: Côte d'Ivoire | E10: 2020/21 | F10: Campagne principale (oct.-mars) | G10: Prix minimum garanti (administré) | H10: Bord champ | I10: Bien fermenté, séché, trié (grade marchand) | J10: 1000 | K10: XOF | L10: kg | M10: 1 | N10: 2020-10:2021-03 | O10: =IF(K10="USD",1,INDEX(Change_periodes!$D$1:$N$400,MATCH($N10,Change_periodes!$A$1:$A$400,0),MATCH($K10,Change_periodes!$D$1:$N$1,0))) -> 547.10364 | P10: BCE (parité fixe 655,957 FCFA/EUR) | Q10: =INDEX(Change_periodes!$D$1:$D$400,MATCH($N10,Change_periodes!$A$1:$A$400,0)) -> 547.10364 | R10: =IFERROR(J10/M10/O10,"") -> 1.8278073 | S10: =IFERROR(R10*Q10,"") -> 1000 | T10: 1 | U10: FCFA/kg de produit tel que vendu | V10: =IFERROR(S10/T10,"") -> 1000 | W10: INT-CAC-2020/21-P | X10: =IF(W10="","",IFERROR(INDEX($V$1:$V$178,MATCH(W10,$A$1:$A$178,0)),"")) -> 1305.3537 | Y10: =IF(OR(X10="",V10=""),"",V10/X10) -> 0.76607588 | AA10: =IF(Z10="","",IFERROR(INDEX($V$1:$V$178,MATCH(Z10,$A$1:$A$178,0)),"")) | AB10: =IF(OR(AA10="",V10=""),"",V10/AA10) | AC10: CCC (via BusinessWorld/Reuters) – Ivory Coast raises 2020/21 cocoa farmgate price by 21% (1 000 FCFA/kg) | AD10: https://www.pressreader.com/philippines/business-world/20201005/281676847366265 | AE10: 2026-10-01 | AF10: B | AG10: Prix administré par le CCC ; ventes anticipées ; règle ≥60 % du prix CAF de référence
A11: CAC-CI-2020/21-I | B11: Cacao | C11: Fèves de cacao marchandes | D11: Côte d'Ivoire | E11: 2020/21 | F11: Campagne intermédiaire (avr.-sept.) | G11: Prix minimum garanti (administré) | H11: Bord champ | I11: Bien fermenté, séché, trié (grade marchand) | J11: 750 | K11: XOF | L11: kg | M11: 1 | N11: 2021-04:2021-09 | O11: =IF(K11="USD",1,INDEX(Change_periodes!$D$1:$N$400,MATCH($N11,Change_periodes!$A$1:$A$400,0),MATCH($K11,Change_periodes!$D$1:$N$1,0))) -> 550.25616 | P11: BCE (parité fixe 655,957 FCFA/EUR) | Q11: =INDEX(Change_periodes!$D$1:$D$400,MATCH($N11,Change_periodes!$A$1:$A$400,0)) -> 550.25616 | R11: =IFERROR(J11/M11/O11,"") -> 1.3630015 | S11: =IFERROR(R11*Q11,"") -> 750 | T11: 1 | U11: FCFA/kg de produit tel que vendu | V11: =IFERROR(S11/T11,"") -> 750 | W11: INT-CAC-2020/21-I | X11: =IF(W11="","",IFERROR(INDEX($V$1:$V$178,MATCH(W11,$A$1:$A$178,0)),"")) -> 1331.3374 | Y11: =IF(OR(X11="",V11=""),"",V11/X11) -> 0.56334328 | AA11: =IF(Z11="","",IFERROR(INDEX($V$1:$V$178,MATCH(Z11,$A$1:$A$178,0)),"")) | AB11: =IF(OR(AA11="",V11=""),"",V11/AA11) | AC11: CCC (via KOACI) – Cacao : le Conseil fixe le kg de la fève à 750 FCFA pour la campagne intermédiaire | AD11: https://www.koaci.com/index.php/article/2021/03/31/cote-divoire/politique/cote-divoire-cacao-le-conseil-fixe-le-kg-de-la-feve-a-750-fcfa-pour-la-campagne-intermediaire_149966.html | AE11: 2026-10-01 | AF11: B | AG11: Prix administré par le CCC ; ventes anticipées ; règle ≥60 % du prix CAF de référence
A12: CAC-CI-2021/22-P | B12: Cacao | C12: Fèves de cacao marchandes | D12: Côte d'Ivoire | E12: 2021/22 | F12: Campagne principale (oct.-mars) | G12: Prix minimum garanti (administré) | H12: Bord champ | I12: Bien fermenté, séché, trié (grade marchand) | J12: 825 | K12: XOF | L12: kg | M12: 1 | N12: 2021-10:2022-03 | O12: =IF(K12="USD",1,INDEX(Change_periodes!$D$1:$N$400,MATCH($N12,Change_periodes!$A$1:$A$400,0),MATCH($K12,Change_periodes!$D$1:$N$1,0))) -> 578.96606 | P12: BCE (parité fixe 655,957 FCFA/EUR) | Q12: =INDEX(Change_periodes!$D$1:$D$400,MATCH($N12,Change_periodes!$A$1:$A$400,0)) -> 578.96606 | R12: =IFERROR(J12/M12/O12,"") -> 1.424954 | S12: =IFERROR(R12*Q12,"") -> 825 | T12: 1 | U12: FCFA/kg de produit tel que vendu | V12: =IFERROR(S12/T12,"") -> 825 | W12: INT-CAC-2021/22-P | X12: =IF(W12="","",IFERROR(INDEX($V$1:$V$178,MATCH(W12,$A$1:$A$178,0)),"")) -> 1430.1041 | Y12: =IF(OR(X12="",V12=""),"",V12/X12) -> 0.5768811 | AA12: =IF(Z12="","",IFERROR(INDEX($V$1:$V$178,MATCH(Z12,$A$1:$A$178,0)),"")) | AB12: =IF(OR(AA12="",V12=""),"",V12/AA12) | AC12: CCC (via Connectionivoirienne) – Le prix bord-champ du café fixé à 700 FCFA/kg, le cacao à 825 FCFA | AD12: https://connectionivoirienne.net/2021/10/01/le-prix-bord-champ-du-cafe-fixe-a-700-fcfa-kg/ | AE12: 2026-10-01 | AF12: B | AG12: Prix administré par le CCC ; ventes anticipées ; règle ≥60 % du prix CAF de référence
A13: CAC-CI-2021/22-I | B13: Cacao | C13: Fèves de cacao marchandes | D13: Côte d'Ivoire | E13: 2021/22 | F13: Campagne intermédiaire (avr.-sept.) | G13: Prix minimum garanti (administré) | H13: Bord champ | I13: Bien fermenté, séché, trié (grade marchand) | J13: 825 | K13: XOF | L13: kg | M13: 1 | N13: 2022-04:2022-09 | O13: =IF(K13="USD",1,INDEX(Change_periodes!$D$1:$N$400,MATCH($N13,Change_periodes!$A$1:$A$400,0),MATCH($K13,Change_periodes!$D$1:$N$1,0))) -> 633.60467 | P13: BCE (parité fixe 655,957 FCFA/EUR) | Q13: =INDEX(Change_periodes!$D$1:$D$400,MATCH($N13,Change_periodes!$A$1:$A$400,0)) -> 633.60467 | R13: =IFERROR(J13/M13/O13,"") -> 1.3020737 | S13: =IFERROR(R13*Q13,"") -> 825 | T13: 1 | U13: FCFA/kg de produit tel que vendu | V13: =IFERROR(S13/T13,"") -> 825 | W13: INT-CAC-2021/22-I | X13: =IF(W13="","",IFERROR(INDEX($V$1:$V$178,MATCH(W13,$A$1:$A$178,0)),"")) -> 1478.9463 | Y13: =IF(OR(X13="",V13=""),"",V13/X13) -> 0.55782959 | AA13: =IF(Z13="","",IFERROR(INDEX($V$1:$V$178,MATCH(Z13,$A$1:$A$178,0)),"")) | AB13: =IF(OR(AA13="",V13=""),"",V13/AA13) | AC13: CCC (via Abidjan.net) – Le prix du kg de cacao pour la campagne intermédiaire maintenu à 825 FCFA | AD13: https://news.abidjan.net/articles/706140/cote-divoire-le-prix-du-kg-de-cacao-pour-la-campagne-intermediaire-maintenu-a-825-fcfa | AE13: 2026-10-01 | AF13: B | AG13: Prix administré par le CCC ; ventes anticipées ; règle ≥60 % du prix CAF de référence
... A42: CAC-CI-2026/27-P | B42: Cacao | C42: Fèves de cacao marchandes | D42: Côte d'Ivoire | E42: 2026/27 | F42: Ouverture campagne principale (annonce 01/09/2026) | G42: Prix minimum garanti (administré) | H42: Bord champ | I42: Bien fermenté, séché, trié | J42: 1200 | K42: XOF | L42: kg | M42: 1 | N42: 2026-09:2026-09 | O42: =IF(K42="USD",1,INDEX(Change_periodes!$D$1:$N$400,MATCH($N42,Change_periodes!$A$1:$A$400,0),MATCH($K42,Change_periodes!$D$1:$N$1,0))) -> 565.22679 | P42: BCE (parité fixe 655,957 FCFA/EUR) | Q42: =INDEX(Change_periodes!$D$1:$D$400,MATCH($N42,Change_periodes!$A$1:$A$400,0)) -> 565.22679 | R42: =IFERROR(J42/M42/O42,"") -> 2.1230416 | S42: =IFERROR(R42*Q42,"") -> 1200 | T42: 1 | U42: FCFA/kg de produit tel que vendu | V42: =IFERROR(S42/T42,"") -> 1200 | W42: INT-CAC-2026-08 | X42: =IF(W42="","",IFERROR(INDEX($V$1:$V$178,MATCH(W42,$A$1:$A$178,0)),"")) -> 3387.5448 | Y42: =IF(OR(X42="",V42=""),"",V42/X42) -> 0.35423886 | AA42: =IF(Z42="","",IFERROR(INDEX($V$1:$V$178,MATCH(Z42,$A$1:$A$178,0)),"")) | AB42: =IF(OR(AA42="",V42=""),"",V42/AA42) | AC42: Gouvernement de Côte d'Ivoire (portail officiel) – Campagne principale 2026-2027 : cacao 1 200 FCFA/kg, café 1 300 FCFA/kg | AD42: https://gouv.ci/actualite/campagne-principale-2026-2027-le-prix-bord-champ-du-cacao-est-fixe-a-1200-fcfa-le-kg-le-prix-du-cafe-setablit-a-1300-fcfa-le-kg-8771 | AE42: 2026-10-01 | AF42: A | AG42: Fondé sur >1,1 Mt de ventes anticipées conclues mars-juin 2026, au creux du marché
A43: CAC-GH-2026/27-P | B43: Cacao | C43: Fèves de cacao marchandes | D43: Ghana | E43: 2026/27 | F43: Ouverture campagne (effet 25/09/2026) | G43: Prix producteur fixé (COCOBOD) | H43: Bord champ (centres d'achat LBC) | I43: Grade I/II | J43: 42400 | K43: GHS | L43: tonne | M43: 1000 | N43: 2026-09:2026-09 | O43: =IF(K43="USD",1,INDEX(Change_periodes!$D$1:$N$400,MATCH($N43,Change_periodes!$A$1:$A$400,0),MATCH($K43,Change_periodes!$D$1:$N$1,0))) -> 11.49 | P43: BRI / Banque du Ghana (moyenne de période) | Q43: =INDEX(Change_periodes!$D$1:$D$400,MATCH($N43,Change_periodes!$A$1:$A$400,0)) -> 565.22679 | R43: =IFERROR(J43/M43/O43,"") -> 3.6901654 | S43: =IFERROR(R43*Q43,"") -> 2085.7803 | T43: 1 | U43: FCFA/kg de produit tel que vendu | V43: =IFERROR(S43/T43,"") -> 2085.7803 | W43: INT-CAC-2026-08 | X43: =IF(W43="","",IFERROR(INDEX($V$1:$V$178,MATCH(W43,$A$1:$A$178,0)),"")) -> 3387.5448 | Y43: =IF(OR(X43="",V43=""),"",V43/X43) -> 0.61572037 | Z43: FOB-GH-CAC-2026/27 | AA43: =IF(Z43="","",IFERROR(INDEX($V$1:$V$178,MATCH(Z43,$A$1:$A$178,0)),"")) -> 2930.2899 | AB43: =IF(OR(AA43="",V43=""),"",V43/AA43) -> 0.7118 | AC43: COCOBOD (via MyJoyOnline) – Producer price GH¢42 400/t for 2026/27 (71,18 % du FOB brut réalisé ; Act 1182 : minimum 70 %) | AD43: https://www.myjoyonline.com/cocobod-increases-cocoa-producer-price-to-gh%C2%A242400-for-2026-27-season/ | AE43: 2026-10-01 | AF43: B | AG43: 71,18 % du FOB brut réalisé (Act 1182 : minimum 70 %) ; GH¢2 650/sac de 64 kg
A44: FOB-GH-CAC-2026/27 | B44: Cacao | C44: Fèves de cacao (valeur FOB brute réalisée) | D44: Ghana | E44: 2026/27 | F44: Ventes de la campagne 2026/27 | G44: Valeur FOB brute réalisée (dérivée) | H44: FOB Tema/Takoradi | I44: Grade I/II | J44: =42400/0.7118 -> 59567.294 | K44: GHS | L44: tonne | M44: 1000 | N44: 2026-09:2026-09 | O44: =IF(K44="USD",1,INDEX(Change_periodes!$D$1:$N$400,MATCH($N44,Change_periodes!$A$1:$A$400,0),MATCH($K44,Change_periodes!$D$1:$N$1,0))) -> 11.49 | P44: BRI / Banque du Ghana (moyenne de période) | Q44: =INDEX(Change_periodes!$D$1:$D$400,MATCH($N44,Change_periodes!$A$1:$A$400,0)) -> 565.22679 | R44: =IFERROR(J44/M44/O44,"") -> 5.1842728 | S44: =IFERROR(R44*Q44,"") -> 2930.2899 | T44: 1 | U44: FCFA/kg de produit tel que vendu | V44: =IFERROR(S44/T44,"") -> 2930.2899 | X44: =IF(W44="","",IFERROR(INDEX($V$1:$V$178,MATCH(W44,$A$1:$A$178,0)),"")) | Y44: =IF(OR(X44="",V44=""),"",V44/X44) | AA44: =IF(Z44="","",IFERROR(INDEX($V$1:$V$178,MATCH(Z44,$A$1:$A$178,0)),"")) | AB44: =IF(OR(AA44="",V44=""),"",V44/AA44) | AC44: COCOBOD (via MyJoyOnline) – Producer price GH¢42 400/t for 2026/27 (71,18 % du FOB brut réalisé ; Act 1182 : minimum 70 %) | AD44: https://www.myjoyonline.com/cocobod-increases-cocoa-producer-price-to-gh%C2%A242400-for-2026-27-season/ | AE44: 2026-10-01 | AF44: B | AG44: Dérivé : prix producteur ÷ 71,18 % (part déclarée par le COCOBOD)
A45: CAC-CM-2026-04 | B45: Cacao | C45: Fèves de cacao marchandes | D45: Cameroun | E45: 2025/26 | F45: Mars-avril 2026 | G45: Prix de marché (libéralisé, relevé ONCC-SIF) | H45: Bord champ (bassins de production) | I45: Fèves marchandes (qualité variable) | J45: =(1200+1450)/2 -> 1325 | K45: XAF | L45: kg | M45: 1 | N45: 2026-03:2026-04 | O45: =IF(K45="USD",1,INDEX(Change_periodes!$D$1:$N$400,MATCH($N45,Change_periodes!$A$1:$A$400,0),MATCH($K45,Change_periodes!$D$1:$N$1,0))) -> 563.92991 | P45: BCE (parité fixe 655,957 FCFA/EUR) | Q45: =INDEX(Change_periodes!$D$1:$D$400,MATCH($N45,Change_periodes!$A$1:$A$400,0)) -> 563.92991 | R45: =IFERROR(J45/M45/O45,"") -> 2.3495828 | S45: =IFERROR(R45*Q45,"") -> 1325 | T45: 1 | U45: FCFA/kg de produit tel que vendu | V45: =IFERROR(S45/T45,"") -> 1325 | W45: INT-CAC-2026-04 | X45: =IF(W45="","",IFERROR(INDEX($V$1:$V$178,MATCH(W45,$A$1:$A$178,0)),"")) -> 1870.4512 | Y45: =IF(OR(X45="",V45=""),"",V45/X45) -> 0.70838523 | AA45: =IF(Z45="","",IFERROR(INDEX($V$1:$V$178,MATCH(Z45,$A$1:$A$178,0)),"")) | AB45: =IF(OR(AA45="",V45=""),"",V45/AA45) | AC45: ONCC-SIF (via Invest-Time) – Cacao au Cameroun : 1 200-1 450 FCFA/kg dans les bassins (mars-avril 2026) | AD45: https://invest-time.com/2026/05/07/cacao-cameroun-prix-campagne/ | AE45: 2026-10-01 | AF45: B | AG45: Milieu de la fourchette 1200-1450 FCFA/kg ; XAF = XOF (même parité avec l'euro)
A46: CAC-CM-2026-05 | B46: Cacao | C46: Fèves de cacao marchandes | D46: Cameroun | E46: 2025/26 | F46: Début mai 2026 | G46: Prix de marché (libéralisé, relevé ONCC-SIF) | H46: Bord champ (bassins de production) | I46: Fèves marchandes (qualité variable) | J46: =(1550+1650)/2 -> 1600 | K46: XAF | L46: kg | M46: 1 | N46: 2026-05:2026-05 | O46: =IF(K46="USD",1,INDEX(Change_periodes!$D$1:$N$400,MATCH($N46,Change_periodes!$A$1:$A$400,0),MATCH($K46,Change_periodes!$D$1:$N$1,0))) -> 561.93417 | P46: BCE (parité fixe 655,957 FCFA/EUR) | Q46: =INDEX(Change_periodes!$D$1:$D$400,MATCH($N46,Change_periodes!$A$1:$A$400,0)) -> 561.93417 | R46: =IFERROR(J46/M46/O46,"") -> 2.8473086 | S46: =IFERROR(R46*Q46,"") -> 1600 | T46: 1 | U46: FCFA/kg de produit tel que vendu | V46: =IFERROR(S46/T46,"") -> 1600 | W46: INT-CAC-2026-05 | X46: =IF(W46="","",IFERROR(INDEX($V$1:$V$178,MATCH(W46,$A$1:$A$178,0)),"")) -> 2328.0764 | Y46: =IF(OR(X46="",V46=""),"",V46/X46) -> 0.68726266 | AA46: =IF(Z46="","",IFERROR(INDEX($V$1:$V$178,MATCH(Z46,$A$1:$A$178,0)),"")) | AB46: =IF(OR(AA46="",V46=""),"",V46/AA46) | AC46: ONCC-SIF (via Investir au Cameroun) – Le prix du kilogramme repasse au-dessus de 1 500 FCFA (1 550-1 650) | AD46: https://www.investiraucameroun.com/agriculture/0705-23372-cacao-le-prix-du-kilogramme-repasse-au-dessus-de-1-500-fcfa-a-deux-mois-de-la-fin-de-campagne | AE46: 2026-10-01 | AF46: B | AG46: Milieu de la fourchette 1550-1650 FCFA/kg ; XAF = XOF (même parité avec l'euro)
A47: CAC-CM-2026-06 | B47: Cacao | C47: Fèves de cacao marchandes | D47: Cameroun | E47: 2025/26 | F47: 30 juin 2026 | G47: Prix de marché (libéralisé, relevé ONCC-SIF) | H47: Bord champ (bassins de production) | I47: Fèves marchandes (qualité variable) | J47: =(2100+2250)/2 -> 2175 | K47: XAF | L47: kg | M47: 1 | N47: 2026-06:2026-06 | O47: =IF(K47="USD",1,INDEX(Change_periodes!$D$1:$N$400,MATCH($N47,Change_periodes!$A$1:$A$400,0),MATCH($K47,Change_periodes!$D$1:$N$1,0))) -> 569.50599 | P47: BCE (parité fixe 655,957 FCFA/EUR) | Q47: =INDEX(Change_periodes!$D$1:$D$400,MATCH($N47,Change_periodes!$A$1:$A$400,0)) -> 569.50599 | R47: =IFERROR(J47/M47/O47,"") -> 3.8190994 | S47: =IFERROR(R47*Q47,"") -> 2175 | T47: 1 | U47: FCFA/kg de produit tel que vendu | V47: =IFERROR(S47/T47,"") -> 2175 | W47: INT-CAC-2026-06 | X47: =IF(W47="","",IFERROR(INDEX($V$1:$V$178,MATCH(W47,$A$1:$A$178,0)),"")) -> 2503.2408 | Y47: =IF(OR(X47="",V47=""),"",V47/X47) -> 0.86887366 | AA47: =IF(Z47="","",IFERROR(INDEX($V$1:$V$178,MATCH(Z47,$A$1:$A$178,0)),"")) | AB47: =IF(OR(AA47="",V47=""),"",V47/AA47) | AC47: ONCC-SIF (via Investir au Cameroun) – Le prix aux producteurs atteint 2 250 FCFA (2 100-2 250 au 30/06/2026) | AD47: https://www.investiraucameroun.com/agriculture/3006-23552-cacao-le-prix-aux-producteurs-atteint-2250-fcfa-son-plus-haut-niveau-depuis-le-debut-de-la-campagne-2025-2026 | AE47: 2026-10-01 | AF47: B | AG47: Milieu de la fourchette 2100-2250 FCFA/kg ; XAF = XOF (même parité avec l'euro)
A48: CAC-NG-2026-09 | B48: Cacao | C48: Fèves de cacao | D48: Nigeria | E48: 2026/27 | F48: 25/09/2026 | G48: Prix de marché (libéralisé) | H48: Bord champ (indicatif) | I48: Non précisée | J48: 5728.5 | K48: NGN | L48: kg | M48: 1 | N48: 2026-09:2026-09 | O48: =IF(K48="USD",1,INDEX(Change_periodes!$D$1:$N$400,MATCH($N48,Change_periodes!$A$1:$A$400,0),MATCH($K48,Change_periodes!$D$1:$N$1,0))) -> 1328.81 | P48: Implicite source (C) | Q48: =INDEX(Change_periodes!$D$1:$D$400,MATCH($N48,Change_periodes!$A$1:$A$400,0)) -> 565.22679 | R48: =IFERROR(J48/M48/O48,"") -> 4.311 | S48: =IFERROR(R48*Q48,"") -> 2436.6927 | T48: 1 | U48: FCFA/kg de produit tel que vendu | V48: =IFERROR(S48/T48,"") -> 2436.6927 | W48: INT-CAC-2026-08 | X48: =IF(W48="","",IFERROR(INDEX($V$1:$V$178,MATCH(W48,$A$1:$A$178,0)),"")) -> 3387.5448 | Y48: =IF(OR(X48="",V48=""),"",V48/X48) -> 0.71930937 | AA48: =IF(Z48="","",IFERROR(INDEX($V$1:$V$178,MATCH(Z48,$A$1:$A$178,0)),"")) | AB48: =IF(OR(AA48="",V48=""),"",V48/AA48) | AC48: Mansa Markets – Nigeria farmgate 5 728,5 NGN/kg (≈4 311 USD/t), 25/09/2026 | AD48: https://www.mansamarkets.com/blog/cocoa-farmgate-price-vs-world-price | AE48: 2026-10-01 | AF48: C | AG48: Source secondaire ; taux de change implicite de la source ; à titre indicatif uniquement
A49: CAC-EC-2026-01 | B49: Cacao | C49: Fèves de cacao sèches (CCN-51 / Nacional) | D49: Équateur | E49: 2025/26 | F49: Janvier 2026 | G49: Prix de marché (libéralisé) | H49: Bord champ | I49: Après décotes usuelles (qualité variable) | J49: =(180+190)/2 -> 185 | K49: USD | L49: quintal (100 lb) | M49: 45.3592 | N49: 2026-01:2026-01 | O49: =IF(K49="USD",1,INDEX(Change_periodes!$D$1:$N$400,MATCH($N49,Change_periodes!$A$1:$A$400,0),MATCH($K49,Change_periodes!$D$1:$N$1,0))) -> 1 | P49: — | Q49: =INDEX(Change_periodes!$D$1:$D$400,MATCH($N49,Change_periodes!$A$1:$A$400,0)) -> 558.82057 | R49: =IFERROR(J49/M49/O49,"") -> 4.0785552 | S49: =IFERROR(R49*Q49,"") -> 2279.1805 | T49: 1 | U49: FCFA/kg de produit tel que vendu | V49: =IFERROR(S49/T49,"") -> 2279.1805 | W49: INT-CAC-2026-01 | X49: =IF(W49="","",IFERROR(INDEX($V$1:$V$178,MATCH(W49,$A$1:$A$178,0)),"")) -> 2778.7353 | Y49: =IF(OR(X49="",V49=""),"",V49/X49) -> 0.82022226 | AA49: =IF(Z49="","",IFERROR(INDEX($V$1:$V$178,MATCH(Z49,$A$1:$A$178,0)),"")) | AB49: =IF(OR(AA49="",V49=""),"",V49/AA49) | AC49: El Universo – Les producteurs reçoivent 180-190 USD/quintal (janv. 2026) | AD49: https://www.eluniverso.com/noticias/economia/precio-cacao-ecuador-exportador-productor-nota/ | AE49: 2026-10-01 | AF49: B | AG49: Milieu de fourchette 180-190 USD/qq
A50: CAC-EC-2026-02 | B50: Cacao | C50: Fèves de cacao sèches | D50: Équateur | E50: 2025/26 | F50: Février 2026 | G50: Prix de marché (libéralisé) | H50: Centres de collecte principaux | I50: Qualité variable | J50: 100 | K50: USD | L50: quintal (100 lb) | M50: 45.3592 | N50: 2026-02:2026-02 | O50: =IF(K50="USD",1,INDEX(Change_periodes!$D$1:$N$400,MATCH($N50,Change_periodes!$A$1:$A$400,0),MATCH($K50,Change_periodes!$D$1:$N$1,0))) -> 1 | P50: — | Q50: =INDEX(Change_periodes!$D$1:$D$400,MATCH($N50,Change_periodes!$A$1:$A$400,0)) -> 554.76977 | R50: =IFERROR(J50/M50/O50,"") -> 2.2046244 | S50: =IFERROR(R50*Q50,"") -> 1223.059 | T50: 1 | U50: FCFA/kg de produit tel que vendu | V50: =IFERROR(S50/T50,"") -> 1223.059 | W50: INT-CAC-2026-02 | X50: =IF(W50="","",IFERROR(INDEX($V$1:$V$178,MATCH(W50,$A$1:$A$178,0)),"")) -> 1990.0646 | Y50: =IF(OR(X50="",V50=""),"",V50/X50) -> 0.61458256 | AA50: =IF(Z50="","",IFERROR(INDEX($V$1:$V$178,MATCH(Z50,$A$1:$A$178,0)),"")) | AB50: =IF(OR(AA50="",V50=""),"",V50/AA50) | AC50: Al Día (Équateur) – Le cacao revient à 100 USD le quintal (80-85 USD dans les petits cantons), fév. 2026 | AD50: https://www.aldia.com.ec/el-cacao-regresa-a-niveles-de-2023-100-el-quintal-y-en-cantones-pequenos-llega-a-80/ | AE50: 2026-10-01 | AF50: B | AG50: 80-85 USD/qq dans les petits cantons
A51: CAF-CI-2016/17 | B51: Café | C51: Café vert robusta (décortiqué) | D51: Côte d'Ivoire | E51: 2016/17 | F51: Campagne (oct.-sept.) | G51: Prix minimum garanti (administré) | H51: Bord champ | I51: Bien séché, décortiqué, trié | J51: 750 | K51: XOF | L51: kg | M51: 1 | N51: 2016-10:2017-09 | O51: =IF(K51="USD",1,INDEX(Change_periodes!$D$1:$N$400,MATCH($N51,Change_periodes!$A$1:$A$400,0),MATCH($K51,Change_periodes!$D$1:$N$1,0))) -> 594.82193 | P51: BCE (parité fixe 655,957 FCFA/EUR) | Q51: =INDEX(Change_periodes!$D$1:$D$400,MATCH($N51,Change_periodes!$A$1:$A$400,0)) -> 594.82193 | R51: =IFERROR(J51/M51/O51,"") -> 1.2608816 | S51: =IFERROR(R51*Q51,"") -> 750 | T51: 1 | U51: FCFA/kg de produit tel que vendu | V51: =IFERROR(S51/T51,"") -> 750 | W51: INT-ROB-2016/17 | X51: =IF(W51="","",IFERROR(INDEX($V$1:$V$178,MATCH(W51,$A$1:$A$178,0)),"")) -> 1358.6634 | Y51: =IF(OR(X51="",V51=""),"",V51/X51) -> 0.55201308 | AA51: =IF(Z51="","",IFERROR(INDEX($V$1:$V$178,MATCH(Z51,$A$1:$A$178,0)),"")) | AB51: =IF(OR(AA51="",V51=""),"",V51/AA51) | AC51: CCC (via Connectionivoirienne) – Le prix du kg de café reste inchangé à 750 FCFA pour la campagne 2017-2018 | AD51: https://connectionivoirienne.net/2017/12/21/cote-divoire-le-prix-du-kg-de-cafe-reste-inchange-a-750-fcfa-pour-la-campagne-2017-2018/ | AE51: 2026-10-01 | AF51: B | AG51: Prix 2016/17 déduit du maintien à 750 FCFA en 2017/18 (« inchangé ») ; Avant 2021/22 la campagne café s'ouvrait en décembre : moyenne oct.-sept. utilisée par homogénéité
A52: CAF-CI-2017/18 | B52: Café | C52: Café vert robusta (décortiqué) | D52: Côte d'Ivoire | E52: 2017/18 | F52: Campagne (oct.-sept.) | G52: Prix minimum garanti (administré) | H52: Bord champ | I52: Bien séché, décortiqué, trié | J52: 750 | K52: XOF | L52: kg | M52: 1 | N52: 2017-10:2018-09 | O52: =IF(K52="USD",1,INDEX(Change_periodes!$D$1:$N$400,MATCH($N52,Change_periodes!$A$1:$A$400,0),MATCH($K52,Change_periodes!$D$1:$N$1,0))) -> 551.24592 | P52: BCE (parité fixe 655,957 FCFA/EUR) | Q52: =INDEX(Change_periodes!$D$1:$D$400,MATCH($N52,Change_periodes!$A$1:$A$400,0)) -> 551.24592 | R52: =IFERROR(J52/M52/O52,"") -> 1.3605543 | S52: =IFERROR(R52*Q52,"") -> 750 | T52: 1 | U52: FCFA/kg de produit tel que vendu | V52: =IFERROR(S52/T52,"") -> 750 | W52: INT-ROB-2017/18 | X52: =IF(W52="","",IFERROR(INDEX($V$1:$V$178,MATCH(W52,$A$1:$A$178,0)),"")) -> 1061.7159 | Y52: =IF(OR(X52="",V52=""),"",V52/X52) -> 0.70640364 | AA52: =IF(Z52="","",IFERROR(INDEX($V$1:$V$178,MATCH(Z52,$A$1:$A$178,0)),"")) | AB52: =IF(OR(AA52="",V52=""),"",V52/AA52) | AC52: CCC (via Connectionivoirienne) – Le prix du kg de café reste inchangé à 750 FCFA pour la campagne 2017-2018 | AD52: https://connectionivoirienne.net/2017/12/21/cote-divoire-le-prix-du-kg-de-cafe-reste-inchange-a-750-fcfa-pour-la-campagne-2017-2018/ | AE52: 2026-10-01 | AF52: B | AG52: Avant 2021/22 la campagne café s'ouvrait en décembre : moyenne oct.-sept. utilisée par homogénéité
A53: CAF-CI-2018/19 | B53: Café | C53: Café vert robusta (décortiqué) | D53: Côte d'Ivoire | E53: 2018/19 | F53: Campagne (oct.-sept.) | G53: Prix minimum garanti (administré) | H53: Bord champ | I53: Bien séché, décortiqué, trié | J53: 700 | K53: XOF | L53: kg | M53: 1 | N53: 2018-10:2019-09 | O53: =IF(K53="USD",1,INDEX(Change_periodes!$D$1:$N$400,MATCH($N53,Change_periodes!$A$1:$A$400,0),MATCH($K53,Change_periodes!$D$1:$N$1,0))) -> 581.5558 | P53: BCE (parité fixe 655,957 FCFA/EUR) | Q53: =INDEX(Change_periodes!$D$1:$D$400,MATCH($N53,Change_periodes!$A$1:$A$400,0)) -> 581.5558 | R53: =IFERROR(J53/M53/O53,"") -> 1.2036678 | S53: =IFERROR(R53*Q53,"") -> 700 | T53: 1 | U53: FCFA/kg de produit tel que vendu | V53: =IFERROR(S53/T53,"") -> 700 | W53: INT-ROB-2018/19 | X53: =IF(W53="","",IFERROR(INDEX($V$1:$V$178,MATCH(W53,$A$1:$A$178,0)),"")) -> 976.56168 | Y53: =IF(OR(X53="",V53=""),"",V53/X53) -> 0.7168006 | AA53: =IF(Z53="","",IFERROR(INDEX($V$1:$V$178,MATCH(Z53,$A$1:$A$178,0)),"")) | AB53: =IF(OR(AA53="",V53=""),"",V53/AA53) | AC53: CCC (via Abidjan.net) – Prix du café 2018-2019 : 700 FCFA/kg (baisse de 50 FCFA) | AD53: https://news.abidjan.net/h/649843.html | AE53: 2026-10-01 | AF53: B | AG53: Avant 2021/22 la campagne café s'ouvrait en décembre : moyenne oct.-sept. utilisée par homogénéité
A54: CAF-CI-2019/20 | B54: Café | C54: Café vert robusta (décortiqué) | D54: Côte d'Ivoire | E54: 2019/20 | F54: Campagne (oct.-sept.) | G54: Prix minimum garanti (administré) | H54: Bord champ | I54: Bien séché, décortiqué, trié | J54: 700 | K54: XOF | L54: kg | M54: 1 | N54: 2019-10:2020-09 | O54: =IF(K54="USD",1,INDEX(Change_periodes!$D$1:$N$400,MATCH($N54,Change_periodes!$A$1:$A$400,0),MATCH($K54,Change_periodes!$D$1:$N$1,0))) -> 586.17851 | P54: BCE (parité fixe 655,957 FCFA/EUR) | Q54: =INDEX(Change_periodes!$D$1:$D$400,MATCH($N54,Change_periodes!$A$1:$A$400,0)) -> 586.17851 | R54: =IFERROR(J54/M54/O54,"") -> 1.1941755 | S54: =IFERROR(R54*Q54,"") -> 700 | T54: 1 | U54: FCFA/kg de produit tel que vendu | V54: =IFERROR(S54/T54,"") -> 700 | W54: INT-ROB-2019/20 | X54: =IF(W54="","",IFERROR(INDEX($V$1:$V$178,MATCH(W54,$A$1:$A$178,0)),"")) -> 891.11683 | Y54: =IF(OR(X54="",V54=""),"",V54/X54) -> 0.78553112 | AA54: =IF(Z54="","",IFERROR(INDEX($V$1:$V$178,MATCH(Z54,$A$1:$A$178,0)),"")) | AB54: =IF(OR(AA54="",V54=""),"",V54/AA54) | AC54: CCC (via Connectionivoirienne) – Café 2019-2020 fixé à 700 FCFA ; maintien permis par une subvention de 32 Mds FCFA (prix de marché : 473 FCFA) | AD54: https://connectionivoirienne.net/2019/12/26/le-prix-du-kg-de-cafe-fixe-a-700-fcfa-pour-la-campagne-2019-2020-en-cote-divoire/ | AE54: 2026-10-01 | AF54: B | AG54: Maintien financé par une subvention de 32 Mds FCFA (prix de marché estimé : 473 FCFA) ; Avant 2021/22 la campagne café s'ouvrait en décembre : moyenne oct.-sept. utilisée par homogénéité
A55: CAF-CI-2020/21 | B55: Café | C55: Café vert robusta (décortiqué) | D55: Côte d'Ivoire | E55: 2020/21 | F55: Campagne (oct.-sept.) | G55: Prix minimum garanti (administré) | H55: Bord champ | I55: Bien séché, décortiqué, trié | J55: 550 | K55: XOF | L55: kg | M55: 1 | N55: 2020-10:2021-09 | O55: =IF(K55="USD",1,INDEX(Change_periodes!$D$1:$N$400,MATCH($N55,Change_periodes!$A$1:$A$400,0),MATCH($K55,Change_periodes!$D$1:$N$1,0))) -> 548.6799 | P55: BCE (parité fixe 655,957 FCFA/EUR) | Q55: =INDEX(Change_periodes!$D$1:$D$400,MATCH($N55,Change_periodes!$A$1:$A$400,0)) -> 548.6799 | R55: =IFERROR(J55/M55/O55,"") -> 1.002406 | S55: =IFERROR(R55*Q55,"") -> 550 | T55: 1 | U55: FCFA/kg de produit tel que vendu | V55: =IFERROR(S55/T55,"") -> 550 | W55: INT-ROB-2020/21 | X55: =IF(W55="","",IFERROR(INDEX($V$1:$V$178,MATCH(W55,$A$1:$A$178,0)),"")) -> 971.59551 | Y55: =IF(OR(X55="",V55=""),"",V55/X55) -> 0.56607919 | AA55: =IF(Z55="","",IFERROR(INDEX($V$1:$V$178,MATCH(Z55,$A$1:$A$178,0)),"")) | AB55: =IF(OR(AA55="",V55=""),"",V55/AA55) | AC55: CCC (via KOACI) – Café : prix bord champ fixé à 550 FCFA/kg (campagne 2020-2021, 28/12/2020) | AD55: https://www.koaci.com/article/2020/12/23/cote-divoire/economie/cote-divoire-cafe-debut-de-la-campagne-commerciale-le-28-decembre-le-prix-bord-champ-du-kilo-fixe-a-550-fcfa-soit-une-baisse-de-155-fcfa_147642.html | AE55: 2026-10-01 | AF55: B | AG55: Campagne ouverte le 28/12/2020 ; Avant 2021/22 la campagne café s'ouvrait en décembre : moyenne oct.-sept. utilisée par homogénéité
A56: CAF-CI-2021/22 | B56: Café | C56: Café vert robusta (décortiqué) | D56: Côte d'Ivoire | E56: 2021/22 | F56: Campagne (oct.-sept.) | G56: Prix minimum garanti (administré) | H56: Bord champ | I56: Bien séché, décortiqué, trié | J56: 700 | K56: XOF | L56: kg | M56: 1 | N56: 2021-10:2022-09 | O56: =IF(K56="USD",1,INDEX(Change_periodes!$D$1:$N$400,MATCH($N56,Change_periodes!$A$1:$A$400,0),MATCH($K56,Change_periodes!$D$1:$N$1,0))) -> 606.28536 | P56: BCE (parité fixe 655,957 FCFA/EUR) | Q56: =INDEX(Change_periodes!$D$1:$D$400,MATCH($N56,Change_periodes!$A$1:$A$400,0)) -> 606.28536 | R56: =IFERROR(J56/M56/O56,"") -> 1.1545718 | S56: =IFERROR(R56*Q56,"") -> 700 | T56: 1 | U56: FCFA/kg de produit tel que vendu | V56: =IFERROR(S56/T56,"") -> 700 | W56: INT-ROB-2021/22 | X56: =IF(W56="","",IFERROR(INDEX($V$1:$V$178,MATCH(W56,$A$1:$A$178,0)),"")) -> 1428.7782 | Y56: =IF(OR(X56="",V56=""),"",V56/X56) -> 0.48992907 | AA56: =IF(Z56="","",IFERROR(INDEX($V$1:$V$178,MATCH(Z56,$A$1:$A$178,0)),"")) | AB56: =IF(OR(AA56="",V56=""),"",V56/AA56) | AC56: CCC (via Connectionivoirienne) – Le prix bord-champ du café fixé à 700 FCFA/kg, le cacao à 825 FCFA | AD56: https://connectionivoirienne.net/2021/10/01/le-prix-bord-champ-du-cafe-fixe-a-700-fcfa-kg/ | AE56: 2026-10-01 | AF56: B | AG56: Avant 2021/22 la campagne café s'ouvrait en décembre : moyenne oct.-sept. utilisée par homogénéité
A57: CAF-CI-2022/23 | B57: Café | C57: Café vert robusta (décortiqué) | D57: Côte d'Ivoire | E57: 2022/23 | F57: Campagne (oct.-sept.) | G57: Prix minimum garanti (administré) | H57: Bord champ | I57: Bien séché, décortiqué, trié | J57: 750 | K57: XOF | L57: kg | M57: 1 | N57: 2022-10:2023-09 | O57: =IF(K57="USD",1,INDEX(Change_periodes!$D$1:$N$400,MATCH($N57,Change_periodes!$A$1:$A$400,0),MATCH($K57,Change_periodes!$D$1:$N$1,0))) -> 614.9479 | P57: BCE (parité fixe 655,957 FCFA/EUR) | Q57: =INDEX(Change_periodes!$D$1:$D$400,MATCH($N57,Change_periodes!$A$1:$A$400,0)) -> 614.9479 | R57: =IFERROR(J57/M57/O57,"") -> 1.2196155 | S57: =IFERROR(R57*Q57,"") -> 750 | T57: 1 | U57: FCFA/kg de produit tel que vendu | V57: =IFERROR(S57/T57,"") -> 750 | W57: INT-ROB-2022/23 | X57: =IF(W57="","",IFERROR(INDEX($V$1:$V$178,MATCH(W57,$A$1:$A$178,0)),"")) -> 1515.3067 | Y57: =IF(OR(X57="",V57=""),"",V57/X57) -> 0.4949493 | AA57: =IF(Z57="","",IFERROR(INDEX($V$1:$V$178,MATCH(Z57,$A$1:$A$178,0)),"")) | AB57: =IF(OR(AA57="",V57=""),"",V57/AA57) | AC57: CCC (via Abidjan.net) – Campagne 2022-2023 : cacao 900 FCFA, café 750 FCFA | AD57: https://news.abidjan.net/articles/712879/campagne-2022-2023-le-prix-bord-champ-du-kilogramme-de-cacao-fixe-a-900-fcfa-et-celui-du-cafe-a-750-fcfa | AE57: 2026-10-01 | AF57: B | AG57: Avant 2021/22 la campagne café s'ouvrait en décembre : moyenne oct.-sept. utilisée par homogénéité
A58: CAF-CI-2023/24 | B58: Café | C58: Café vert robusta (décortiqué) | D58: Côte d'Ivoire | E58: 2023/24 | F58: Campagne (oct.-sept.) | G58: Prix minimum garanti (administré) | H58: Bord champ | I58: Bien séché, décortiqué, trié | J58: 900 | K58: XOF | L58: kg | M58: 1 | N58: 2023-10:2024-09 | O58: =IF(K58="USD",1,INDEX(Change_periodes!$D$1:$N$400,MATCH($N58,Change_periodes!$A$1:$A$400,0),MATCH($K58,Change_periodes!$D$1:$N$1,0))) -> 605.0901 | P58: BCE (parité fixe 655,957 FCFA/EUR) | Q58: =INDEX(Change_periodes!$D$1:$D$400,MATCH($N58,Change_periodes!$A$1:$A$400,0)) -> 605.0901 | R58: =IFERROR(J58/M58/O58,"") -> 1.4873818 | S58: =IFERROR(R58*Q58,"") -> 900 | T58: 1 | U58: FCFA/kg de produit tel que vendu | V58: =IFERROR(S58/T58,"") -> 900 | W58: INT-ROB-2023/24 | X58: =IF(W58="","",IFERROR(INDEX($V$1:$V$178,MATCH(W58,$A$1:$A$178,0)),"")) -> 2328.864 | Y58: =IF(OR(X58="",V58=""),"",V58/X58) -> 0.38645451 | AA58: =IF(Z58="","",IFERROR(INDEX($V$1:$V$178,MATCH(Z58,$A$1:$A$178,0)),"")) | AB58: =IF(OR(AA58="",V58=""),"",V58/AA58) | AC58: CCC (via Abidjan.net) – Campagne 2023-2024 : cacao 1 000 FCFA, café 900 FCFA | AD58: https://news.abidjan.net/articles/724364/campagne-principale-de-commercialisation-2023-2024-cafe-cacao-le-prix-du-kg-de-cacao-fixe-a-1000-fcfa-et-celui-du-cafe-a-900-fcfa | AE58: 2026-10-01 | AF58: B | AG58: Avant 2021/22 la campagne café s'ouvrait en décembre : moyenne oct.-sept. utilisée par homogénéité
A59: CAF-CI-2024/25 | B59: Café | C59: Café vert robusta (décortiqué) | D59: Côte d'Ivoire | E59: 2024/25 | F59: Campagne (oct.-sept.) | G59: Prix minimum garanti (administré) | H59: Bord champ | I59: Bien séché, décortiqué, trié | J59: 1500 | K59: XOF | L59: kg | M59: 1 | N59: 2024-10:2025-09 | O59: =IF(K59="USD",1,INDEX(Change_periodes!$D$1:$N$400,MATCH($N59,Change_periodes!$A$1:$A$400,0),MATCH($K59,Change_periodes!$D$1:$N$1,0))) -> 594.67501 | P59: BCE (parité fixe 655,957 FCFA/EUR) | Q59: =INDEX(Change_periodes!$D$1:$D$400,MATCH($N59,Change_periodes!$A$1:$A$400,0)) -> 594.67501 | R59: =IFERROR(J59/M59/O59,"") -> 2.5223861 | S59: =IFERROR(R59*Q59,"") -> 1500 | T59: 1 | U59: FCFA/kg de produit tel que vendu | V59: =IFERROR(S59/T59,"") -> 1500 | W59: INT-ROB-2024/25 | X59: =IF(W59="","",IFERROR(INDEX($V$1:$V$178,MATCH(W59,$A$1:$A$178,0)),"")) -> 2960.0927 | Y59: =IF(OR(X59="",V59=""),"",V59/X59) -> 0.50674089 | AA59: =IF(Z59="","",IFERROR(INDEX($V$1:$V$178,MATCH(Z59,$A$1:$A$178,0)),"")) | AB59: =IF(OR(AA59="",V59=""),"",V59/AA59) | AC59: CCC (via Agence Ecofin) – Hausse de plus de 66 % du prix bord champ du café en 2024/2025 (1 500 FCFA) | AD59: https://www.agenceecofin.com/breves-agro/0110-122027-cote-d-ivoire-hausse-de-plus-de-66-du-prix-bord-champ-du-cafe-en-2024/2025 | AE59: 2026-10-01 | AF59: B | AG59: Avant 2021/22 la campagne café s'ouvrait en décembre : moyenne oct.-sept. utilisée par homogénéité
A60: CAF-CI-2025/26 | B60: Café | C60: Café vert robusta (décortiqué) | D60: Côte d'Ivoire | E60: 2025/26 | F60: Campagne (oct.-sept.) | G60: Prix minimum garanti (administré) | H60: Bord champ | I60: Bien séché, décortiqué, trié | J60: 1700 | K60: XOF | L60: kg | M60: 1 | N60: 2025-10:2026-09 | O60: =IF(K60="USD",1,INDEX(Change_periodes!$D$1:$N$400,MATCH($N60,Change_periodes!$A$1:$A$400,0),MATCH($K60,Change_periodes!$D$1:$N$1,0))) -> 564.17595 | P60: BCE (parité fixe 655,957 FCFA/EUR) | Q60: =INDEX(Change_periodes!$D$1:$D$400,MATCH($N60,Change_periodes!$A$1:$A$400,0)) -> 564.17595 | R60: =IFERROR(J60/M60/O60,"") -> 3.0132443 | S60: =IFERROR(R60*Q60,"") -> 1700 | T60: 1 | U60: FCFA/kg de produit tel que vendu | V60: =IFERROR(S60/T60,"") -> 1700 | W60: INT-ROB-2025/26 | X60: =IF(W60="","",IFERROR(INDEX($V$1:$V$178,MATCH(W60,$A$1:$A$178,0)),"")) -> 2301.7138 | Y60: =IF(OR(X60="",V60=""),"",V60/X60) -> 0.7385801 | AA60: =IF(Z60="","",IFERROR(INDEX($V$1:$V$178,MATCH(Z60,$A$1:$A$178,0)),"")) | AB60: =IF(OR(AA60="",V60=""),"",V60/AA60) | AC60: Présidence / CCC (via AIP) – Campagne 2025-2026 : prix bord champ du cacao 2 800 FCFA/kg et café 1 700 FCFA/kg | AD60: https://www.aip.ci/257389/cote-divoire-aip-campagne-2025-2026-le-prix-bord-champ-du-cacao-fixe-a-2-800-fcfa-kg-et-celui-du-cafe-a-1-700-fcfa-kg-alassane-ouattara/ | AE60: 2026-10-01 | AF60: B | AG60: Avant 2021/22 la campagne café s'ouvrait en décembre : moyenne oct.-sept. utilisée par homogénéité
A61: CAF-CI-2026/27 | B61: Café | C61: Café vert robusta (décortiqué) | D61: Côte d'Ivoire | E61: 2026/27 | F61: Ouverture (annonce 01/09/2026) | G61: Prix minimum garanti (administré) | H61: Bord champ | I61: Bien séché, décortiqué, trié | J61: 1300 | K61: XOF | L61: kg | M61: 1 | N61: 2026-09:2026-09 | O61: =IF(K61="USD",1,INDEX(Change_periodes!$D$1:$N$400,MATCH($N61,Change_periodes!$A$1:$A$400,0),MATCH($K61,Change_periodes!$D$1:$N$1,0))) -> 565.22679 | P61: BCE (parité fixe 655,957 FCFA/EUR) | Q61: =INDEX(Change_periodes!$D$1:$D$400,MATCH($N61,Change_periodes!$A$1:$A$400,0)) -> 565.22679 | R61: =IFERROR(J61/M61/O61,"") -> 2.2999617 | S61: =IFERROR(R61*Q61,"") -> 1300 | T61: 1 | U61: FCFA/kg de produit tel que vendu | V61: =IFERROR(S61/T61,"") -> 1300 | W61: INT-ROB-2026-08 | X61: =IF(W61="","",IFERROR(INDEX($V$1:$V$178,MATCH(W61,$A$1:$A$178,0)),"")) -> 2253.1983 | Y61: =IF(OR(X61="",V61=""),"",V61/X61) -> 0.57695765 | AA61: =IF(Z61="","",IFERROR(INDEX($V$1:$V$178,MATCH(Z61,$A$1:$A$178,0)),"")) | AB61: =IF(OR(AA61="",V61=""),"",V61/AA61) | AC61: Gouvernement de Côte d'Ivoire (portail officiel) – Campagne principale 2026-2027 : cacao 1 200 FCFA/kg, café 1 300 FCFA/kg | AD61: https://gouv.ci/actualite/campagne-principale-2026-2027-le-prix-bord-champ-du-cacao-est-fixe-a-1200-fcfa-le-kg-le-prix-du-cafe-setablit-a-1300-fcfa-le-kg-8771 | AE61: 2026-10-01 | AF61: A
A62: CAF-UG-2026-07 | B62: Café | C62: Café robusta FAQ (vert, non classé) | D62: Ouganda | E62: 2025/26 | F62: Juillet 2026 | G62: Prix de marché (libéralisé, relevé UCDA) | H62: Bord champ | I62: FAQ (Fair Average Quality) | J62: 11500 | K62: UGX | L62: kg | M62: 1 | N62: 2026-07:2026-07 | O62: =IF(K62="USD",1,INDEX(Change_periodes!$D$1:$N$400,MATCH($N62,Change_periodes!$A$1:$A$400,0),MATCH($K62,Change_periodes!$D$1:$N$1,0))) -> 3678.495 | P62: BRI ; juil. 2026 : source secondaire (C) | Q62: =INDEX(Change_periodes!$D$1:$D$400,MATCH($N62,Change_periodes!$A$1:$A$400,0)) -> 574.51995 | R62: =IFERROR(J62/M62/O62,"") -> 3.1262785 | S62: =IFERROR(R62*Q62,"") -> 1796.1094 | T62: 1 | U62: FCFA/kg de produit tel que vendu | V62: =IFERROR(S62/T62,"") -> 1796.1094 | W62: INT-ROB-2026-07 | X62: =IF(W62="","",IFERROR(INDEX($V$1:$V$178,MATCH(W62,$A$1:$A$178,0)),"")) -> 2346.1198 | Y62: =IF(OR(X62="",V62=""),"",V62/X62) -> 0.76556593 | AA62: =IF(Z62="","",IFERROR(INDEX($V$1:$V$178,MATCH(Z62,$A$1:$A$178,0)),"")) | AB62: =IF(OR(AA62="",V62=""),"",V62/AA62) | AC62: Uganda Coffee Development Authority (UCDA) – Monthly report July 2026 : prix bord champ Robusta FAQ moyen 11 500 UGX/kg | AD62: https://ugandacoffee.go.ug/sites/default/files/2026-09/10%20July%202026%20Report%20draft(2)(1)(1).pdf | AE62: 2026-10-01 | AF62: A | AG62: Moyenne UCDA (fourchette 11 000-12 000) ; taux de change de source secondaire (C)
A63: CAF-VN-2026-09 | B63: Café | C63: Café vert robusta (nhân xô) | D63: Vietnam | E63: 2025/26 | F63: 28/09/2026 | G63: Prix de marché intérieur | H63: Départ exploitation / collecteur (Dak Lak) | I63: Robusta courant (FAQ) | J63: 93600 | K63: VND | L63: kg | M63: 1 | N63: 2026-09:2026-09 | O63: =IF(K63="USD",1,INDEX(Change_periodes!$D$1:$N$400,MATCH($N63,Change_periodes!$A$1:$A$400,0),MATCH($K63,Change_periodes!$D$1:$N$1,0))) -> 25970 | P63: BRI ; sept. 2026 : Vietcombank | Q63: =INDEX(Change_periodes!$D$1:$D$400,MATCH($N63,Change_periodes!$A$1:$A$400,0)) -> 565.22679 | R63: =IFERROR(J63/M63/O63,"") -> 3.6041586 | S63: =IFERROR(R63*Q63,"") -> 2037.167 | T63: 1 | U63: FCFA/kg de produit tel que vendu | V63: =IFERROR(S63/T63,"") -> 2037.167 | W63: INT-ROB-2026-08 | X63: =IF(W63="","",IFERROR(INDEX($V$1:$V$178,MATCH(W63,$A$1:$A$178,0)),"")) -> 2253.1983 | Y63: =IF(OR(X63="",V63=""),"",V63/X63) -> 0.9041224 | AA63: =IF(Z63="","",IFERROR(INDEX($V$1:$V$178,MATCH(Z63,$A$1:$A$178,0)),"")) | AB63: =IF(OR(AA63="",V63=""),"",V63/AA63) | AC63: Vietnam.vn (prix Dak Lak) – Prix intérieur du café robusta, Dak Lak : 93 600 VND/kg (28/09/2026) | AD63: https://www.vietnam.vn/en/gia-nong-san-hom-nay-28-9-2026-gia-ca-phe-trong-nuoc-di-nguoc-the-gioi-hang-vu-moi-sap-bat-dau-my-trung-giam-thue-doi-voi-60-ty-usd-hang-hoa | AE63: 2026-10-01 | AF63: B | AG63: Prix Dak Lak ; marché très concurrentiel, rendements très élevés
A64: ANA-CI-2016 | B64: Anacarde | C64: Noix de cajou brute (RCN) | D64: Côte d'Ivoire | E64: 2016 | F64: Campagne (févr.-juil.) | G64: Prix plancher obligatoire (administré) | H64: Bord champ | I64: Bien séchée, bien triée | J64: 350 | K64: XOF | L64: kg | M64: 1 | N64: 2016-02:2016-07 | O64: =IF(K64="USD",1,INDEX(Change_periodes!$D$1:$N$400,MATCH($N64,Change_periodes!$A$1:$A$400,0),MATCH($K64,Change_periodes!$D$1:$N$1,0))) -> 586.25151 | P64: BCE (parité fixe 655,957 FCFA/EUR) | Q64: =INDEX(Change_periodes!$D$1:$D$400,MATCH($N64,Change_periodes!$A$1:$A$400,0)) -> 586.25151 | R64: =IFERROR(J64/M64/O64,"") -> 0.59701339 | S64: =IFERROR(R64*Q64,"") -> 350 | T64: 1 | U64: FCFA/kg de produit tel que vendu | V64: =IFERROR(S64/T64,"") -> 350 | X64: =IF(W64="","",IFERROR(INDEX($V$1:$V$178,MATCH(W64,$A$1:$A$178,0)),"")) | Y64: =IF(OR(X64="",V64=""),"",V64/X64) | AA64: =IF(Z64="","",IFERROR(INDEX($V$1:$V$178,MATCH(Z64,$A$1:$A$178,0)),"")) | AB64: =IF(OR(AA64="",V64=""),"",V64/AA64) | AC64: Gouvernement (via Abidjan.net) – Anacarde : le prix du kilogramme fixé à 350 FCFA (2016) | AD64: https://news.abidjan.net/articles/582020/anacarde-le-prix-du-kilogramme-fixe-a-350-fcfa-par-le-gouvernement-ivoirien | AE64: 2026-10-01 | AF64: B | AG64: Prix plancher ; le prix réellement payé peut s'en écarter (ex. 2015 : 410 FCFA obtenus pour un plancher de 275)
A65: ANA-CI-2017 | B65: Anacarde | C65: Noix de cajou brute (RCN) | D65: Côte d'Ivoire | E65: 2017 | F65: Campagne (févr.-juil.) | G65: Prix plancher obligatoire (administré) | H65: Bord champ | I65: Bien séchée, bien triée | J65: 440 | K65: XOF | L65: kg | M65: 1 | N65: 2017-02:2017-07 | O65: =IF(K65="USD",1,INDEX(Change_periodes!$D$1:$N$400,MATCH($N65,Change_periodes!$A$1:$A$400,0),MATCH($K65,Change_periodes!$D$1:$N$1,0))) -> 598.20432 | P65: BCE (parité fixe 655,957 FCFA/EUR) | Q65: =INDEX(Change_periodes!$D$1:$D$400,MATCH($N65,Change_periodes!$A$1:$A$400,0)) -> 598.20432 | R65: =IFERROR(J65/M65/O65,"") -> 0.73553464 | S65: =IFERROR(R65*Q65,"") -> 440 | T65: 1 | U65: FCFA/kg de produit tel que vendu | V65: =IFERROR(S65/T65,"") -> 440 | X65: =IF(W65="","",IFERROR(INDEX($V$1:$V$178,MATCH(W65,$A$1:$A$178,0)),"")) | Y65: =IF(OR(X65="",V65=""),"",V65/X65) | AA65: =IF(Z65="","",IFERROR(INDEX($V$1:$V$178,MATCH(Z65,$A$1:$A$178,0)),"")) | AB65: =IF(OR(AA65="",V65=""),"",V65/AA65) | AC65: CCA (via allAfrica) – Campagne cajou 2017 : mesures arrêtées par le Conseil du coton et de l'anacarde (440 FCFA) | AD65: https://fr.allafrica.com/stories/201702210313.html | AE65: 2026-10-01 | AF65: B | AG65: Prix plancher ; le prix réellement payé peut s'en écarter (ex. 2015 : 410 FCFA obtenus pour un plancher de 275)
A66: ANA-CI-2018 | B66: Anacarde | C66: Noix de cajou brute (RCN) | D66: Côte d'Ivoire | E66: 2018 | F66: Campagne (févr.-juil.) | G66: Prix plancher obligatoire (administré) | H66: Bord champ | I66: Bien séchée, bien triée | J66: 500 | K66: XOF | L66: kg | M66: 1 | N66: 2018-02:2018-07 | O66: =IF(K66="USD",1,INDEX(Change_periodes!$D$1:$N$400,MATCH($N66,Change_periodes!$A$1:$A$400,0),MATCH($K66,Change_periodes!$D$1:$N$1,0))) -> 545.93947 | P66: BCE (parité fixe 655,957 FCFA/EUR) | Q66: =INDEX(Change_periodes!$D$1:$D$400,MATCH($N66,Change_periodes!$A$1:$A$400,0)) -> 545.93947 | R66: =IFERROR(J66/M66/O66,"") -> 0.91585245 | S66: =IFERROR(R66*Q66,"") -> 500 | T66: 1 | U66: FCFA/kg de produit tel que vendu | V66: =IFERROR(S66/T66,"") -> 500 | X66: =IF(W66="","",IFERROR(INDEX($V$1:$V$178,MATCH(W66,$A$1:$A$178,0)),"")) | Y66: =IF(OR(X66="",V66=""),"",V66/X66) | AA66: =IF(Z66="","",IFERROR(INDEX($V$1:$V$178,MATCH(Z66,$A$1:$A$178,0)),"")) | AB66: =IF(OR(AA66="",V66=""),"",V66/AA66) | AC66: CCA (via Financial Afrik) – La campagne de commercialisation des noix de cajou s'annonce sous de bons auspices en 2018 (500 FCFA) | AD66: https://www.financialafrik.com/2018/02/17/cote-divoire-la-campagne-de-commercialisation-des-noix-de-cajou-sannonce-sous-de-bons-auspices-en-2018 | AE66: 2026-10-01 | AF66: B | AG66: Prix plancher ; le prix réellement payé peut s'en écarter (ex. 2015 : 410 FCFA obtenus pour un plancher de 275)
A67: ANA-CI-2019 | B67: Anacarde | C67: Noix de cajou brute (RCN) | D67: Côte d'Ivoire | E67: 2019 | F67: Campagne (févr.-juil.) | G67: Prix plancher obligatoire (administré) | H67: Bord champ | I67: Bien séchée, bien triée | J67: 375 | K67: XOF | L67: kg | M67: 1 | N67: 2019-02:2019-07 | O67: =IF(K67="USD",1,INDEX(Change_periodes!$D$1:$N$400,MATCH($N67,Change_periodes!$A$1:$A$400,0),MATCH($K67,Change_periodes!$D$1:$N$1,0))) -> 582.326 | P67: BCE (parité fixe 655,957 FCFA/EUR) | Q67: =INDEX(Change_periodes!$D$1:$D$400,MATCH($N67,Change_periodes!$A$1:$A$400,0)) -> 582.326 | R67: =IFERROR(J67/M67/O67,"") -> 0.64396919 | S67: =IFERROR(R67*Q67,"") -> 375 | T67: 1 | U67: FCFA/kg de produit tel que vendu | V67: =IFERROR(S67/T67,"") -> 375 | X67: =IF(W67="","",IFERROR(INDEX($V$1:$V$178,MATCH(W67,$A$1:$A$178,0)),"")) | Y67: =IF(OR(X67="",V67=""),"",V67/X67) | AA67: =IF(Z67="","",IFERROR(INDEX($V$1:$V$178,MATCH(Z67,$A$1:$A$178,0)),"")) | AB67: =IF(OR(AA67="",V67=""),"",V67/AA67) | AC67: Gouvernement (via Fraternité Matin) – Noix de cajou : le prix fixé à 375 FCFA/kg pour la campagne 2019 | AD67: https://www.fratmat.info/article/87617/62/noix-de-cajou-le-prix-fixe-a-375-f-cfa-kg-pour-la-campagne-2019 | AE67: 2026-10-01 | AF67: B | AG67: Prix plancher ; le prix réellement payé peut s'en écarter (ex. 2015 : 410 FCFA obtenus pour un plancher de 275)
A68: ANA-CI-2020 | B68: Anacarde | C68: Noix de cajou brute (RCN) | D68: Côte d'Ivoire | E68: 2020 | F68: Campagne (févr.-juil.) | G68: Prix plancher obligatoire (administré) | H68: Bord champ | I68: Bien séchée, bien triée | J68: 400 | K68: XOF | L68: kg | M68: 1 | N68: 2020-02:2020-07 | O68: =IF(K68="USD",1,INDEX(Change_periodes!$D$1:$N$400,MATCH($N68,Change_periodes!$A$1:$A$400,0),MATCH($K68,Change_periodes!$D$1:$N$1,0))) -> 592.51332 | P68: BCE (parité fixe 655,957 FCFA/EUR) | Q68: =INDEX(Change_periodes!$D$1:$D$400,MATCH($N68,Change_periodes!$A$1:$A$400,0)) -> 592.51332 | R68: =IFERROR(J68/M68/O68,"") -> 0.67509031 | S68: =IFERROR(R68*Q68,"") -> 400 | T68: 1 | U68: FCFA/kg de produit tel que vendu | V68: =IFERROR(S68/T68,"") -> 400 | X68: =IF(W68="","",IFERROR(INDEX($V$1:$V$178,MATCH(W68,$A$1:$A$178,0)),"")) | Y68: =IF(OR(X68="",V68=""),"",V68/X68) | AA68: =IF(Z68="","",IFERROR(INDEX($V$1:$V$178,MATCH(Z68,$A$1:$A$178,0)),"")) | AB68: =IF(OR(AA68="",V68=""),"",V68/AA68) | AC68: Gouvernement (via Fraternité Matin) – Anacarde : le prix bord champ fixé à 400 FCFA le kg (2020) | AD68: https://www.fratmat.info/article/201657/economie/anacarde-le-prix-bord-champ-fixe-a-400-fcfa-le-kg | AE68: 2026-10-01 | AF68: B | AG68: Prix plancher ; le prix réellement payé peut s'en écarter (ex. 2015 : 410 FCFA obtenus pour un plancher de 275)
A69: ANA-CI-2021 | B69: Anacarde | C69: Noix de cajou brute (RCN) | D69: Côte d'Ivoire | E69: 2021 | F69: Campagne (févr.-juil.) | G69: Prix plancher obligatoire (administré) | H69: Bord champ | I69: Bien séchée, bien triée | J69: 305 | K69: XOF | L69: kg | M69: 1 | N69: 2021-02:2021-07 | O69: =IF(K69="USD",1,INDEX(Change_periodes!$D$1:$N$400,MATCH($N69,Change_periodes!$A$1:$A$400,0),MATCH($K69,Change_periodes!$D$1:$N$1,0))) -> 546.7478 | P69: BCE (parité fixe 655,957 FCFA/EUR) | Q69: =INDEX(Change_periodes!$D$1:$D$400,MATCH($N69,Change_periodes!$A$1:$A$400,0)) -> 546.7478 | R69: =IFERROR(J69/M69/O69,"") -> 0.55784403 | S69: =IFERROR(R69*Q69,"") -> 305 | T69: 1 | U69: FCFA/kg de produit tel que vendu | V69: =IFERROR(S69/T69,"") -> 305 | X69: =IF(W69="","",IFERROR(INDEX($V$1:$V$178,MATCH(W69,$A$1:$A$178,0)),"")) | Y69: =IF(OR(X69="",V69=""),"",V69/X69) | AA69: =IF(Z69="","",IFERROR(INDEX($V$1:$V$178,MATCH(Z69,$A$1:$A$178,0)),"")) | AB69: =IF(OR(AA69="",V69=""),"",V69/AA69) | AC69: CCA (via Abidjan.net) – Démarrage de la campagne 2022 de commercialisation de la noix de cajou (prix plancher 305 FCFA, inchangé depuis 2021) | AD69: https://news.abidjan.net/articles/703951/demarrage-ce-vendredi-de-la-campagne-2022-de-la-commercialisation-de-la-noix-de-cajou-communique | AE69: 2026-10-01 | AF69: B | AG69: Prix plancher ; le prix réellement payé peut s'en écarter (ex. 2015 : 410 FCFA obtenus pour un plancher de 275)
A70: ANA-CI-2022 | B70: Anacarde | C70: Noix de cajou brute (RCN) | D70: Côte d'Ivoire | E70: 2022 | F70: Campagne (févr.-juil.) | G70: Prix plancher obligatoire (administré) | H70: Bord champ | I70: Bien séchée, bien triée | J70: 305 | K70: XOF | L70: kg | M70: 1 | N70: 2022-02:2022-07 | O70: =IF(K70="USD",1,INDEX(Change_periodes!$D$1:$N$400,MATCH($N70,Change_periodes!$A$1:$A$400,0),MATCH($K70,Change_periodes!$D$1:$N$1,0))) -> 610.88415 | P70: BCE (parité fixe 655,957 FCFA/EUR) | Q70: =INDEX(Change_periodes!$D$1:$D$400,MATCH($N70,Change_periodes!$A$1:$A$400,0)) -> 610.88415 | R70: =IFERROR(J70/M70/O70,"") -> 0.49927633 | S70: =IFERROR(R70*Q70,"") -> 305 | T70: 1 | U70: FCFA/kg de produit tel que vendu | V70: =IFERROR(S70/T70,"") -> 305 | X70: =IF(W70="","",IFERROR(INDEX($V$1:$V$178,MATCH(W70,$A$1:$A$178,0)),"")) | Y70: =IF(OR(X70="",V70=""),"",V70/X70) | AA70: =IF(Z70="","",IFERROR(INDEX($V$1:$V$178,MATCH(Z70,$A$1:$A$178,0)),"")) | AB70: =IF(OR(AA70="",V70=""),"",V70/AA70) | AC70: CCA (via Abidjan.net) – Démarrage de la campagne 2022 de commercialisation de la noix de cajou (prix plancher 305 FCFA, inchangé depuis 2021) | AD70: https://news.abidjan.net/articles/703951/demarrage-ce-vendredi-de-la-campagne-2022-de-la-commercialisation-de-la-noix-de-cajou-communique | AE70: 2026-10-01 | AF70: B | AG70: Prix plancher ; le prix réellement payé peut s'en écarter (ex. 2015 : 410 FCFA obtenus pour un plancher de 275)
A71: ANA-CI-2023 | B71: Anacarde | C71: Noix de cajou brute (RCN) | D71: Côte d'Ivoire | E71: 2023 | F71: Campagne (févr.-juil.) | G71: Prix plancher obligatoire (administré) | H71: Bord champ | I71: Bien séchée, bien triée | J71: 315 | K71: XOF | L71: kg | M71: 1 | N71: 2023-02:2023-07 | O71: =IF(K71="USD",1,INDEX(Change_periodes!$D$1:$N$400,MATCH($N71,Change_periodes!$A$1:$A$400,0),MATCH($K71,Change_periodes!$D$1:$N$1,0))) -> 604.14805 | P71: BCE (parité fixe 655,957 FCFA/EUR) | Q71: =INDEX(Change_periodes!$D$1:$D$400,MATCH($N71,Change_periodes!$A$1:$A$400,0)) -> 604.14805 | R71: =IFERROR(J71/M71/O71,"") -> 0.52139537 | S71: =IFERROR(R71*Q71,"") -> 315 | T71: 1 | U71: FCFA/kg de produit tel que vendu | V71: =IFERROR(S71/T71,"") -> 315 | X71: =IF(W71="","",IFERROR(INDEX($V$1:$V$178,MATCH(W71,$A$1:$A$178,0)),"")) | Y71: =IF(OR(X71="",V71=""),"",V71/X71) | AA71: =IF(Z71="","",IFERROR(INDEX($V$1:$V$178,MATCH(Z71,$A$1:$A$178,0)),"")) | AB71: =IF(OR(AA71="",V71=""),"",V71/AA71) | AC71: Gouvernement (via Abidjan.net) – Le prix de la noix de cajou fixé à 315 FCFA/kg (2023) | AD71: https://news.abidjan.net/articles/717534/cote-divoire-le-prix-de-la-noix-de-cajou-fixe-a-315-f-cfa-kg-officiel | AE71: 2026-10-01 | AF71: B | AG71: Prix plancher ; le prix réellement payé peut s'en écarter (ex. 2015 : 410 FCFA obtenus pour un plancher de 275)
A72: ANA-CI-2024 | B72: Anacarde | C72: Noix de cajou brute (RCN) | D72: Côte d'Ivoire | E72: 2024 | F72: Campagne (févr.-juil.) | G72: Prix plancher obligatoire (administré) | H72: Bord champ | I72: Bien séchée, bien triée | J72: 275 | K72: XOF | L72: kg | M72: 1 | N72: 2024-02:2024-07 | O72: =IF(K72="USD",1,INDEX(Change_periodes!$D$1:$N$400,MATCH($N72,Change_periodes!$A$1:$A$400,0),MATCH($K72,Change_periodes!$D$1:$N$1,0))) -> 607.28631 | P72: BCE (parité fixe 655,957 FCFA/EUR) | Q72: =INDEX(Change_periodes!$D$1:$D$400,MATCH($N72,Change_periodes!$A$1:$A$400,0)) -> 607.28631 | R72: =IFERROR(J72/M72/O72,"") -> 0.45283418 | S72: =IFERROR(R72*Q72,"") -> 275 | T72: 1 | U72: FCFA/kg de produit tel que vendu | V72: =IFERROR(S72/T72,"") -> 275 | X72: =IF(W72="","",IFERROR(INDEX($V$1:$V$178,MATCH(W72,$A$1:$A$178,0)),"")) | Y72: =IF(OR(X72="",V72=""),"",V72/X72) | AA72: =IF(Z72="","",IFERROR(INDEX($V$1:$V$178,MATCH(Z72,$A$1:$A$178,0)),"")) | AB72: =IF(OR(AA72="",V72=""),"",V72/AA72) | AC72: MINADERPV (via AIP) – Le prix bord champ du kg de l'anacarde fixé à 275 FCFA (campagne 2024) | AD72: https://www.aip.ci/33996/cote-divoire-aip-le-prix-bord-champ-du-kg-de-lanacarde-fixe-a-275-fcfa-pour-la-campagne-2023-2024/ | AE72: 2026-10-01 | AF72: B | AG72: Prix plancher ; le prix réellement payé peut s'en écarter (ex. 2015 : 410 FCFA obtenus pour un plancher de 275)
A73: ANA-CI-2025 | B73: Anacarde | C73: Noix de cajou brute (RCN) | D73: Côte d'Ivoire | E73: 2025 | F73: Campagne (févr.-juil.) | G73: Prix plancher obligatoire (administré) | H73: Bord champ | I73: Bien séchée, bien triée | J73: 425 | K73: XOF | L73: kg | M73: 1 | N73: 2025-02:2025-07 | O73: =IF(K73="USD",1,INDEX(Change_periodes!$D$1:$N$400,MATCH($N73,Change_periodes!$A$1:$A$400,0),MATCH($K73,Change_periodes!$D$1:$N$1,0))) -> 589.14644 | P73: BCE (parité fixe 655,957 FCFA/EUR) | Q73: =INDEX(Change_periodes!$D$1:$D$400,MATCH($N73,Change_periodes!$A$1:$A$400,0)) -> 589.14644 | R73: =IFERROR(J73/M73/O73,"") -> 0.72138261 | S73: =IFERROR(R73*Q73,"") -> 425 | T73: 1 | U73: FCFA/kg de produit tel que vendu | V73: =IFERROR(S73/T73,"") -> 425 | X73: =IF(W73="","",IFERROR(INDEX($V$1:$V$178,MATCH(W73,$A$1:$A$178,0)),"")) | Y73: =IF(OR(X73="",V73=""),"",V73/X73) | AA73: =IF(Z73="","",IFERROR(INDEX($V$1:$V$178,MATCH(Z73,$A$1:$A$178,0)),"")) | AB73: =IF(OR(AA73="",V73=""),"",V73/AA73) | AC73: MINADERPV (via KOACI) – Anacarde : prix bord-champ fixé à 425 FCFA (+54 %), campagne 2025 | AD73: https://www.koaci.com/article/2025/01/17/cote-divoire/societe/cote-divoire-anacarde-le-prix-bord-champ-du-kg-fixe-a-425-fcfa-soit-une-hausse-de-54-par-rapport-a-la-campagne-precedente_183836.html | AE73: 2026-10-01 | AF73: B | AG73: Prix plancher ; le prix réellement payé peut s'en écarter (ex. 2015 : 410 FCFA obtenus pour un plancher de 275)
A74: ANA-CI-2026 | B74: Anacarde | C74: Noix de cajou brute (RCN) | D74: Côte d'Ivoire | E74: 2026 | F74: Campagne (févr.-juil.) | G74: Prix plancher obligatoire (administré) | H74: Bord champ | I74: Bien séchée, bien triée | J74: 400 | K74: XOF | L74: kg | M74: 1 | N74: 2026-02:2026-07 | O74: =IF(K74="USD",1,INDEX(Change_periodes!$D$1:$N$400,MATCH($N74,Change_periodes!$A$1:$A$400,0),MATCH($K74,Change_periodes!$D$1:$N$1,0))) -> 564.76495 | P74: BCE (parité fixe 655,957 FCFA/EUR) | Q74: =INDEX(Change_periodes!$D$1:$D$400,MATCH($N74,Change_periodes!$A$1:$A$400,0)) -> 564.76495 | R74: =IFERROR(J74/M74/O74,"") -> 0.70825925 | S74: =IFERROR(R74*Q74,"") -> 400 | T74: 1 | U74: FCFA/kg de produit tel que vendu | V74: =IFERROR(S74/T74,"") -> 400 | W74: INT-ANA-CI-2026 | X74: =IF(W74="","",IFERROR(INDEX($V$1:$V$178,MATCH(W74,$A$1:$A$178,0)),"")) -> 875.37424 | Y74: =IF(OR(X74="",V74=""),"",V74/X74) -> 0.45694742 | AA74: =IF(Z74="","",IFERROR(INDEX($V$1:$V$178,MATCH(Z74,$A$1:$A$178,0)),"")) | AB74: =IF(OR(AA74="",V74=""),"",V74/AA74) | AC74: MINADERPV (via Agence Ecofin) – Baisse de 6 % du prix minimum bord champ de la noix de cajou en 2026 (400 FCFA) | AD74: https://www.agenceecofin.com/actualites-agro/0902-135589-cote-d-ivoire-baisse-de-6-du-prix-minimum-bord-champ-de-la-noix-de-cajou-en-2026 | AE74: 2026-10-01 | AF74: B | AG74: Prix plancher ; le prix réellement payé peut s'en écarter (ex. 2015 : 410 FCFA obtenus pour un plancher de 275)
A75: ANA-CI-2026-REAL | B75: Anacarde | C75: Noix de cajou brute (RCN) | D75: Côte d'Ivoire | E75: 2026 | F75: Campagne 2026 (bilan août 2026) | G75: Prix moyen réellement payé | H75: Bord champ (département de Niakara) | I75: Bien séchée, bien triée | J75: 416 | K75: XOF | L75: kg | M75: 1 | N75: 2026-02:2026-07 | O75: =IF(K75="USD",1,INDEX(Change_periodes!$D$1:$N$400,MATCH($N75,Change_periodes!$A$1:$A$400,0),MATCH($K75,Change_periodes!$D$1:$N$1,0))) -> 564.76495 | P75: BCE (parité fixe 655,957 FCFA/EUR) | Q75: =INDEX(Change_periodes!$D$1:$D$400,MATCH($N75,Change_periodes!$A$1:$A$400,0)) -> 564.76495 | R75: =IFERROR(J75/M75/O75,"") -> 0.73658962 | S75: =IFERROR(R75*Q75,"") -> 416 | T75: 1 | U75: FCFA/kg de produit tel que vendu | V75: =IFERROR(S75/T75,"") -> 416 | W75: INT-ANA-CI-2026 | X75: =IF(W75="","",IFERROR(INDEX($V$1:$V$178,MATCH(W75,$A$1:$A$178,0)),"")) -> 875.37424 | Y75: =IF(OR(X75="",V75=""),"",V75/X75) -> 0.47522531 | AA75: =IF(Z75="","",IFERROR(INDEX($V$1:$V$178,MATCH(Z75,$A$1:$A$178,0)),"")) | AB75: =IF(OR(AA75="",V75=""),"",V75/AA75) | AC75: AIP – Campagne anacarde 2026 : près de 15 Mds FCFA de revenus à Niakara (prix moyen 416 FCFA/kg) | AD75: https://www.aip.ci/cote-divoire-aip-campagne-anacarde-2026-pres-de-15-milliards-fcfa-de-revenus-engranges-par-les-producteurs-du-departement-de-niakara/ | AE75: 2026-10-01 | AF75: B | AG75: Moyenne locale (450 en mars, 375 en mai, ventes groupées à 400)
A76: ANA-CI-2026-PORT | B76: Anacarde | C76: Noix de cajou brute (RCN) | D76: Côte d'Ivoire | E76: 2026 | F76: Campagne 2026 | G76: Prix plancher obligatoire | H76: Magasin portuaire (Abidjan/San-Pedro) | I76: Bien séchée, bien triée | J76: 484 | K76: XOF | L76: kg | M76: 1 | N76: 2026-02:2026-07 | O76: =IF(K76="USD",1,INDEX(Change_periodes!$D$1:$N$400,MATCH($N76,Change_periodes!$A$1:$A$400,0),MATCH($K76,Change_periodes!$D$1:$N$1,0))) -> 564.76495 | P76: BCE (parité fixe 655,957 FCFA/EUR) | Q76: =INDEX(Change_periodes!$D$1:$D$400,MATCH($N76,Change_periodes!$A$1:$A$400,0)) -> 564.76495 | R76: =IFERROR(J76/M76/O76,"") -> 0.85699369 | S76: =IFERROR(R76*Q76,"") -> 484 | T76: 1 | U76: FCFA/kg de produit tel que vendu | V76: =IFERROR(S76/T76,"") -> 484 | W76: INT-ANA-CI-2026 | X76: =IF(W76="","",IFERROR(INDEX($V$1:$V$178,MATCH(W76,$A$1:$A$178,0)),"")) -> 875.37424 | Y76: =IF(OR(X76="",V76=""),"",V76/X76) -> 0.55290638 | AA76: =IF(Z76="","",IFERROR(INDEX($V$1:$V$178,MATCH(Z76,$A$1:$A$178,0)),"")) | AB76: =IF(OR(AA76="",V76=""),"",V76/AA76) | AC76: Gouvernement / CCAK (via Abidjan.net) – Prix planchers 2026 : bord champ 400, magasin intérieur 425, magasin usine 454, magasin portuaire 484 FCFA/kg | AD76: https://news.abidjan.net/articles/747086/commercialisation-de-lanacarde-le-gouvernement-fixe-les-prix-planchers-pour-la-campagne-2026 | AE76: 2026-10-01 | AF76: B | AG76: Barème 2026 : 400 bord champ → 425 magasin intérieur → 454 usine → 484 port
A77: ANA-BF-2026 | B77: Anacarde | C77: Noix de cajou brute (RCN) | D77: Burkina Faso | E77: 2026 | F77: Campagne 2026 | G77: Prix plancher (administré) | H77: Bord champ | I77: Noix brute | J77: 385 | K77: XOF | L77: kg | M77: 1 | N77: 2026-02:2026-07 | O77: =IF(K77="USD",1,INDEX(Change_periodes!$D$1:$N$400,MATCH($N77,Change_periodes!$A$1:$A$400,0),MATCH($K77,Change_periodes!$D$1:$N$1,0))) -> 564.76495 | P77: BCE (parité fixe 655,957 FCFA/EUR) | Q77: =INDEX(Change_periodes!$D$1:$D$400,MATCH($N77,Change_periodes!$A$1:$A$400,0)) -> 564.76495 | R77: =IFERROR(J77/M77/O77,"") -> 0.68169953 | S77: =IFERROR(R77*Q77,"") -> 385 | T77: 1 | U77: FCFA/kg de produit tel que vendu | V77: =IFERROR(S77/T77,"") -> 385 | W77: INT-ANA-CI-2026 | X77: =IF(W77="","",IFERROR(INDEX($V$1:$V$178,MATCH(W77,$A$1:$A$178,0)),"")) -> 875.37424 | Y77: =IF(OR(X77="",V77=""),"",V77/X77) -> 0.43981189 | AA77: =IF(Z77="","",IFERROR(INDEX($V$1:$V$178,MATCH(Z77,$A$1:$A$178,0)),"")) | AB77: =IF(OR(AA77="",V77=""),"",V77/AA77) | AC77: Gouvernement du Burkina Faso (via Sika Finance) – Prix bord champ de la noix de cajou maintenu à 385 FCFA/kg (2026) | AD77: https://www.sikafinance.com/marches/burkina-le-prix-bord-champ-de-la-noix-de-cajou-maintenu-a-385-fcfakg-pour-soutenir-la-transformation-locale_60008 | AE77: 2026-10-01 | AF77: B
A78: ANA-GW-2026 | B78: Anacarde | C78: Noix de cajou brute (RCN) | D78: Guinée-Bissau | E78: 2026 | F78: Campagne 2026 (ouverte le 11/03/2026) | G78: Prix de référence producteur (administré) | H78: Bord champ | I78: Noix brute | J78: 410 | K78: XOF | L78: kg | M78: 1 | N78: 2026-03:2026-07 | O78: =IF(K78="USD",1,INDEX(Change_periodes!$D$1:$N$400,MATCH($N78,Change_periodes!$A$1:$A$400,0),MATCH($K78,Change_periodes!$D$1:$N$1,0))) -> 566.76399 | P78: BCE (parité fixe 655,957 FCFA/EUR) | Q78: =INDEX(Change_periodes!$D$1:$D$400,MATCH($N78,Change_periodes!$A$1:$A$400,0)) -> 566.76399 | R78: =IFERROR(J78/M78/O78,"") -> 0.72340517 | S78: =IFERROR(R78*Q78,"") -> 410 | T78: 1 | U78: FCFA/kg de produit tel que vendu | V78: =IFERROR(S78/T78,"") -> 410 | W78: INT-ANA-CI-2026 | X78: =IF(W78="","",IFERROR(INDEX($V$1:$V$178,MATCH(W78,$A$1:$A$178,0)),"")) -> 875.37424 | Y78: =IF(OR(X78="",V78=""),"",V78/X78) -> 0.4683711 | AA78: =IF(Z78="","",IFERROR(INDEX($V$1:$V$178,MATCH(Z78,$A$1:$A$178,0)),"")) | AB78: =IF(OR(AA78="",V78=""),"",V78/AA78) | AC78: Gouvernement de transition de Guinée-Bissau (via Xinhua) – Campagne 2026 : 410 FCFA/kg au producteur, 478 FCFA/kg à Bissau | AD78: https://english.news.cn/20260311/508ae13acd8c44109ea651276bd01b86/c.html | AE78: 2026-10-01 | AF78: B | AG78: Prix d'achat à Bissau par les intermédiaires : 478 FCFA/kg
A79: ANA-ML-2025 | B79: Anacarde | C79: Noix de cajou brute (RCN) | D79: Mali | E79: 2025 | F79: Campagne 2025 | G79: Prix plancher (administré) | H79: Bord champ | I79: Noix brute | J79: 390 | K79: XOF | L79: kg | M79: 1 | N79: 2025-03:2025-07 | O79: =IF(K79="USD",1,INDEX(Change_periodes!$D$1:$N$400,MATCH($N79,Change_periodes!$A$1:$A$400,0),MATCH($K79,Change_periodes!$D$1:$N$1,0))) -> 580.98159 | P79: BCE (parité fixe 655,957 FCFA/EUR) | Q79: =INDEX(Change_periodes!$D$1:$D$400,MATCH($N79,Change_periodes!$A$1:$A$400,0)) -> 580.98159 | R79: =IFERROR(J79/M79/O79,"") -> 0.67127773 | S79: =IFERROR(R79*Q79,"") -> 390 | T79: 1 | U79: FCFA/kg de produit tel que vendu | V79: =IFERROR(S79/T79,"") -> 390 | X79: =IF(W79="","",IFERROR(INDEX($V$1:$V$178,MATCH(W79,$A$1:$A$178,0)),"")) | Y79: =IF(OR(X79="",V79=""),"",V79/X79) | AA79: =IF(Z79="","",IFERROR(INDEX($V$1:$V$178,MATCH(Z79,$A$1:$A$178,0)),"")) | AB79: =IF(OR(AA79="",V79=""),"",V79/AA79) | AC79: Gouvernement du Mali (via Agence Ecofin) – Mali : la filière anacarde face au défi du respect du prix plancher (390 FCFA ; achats à 350-375) | AD79: https://www.agenceecofin.com/actualites/0104-127164-mali-la-filiere-anacarde-face-au-defi-du-respect-du-prix-plancher | AE79: 2026-10-01 | AF79: B | AG79: Campagne 2025 (2026 non trouvée) ; achats effectifs 350-375 FCFA/kg selon la source
A80: ANA-GH-2026 | B80: Anacarde | C80: Noix de cajou brute (RCN) | D80: Ghana | E80: 2025/26 (récolte 2026) | F80: Saison 2026 | G80: Prix minimum producteur (administré, TCDA) | H80: Bord champ | I80: KOR 46, 190 noix/kg, humidité ≤10 % | J80: 12 | K80: GHS | L80: kg | M80: 1 | N80: 2026-02:2026-05 | O80: =IF(K80="USD",1,INDEX(Change_periodes!$D$1:$N$400,MATCH($N80,Change_periodes!$A$1:$A$400,0),MATCH($K80,Change_periodes!$D$1:$N$1,0))) -> 11.076775 | P80: BRI / Banque du Ghana (moyenne de période) | Q80: =INDEX(Change_periodes!$D$1:$D$400,MATCH($N80,Change_periodes!$A$1:$A$400,0)) -> 561.14094 | R80: =IFERROR(J80/M80/O80,"") -> 1.0833478 | S80: =IFERROR(R80*Q80,"") -> 607.91081 | T80: 1 | U80: FCFA/kg de produit tel que vendu | V80: =IFERROR(S80/T80,"") -> 607.91081 | W80: INT-ANA-CI-2026 | X80: =IF(W80="","",IFERROR(INDEX($V$1:$V$178,MATCH(W80,$A$1:$A$178,0)),"")) -> 875.37424 | Y80: =IF(OR(X80="",V80=""),"",V80/X80) -> 0.69445819 | Z80: FOB-GH-ANA-2026 | AA80: =IF(Z80="","",IFERROR(INDEX($V$1:$V$178,MATCH(Z80,$A$1:$A$178,0)),"")) -> 785.59732 | AB80: =IF(OR(AA80="",V80=""),"",V80/AA80) -> 0.77381987 | AC80: Tree Crops Development Authority (TCDA, Ghana) – Government sets GHS 12.00/kg as minimum producer price for RCN (2025/2026) – benchmark FOB 1 400 USD/t, 11,0241 GH¢/USD | AD80: https://tcda.gov.gh/government-sets-ghs-12-00-per-kilogram-as-minimum-producer-price-for-raw-cashew-nuts-2025-2026-season/ | AE80: 2026-10-01 | AF80: A | AG80: Prix arrondi à la hausse ; respect effectif non documenté
A81: FOB-GH-ANA-2026 | B81: Anacarde | C81: Noix de cajou brute (référence FOB) | D81: Ghana | E81: 2025/26 (récolte 2026) | F81: Référence de calcul TCDA | G81: FOB de référence (modèle de prix) | H81: FOB Tema | I81: KOR 48, 180 noix/kg | J81: 1400 | K81: USD | L81: tonne | M81: 1000 | N81: 2026-02:2026-05 | O81: =IF(K81="USD",1,INDEX(Change_periodes!$D$1:$N$400,MATCH($N81,Change_periodes!$A$1:$A$400,0),MATCH($K81,Change_periodes!$D$1:$N$1,0))) -> 1 | P81: — | Q81: =INDEX(Change_periodes!$D$1:$D$400,MATCH($N81,Change_periodes!$A$1:$A$400,0)) -> 561.14094 | R81: =IFERROR(J81/M81/O81,"") -> 1.4 | S81: =IFERROR(R81*Q81,"") -> 785.59732 | T81: 1 | U81: FCFA/kg de produit tel que vendu | V81: =IFERROR(S81/T81,"") -> 785.59732 | X81: =IF(W81="","",IFERROR(INDEX($V$1:$V$178,MATCH(W81,$A$1:$A$178,0)),"")) | Y81: =IF(OR(X81="",V81=""),"",V81/X81) | AA81: =IF(Z81="","",IFERROR(INDEX($V$1:$V$178,MATCH(Z81,$A$1:$A$178,0)),"")) | AB81: =IF(OR(AA81="",V81=""),"",V81/AA81) | AC81: Tree Crops Development Authority (TCDA, Ghana) – Government sets GHS 12.00/kg as minimum producer price for RCN (2025/2026) – benchmark FOB 1 400 USD/t, 11,0241 GH¢/USD | AD81: https://tcda.gov.gh/government-sets-ghs-12-00-per-kilogram-as-minimum-producer-price-for-raw-cashew-nuts-2025-2026-season/ | AE81: 2026-10-01 | AF81: A | AG81: Référence FOB utilisée par la TCDA pour fixer le prix producteur
A82: ANA-TZ-2025/26 | B82: Anacarde | C82: Noix de cajou brute (RCN) | D82: Tanzanie | E82: 2025/26 | F82: Enchères oct. 2025-janv. 2026 | G82: Prix moyen d'enchères (système de récépissés d'entrepôt) | H82: Magasin primaire (coopératives) | I82: Grade standard, KOR élevé (≈50 lb) | J82: =1279000000000/430961420 -> 2967.7831 | K82: TZS | L82: kg | M82: 1 | N82: 2025-11:2025-11 | O82: =IF(K82="USD",1,INDEX(Change_periodes!$D$1:$N$400,MATCH($N82,Change_periodes!$A$1:$A$400,0),MATCH($K82,Change_periodes!$D$1:$N$1,0))) -> 2434.1667 | P82: UBA Tanzania (approximation, C) | Q82: =INDEX(Change_periodes!$D$1:$D$400,MATCH($N82,Change_periodes!$A$1:$A$400,0)) -> 567.42703 | R82: =IFERROR(J82/M82/O82,"") -> 1.2192193 | S82: =IFERROR(R82*Q82,"") -> 691.81801 | T82: 1 | U82: FCFA/kg de produit tel que vendu | V82: =IFERROR(S82/T82,"") -> 691.81801 | W82: INT-ANA-CI-2026 | X82: =IF(W82="","",IFERROR(INDEX($V$1:$V$178,MATCH(W82,$A$1:$A$178,0)),"")) -> 875.37424 | Y82: =IF(OR(X82="",V82=""),"",V82/X82) -> 0.79031113 | AA82: =IF(Z82="","",IFERROR(INDEX($V$1:$V$178,MATCH(Z82,$A$1:$A$178,0)),"")) | AB82: =IF(OR(AA82="",V82=""),"",V82/AA82) | AC82: The Citizen (données TMX/CBT) – Cashew farmers earn Sh1.3tr : 430 961 t vendues pour 1 279 Mds TZS (2025/26) | AD82: https://www.thecitizen.co.tz/tanzania/business/cashew-farmers-earn-sh1-3tr-as-production-heads-toward-record-5311708 | AE82: 2026-10-01 | AF82: B | AG82: Prix moyen = recettes / volumes ; saison décalée (oct.-janv.) ; taux de change approché (C)
A83: INT-ANA-CI-2026 | B83: Anacarde | C83: Noix de cajou brute d'origine ivoirienne | D83: International (Asie) | E83: 2026 | F83: Avril-mai 2026 | G83: Prix de marché CFR (cotation négoce) | H83: CFR Vietnam/Inde | I83: RCN Côte d'Ivoire (KOR 46-48) | J83: 1560 | K83: USD | L83: tonne | M83: 1000 | N83: 2026-04:2026-05 | O83: =IF(K83="USD",1,INDEX(Change_periodes!$D$1:$N$400,MATCH($N83,Change_periodes!$A$1:$A$400,0),MATCH($K83,Change_periodes!$D$1:$N$1,0))) -> 1 | P83: — | Q83: =INDEX(Change_periodes!$D$1:$D$400,MATCH($N83,Change_periodes!$A$1:$A$400,0)) -> 561.13734 | R83: =IFERROR(J83/M83/O83,"") -> 1.56 | S83: =IFERROR(R83*Q83,"") -> 875.37424 | T83: 1 | U83: FCFA/kg de produit tel que vendu | V83: =IFERROR(S83/T83,"") -> 875.37424 | X83: =IF(W83="","",IFERROR(INDEX($V$1:$V$178,MATCH(W83,$A$1:$A$178,0)),"")) | Y83: =IF(OR(X83="",V83=""),"",V83/X83) | AA83: =IF(Z83="","",IFERROR(INDEX($V$1:$V$178,MATCH(Z83,$A$1:$A$178,0)),"")) | AB83: =IF(OR(AA83="",V83=""),"",V83/AA83) | AC83: Cardassilaris (négociant) – Cashew market report May 2026 : RCN Côte d'Ivoire 1 560 USD/t (avr.-mai 2026) | AD83: https://www.cardassilaris.com/news/cashew-market-report-may-2026-rcn-quality-vietnam | AE83: 2026-10-01 | AF83: C | AG83: Pas de bourse pour la noix brute : cotation de négoce, à recouper
A84: INT-ANA-VN-2026 | B84: Anacarde | C84: Noix de cajou brute (toutes origines) | D84: Vietnam (importations) | E84: 2026 | F84: Janvier-avril 2026 | G84: Valeur unitaire à l'importation | H84: CIF/CFR Vietnam | I84: Toutes origines (Cambodge, Côte d'Ivoire, Nigeria…) | J84: =2200000000/1300000 -> 1692.3077 | K84: USD | L84: tonne | M84: 1000 | N84: 2026-01:2026-04 | O84: =IF(K84="USD",1,INDEX(Change_periodes!$D$1:$N$400,MATCH($N84,Change_periodes!$A$1:$A$400,0),MATCH($K84,Change_periodes!$D$1:$N$1,0))) -> 1 | P84: — | Q84: =INDEX(Change_periodes!$D$1:$D$400,MATCH($N84,Change_periodes!$A$1:$A$400,0)) -> 560.36254 | R84: =IFERROR(J84/M84/O84,"") -> 1.6923077 | S84: =IFERROR(R84*Q84,"") -> 948.30584 | T84: 1 | U84: FCFA/kg de produit tel que vendu | V84: =IFERROR(S84/T84,"") -> 948.30584 | X84: =IF(W84="","",IFERROR(INDEX($V$1:$V$178,MATCH(W84,$A$1:$A$178,0)),"")) | Y84: =IF(OR(X84="",V84=""),"",V84/X84) | AA84: =IF(Z84="","",IFERROR(INDEX($V$1:$V$178,MATCH(Z84,$A$1:$A$178,0)),"")) | AB84: =IF(OR(AA84="",V84=""),"",V84/AA84) | AC84: Douanes vietnamiennes (via Viet Nam News) – Raw cashew nut imports Jan-Apr 2026 : ~1,3 Mt pour ~2,2 Mds USD (≈1 704 USD/t) | AD84: https://vietnamnews.vn/economy/945883/raw-cashew-nut-imports-rocket-in-first-four-months.html | AE84: 2026-10-01 | AF84: B | AG84: Valeur unitaire = valeur ÷ volume ; mélange de qualités (limite de l'indicateur)
A85: COT-CI-2017/18 | B85: Coton | C85: Coton graine 1er choix | D85: Côte d'Ivoire | E85: 2017/18 | F85: Achats nov.-mars ; fibre commercialisée août-juillet | G85: Prix d'achat fixé (administré) | H85: Bord champ (marchés coton) | I85: 1er choix | J85: 265 | K85: XOF | L85: kg | M85: 1 | N85: 2017-08:2018-07 | O85: =IF(K85="USD",1,INDEX(Change_periodes!$D$1:$N$400,MATCH($N85,Change_periodes!$A$1:$A$400,0),MATCH($K85,Change_periodes!$D$1:$N$1,0))) -> 549.20561 | P85: BCE (parité fixe 655,957 FCFA/EUR) | Q85: =INDEX(Change_periodes!$D$1:$D$400,MATCH($N85,Change_periodes!$A$1:$A$400,0)) -> 549.20561 | R85: =IFERROR(J85/M85/O85,"") -> 0.4825151 | S85: =IFERROR(R85*Q85,"") -> 265 | T85: =Parametres!$C$5 -> 0.45183352 | U85: équivalent fibre (÷ rendement égrenage) | V85: =IFERROR(S85/T85,"") -> 586.4992 | W85: INT-COT-2017/18 | X85: =IF(W85="","",IFERROR(INDEX($V$1:$V$178,MATCH(W85,$A$1:$A$178,0)),"")) -> 1065.949 | Y85: =IF(OR(X85="",V85=""),"",V85/X85) -> 0.55021321 | AA85: =IF(Z85="","",IFERROR(INDEX($V$1:$V$178,MATCH(Z85,$A$1:$A$178,0)),"")) | AB85: =IF(OR(AA85="",V85=""),"",V85/AA85) | AC85: Gouvernement (via KOACI) – Coton graine : 300 FCFA/kg (+35 FCFA par rapport à 265 FCFA en 2017-2018) | AD85: https://www.koaci.com/index.php/article/2019/05/22/cote-divoire/economie/cote-divoire-le-prix-du-kilogramme-de-coton-graine-pour-la-campagne-2018-2019-fixe-a-300-fcfa-soit-une-hausse-de-35-fcfa_131167.html | AE85: 2026-10-01 | AF85: B | AG85: Équivalent fibre = prix coton graine ÷ rendement à l'égrenage (graine de coton non valorisée)
A86: COT-CI-2018/19 | B86: Coton | C86: Coton graine 1er choix | D86: Côte d'Ivoire | E86: 2018/19 | F86: Achats nov.-mars ; fibre commercialisée août-juillet | G86: Prix d'achat fixé (administré) | H86: Bord champ (marchés coton) | I86: 1er choix | J86: 265 | K86: XOF | L86: kg | M86: 1 | N86: 2018-08:2019-07 | O86: =IF(K86="USD",1,INDEX(Change_periodes!$D$1:$N$400,MATCH($N86,Change_periodes!$A$1:$A$400,0),MATCH($K86,Change_periodes!$D$1:$N$1,0))) -> 576.96747 | P86: BCE (parité fixe 655,957 FCFA/EUR) | Q86: =INDEX(Change_periodes!$D$1:$D$400,MATCH($N86,Change_periodes!$A$1:$A$400,0)) -> 576.96747 | R86: =IFERROR(J86/M86/O86,"") -> 0.45929799 | S86: =IFERROR(R86*Q86,"") -> 265 | T86: =Parametres!$C$5 -> 0.45183352 | U86: équivalent fibre (÷ rendement égrenage) | V86: =IFERROR(S86/T86,"") -> 586.4992 | W86: INT-COT-2018/19 | X86: =IF(W86="","",IFERROR(INDEX($V$1:$V$178,MATCH(W86,$A$1:$A$178,0)),"")) -> 1073.1071 | Y86: =IF(OR(X86="",V86=""),"",V86/X86) -> 0.54654301 | AA86: =IF(Z86="","",IFERROR(INDEX($V$1:$V$178,MATCH(Z86,$A$1:$A$178,0)),"")) | AB86: =IF(OR(AA86="",V86=""),"",V86/AA86) | AC86: Gouvernement (via Abidjan.net) – Le prix du coton graine de premier choix maintenu à 265 FCFA/kg (2018-2019) | AD86: https://news.abidjan.net/h/638493.html | AE86: 2026-10-01 | AF86: B | AG86: Équivalent fibre = prix coton graine ÷ rendement à l'égrenage (graine de coton non valorisée)
A87: COT-CI-2019/20 | B87: Coton | C87: Coton graine 1er choix | D87: Côte d'Ivoire | E87: 2019/20 | F87: Achats nov.-mars ; fibre commercialisée août-juillet | G87: Prix d'achat fixé (administré) | H87: Bord champ (marchés coton) | I87: 1er choix | J87: 300 | K87: XOF | L87: kg | M87: 1 | N87: 2019-08:2020-07 | O87: =IF(K87="USD",1,INDEX(Change_periodes!$D$1:$N$400,MATCH($N87,Change_periodes!$A$1:$A$400,0),MATCH($K87,Change_periodes!$D$1:$N$1,0))) -> 592.41548 | P87: BCE (parité fixe 655,957 FCFA/EUR) | Q87: =INDEX(Change_periodes!$D$1:$D$400,MATCH($N87,Change_periodes!$A$1:$A$400,0)) -> 592.41548 | R87: =IFERROR(J87/M87/O87,"") -> 0.50640135 | S87: =IFERROR(R87*Q87,"") -> 300 | T87: =Parametres!$C$5 -> 0.45183352 | U87: équivalent fibre (÷ rendement égrenage) | V87: =IFERROR(S87/T87,"") -> 663.96136 | W87: INT-COT-2019/20 | X87: =IF(W87="","",IFERROR(INDEX($V$1:$V$178,MATCH(W87,$A$1:$A$178,0)),"")) -> 931.14908 | Y87: =IF(OR(X87="",V87=""),"",V87/X87) -> 0.71305592 | AA87: =IF(Z87="","",IFERROR(INDEX($V$1:$V$178,MATCH(Z87,$A$1:$A$178,0)),"")) | AB87: =IF(OR(AA87="",V87=""),"",V87/AA87) | AC87: Gouvernement (via KOACI) – Le prix du coton graine reste inchangé pour la campagne 2019-2020 : 300 FCFA/kg | AD87: https://www.koaci.com/article/2019/10/29/cote-divoire/economie/cote-divoire-le-prix-du-coton-de-graine-reste-inchange-pour-la-campagne-2019-2020-300-fcfakg_136257.html | AE87: 2026-10-01 | AF87: B | AG87: Équivalent fibre = prix coton graine ÷ rendement à l'égrenage (graine de coton non valorisée)
A88: COT-CI-2020/21 | B88: Coton | C88: Coton graine 1er choix | D88: Côte d'Ivoire | E88: 2020/21 | F88: Achats nov.-mars ; fibre commercialisée août-juillet | G88: Prix d'achat fixé (administré) | H88: Bord champ (marchés coton) | I88: 1er choix | J88: 300 | K88: XOF | L88: kg | M88: 1 | N88: 2020-08:2021-07 | O88: =IF(K88="USD",1,INDEX(Change_periodes!$D$1:$N$400,MATCH($N88,Change_periodes!$A$1:$A$400,0),MATCH($K88,Change_periodes!$D$1:$N$1,0))) -> 548.37195 | P88: BCE (parité fixe 655,957 FCFA/EUR) | Q88: =INDEX(Change_periodes!$D$1:$D$400,MATCH($N88,Change_periodes!$A$1:$A$400,0)) -> 548.37195 | R88: =IFERROR(J88/M88/O88,"") -> 0.54707393 | S88: =IFERROR(R88*Q88,"") -> 300 | T88: =Parametres!$C$5 -> 0.45183352 | U88: équivalent fibre (÷ rendement égrenage) | V88: =IFERROR(S88/T88,"") -> 663.96136 | W88: INT-COT-2020/21 | X88: =IF(W88="","",IFERROR(INDEX($V$1:$V$178,MATCH(W88,$A$1:$A$178,0)),"")) -> 1027.1758 | Y88: =IF(OR(X88="",V88=""),"",V88/X88) -> 0.64639503 | AA88: =IF(Z88="","",IFERROR(INDEX($V$1:$V$178,MATCH(Z88,$A$1:$A$178,0)),"")) | AB88: =IF(OR(AA88="",V88=""),"",V88/AA88) | AC88: Gouvernement (via allAfrica) – Campagne 2021-2022 du coton : le prix du kilo demeure à 300 F (inchangé depuis 2020-2021) | AD88: https://fr.allafrica.com/stories/202110080394.html | AE88: 2026-10-01 | AF88: B | AG88: Équivalent fibre = prix coton graine ÷ rendement à l'égrenage (graine de coton non valorisée)
A89: COT-CI-2021/22 | B89: Coton | C89: Coton graine 1er choix | D89: Côte d'Ivoire | E89: 2021/22 | F89: Achats nov.-mars ; fibre commercialisée août-juillet | G89: Prix d'achat fixé (administré) | H89: Bord champ (marchés coton) | I89: 1er choix | J89: 300 | K89: XOF | L89: kg | M89: 1 | N89: 2021-08:2022-07 | O89: =IF(K89="USD",1,INDEX(Change_periodes!$D$1:$N$400,MATCH($N89,Change_periodes!$A$1:$A$400,0),MATCH($K89,Change_periodes!$D$1:$N$1,0))) -> 589.9982 | P89: BCE (parité fixe 655,957 FCFA/EUR) | Q89: =INDEX(Change_periodes!$D$1:$D$400,MATCH($N89,Change_periodes!$A$1:$A$400,0)) -> 589.9982 | R89: =IFERROR(J89/M89/O89,"") -> 0.50847613 | S89: =IFERROR(R89*Q89,"") -> 300 | T89: =Parametres!$C$5 -> 0.45183352 | U89: équivalent fibre (÷ rendement égrenage) | V89: =IFERROR(S89/T89,"") -> 663.96136 | W89: INT-COT-2021/22 | X89: =IF(W89="","",IFERROR(INDEX($V$1:$V$178,MATCH(W89,$A$1:$A$178,0)),"")) -> 1717.82 | Y89: =IF(OR(X89="",V89=""),"",V89/X89) -> 0.38651393 | AA89: =IF(Z89="","",IFERROR(INDEX($V$1:$V$178,MATCH(Z89,$A$1:$A$178,0)),"")) | AB89: =IF(OR(AA89="",V89=""),"",V89/AA89) | AC89: Gouvernement (via allAfrica) – Campagne 2021-2022 du coton : le prix du kilo demeure à 300 F (inchangé depuis 2020-2021) | AD89: https://fr.allafrica.com/stories/202110080394.html | AE89: 2026-10-01 | AF89: B | AG89: Équivalent fibre = prix coton graine ÷ rendement à l'égrenage (graine de coton non valorisée)
A90: COT-CI-2022/23 | B90: Coton | C90: Coton graine 1er choix | D90: Côte d'Ivoire | E90: 2022/23 | F90: Achats nov.-mars ; fibre commercialisée août-juillet | G90: Prix d'achat fixé (administré) | H90: Bord champ (marchés coton) | I90: 1er choix | J90: 310 | K90: XOF | L90: kg | M90: 1 | N90: 2022-08:2023-07 | O90: =IF(K90="USD",1,INDEX(Change_periodes!$D$1:$N$400,MATCH($N90,Change_periodes!$A$1:$A$400,0),MATCH($K90,Change_periodes!$D$1:$N$1,0))) -> 622.83882 | P90: BCE (parité fixe 655,957 FCFA/EUR) | Q90: =INDEX(Change_periodes!$D$1:$D$400,MATCH($N90,Change_periodes!$A$1:$A$400,0)) -> 622.83882 | R90: =IFERROR(J90/M90/O90,"") -> 0.49772106 | S90: =IFERROR(R90*Q90,"") -> 310 | T90: =Parametres!$C$5 -> 0.45183352 | U90: équivalent fibre (÷ rendement égrenage) | V90: =IFERROR(S90/T90,"") -> 686.09341 | W90: INT-COT-2022/23 | X90: =IF(W90="","",IFERROR(INDEX($V$1:$V$178,MATCH(W90,$A$1:$A$178,0)),"")) -> 1388.5133 | Y90: =IF(OR(X90="",V90=""),"",V90/X90) -> 0.49412089 | AA90: =IF(Z90="","",IFERROR(INDEX($V$1:$V$178,MATCH(Z90,$A$1:$A$178,0)),"")) | AB90: =IF(OR(AA90="",V90=""),"",V90/AA90) | AC90: Gouvernement (via Connectionivoirienne) – Coton campagne 2022/2023 : le prix du kilogramme fixé à 310 FCFA | AD90: https://connectionivoirienne.net/2022/07/14/coton-camapagne-2022-2023-le-prix-du-kilogramme-fixe-a-310-fcfa/ | AE90: 2026-10-01 | AF90: B | AG90: Équivalent fibre = prix coton graine ÷ rendement à l'égrenage (graine de coton non valorisée)
A91: COT-CI-2023/24 | B91: Coton | C91: Coton graine 1er choix | D91: Côte d'Ivoire | E91: 2023/24 | F91: Achats nov.-mars ; fibre commercialisée août-juillet | G91: Prix d'achat fixé (administré) | H91: Bord champ (marchés coton) | I91: 1er choix | J91: 310 | K91: XOF | L91: kg | M91: 1 | N91: 2023-08:2024-07 | O91: =IF(K91="USD",1,INDEX(Change_periodes!$D$1:$N$400,MATCH($N91,Change_periodes!$A$1:$A$400,0),MATCH($K91,Change_periodes!$D$1:$N$1,0))) -> 607.50519 | P91: BCE (parité fixe 655,957 FCFA/EUR) | Q91: =INDEX(Change_periodes!$D$1:$D$400,MATCH($N91,Change_periodes!$A$1:$A$400,0)) -> 607.50519 | R91: =IFERROR(J91/M91/O91,"") -> 0.51028371 | S91: =IFERROR(R91*Q91,"") -> 310 | T91: =Parametres!$C$5 -> 0.45183352 | U91: équivalent fibre (÷ rendement égrenage) | V91: =IFERROR(S91/T91,"") -> 686.09341 | W91: INT-COT-2023/24 | X91: =IF(W91="","",IFERROR(INDEX($V$1:$V$178,MATCH(W91,$A$1:$A$178,0)),"")) -> 1231.0788 | Y91: =IF(OR(X91="",V91=""),"",V91/X91) -> 0.5573107 | AA91: =IF(Z91="","",IFERROR(INDEX($V$1:$V$178,MATCH(Z91,$A$1:$A$178,0)),"")) | AB91: =IF(OR(AA91="",V91=""),"",V91/AA91) | AC91: Gouvernement (via Abidjan.net) – Coton graine 1er choix 310 FCFA, 2e choix 285 FCFA (2023-2024) | AD91: https://news.abidjan.net/articles/720825/cote-divoire-le-prix-du-coton-graines-1er-choix-fixe-a-310-fcfa-et-a-285-f-cfa-le-kilo-du-2e-choix | AE91: 2026-10-01 | AF91: B | AG91: Équivalent fibre = prix coton graine ÷ rendement à l'égrenage (graine de coton non valorisée)
A92: COT-CI-2024/25 | B92: Coton | C92: Coton graine 1er choix | D92: Côte d'Ivoire | E92: 2024/25 | F92: Achats nov.-mars ; fibre commercialisée août-juillet | G92: Prix d'achat fixé (administré) | H92: Bord champ (marchés coton) | I92: 1er choix | J92: 310 | K92: XOF | L92: kg | M92: 1 | N92: 2024-08:2025-07 | O92: =IF(K92="USD",1,INDEX(Change_periodes!$D$1:$N$400,MATCH($N92,Change_periodes!$A$1:$A$400,0),MATCH($K92,Change_periodes!$D$1:$N$1,0))) -> 599.94493 | P92: BCE (parité fixe 655,957 FCFA/EUR) | Q92: =INDEX(Change_periodes!$D$1:$D$400,MATCH($N92,Change_periodes!$A$1:$A$400,0)) -> 599.94493 | R92: =IFERROR(J92/M92/O92,"") -> 0.51671409 | S92: =IFERROR(R92*Q92,"") -> 310 | T92: =Parametres!$C$5 -> 0.45183352 | U92: équivalent fibre (÷ rendement égrenage) | V92: =IFERROR(S92/T92,"") -> 686.09341 | W92: INT-COT-2024/25 | X92: =IF(W92="","",IFERROR(INDEX($V$1:$V$178,MATCH(W92,$A$1:$A$178,0)),"")) -> 1052.4441 | Y92: =IF(OR(X92="",V92=""),"",V92/X92) -> 0.65190482 | AA92: =IF(Z92="","",IFERROR(INDEX($V$1:$V$178,MATCH(Z92,$A$1:$A$178,0)),"")) | AB92: =IF(OR(AA92="",V92=""),"",V92/AA92) | AC92: Agence Ecofin – La subvention à la filière coton a plus que doublé en 2025/2026 (25,3 Mds FCFA contre 11,9 Mds) | AD92: https://www.agenceecofin.com/actualites-agro/0108-130586-cote-d-ivoire-la-subvention-a-la-filiere-coton-a-plus-que-double-en-2025/2026 | AE92: 2026-10-01 | AF92: B | AG92: Équivalent fibre = prix coton graine ÷ rendement à l'égrenage (graine de coton non valorisée)
A93: COT-CI-2025/26 | B93: Coton | C93: Coton graine 1er choix | D93: Côte d'Ivoire | E93: 2025/26 | F93: Achats nov.-mars ; fibre commercialisée août-juillet | G93: Prix d'achat fixé (administré) | H93: Bord champ (marchés coton) | I93: 1er choix | J93: 310 | K93: XOF | L93: kg | M93: 1 | N93: 2025-08:2026-07 | O93: =IF(K93="USD",1,INDEX(Change_periodes!$D$1:$N$400,MATCH($N93,Change_periodes!$A$1:$A$400,0),MATCH($K93,Change_periodes!$D$1:$N$1,0))) -> 563.51057 | P93: BCE (parité fixe 655,957 FCFA/EUR) | Q93: =INDEX(Change_periodes!$D$1:$D$400,MATCH($N93,Change_periodes!$A$1:$A$400,0)) -> 563.51057 | R93: =IFERROR(J93/M93/O93,"") -> 0.55012277 | S93: =IFERROR(R93*Q93,"") -> 310 | T93: =Parametres!$C$5 -> 0.45183352 | U93: équivalent fibre (÷ rendement égrenage) | V93: =IFERROR(S93/T93,"") -> 686.09341 | W93: INT-COT-2025/26 | X93: =IF(W93="","",IFERROR(INDEX($V$1:$V$178,MATCH(W93,$A$1:$A$178,0)),"")) -> 942.50032 | Y93: =IF(OR(X93="",V93=""),"",V93/X93) -> 0.72795032 | AA93: =IF(Z93="","",IFERROR(INDEX($V$1:$V$178,MATCH(Z93,$A$1:$A$178,0)),"")) | AB93: =IF(OR(AA93="",V93=""),"",V93/AA93) | AC93: MINADERPV (via KOACI) – Campagne 2025-2026 : coton 1er choix 310 FCFA/kg, 2e choix 285 FCFA/kg (31/07/2025) | AD93: https://www.koaci.com/article/2025/07/31/cote-divoire/societe/cote-divoire-campagne-2025-2026-le-prix-du-coton-de-1er-choix-est-fixe-a-310-fcfakg-et-celui-de-2e-choix-a-285-fcfakg_189056.html | AE93: 2026-10-01 | AF93: B | AG93: Équivalent fibre = prix coton graine ÷ rendement à l'égrenage (graine de coton non valorisée)
A94: COT-BF-2025/26 | B94: Coton | C94: Coton graine 1er choix | D94: Burkina Faso | E94: 2025/26 | F94: Campagne | G94: Prix d'achat fixé (administré) | H94: Bord champ | I94: 1er choix (conventionnel) | J94: 325 | K94: XOF | L94: kg | M94: 1 | N94: 2025-08:2026-07 | O94: =IF(K94="USD",1,INDEX(Change_periodes!$D$1:$N$400,MATCH($N94,Change_periodes!$A$1:$A$400,0),MATCH($K94,Change_periodes!$D$1:$N$1,0))) -> 563.51057 | P94: BCE (parité fixe 655,957 FCFA/EUR) | Q94: =INDEX(Change_periodes!$D$1:$D$400,MATCH($N94,Change_periodes!$A$1:$A$400,0)) -> 563.51057 | R94: =IFERROR(J94/M94/O94,"") -> 0.57674162 | S94: =IFERROR(R94*Q94,"") -> 325 | T94: 1 | U94: FCFA/kg de produit tel que vendu | V94: =IFERROR(S94/T94,"") -> 325 | X94: =IF(W94="","",IFERROR(INDEX($V$1:$V$178,MATCH(W94,$A$1:$A$178,0)),"")) | Y94: =IF(OR(X94="",V94=""),"",V94/X94) | AA94: =IF(Z94="","",IFERROR(INDEX($V$1:$V$178,MATCH(Z94,$A$1:$A$178,0)),"")) | AB94: =IF(OR(AA94="",V94=""),"",V94/AA94) | AC94: SOFITEX (Burkina Faso) – Campagne 2025-2026 : engrais 17 500 FCFA, kg de coton 325 FCFA | AD94: https://www.sofitex.bf/2025/04/10/campagne-cotonniere-2025-2026-les-engrais-a-17-500-f-cfa-les-insecticides-a-5-200-f-cfa-et-le-kg-de-coton-a-325-f-cfa/ | AE94: 2026-10-01 | AF94: A | AG94: 2e choix 300 FCFA
A95: COT-ML-2025/26 | B95: Coton | C95: Coton graine 1er choix | D95: Mali | E95: 2025/26 | F95: Campagne | G95: Prix d'achat fixé (administré) | H95: Bord champ | I95: 1er choix (conventionnel) | J95: 300 | K95: XOF | L95: kg | M95: 1 | N95: 2025-08:2026-07 | O95: =IF(K95="USD",1,INDEX(Change_periodes!$D$1:$N$400,MATCH($N95,Change_periodes!$A$1:$A$400,0),MATCH($K95,Change_periodes!$D$1:$N$1,0))) -> 563.51057 | P95: BCE (parité fixe 655,957 FCFA/EUR) | Q95: =INDEX(Change_periodes!$D$1:$D$400,MATCH($N95,Change_periodes!$A$1:$A$400,0)) -> 563.51057 | R95: =IFERROR(J95/M95/O95,"") -> 0.53237688 | S95: =IFERROR(R95*Q95,"") -> 300 | T95: 1 | U95: FCFA/kg de produit tel que vendu | V95: =IFERROR(S95/T95,"") -> 300 | X95: =IF(W95="","",IFERROR(INDEX($V$1:$V$178,MATCH(W95,$A$1:$A$178,0)),"")) | Y95: =IF(OR(X95="",V95=""),"",V95/X95) | AA95: =IF(Z95="","",IFERROR(INDEX($V$1:$V$178,MATCH(Z95,$A$1:$A$178,0)),"")) | AB95: =IF(OR(AA95="",V95=""),"",V95/AA95) | AC95: Gouvernement du Mali (via Mali 24) – Prix du kilo du coton graine maintenu à 300 FCFA | AD95: https://mali24.info/mali-433-700-tonnes-de-coton-produites-le-prix-du-kilo-du-coton-graine-maintenu-a-300-f-cfa/ | AE95: 2026-10-01 | AF95: B | AG95: Décision du Conseil supérieur de l'agriculture du 06/05/2025
A96: COT-BJ-2025/26 | B96: Coton | C96: Coton graine 1er choix | D96: Bénin | E96: 2025/26 | F96: Campagne | G96: Prix d'achat fixé (administré) | H96: Bord champ | I96: 1er choix (conventionnel) | J96: 300 | K96: XOF | L96: kg | M96: 1 | N96: 2025-08:2026-07 | O96: =IF(K96="USD",1,INDEX(Change_periodes!$D$1:$N$400,MATCH($N96,Change_periodes!$A$1:$A$400,0),MATCH($K96,Change_periodes!$D$1:$N$1,0))) -> 563.51057 | P96: BCE (parité fixe 655,957 FCFA/EUR) | Q96: =INDEX(Change_periodes!$D$1:$D$400,MATCH($N96,Change_periodes!$A$1:$A$400,0)) -> 563.51057 | R96: =IFERROR(J96/M96/O96,"") -> 0.53237688 | S96: =IFERROR(R96*Q96,"") -> 300 | T96: 1 | U96: FCFA/kg de produit tel que vendu | V96: =IFERROR(S96/T96,"") -> 300 | X96: =IF(W96="","",IFERROR(INDEX($V$1:$V$178,MATCH(W96,$A$1:$A$178,0)),"")) | Y96: =IF(OR(X96="",V96=""),"",V96/X96) | AA96: =IF(Z96="","",IFERROR(INDEX($V$1:$V$178,MATCH(Z96,$A$1:$A$178,0)),"")) | AB96: =IF(OR(AA96="",V96=""),"",V96/AA96) | AC96: Gouvernement du Bénin (via La Nation) – Campagne cotonnière 2025-2026 : prix des insecticides et du coton graine homologués (300 FCFA) | AD96: https://lanation.bj/actualites/campagne-cotonniere-2025-2026-les-prix-des-insecticides-et-du-coton-graine-homologues | AE96: 2026-10-01 | AF96: B | AG96: Conventionnel ; biologique 360 FCFA
A97: COT-TG-2025/26 | B97: Coton | C97: Coton graine 1er choix | D97: Togo | E97: 2025/26 | F97: Campagne | G97: Prix d'achat fixé (administré) | H97: Bord champ | I97: 1er choix (conventionnel) | J97: 300 | K97: XOF | L97: kg | M97: 1 | N97: 2025-08:2026-07 | O97: =IF(K97="USD",1,INDEX(Change_periodes!$D$1:$N$400,MATCH($N97,Change_periodes!$A$1:$A$400,0),MATCH($K97,Change_periodes!$D$1:$N$1,0))) -> 563.51057 | P97: BCE (parité fixe 655,957 FCFA/EUR) | Q97: =INDEX(Change_periodes!$D$1:$D$400,MATCH($N97,Change_periodes!$A$1:$A$400,0)) -> 563.51057 | R97: =IFERROR(J97/M97/O97,"") -> 0.53237688 | S97: =IFERROR(R97*Q97,"") -> 300 | T97: 1 | U97: FCFA/kg de produit tel que vendu | V97: =IFERROR(S97/T97,"") -> 300 | X97: =IF(W97="","",IFERROR(INDEX($V$1:$V$178,MATCH(W97,$A$1:$A$178,0)),"")) | Y97: =IF(OR(X97="",V97=""),"",V97/X97) | AA97: =IF(Z97="","",IFERROR(INDEX($V$1:$V$178,MATCH(Z97,$A$1:$A$178,0)),"")) | AB97: =IF(OR(AA97="",V97=""),"",V97/AA97) | AC97: Africa Radio – Coton africain : ~300 FCFA au Bénin et au Mali, 310 en Côte d'Ivoire, 325 au Burkina, jusqu'à 350 au Sénégal | AD97: https://www.africaradio.com/actualite-115836-coton-africain-pourquoi-les-producteurs-ouest-africains-perdent-ils-du-terrain | AE97: 2026-10-01 | AF97: C | AG97: Source régionale secondaire (C)
A98: COT-SN-2025/26 | B98: Coton | C98: Coton graine 1er choix | D98: Sénégal | E98: 2025/26 | F98: Campagne | G98: Prix d'achat fixé (administré) | H98: Bord champ | I98: 1er choix (conventionnel) | J98: 350 | K98: XOF | L98: kg | M98: 1 | N98: 2025-08:2026-07 | O98: =IF(K98="USD",1,INDEX(Change_periodes!$D$1:$N$400,MATCH($N98,Change_periodes!$A$1:$A$400,0),MATCH($K98,Change_periodes!$D$1:$N$1,0))) -> 563.51057 | P98: BCE (parité fixe 655,957 FCFA/EUR) | Q98: =INDEX(Change_periodes!$D$1:$D$400,MATCH($N98,Change_periodes!$A$1:$A$400,0)) -> 563.51057 | R98: =IFERROR(J98/M98/O98,"") -> 0.62110636 | S98: =IFERROR(R98*Q98,"") -> 350 | T98: 1 | U98: FCFA/kg de produit tel que vendu | V98: =IFERROR(S98/T98,"") -> 350 | X98: =IF(W98="","",IFERROR(INDEX($V$1:$V$178,MATCH(W98,$A$1:$A$178,0)),"")) | Y98: =IF(OR(X98="",V98=""),"",V98/X98) | AA98: =IF(Z98="","",IFERROR(INDEX($V$1:$V$178,MATCH(Z98,$A$1:$A$178,0)),"")) | AB98: =IF(OR(AA98="",V98=""),"",V98/AA98) | AC98: Africa Radio – Coton africain : ~300 FCFA au Bénin et au Mali, 310 en Côte d'Ivoire, 325 au Burkina, jusqu'à 350 au Sénégal | AD98: https://www.africaradio.com/actualite-115836-coton-africain-pourquoi-les-producteurs-ouest-africains-perdent-ils-du-terrain | AE98: 2026-10-01 | AF98: C | AG98: « jusqu'à 350 FCFA » : source secondaire (C)
A99: COT-BF-2026/27 | B99: Coton | C99: Coton graine 1er choix | D99: Burkina Faso | E99: 2026/27 | F99: Campagne | G99: Prix d'achat fixé (administré) | H99: Bord champ | I99: 1er choix (conventionnel) | J99: 310 | K99: XOF | L99: kg | M99: 1 | N99: 2026-04:2026-07 | O99: =IF(K99="USD",1,INDEX(Change_periodes!$D$1:$N$400,MATCH($N99,Change_periodes!$A$1:$A$400,0),MATCH($K99,Change_periodes!$D$1:$N$1,0))) -> 566.57515 | P99: BCE (parité fixe 655,957 FCFA/EUR) | Q99: =INDEX(Change_periodes!$D$1:$D$400,MATCH($N99,Change_periodes!$A$1:$A$400,0)) -> 566.57515 | R99: =IFERROR(J99/M99/O99,"") -> 0.54714719 | S99: =IFERROR(R99*Q99,"") -> 310 | T99: 1 | U99: FCFA/kg de produit tel que vendu | V99: =IFERROR(S99/T99,"") -> 310 | X99: =IF(W99="","",IFERROR(INDEX($V$1:$V$178,MATCH(W99,$A$1:$A$178,0)),"")) | Y99: =IF(OR(X99="",V99=""),"",V99/X99) | AA99: =IF(Z99="","",IFERROR(INDEX($V$1:$V$178,MATCH(Z99,$A$1:$A$178,0)),"")) | AB99: =IF(OR(AA99="",V99=""),"",V99/AA99) | AC99: Africa Radio – Coton africain : ~300 FCFA au Bénin et au Mali, 310 en Côte d'Ivoire, 325 au Burkina, jusqu'à 350 au Sénégal | AD99: https://www.africaradio.com/actualite-115836-coton-africain-pourquoi-les-producteurs-ouest-africains-perdent-ils-du-terrain | AE99: 2026-10-01 | AF99: C | AG99: Prix plancher 2026/27 (310/285) ; source de presse non primaire
A100: COT-BJ-2026/27 | B100: Coton | C100: Coton graine 1er choix | D100: Bénin | E100: 2026/27 | F100: Campagne | G100: Prix d'achat fixé (administré) | H100: Bord champ | I100: 1er choix (conventionnel) | J100: 300 | K100: XOF | L100: kg | M100: 1 | N100: 2026-04:2026-07 | O100: =IF(K100="USD",1,INDEX(Change_periodes!$D$1:$N$400,MATCH($N100,Change_periodes!$A$1:$A$400,0),MATCH($K100,Change_periodes!$D$1:$N$1,0))) -> 566.57515 | P100: BCE (parité fixe 655,957 FCFA/EUR) | Q100: =INDEX(Change_periodes!$D$1:$D$400,MATCH($N100,Change_periodes!$A$1:$A$400,0)) -> 566.57515 | R100: =IFERROR(J100/M100/O100,"") -> 0.52949728 | S100: =IFERROR(R100*Q100,"") -> 300 | T100: 1 | U100: FCFA/kg de produit tel que vendu | V100: =IFERROR(S100/T100,"") -> 300 | X100: =IF(W100="","",IFERROR(INDEX($V$1:$V$178,MATCH(W100,$A$1:$A$178,0)),"")) | Y100: =IF(OR(X100="",V100=""),"",V100/X100) | AA100: =IF(Z100="","",IFERROR(INDEX($V$1:$V$178,MATCH(Z100,$A$1:$A$178,0)),"")) | AB100: =IF(OR(AA100="",V100=""),"",V100/AA100) | AC100: Gouvernement du Bénin (via Le Matinal) – Campagne 2026-2027 : coton conventionnel 300 FCFA (1er choix), biologique 360 FCFA (CM du 13/05/2026) | AD100: https://lematinal.bj/campagne-cotonniere-2026-2027-le-prix-de-cession-des-intrants-et-dachat-de-coton-graine-homologue/ | AE100: 2026-10-01 | AF100: B | AG100: Conventionnel 1er choix ; biologique 360
A101: CAO-CI-2025-01 | B101: Caoutchouc | C101: Caoutchouc naturel (fonds de tasse) | D101: Côte d'Ivoire | E101: 2025 | F101: Mois 2025-01 | G101: Prix bord champ fixé (APROMAC, loi 2017-540) | H101: Bord champ | I101: Coagulum humide, DRC de référence 60 % | J101: 442 | K101: XOF | L101: kg | M101: 1 | N101: 2024-12:2024-12 | O101: =IF(K101="USD",1,INDEX(Change_periodes!$D$1:$N$400,MATCH($N101,Change_periodes!$A$1:$A$400,0),MATCH($K101,Change_periodes!$D$1:$N$1,0))) -> 625.98783 | P101: BCE (parité fixe 655,957 FCFA/EUR) | Q101: =INDEX(Change_periodes!$D$1:$D$400,MATCH($N101,Change_periodes!$A$1:$A$400,0)) -> 625.98783 | R101: =IFERROR(J101/M101/O101,"") -> 0.70608401 | S101: =IFERROR(R101*Q101,"") -> 442 | T101: =Parametres!$C$6 -> 0.6 | U101: kg de caoutchouc sec (÷ DRC 60 %) | V101: =IFERROR(S101/T101,"") -> 736.66667 | W101: INT-TSR-2024-12 | X101: =IF(W101="","",IFERROR(INDEX($V$1:$V$178,MATCH(W101,$A$1:$A$178,0)),"")) -> 1248.0319 | Y101: =IF(OR(X101="",V101=""),"",V101/X101) -> 0.59026267 | AA101: =IF(Z101="","",IFERROR(INDEX($V$1:$V$178,MATCH(Z101,$A$1:$A$178,0)),"")) | AB101: =IF(OR(AA101="",V101=""),"",V101/AA101) | AC101: APROMAC (via Yessouan) – Prix caoutchouc Côte d'Ivoire : 442 FCFA/kg en janvier 2025 | AD101: https://www.yessouan.ci/Prix-caoutchouc-Cote-d-Ivoire-442-FCFA-kg-en-janvier-2025_a1537.html | AE101: 2026-10-01 | AF101: B | AG101: Prix du mois M calculé sur les cours SICOM du mois M-1 ; producteur = 63 % (66 % en 2026) du prix de référence
A102: CAO-CI-2025-04 | B102: Caoutchouc | C102: Caoutchouc naturel (fonds de tasse) | D102: Côte d'Ivoire | E102: 2025 | F102: Mois 2025-04 | G102: Prix bord champ fixé (APROMAC, loi 2017-540) | H102: Bord champ | I102: Coagulum humide, DRC de référence 60 % | J102: 438 | K102: XOF | L102: kg | M102: 1 | N102: 2025-03:2025-03 | O102: =IF(K102="USD",1,INDEX(Change_periodes!$D$1:$N$400,MATCH($N102,Change_periodes!$A$1:$A$400,0),MATCH($K102,Change_periodes!$D$1:$N$1,0))) -> 606.98485 | P102: BCE (parité fixe 655,957 FCFA/EUR) | Q102: =INDEX(Change_periodes!$D$1:$D$400,MATCH($N102,Change_periodes!$A$1:$A$400,0)) -> 606.98485 | R102: =IFERROR(J102/M102/O102,"") -> 0.72159955 | S102: =IFERROR(R102*Q102,"") -> 438 | T102: =Parametres!$C$6 -> 0.6 | U102: kg de caoutchouc sec (÷ DRC 60 %) | V102: =IFERROR(S102/T102,"") -> 730 | W102: INT-TSR-2025-03 | X102: =IF(W102="","",IFERROR(INDEX($V$1:$V$178,MATCH(W102,$A$1:$A$178,0)),"")) -> 1202.8012 | Y102: =IF(OR(X102="",V102=""),"",V102/X102) -> 0.60691659 | AA102: =IF(Z102="","",IFERROR(INDEX($V$1:$V$178,MATCH(Z102,$A$1:$A$178,0)),"")) | AB102: =IF(OR(AA102="",V102=""),"",V102/AA102) | AC102: APROMAC (via 7info) – Caoutchouc naturel : prix du kg pour le mois d'avril (438 FCFA) | AD102: https://www.7info.ci/caoutchouc-naturel-voici-le-prix-du-kg-pour-le-mois-davril/ | AE102: 2026-10-01 | AF102: B | AG102: Prix du mois M calculé sur les cours SICOM du mois M-1 ; producteur = 63 % (66 % en 2026) du prix de référence
A103: CAO-CI-2026-01 | B103: Caoutchouc | C103: Caoutchouc naturel (fonds de tasse) | D103: Côte d'Ivoire | E103: 2026 | F103: Mois 2026-01 | G103: Prix bord champ fixé (APROMAC, loi 2017-540) | H103: Bord champ | I103: Coagulum humide, DRC de référence 60 % | J103: 352 | K103: XOF | L103: kg | M103: 1 | N103: 2025-12:2025-12 | O103: =IF(K103="USD",1,INDEX(Change_periodes!$D$1:$N$400,MATCH($N103,Change_periodes!$A$1:$A$400,0),MATCH($K103,Change_periodes!$D$1:$N$1,0))) -> 560.22995 | P103: BCE (parité fixe 655,957 FCFA/EUR) | Q103: =INDEX(Change_periodes!$D$1:$D$400,MATCH($N103,Change_periodes!$A$1:$A$400,0)) -> 560.22995 | R103: =IFERROR(J103/M103/O103,"") -> 0.62831343 | S103: =IFERROR(R103*Q103,"") -> 352 | T103: =Parametres!$C$6 -> 0.6 | U103: kg de caoutchouc sec (÷ DRC 60 %) | V103: =IFERROR(S103/T103,"") -> 586.66667 | W103: INT-TSR-2025-12 | X103: =IF(W103="","",IFERROR(INDEX($V$1:$V$178,MATCH(W103,$A$1:$A$178,0)),"")) -> 974.85613 | Y103: =IF(OR(X103="",V103=""),"",V103/X103) -> 0.6017982 | AA103: =IF(Z103="","",IFERROR(INDEX($V$1:$V$178,MATCH(Z103,$A$1:$A$178,0)),"")) | AB103: =IF(OR(AA103="",V103=""),"",V103/AA103) | AC103: APROMAC (via 7info) – Caoutchouc : nouveaux prix du kg (janv. 352, fév. 368, avr. 401, mai 439, juil. 493 FCFA) | AD103: https://www.7info.ci/caoutchouc-voici-le-nouveau-prix-du-kg/ | AE103: 2026-10-01 | AF103: B | AG103: Prix du mois M calculé sur les cours SICOM du mois M-1 ; producteur = 63 % (66 % en 2026) du prix de référence
A104: CAO-CI-2026-02 | B104: Caoutchouc | C104: Caoutchouc naturel (fonds de tasse) | D104: Côte d'Ivoire | E104: 2026 | F104: Mois 2026-02 | G104: Prix bord champ fixé (APROMAC, loi 2017-540) | H104: Bord champ | I104: Coagulum humide, DRC de référence 60 % | J104: 368 | K104: XOF | L104: kg | M104: 1 | N104: 2026-01:2026-01 | O104: =IF(K104="USD",1,INDEX(Change_periodes!$D$1:$N$400,MATCH($N104,Change_periodes!$A$1:$A$400,0),MATCH($K104,Change_periodes!$D$1:$N$1,0))) -> 558.82057 | P104: BCE (parité fixe 655,957 FCFA/EUR) | Q104: =INDEX(Change_periodes!$D$1:$D$400,MATCH($N104,Change_periodes!$A$1:$A$400,0)) -> 558.82057 | R104: =IFERROR(J104/M104/O104,"") -> 0.6585298 | S104: =IFERROR(R104*Q104,"") -> 368 | T104: =Parametres!$C$6 -> 0.6 | U104: kg de caoutchouc sec (÷ DRC 60 %) | V104: =IFERROR(S104/T104,"") -> 613.33333 | W104: INT-TSR-2026-01 | X104: =IF(W104="","",IFERROR(INDEX($V$1:$V$178,MATCH(W104,$A$1:$A$178,0)),"")) -> 1029.9622 | Y104: =IF(OR(X104="",V104=""),"",V104/X104) -> 0.59549111 | AA104: =IF(Z104="","",IFERROR(INDEX($V$1:$V$178,MATCH(Z104,$A$1:$A$178,0)),"")) | AB104: =IF(OR(AA104="",V104=""),"",V104/AA104) | AC104: APROMAC (via 7info) – Caoutchouc : nouveaux prix du kg (janv. 352, fév. 368, avr. 401, mai 439, juil. 493 FCFA) | AD104: https://www.7info.ci/caoutchouc-voici-le-nouveau-prix-du-kg/ | AE104: 2026-10-01 | AF104: B | AG104: Prix du mois M calculé sur les cours SICOM du mois M-1 ; producteur = 63 % (66 % en 2026) du prix de référence
A105: CAO-CI-2026-04 | B105: Caoutchouc | C105: Caoutchouc naturel (fonds de tasse) | D105: Côte d'Ivoire | E105: 2026 | F105: Mois 2026-04 | G105: Prix bord champ fixé (APROMAC, loi 2017-540) | H105: Bord champ | I105: Coagulum humide, DRC de référence 60 % | J105: 401 | K105: XOF | L105: kg | M105: 1 | N105: 2026-03:2026-03 | O105: =IF(K105="USD",1,INDEX(Change_periodes!$D$1:$N$400,MATCH($N105,Change_periodes!$A$1:$A$400,0),MATCH($K105,Change_periodes!$D$1:$N$1,0))) -> 567.51933 | P105: BCE (parité fixe 655,957 FCFA/EUR) | Q105: =INDEX(Change_periodes!$D$1:$D$400,MATCH($N105,Change_periodes!$A$1:$A$400,0)) -> 567.51933 | R105: =IFERROR(J105/M105/O105,"") -> 0.70658386 | S105: =IFERROR(R105*Q105,"") -> 401 | T105: =Parametres!$C$6 -> 0.6 | U105: kg de caoutchouc sec (÷ DRC 60 %) | V105: =IFERROR(S105/T105,"") -> 668.33333 | W105: INT-TSR-2026-03 | X105: =IF(W105="","",IFERROR(INDEX($V$1:$V$178,MATCH(W105,$A$1:$A$178,0)),"")) -> 1115.1755 | Y105: =IF(OR(X105="",V105=""),"",V105/X105) -> 0.59930777 | AA105: =IF(Z105="","",IFERROR(INDEX($V$1:$V$178,MATCH(Z105,$A$1:$A$178,0)),"")) | AB105: =IF(OR(AA105="",V105=""),"",V105/AA105) | AC105: APROMAC (via 7info) – Caoutchouc : nouveaux prix du kg (janv. 352, fév. 368, avr. 401, mai 439, juil. 493 FCFA) | AD105: https://www.7info.ci/caoutchouc-voici-le-nouveau-prix-du-kg/ | AE105: 2026-10-01 | AF105: B | AG105: Prix du mois M calculé sur les cours SICOM du mois M-1 ; producteur = 63 % (66 % en 2026) du prix de référence
A106: CAO-CI-2026-05 | B106: Caoutchouc | C106: Caoutchouc naturel (fonds de tasse) | D106: Côte d'Ivoire | E106: 2026 | F106: Mois 2026-05 | G106: Prix bord champ fixé (APROMAC, loi 2017-540) | H106: Bord champ | I106: Coagulum humide, DRC de référence 60 % | J106: 439 | K106: XOF | L106: kg | M106: 1 | N106: 2026-05:2026-05 | O106: =IF(K106="USD",1,INDEX(Change_periodes!$D$1:$N$400,MATCH($N106,Change_periodes!$A$1:$A$400,0),MATCH($K106,Change_periodes!$D$1:$N$1,0))) -> 561.93417 | P106: BCE (parité fixe 655,957 FCFA/EUR) | Q106: =INDEX(Change_periodes!$D$1:$D$400,MATCH($N106,Change_periodes!$A$1:$A$400,0)) -> 561.93417 | R106: =IFERROR(J106/M106/O106,"") -> 0.78123029 | S106: =IFERROR(R106*Q106,"") -> 439 | T106: =Parametres!$C$6 -> 0.6 | U106: kg de caoutchouc sec (÷ DRC 60 %) | V106: =IFERROR(S106/T106,"") -> 731.66667 | X106: =IF(W106="","",IFERROR(INDEX($V$1:$V$178,MATCH(W106,$A$1:$A$178,0)),"")) | Y106: =IF(OR(X106="",V106=""),"",V106/X106) | AA106: =IF(Z106="","",IFERROR(INDEX($V$1:$V$178,MATCH(Z106,$A$1:$A$178,0)),"")) | AB106: =IF(OR(AA106="",V106=""),"",V106/AA106) | AC106: APROMAC (via 7info) – Caoutchouc : nouveaux prix du kg (janv. 352, fév. 368, avr. 401, mai 439, juil. 493 FCFA) | AD106: https://www.7info.ci/caoutchouc-voici-le-nouveau-prix-du-kg/ | AE106: 2026-10-01 | AF106: B | AG106: Prix du mois M calculé sur les cours SICOM du mois M-1 ; producteur = 63 % (66 % en 2026) du prix de référence
A107: CAO-CI-2026-07 | B107: Caoutchouc | C107: Caoutchouc naturel (fonds de tasse) | D107: Côte d'Ivoire | E107: 2026 | F107: Mois 2026-07 | G107: Prix bord champ fixé (APROMAC, loi 2017-540) | H107: Bord champ | I107: Coagulum humide, DRC de référence 60 % | J107: 493 | K107: XOF | L107: kg | M107: 1 | N107: 2026-07:2026-07 | O107: =IF(K107="USD",1,INDEX(Change_periodes!$D$1:$N$400,MATCH($N107,Change_periodes!$A$1:$A$400,0),MATCH($K107,Change_periodes!$D$1:$N$1,0))) -> 574.51995 | P107: BCE (parité fixe 655,957 FCFA/EUR) | Q107: =INDEX(Change_periodes!$D$1:$D$400,MATCH($N107,Change_periodes!$A$1:$A$400,0)) -> 574.51995 | R107: =IFERROR(J107/M107/O107,"") -> 0.85810772 | S107: =IFERROR(R107*Q107,"") -> 493 | T107: =Parametres!$C$6 -> 0.6 | U107: kg de caoutchouc sec (÷ DRC 60 %) | V107: =IFERROR(S107/T107,"") -> 821.66667 | X107: =IF(W107="","",IFERROR(INDEX($V$1:$V$178,MATCH(W107,$A$1:$A$178,0)),"")) | Y107: =IF(OR(X107="",V107=""),"",V107/X107) | AA107: =IF(Z107="","",IFERROR(INDEX($V$1:$V$178,MATCH(Z107,$A$1:$A$178,0)),"")) | AB107: =IF(OR(AA107="",V107=""),"",V107/AA107) | AC107: APROMAC (via 7info) – Caoutchouc : nouveaux prix du kg (janv. 352, fév. 368, avr. 401, mai 439, juil. 493 FCFA) | AD107: https://www.7info.ci/caoutchouc-voici-le-nouveau-prix-du-kg/ | AE107: 2026-10-01 | AF107: B | AG107: Prix du mois M calculé sur les cours SICOM du mois M-1 ; producteur = 63 % (66 % en 2026) du prix de référence
A108: CAO-CI-2026-09 | B108: Caoutchouc | C108: Caoutchouc naturel (fonds de tasse) | D108: Côte d'Ivoire | E108: 2026 | F108: Mois 2026-09 | G108: Prix bord champ fixé (APROMAC, loi 2017-540) | H108: Bord champ | I108: Coagulum humide, DRC de référence 60 % | J108: 484 | K108: XOF | L108: kg | M108: 1 | N108: 2026-09:2026-09 | O108: =IF(K108="USD",1,INDEX(Change_periodes!$D$1:$N$400,MATCH($N108,Change_periodes!$A$1:$A$400,0),MATCH($K108,Change_periodes!$D$1:$N$1,0))) -> 565.22679 | P108: BCE (parité fixe 655,957 FCFA/EUR) | Q108: =INDEX(Change_periodes!$D$1:$D$400,MATCH($N108,Change_periodes!$A$1:$A$400,0)) -> 565.22679 | R108: =IFERROR(J108/M108/O108,"") -> 0.85629345 | S108: =IFERROR(R108*Q108,"") -> 484 | T108: =Parametres!$C$6 -> 0.6 | U108: kg de caoutchouc sec (÷ DRC 60 %) | V108: =IFERROR(S108/T108,"") -> 806.66667 | X108: =IF(W108="","",IFERROR(INDEX($V$1:$V$178,MATCH(W108,$A$1:$A$178,0)),"")) | Y108: =IF(OR(X108="",V108=""),"",V108/X108) | AA108: =IF(Z108="","",IFERROR(INDEX($V$1:$V$178,MATCH(Z108,$A$1:$A$178,0)),"")) | AB108: =IF(OR(AA108="",V108=""),"",V108/AA108) | AC108: APROMAC (via Business & Actuality) – Prix du caoutchouc : 484 FCFA/kg en septembre 2026 | AD108: https://businessactuality.com/cote-divoire-prix-du-caoutchouc-484-fcfa-kg-en-septembre-2026/ | AE108: 2026-10-01 | AF108: B | AG108: Prix du mois M calculé sur les cours SICOM du mois M-1 ; producteur = 63 % (66 % en 2026) du prix de référence
A109: CAO-TH-2025-05 | B109: Caoutchouc | C109: Caoutchouc (cup lump) base 100 % DRC | D109: Thaïlande | E109: 2025 | F109: 02/05/2025 | G109: Prix de marché intérieur | H109: Marché central / bord champ | I109: Cup lump 100 % DRC (sec) | J109: 58 | K109: THB | L109: kg | M109: 1 | N109: 2025-04:2025-04 | O109: =IF(K109="USD",1,INDEX(Change_periodes!$D$1:$N$400,MATCH($N109,Change_periodes!$A$1:$A$400,0),MATCH($K109,Change_periodes!$D$1:$N$1,0))) -> 33.781852 | P109: BCE (taux croisé) | Q109: =INDEX(Change_periodes!$D$1:$D$400,MATCH($N109,Change_periodes!$A$1:$A$400,0)) -> 584.94732 | R109: =IFERROR(J109/M109/O109,"") -> 1.7168982 | S109: =IFERROR(R109*Q109,"") -> 1004.295 | T109: 1 | U109: FCFA/kg de produit tel que vendu | V109: =IFERROR(S109/T109,"") -> 1004.295 | W109: INT-TSR-2025-04 | X109: =IF(W109="","",IFERROR(INDEX($V$1:$V$178,MATCH(W109,$A$1:$A$178,0)),"")) -> 998.2126 | Y109: =IF(OR(X109="",V109=""),"",V109/X109) -> 1.0060933 | AA109: =IF(Z109="","",IFERROR(INDEX($V$1:$V$178,MATCH(Z109,$A$1:$A$178,0)),"")) | AB109: =IF(OR(AA109="",V109=""),"",V109/AA109) | AC109: Thai Rubber Association – Prix intérieurs (cup lump 100 %) : 58 THB/kg (2 mai 2025) | AD109: https://www.thainr.com/en/?detail=pr-local | AE109: 2026-10-01 | AF109: B | AG109: Comparé au TSR20 du mois précédent, comme pour la Côte d'Ivoire
A110: CAO-ID-2026-08 | B110: Caoutchouc | C110: Bokar base KKK 100 % (sec) | D110: Indonésie | E110: 2026 | F110: Août 2026 (4 relevés) | G110: Prix de référence provincial (Sumatra-Sud) | H110: Bord champ (prix de référence) | I110: KKK 100 % (sec) | J110: =(38835+39076+41446+42238)/4 -> 40398.75 | K110: IDR | L110: kg | M110: 1 | N110: 2026-08:2026-08 | O110: =IF(K110="USD",1,INDEX(Change_periodes!$D$1:$N$400,MATCH($N110,Change_periodes!$A$1:$A$400,0),MATCH($K110,Change_periodes!$D$1:$N$1,0))) -> 17804.655 | P110: BCE (taux croisé) | Q110: =INDEX(Change_periodes!$D$1:$D$400,MATCH($N110,Change_periodes!$A$1:$A$400,0)) -> 565.81674 | R110: =IFERROR(J110/M110/O110,"") -> 2.2689993 | S110: =IFERROR(R110*Q110,"") -> 1283.8378 | T110: 1 | U110: FCFA/kg de produit tel que vendu | V110: =IFERROR(S110/T110,"") -> 1283.8378 | X110: =IF(W110="","",IFERROR(INDEX($V$1:$V$178,MATCH(W110,$A$1:$A$178,0)),"")) | Y110: =IF(OR(X110="",V110=""),"",V110/X110) | AA110: =IF(Z110="","",IFERROR(INDEX($V$1:$V$178,MATCH(Z110,$A$1:$A$178,0)),"")) | AB110: =IF(OR(AA110="",V110=""),"",V110/AA110) | AC110: Disperindag/Gapkindo Sumatra-Sud (via IDN Times) – Prix de référence KKK 100 % : 38 835 à 42 238 Rp/kg (août 2026) | AD110: https://sumsel.idntimes.com/news/sumatra-selatan/harga-karet-sumsel-kembali-menguat-akhir-agustus-tembus-rp41-ribu-00-pbgds-3n14cx | AE110: 2026-10-01 | AF110: B | AG110: Prix de référence non reçu uniformément (dépend du KKK) ; TSR20 juil.-août 2026 non vérifié : pas de taux de transmission calculé
A111: PAL-CI-FFB-2026-01 | B111: Palmier à huile | C111: Régimes de palme (FFB) | D111: Côte d'Ivoire | E111: 2026 | F111: Janvier 2026 | G111: Prix fixé (Conseil Hévéa-Palmier à huile-Coco) | H111: Bord champ | I111: Régimes frais (planteurs villageois) | J111: 80000 | K111: XOF | L111: tonne | M111: 1000 | N111: 2026-01:2026-01 | O111: =IF(K111="USD",1,INDEX(Change_periodes!$D$1:$N$400,MATCH($N111,Change_periodes!$A$1:$A$400,0),MATCH($K111,Change_periodes!$D$1:$N$1,0))) -> 558.82057 | P111: BCE (parité fixe 655,957 FCFA/EUR) | Q111: =INDEX(Change_periodes!$D$1:$D$400,MATCH($N111,Change_periodes!$A$1:$A$400,0)) -> 558.82057 | R111: =IFERROR(J111/M111/O111,"") -> 0.14315865 | S111: =IFERROR(R111*Q111,"") -> 80 | T111: 1 | U111: FCFA/kg de produit tel que vendu | V111: =IFERROR(S111/T111,"") -> 80 | W111: INT-CPO-2026-01 | X111: =IF(W111="","",IFERROR(INDEX($V$1:$V$178,MATCH(W111,$A$1:$A$178,0)),"")) -> 557.60234 | Y111: =IF(OR(X111="",V111=""),"",V111/X111) -> 0.14347142 | AA111: =IF(Z111="","",IFERROR(INDEX($V$1:$V$178,MATCH(Z111,$A$1:$A$178,0)),"")) | AB111: =IF(OR(AA111="",V111=""),"",V111/AA111) | AC111: Conseil Hévéa-Palmier à huile-Coco (via Afrik Soir) – Prix de janvier 2026 : huile de palme brute 620 000 FCFA/t ; régimes bord champ 80 000 FCFA/t | AD111: https://afriksoir.net/cote-divoire-le-conseil-hevea-palmier-a-huile-coco-fixe-les-prix-du-palmier-a-huile-pour-janvier-2026/ | AE111: 2026-10-01 | AF111: B | AG111: Ratio = prix régime / prix mondial de l'huile brute (pas une transmission au sens strict)
A112: PAL-CI-CPO-2026-01 | B112: Palmier à huile | C112: Huile de palme brute (CPO) | D112: Côte d'Ivoire | E112: 2026 | F112: Janvier 2026 | G112: Prix fixé (marché intérieur) | H112: Départ huilerie | I112: CPO | J112: 620000 | K112: XOF | L112: tonne | M112: 1000 | N112: 2026-01:2026-01 | O112: =IF(K112="USD",1,INDEX(Change_periodes!$D$1:$N$400,MATCH($N112,Change_periodes!$A$1:$A$400,0),MATCH($K112,Change_periodes!$D$1:$N$1,0))) -> 558.82057 | P112: BCE (parité fixe 655,957 FCFA/EUR) | Q112: =INDEX(Change_periodes!$D$1:$D$400,MATCH($N112,Change_periodes!$A$1:$A$400,0)) -> 558.82057 | R112: =IFERROR(J112/M112/O112,"") -> 1.1094796 | S112: =IFERROR(R112*Q112,"") -> 620 | T112: 1 | U112: FCFA/kg de produit tel que vendu | V112: =IFERROR(S112/T112,"") -> 620 | W112: INT-CPO-2026-01 | X112: =IF(W112="","",IFERROR(INDEX($V$1:$V$178,MATCH(W112,$A$1:$A$178,0)),"")) -> 557.60234 | Y112: =IF(OR(X112="",V112=""),"",V112/X112) -> 1.1119035 | AA112: =IF(Z112="","",IFERROR(INDEX($V$1:$V$178,MATCH(Z112,$A$1:$A$178,0)),"")) | AB112: =IF(OR(AA112="",V112=""),"",V112/AA112) | AC112: Conseil Hévéa-Palmier à huile-Coco (via Afrik Soir) – Prix de janvier 2026 : huile de palme brute 620 000 FCFA/t ; régimes bord champ 80 000 FCFA/t | AD112: https://afriksoir.net/cote-divoire-le-conseil-hevea-palmier-a-huile-coco-fixe-les-prix-du-palmier-a-huile-pour-janvier-2026/ | AE112: 2026-10-01 | AF112: B | AG112: Prix intérieur de l'huile brute comparé au prix mondial (CIF Rotterdam)
A113: PAL-CI-FFB-2024-Q4 | B113: Palmier à huile | C113: Régimes de palme (FFB) | D113: Côte d'Ivoire | E113: 2024 | F113: Octobre-décembre 2024 | G113: Prix fixé (CHP-HC) | H113: Bord champ | I113: Régimes frais | J113: 75000 | K113: XOF | L113: tonne | M113: 1000 | N113: 2024-10:2024-12 | O113: =IF(K113="USD",1,INDEX(Change_periodes!$D$1:$N$400,MATCH($N113,Change_periodes!$A$1:$A$400,0),MATCH($K113,Change_periodes!$D$1:$N$1,0))) -> 614.87198 | P113: BCE (parité fixe 655,957 FCFA/EUR) | Q113: =INDEX(Change_periodes!$D$1:$D$400,MATCH($N113,Change_periodes!$A$1:$A$400,0)) -> 614.87198 | R113: =IFERROR(J113/M113/O113,"") -> 0.12197661 | S113: =IFERROR(R113*Q113,"") -> 75 | T113: 1 | U113: FCFA/kg de produit tel que vendu | V113: =IFERROR(S113/T113,"") -> 75 | W113: INT-CPO-2024-Q4 | X113: =IF(W113="","",IFERROR(INDEX($V$1:$V$178,MATCH(W113,$A$1:$A$178,0)),"")) -> 704.14482 | Y113: =IF(OR(X113="",V113=""),"",V113/X113) -> 0.10651218 | AA113: =IF(Z113="","",IFERROR(INDEX($V$1:$V$178,MATCH(Z113,$A$1:$A$178,0)),"")) | AB113: =IF(OR(AA113="",V113=""),"",V113/AA113) | AC113: CHP-HC (via Abidjan Économie) – Huile de palme brute 600 000 FCFA/t ; régimes bord champ 75 000 FCFA/t (oct.-déc. 2024) | AD113: https://www.abidjaneconomie.net/2024/10/19/cote-divoire-nouvelles-tarifications-pour-lhuile-de-palme-brut-et-regimes-de-palme-pour-octobre-a-decembre-2024/ | AE113: 2026-10-01 | AF113: B
A114: PAL-ID-FFB-2026-01 | B114: Palmier à huile | C114: Régimes de palme (TBS) | D114: Indonésie | E114: 2026 | F114: Janvier 2026 (3 semaines) | G114: Prix de référence provincial (Disbun Riau) | H114: Livraison usine (planteurs partenaires) | I114: Palmiers de 10-20 ans | J114: =(3496.91+3430.63+3449.84)/3 -> 3459.1267 | K114: IDR | L114: kg | M114: 1 | N114: 2026-01:2026-01 | O114: =IF(K114="USD",1,INDEX(Change_periodes!$D$1:$N$400,MATCH($N114,Change_periodes!$A$1:$A$400,0),MATCH($K114,Change_periodes!$D$1:$N$1,0))) -> 16831.33 | P114: BCE (taux croisé) | Q114: =INDEX(Change_periodes!$D$1:$D$400,MATCH($N114,Change_periodes!$A$1:$A$400,0)) -> 558.82057 | R114: =IFERROR(J114/M114/O114,"") -> 0.20551713 | S114: =IFERROR(R114*Q114,"") -> 114.8472 | T114: 1 | U114: FCFA/kg de produit tel que vendu | V114: =IFERROR(S114/T114,"") -> 114.8472 | W114: INT-CPO-2026-01 | X114: =IF(W114="","",IFERROR(INDEX($V$1:$V$178,MATCH(W114,$A$1:$A$178,0)),"")) -> 557.60234 | Y114: =IF(OR(X114="",V114=""),"",V114/X114) -> 0.20596614 | AA114: =IF(Z114="","",IFERROR(INDEX($V$1:$V$178,MATCH(Z114,$A$1:$A$178,0)),"")) | AB114: =IF(OR(AA114="",V114=""),"",V114/AA114) | AC114: Disbun Riau (via HaiSawit / Media Center Riau) – Prix TBS (régimes) Riau, palmiers 10-20 ans : 3 496,91 / 3 430,63 / 3 449,84 Rp/kg (janv. 2026) | AD114: https://haisawit.co.id/news/detail/resmi-naik-cek-daftar-harga-sawit-riau-periode-1420-januari-2026 | AE114: 2026-10-01 | AF114: B | AG114: Prix départ planteur partenaire ; les planteurs indépendants vendent souvent en dessous
A115: PAL-MY-FFB-2025 | B115: Palmier à huile | C115: Régimes de palme (FFB) | D115: Malaisie | E115: 2025 | F115: Moyenne 2025 | G115: Prix de référence MPOB (1 % OER × OER national) | H115: Départ plantation (référence) | I115: FFB, OER national 19,74 % | J115: =47.39*19.74 -> 935.4786 | K115: MYR | L115: tonne | M115: 1000 | N115: 2025-01:2025-12 | O115: =IF(K115="USD",1,INDEX(Change_periodes!$D$1:$N$400,MATCH($N115,Change_periodes!$A$1:$A$400,0),MATCH($K115,Change_periodes!$D$1:$N$1,0))) -> 4.2834039 | P115: BCE (taux croisé) | Q115: =INDEX(Change_periodes!$D$1:$D$400,MATCH($N115,Change_periodes!$A$1:$A$400,0)) -> 581.92849 | R115: =IFERROR(J115/M115/O115,"") -> 0.21839608 | S115: =IFERROR(R115*Q115,"") -> 127.0909 | T115: 1 | U115: FCFA/kg de produit tel que vendu | V115: =IFERROR(S115/T115,"") -> 127.0909 | W115: INT-CPO-2025 | X115: =IF(W115="","",IFERROR(INDEX($V$1:$V$178,MATCH(W115,$A$1:$A$178,0)),"")) -> 585.97167 | Y115: =IF(OR(X115="",V115=""),"",V115/X115) -> 0.21688915 | AA115: =IF(Z115="","",IFERROR(INDEX($V$1:$V$178,MATCH(Z115,$A$1:$A$178,0)),"")) | AB115: =IF(OR(AA115="",V115=""),"",V115/AA115) | AC115: Malaysian Palm Oil Board (MPOB) – Overview of the Malaysian Oil Palm Industry 2025 : prix des régimes à 1 % OER 47,39 RM ; OER 19,74 % | AD115: https://bepi.mpob.gov.my/images/overview/Overview2025.pdf | AE115: 2026-10-01 | AF115: A | AG115: Prix à 1 % OER (47,39 RM) × taux d'extraction national (19,74 %)
A116: RIZ-CI-2025 | B116: Riz | C116: Riz paddy | D116: Côte d'Ivoire | E116: 2025 | F116: Moyenne janv.-déc. 2025 | G116: Prix moyen observé | H116: Bord champ | I116: Paddy sec (non précisé) | J116: 233 | K116: XOF | L116: kg | M116: 1 | N116: 2025-01:2025-12 | O116: =IF(K116="USD",1,INDEX(Change_periodes!$D$1:$N$400,MATCH($N116,Change_periodes!$A$1:$A$400,0),MATCH($K116,Change_periodes!$D$1:$N$1,0))) -> 581.92849 | P116: BCE (parité fixe 655,957 FCFA/EUR) | Q116: =INDEX(Change_periodes!$D$1:$D$400,MATCH($N116,Change_periodes!$A$1:$A$400,0)) -> 581.92849 | R116: =IFERROR(J116/M116/O116,"") -> 0.40039284 | S116: =IFERROR(R116*Q116,"") -> 233 | T116: 1 | U116: FCFA/kg de produit tel que vendu | V116: =IFERROR(S116/T116,"") -> 233 | W116: INT-RIZ-2025 | X116: =IF(W116="","",IFERROR(INDEX($V$1:$V$178,MATCH(W116,$A$1:$A$178,0)),"")) -> 154.26439 | Y116: =IF(OR(X116="",V116=""),"",V116/X116) -> 1.5103939 | AA116: =IF(Z116="","",IFERROR(INDEX($V$1:$V$178,MATCH(Z116,$A$1:$A$178,0)),"")) | AB116: =IF(OR(AA116="",V116=""),"",V116/AA116) | AC116: USDA FAS – Côte d'Ivoire Grain and Feed Annual 2026 : paddy bord champ 233 FCFA/kg en moyenne 2025 (+8,5 %) | AD116: https://apps.fas.usda.gov/newgainapi/api/Report/DownloadReportByFileName?fileName=Grain+and+Feed+Annual_Accra_Cote+d%27Ivoire_IV2026-0003 | AE116: 2026-10-01 | AF116: A | AG116: +8,5 % par rapport à 2024
A117: RIZ-SN-2025 | B117: Riz | C117: Riz paddy | D117: Sénégal | E117: 2025 | F117: Campagne | G117: Prix producteur fixé (interprofession) | H117: Bord champ | I117: Paddy | J117: 130 | K117: XOF | L117: kg | M117: 1 | N117: 2025-01:2025-12 | O117: =IF(K117="USD",1,INDEX(Change_periodes!$D$1:$N$400,MATCH($N117,Change_periodes!$A$1:$A$400,0),MATCH($K117,Change_periodes!$D$1:$N$1,0))) -> 581.92849 | P117: BCE (parité fixe 655,957 FCFA/EUR) | Q117: =INDEX(Change_periodes!$D$1:$D$400,MATCH($N117,Change_periodes!$A$1:$A$400,0)) -> 581.92849 | R117: =IFERROR(J117/M117/O117,"") -> 0.22339515 | S117: =IFERROR(R117*Q117,"") -> 130 | T117: 1 | U117: FCFA/kg de produit tel que vendu | V117: =IFERROR(S117/T117,"") -> 130 | W117: INT-RIZ-2025 | X117: =IF(W117="","",IFERROR(INDEX($V$1:$V$178,MATCH(W117,$A$1:$A$178,0)),"")) -> 154.26439 | Y117: =IF(OR(X117="",V117=""),"",V117/X117) -> 0.84270905 | AA117: =IF(Z117="","",IFERROR(INDEX($V$1:$V$178,MATCH(Z117,$A$1:$A$178,0)),"")) | AB117: =IF(OR(AA117="",V117=""),"",V117/AA117) | AC117: USDA FAS – Senegal Grain and Feed Annual 2025 : paddy 130 FCFA/kg + subvention 30 FCFA (prix usinier 160) | AD117: https://apps.fas.usda.gov/newgainapi/api/Report/DownloadReportByFileName?fileName=Grain+and+Feed+Annual_Dakar_Senegal_SG2025-0008.pdf | AE117: 2026-10-01 | AF117: A | AG117: Subvention de 30 FCFA/kg depuis 2022 : prix payé par les usiniers 160 FCFA/kg
A118: RIZ-VN-2025 | B118: Riz | C118: Riz paddy frais (IR 50404 / OM 5451) | D118: Vietnam | E118: 2025 | F118: Fin 2025 | G118: Prix de marché | H118: Bord champ (delta du Mékong) | I118: Paddy frais (humide) | J118: =(5450+5650)/2 -> 5550 | K118: VND | L118: kg | M118: 1 | N118: 2025-09:2025-10 | O118: =IF(K118="USD",1,INDEX(Change_periodes!$D$1:$N$400,MATCH($N118,Change_periodes!$A$1:$A$400,0),MATCH($K118,Change_periodes!$D$1:$N$1,0))) -> 25196.815 | P118: BRI ; sept. 2026 : Vietcombank | Q118: =INDEX(Change_periodes!$D$1:$D$400,MATCH($N118,Change_periodes!$A$1:$A$400,0)) -> 561.55374 | R118: =IFERROR(J118/M118/O118,"") -> 0.22026593 | S118: =IFERROR(R118*Q118,"") -> 123.69116 | T118: 1 | U118: FCFA/kg de produit tel que vendu | V118: =IFERROR(S118/T118,"") -> 123.69116 | W118: INT-RIZ-2025 | X118: =IF(W118="","",IFERROR(INDEX($V$1:$V$178,MATCH(W118,$A$1:$A$178,0)),"")) -> 154.26439 | Y118: =IF(OR(X118="",V118=""),"",V118/X118) -> 0.80181277 | AA118: =IF(Z118="","",IFERROR(INDEX($V$1:$V$178,MATCH(Z118,$A$1:$A$178,0)),"")) | AB118: =IF(OR(AA118="",V118=""),"",V118/AA118) | AC118: SGGP News – Paddy frais du delta du Mékong : IR 50404 5 400-5 500 ; OM 5451 5 600-5 700 VND/kg (2025) | AD118: https://en.sggp.org.vn/rice-farmers-in-mekong-delta-struggle-as-prices-plunge-yields-decline-post120063.html | AE118: 2026-10-01 | AF118: B | AG118: Paddy frais (humidité élevée) : sous-estime le prix du paddy sec ; comparaison indicative
A119: BAN-EC-2026 | B119: Banane dessert | C119: Banane d'exportation (caisse 22XU, 43 lb) | D119: Équateur | E119: 2026 | F119: Année 2026 | G119: Prix minimum de soutien (administré) | H119: Pied du navire (producteur → exportateur) | I119: Banane export | J119: 7.5 | K119: USD | L119: caisse 43 lb | M119: 19.5045 | N119: 2026-01:2026-08 | O119: =IF(K119="USD",1,INDEX(Change_periodes!$D$1:$N$400,MATCH($N119,Change_periodes!$A$1:$A$400,0),MATCH($K119,Change_periodes!$D$1:$N$1,0))) -> 1 | P119: — | Q119: =INDEX(Change_periodes!$D$1:$D$400,MATCH($N119,Change_periodes!$A$1:$A$400,0)) -> 564.15338 | R119: =IFERROR(J119/M119/O119,"") -> 0.38452665 | S119: =IFERROR(R119*Q119,"") -> 216.93201 | T119: 1 | U119: FCFA/kg de produit tel que vendu | V119: =IFERROR(S119/T119,"") -> 216.93201 | X119: =IF(W119="","",IFERROR(INDEX($V$1:$V$178,MATCH(W119,$A$1:$A$178,0)),"")) | Y119: =IF(OR(X119="",V119=""),"",V119/X119) | AA119: =IF(Z119="","",IFERROR(INDEX($V$1:$V$178,MATCH(Z119,$A$1:$A$178,0)),"")) | AB119: =IF(OR(AA119="",V119=""),"",V119/AA119) | AC119: MAGP Équateur, Acuerdo Ministerial 107 (via Agraria.pe) – Prix minimum de soutien 2026 : 7,50 USD la caisse 22XU de 43 lb | AD119: https://agraria.pe/noticias/ecuador-fija-en-us-7-50-el-precio-minimo-de-la-caja-de-banan-40795 | AE119: 2026-10-01 | AF119: B | AG119: Pas de prix producteur public comparable en Côte d'Ivoire (filière intégrée)
A120: MAN-CI-2026 | B120: Mangue | C120: Mangue export (Kent) | D120: Côte d'Ivoire | E120: 2026 | F120: Campagne 2026 | G120: Prix interprofessionnel (Inter-Mangue) | H120: Station de conditionnement | I120: Mangue export | J120: 220 | K120: XOF | L120: kg | M120: 1 | N120: 2026-03:2026-06 | O120: =IF(K120="USD",1,INDEX(Change_periodes!$D$1:$N$400,MATCH($N120,Change_periodes!$A$1:$A$400,0),MATCH($K120,Change_periodes!$D$1:$N$1,0))) -> 564.825 | P120: BCE (parité fixe 655,957 FCFA/EUR) | Q120: =INDEX(Change_periodes!$D$1:$D$400,MATCH($N120,Change_periodes!$A$1:$A$400,0)) -> 564.825 | R120: =IFERROR(J120/M120/O120,"") -> 0.38950117 | S120: =IFERROR(R120*Q120,"") -> 220 | T120: 1 | U120: FCFA/kg de produit tel que vendu | V120: =IFERROR(S120/T120,"") -> 220 | X120: =IF(W120="","",IFERROR(INDEX($V$1:$V$178,MATCH(W120,$A$1:$A$178,0)),"")) | Y120: =IF(OR(X120="",V120=""),"",V120/X120) | AA120: =IF(Z120="","",IFERROR(INDEX($V$1:$V$178,MATCH(Z120,$A$1:$A$178,0)),"")) | AB120: =IF(OR(AA120="",V120=""),"",V120/AA120) | AC120: Inter-Mangue (via AIP) – Mangue 2026 : prix bord champ maintenu à 2 450 FCFA la caisse ; 220 FCFA/kg en station | AD120: https://www.aip.ci/332817/cote-divoire-aip-filiere-mangue-le-prix-bord-champ-maintenu-a-2-450-fcfa-la-caisse-pour-la-campagne-2026/ | AE120: 2026-10-01 | AF120: B | AG120: Bord champ : 2 450 FCFA la caisse (poids non publié) : non convertible en FCFA/kg
A121: MAN-BF-2026 | B121: Mangue | C121: Mangue | D121: Burkina Faso | E121: 2026 | F121: Campagne 2026 | G121: Prix plancher (administré) | H121: Bord champ | I121: Mangue | J121: 95 | K121: XOF | L121: kg | M121: 1 | N121: 2026-03:2026-06 | O121: =IF(K121="USD",1,INDEX(Change_periodes!$D$1:$N$400,MATCH($N121,Change_periodes!$A$1:$A$400,0),MATCH($K121,Change_periodes!$D$1:$N$1,0))) -> 564.825 | P121: BCE (parité fixe 655,957 FCFA/EUR) | Q121: =INDEX(Change_periodes!$D$1:$D$400,MATCH($N121,Change_periodes!$A$1:$A$400,0)) -> 564.825 | R121: =IFERROR(J121/M121/O121,"") -> 0.16819369 | S121: =IFERROR(R121*Q121,"") -> 95 | T121: 1 | U121: FCFA/kg de produit tel que vendu | V121: =IFERROR(S121/T121,"") -> 95 | X121: =IF(W121="","",IFERROR(INDEX($V$1:$V$178,MATCH(W121,$A$1:$A$178,0)),"")) | Y121: =IF(OR(X121="",V121=""),"",V121/X121) | AA121: =IF(Z121="","",IFERROR(INDEX($V$1:$V$178,MATCH(Z121,$A$1:$A$178,0)),"")) | AB121: =IF(OR(AA121="",V121=""),"",V121/AA121) | AC121: Gouvernement du Burkina Faso (via leFaso.net) – Campagne fruitière 2026 : anacarde 385 FCFA, mangue 95 FCFA le kg | AD121: https://lefaso.net/spip.php?article144610 | AE121: 2026-10-01 | AF121: B | AG121: Stade différent du prix ivoirien (station) : pas de comparaison directe
A122: INT-CAC-2016/17-P | B122: Cacao | C122: Fèves de cacao | D122: International | E122: 2016-10 → 2017-03 | F122: Moyenne 2016-10 à 2017-03 | G122: Cours international (moyenne mensuelle) | H122: Bourses Londres/New York (prix ICCO) | I122: Standard | J122: =INDEX(Cours_periodes!$E$1:$E$400,MATCH("cacao:2016-10:2017-03",Cours_periodes!$A$1:$A$400,0)) -> 2.2961967 | K122: USD | L122: kg | M122: 1 | N122: 2016-10:2017-03 | O122: =IF(K122="USD",1,INDEX(Change_periodes!$D$1:$N$400,MATCH($N122,Change_periodes!$A$1:$A$400,0),MATCH($K122,Change_periodes!$D$1:$N$1,0))) -> 1 | P122: — | Q122: =INDEX(Change_periodes!$D$1:$D$400,MATCH($N122,Change_periodes!$A$1:$A$400,0)) -> 612.12961 | R122: =IFERROR(J122/M122/O122,"") -> 2.2961967 | S122: =IFERROR(R122*Q122,"") -> 1405.57 | T122: 1 | U122: FCFA/kg de produit tel que vendu | V122: =IFERROR(S122/T122,"") -> 1405.57 | X122: =IF(W122="","",IFERROR(INDEX($V$1:$V$178,MATCH(W122,$A$1:$A$178,0)),"")) | Y122: =IF(OR(X122="",V122=""),"",V122/X122) | AA122: =IF(Z122="","",IFERROR(INDEX($V$1:$V$178,MATCH(Z122,$A$1:$A$178,0)),"")) | AB122: =IF(OR(AA122="",V122=""),"",V122/AA122) | AC122: Banque mondiale – Commodity Price Data (Pink Sheet), CMO-Historical-Data-Monthly.xlsx, mise à jour 3 février 2026 | AD122: https://www.worldbank.org/en/research/commodity-markets | AE122: 2026-10-01 | AF122: A | AG122: Banque mondiale (ICCO) jusqu'en janv. 2026, FMI ensuite
A123: INT-CAC-2016/17-I | B123: Cacao | C123: Fèves de cacao | D123: International | E123: 2017-04 → 2017-09 | F123: Moyenne 2017-04 à 2017-09 | G123: Cours international (moyenne mensuelle) | H123: Bourses Londres/New York (prix ICCO) | I123: Standard | J123: =INDEX(Cours_periodes!$E$1:$E$400,MATCH("cacao:2017-04:2017-09",Cours_periodes!$A$1:$A$400,0)) -> 1.9863883 | K123: USD | L123: kg | M123: 1 | N123: 2017-04:2017-09 | O123: =IF(K123="USD",1,INDEX(Change_periodes!$D$1:$N$400,MATCH($N123,Change_periodes!$A$1:$A$400,0),MATCH($K123,Change_periodes!$D$1:$N$1,0))) -> 1 | P123: — | Q123: =INDEX(Change_periodes!$D$1:$D$400,MATCH($N123,Change_periodes!$A$1:$A$400,0)) -> 577.51424 | R123: =IFERROR(J123/M123/O123,"") -> 1.9863883 | S123: =IFERROR(R123*Q123,"") -> 1147.1675 | T123: 1 | U123: FCFA/kg de produit tel que vendu | V123: =IFERROR(S123/T123,"") -> 1147.1675 | X123: =IF(W123="","",IFERROR(INDEX($V$1:$V$178,MATCH(W123,$A$1:$A$178,0)),"")) | Y123: =IF(OR(X123="",V123=""),"",V123/X123) | AA123: =IF(Z123="","",IFERROR(INDEX($V$1:$V$178,MATCH(Z123,$A$1:$A$178,0)),"")) | AB123: =IF(OR(AA123="",V123=""),"",V123/AA123) | AC123: Banque mondiale – Commodity Price Data (Pink Sheet), CMO-Historical-Data-Monthly.xlsx, mise à jour 3 février 2026 | AD123: https://www.worldbank.org/en/research/commodity-markets | AE123: 2026-10-01 | AF123: A | AG123: Banque mondiale (ICCO) jusqu'en janv. 2026, FMI ensuite
A124: INT-CAC-2017/18-P | B124: Cacao | C124: Fèves de cacao | D124: International | E124: 2017-10 → 2018-03 | F124: Moyenne 2017-10 à 2018-03 | G124: Cours international (moyenne mensuelle) | H124: Bourses Londres/New York (prix ICCO) | I124: Standard | J124: =INDEX(Cours_periodes!$E$1:$E$400,MATCH("cacao:2017-10:2018-03",Cours_periodes!$A$1:$A$400,0)) -> 2.1202017 | K124: USD | L124: kg | M124: 1 | N124: 2017-10:2018-03 | O124: =IF(K124="USD",1,INDEX(Change_periodes!$D$1:$N$400,MATCH($N124,Change_periodes!$A$1:$A$400,0),MATCH($K124,Change_periodes!$D$1:$N$1,0))) -> 1 | P124: — | Q124: =INDEX(Change_periodes!$D$1:$D$400,MATCH($N124,Change_periodes!$A$1:$A$400,0)) -> 545.27827 | R124: =IFERROR(J124/M124/O124,"") -> 2.1202017 | S124: =IFERROR(R124*Q124,"") -> 1156.0999 | T124: 1 | U124: FCFA/kg de produit tel que vendu | V124: =IFERROR(S124/T124,"") -> 1156.0999 | X124: =IF(W124="","",IFERROR(INDEX($V$1:$V$178,MATCH(W124,$A$1:$A$178,0)),"")) | Y124: =IF(OR(X124="",V124=""),"",V124/X124) | AA124: =IF(Z124="","",IFERROR(INDEX($V$1:$V$178,MATCH(Z124,$A$1:$A$178,0)),"")) | AB124: =IF(OR(AA124="",V124=""),"",V124/AA124) | AC124: Banque mondiale – Commodity Price Data (Pink Sheet), CMO-Historical-Data-Monthly.xlsx, mise à jour 3 février 2026 | AD124: https://www.worldbank.org/en/research/commodity-markets | AE124: 2026-10-01 | AF124: A | AG124: Banque mondiale (ICCO) jusqu'en janv. 2026, FMI ensuite
A125: INT-CAC-2017/18-I | B125: Cacao | C125: Fèves de cacao | D125: International | E125: 2018-04 → 2018-09 | F125: Moyenne 2018-04 à 2018-09 | G125: Cours international (moyenne mensuelle) | H125: Bourses Londres/New York (prix ICCO) | I125: Standard | J125: =INDEX(Cours_periodes!$E$1:$E$400,MATCH("cacao:2018-04:2018-09",Cours_periodes!$A$1:$A$400,0)) -> 2.403165 | K125: USD | L125: kg | M125: 1 | N125: 2018-04:2018-09 | O125: =IF(K125="USD",1,INDEX(Change_periodes!$D$1:$N$400,MATCH($N125,Change_periodes!$A$1:$A$400,0),MATCH($K125,Change_periodes!$D$1:$N$1,0))) -> 1 | P125: — | Q125: =INDEX(Change_periodes!$D$1:$D$400,MATCH($N125,Change_periodes!$A$1:$A$400,0)) -> 557.21356 | R125: =IFERROR(J125/M125/O125,"") -> 2.403165 | S125: =IFERROR(R125*Q125,"") -> 1339.0761 | T125: 1 | U125: FCFA/kg de produit tel que vendu | V125: =IFERROR(S125/T125,"") -> 1339.0761 | X125: =IF(W125="","",IFERROR(INDEX($V$1:$V$178,MATCH(W125,$A$1:$A$178,0)),"")) | Y125: =IF(OR(X125="",V125=""),"",V125/X125) | AA125: =IF(Z125="","",IFERROR(INDEX($V$1:$V$178,MATCH(Z125,$A$1:$A$178,0)),"")) | AB125: =IF(OR(AA125="",V125=""),"",V125/AA125) | AC125: Banque mondiale – Commodity Price Data (Pink Sheet), CMO-Historical-Data-Monthly.xlsx, mise à jour 3 février 2026 | AD125: https://www.worldbank.org/en/research/commodity-markets | AE125: 2026-10-01 | AF125: A | AG125: Banque mondiale (ICCO) jusqu'en janv. 2026, FMI ensuite
A126: INT-CAC-2018/19-P | B126: Cacao | C126: Fèves de cacao | D126: International | E126: 2018-10 → 2019-03 | F126: Moyenne 2018-10 à 2019-03 | G126: Cours international (moyenne mensuelle) | H126: Bourses Londres/New York (prix ICCO) | I126: Standard | J126: =INDEX(Cours_periodes!$E$1:$E$400,MATCH("cacao:2018-10:2019-03",Cours_periodes!$A$1:$A$400,0)) -> 2.20788 | K126: USD | L126: kg | M126: 1 | N126: 2018-10:2019-03 | O126: =IF(K126="USD",1,INDEX(Change_periodes!$D$1:$N$400,MATCH($N126,Change_periodes!$A$1:$A$400,0),MATCH($K126,Change_periodes!$D$1:$N$1,0))) -> 1 | P126: — | Q126: =INDEX(Change_periodes!$D$1:$D$400,MATCH($N126,Change_periodes!$A$1:$A$400,0)) -> 576.214 | R126: =IFERROR(J126/M126/O126,"") -> 2.20788 | S126: =IFERROR(R126*Q126,"") -> 1272.2114 | T126: 1 | U126: FCFA/kg de produit tel que vendu | V126: =IFERROR(S126/T126,"") -> 1272.2114 | X126: =IF(W126="","",IFERROR(INDEX($V$1:$V$178,MATCH(W126,$A$1:$A$178,0)),"")) | Y126: =IF(OR(X126="",V126=""),"",V126/X126) | AA126: =IF(Z126="","",IFERROR(INDEX($V$1:$V$178,MATCH(Z126,$A$1:$A$178,0)),"")) | AB126: =IF(OR(AA126="",V126=""),"",V126/AA126) | AC126: Banque mondiale – Commodity Price Data (Pink Sheet), CMO-Historical-Data-Monthly.xlsx, mise à jour 3 février 2026 | AD126: https://www.worldbank.org/en/research/commodity-markets | AE126: 2026-10-01 | AF126: A | AG126: Banque mondiale (ICCO) jusqu'en janv. 2026, FMI ensuite
A127: INT-CAC-2018/19-I | B127: Cacao | C127: Fèves de cacao | D127: International | E127: 2019-04 → 2019-09 | F127: Moyenne 2019-04 à 2019-09 | G127: Cours international (moyenne mensuelle) | H127: Bourses Londres/New York (prix ICCO) | I127: Standard | J127: =INDEX(Cours_periodes!$E$1:$E$400,MATCH("cacao:2019-04:2019-09",Cours_periodes!$A$1:$A$400,0)) -> 2.3284317 | K127: USD | L127: kg | M127: 1 | N127: 2019-04:2019-09 | O127: =IF(K127="USD",1,INDEX(Change_periodes!$D$1:$N$400,MATCH($N127,Change_periodes!$A$1:$A$400,0),MATCH($K127,Change_periodes!$D$1:$N$1,0))) -> 1 | P127: — | Q127: =INDEX(Change_periodes!$D$1:$D$400,MATCH($N127,Change_periodes!$A$1:$A$400,0)) -> 586.8976 | R127: =IFERROR(J127/M127/O127,"") -> 2.3284317 | S127: =IFERROR(R127*Q127,"") -> 1366.551 | T127: 1 | U127: FCFA/kg de produit tel que vendu | V127: =IFERROR(S127/T127,"") -> 1366.551 | X127: =IF(W127="","",IFERROR(INDEX($V$1:$V$178,MATCH(W127,$A$1:$A$178,0)),"")) | Y127: =IF(OR(X127="",V127=""),"",V127/X127) | AA127: =IF(Z127="","",IFERROR(INDEX($V$1:$V$178,MATCH(Z127,$A$1:$A$178,0)),"")) | AB127: =IF(OR(AA127="",V127=""),"",V127/AA127) | AC127: Banque mondiale – Commodity Price Data (Pink Sheet), CMO-Historical-Data-Monthly.xlsx, mise à jour 3 février 2026 | AD127: https://www.worldbank.org/en/research/commodity-markets | AE127: 2026-10-01 | AF127: A | AG127: Banque mondiale (ICCO) jusqu'en janv. 2026, FMI ensuite
A128: INT-CAC-2019/20-P | B128: Cacao | C128: Fèves de cacao | D128: International | E128: 2019-10 → 2020-03 | F128: Moyenne 2019-10 à 2020-03 | G128: Cours international (moyenne mensuelle) | H128: Bourses Londres/New York (prix ICCO) | I128: Standard | J128: =INDEX(Cours_periodes!$E$1:$E$400,MATCH("cacao:2019-10:2020-03",Cours_periodes!$A$1:$A$400,0)) -> 2.509565 | K128: USD | L128: kg | M128: 1 | N128: 2019-10:2020-03 | O128: =IF(K128="USD",1,INDEX(Change_periodes!$D$1:$N$400,MATCH($N128,Change_periodes!$A$1:$A$400,0),MATCH($K128,Change_periodes!$D$1:$N$1,0))) -> 1 | P128: — | Q128: =INDEX(Change_periodes!$D$1:$D$400,MATCH($N128,Change_periodes!$A$1:$A$400,0)) -> 593.77663 | R128: =IFERROR(J128/M128/O128,"") -> 2.509565 | S128: =IFERROR(R128*Q128,"") -> 1490.121 | T128: 1 | U128: FCFA/kg de produit tel que vendu | V128: =IFERROR(S128/T128,"") -> 1490.121 | X128: =IF(W128="","",IFERROR(INDEX($V$1:$V$178,MATCH(W128,$A$1:$A$178,0)),"")) | Y128: =IF(OR(X128="",V128=""),"",V128/X128) | AA128: =IF(Z128="","",IFERROR(INDEX($V$1:$V$178,MATCH(Z128,$A$1:$A$178,0)),"")) | AB128: =IF(OR(AA128="",V128=""),"",V128/AA128) | AC128: Banque mondiale – Commodity Price Data (Pink Sheet), CMO-Historical-Data-Monthly.xlsx, mise à jour 3 février 2026 | AD128: https://www.worldbank.org/en/research/commodity-markets | AE128: 2026-10-01 | AF128: A | AG128: Banque mondiale (ICCO) jusqu'en janv. 2026, FMI ensuite
...

Sheet Cacao_transmission
A1: Cacao – prix producteur Côte d'Ivoire vs Ghana vs cours mondial (FCFA/kg, même demi-campagne)
A3: Campagne | B3: Demi-campagne | C3: Prix CI (FCFA/kg) | D3: Prix Ghana (FCFA/kg) | E3: Cours mondial ICCO (FCFA/kg) | F3: Transmission CI | G3: Transmission Ghana | H3: Indice CI (Ghana = 100) | I3: FCFA/USD | J3: GHS/USD
A4: 2016/17 | B4: Principale (oct.-mars) | C4: =Observations!$S$2 -> 1100 | D4: =Observations!$S$22 -> 1110.9961 | E4: =Observations!$X$2 -> 1405.57 | F4: =C4/E4 -> 0.78260066 | G4: =D4/E4 -> 0.7904239 | H4: =C4/D4*100 -> 99.010249 | I4: =Observations!$Q$2 -> 612.12961 | J4: =Observations!$O$22 -> 4.1874
A5: 2016/17 | B5: Intermédiaire (avr.-sept.) | C5: =Observations!$S$3 -> 700 | D5: =Observations!$S$23 -> 1015.8366 | E5: =Observations!$X$3 -> 1147.1675 | F5: =C5/E5 -> 0.61019857 | G5: =D5/E5 -> 0.8855172 | H5: =C5/D5*100 -> 68.908721 | I5: =Observations!$Q$3 -> 577.51424 | J5: =Observations!$O$23 -> 4.3206833
A6: 2017/18 | B6: Principale (oct.-mars) | C6: =Observations!$S$4 -> 700 | D6: =Observations!$S$24 -> 940.29138 | E6: =Observations!$X$4 -> 1156.0999 | F6: =C6/E6 -> 0.60548401 | G6: =D6/E6 -> 0.81333056 | H6: =C6/D6*100 -> 74.445009 | I6: =Observations!$Q$4 -> 545.27827 | J6: =Observations!$O$24 -> 4.4072667
A7: 2017/18 | B7: Intermédiaire (avr.-sept.) | C7: =Observations!$S$5 -> 700 | D7: =Observations!$S$25 -> 928.12276 | E7: =Observations!$X$5 -> 1339.0761 | F7: =C7/E7 -> 0.52274847 | G7: =D7/E7 -> 0.69310679 | H7: =C7/D7*100 -> 75.421057 | I7: =Observations!$Q$5 -> 557.21356 | J7: =Observations!$O$25 -> 4.5627833
A8: 2018/19 | B8: Principale (oct.-mars) | C8: =Observations!$S$6 -> 750 | D8: =Observations!$S$26 -> 891.17951 | E8: =Observations!$X$6 -> 1272.2114 | F8: =C8/E8 -> 0.58952468 | G8: =D8/E8 -> 0.70049642 | H8: =C8/D8*100 -> 84.158129 | I8: =Observations!$Q$6 -> 576.214 | J8: =Observations!$O$26 -> 4.9139667
A9: 2018/19 | B9: Intermédiaire (avr.-sept.) | C9: =Observations!$S$7 -> 750 | D9: =Observations!$S$27 -> 855.91345 | E9: =Observations!$X$7 -> 1366.551 | F9: =C9/E9 -> 0.54882695 | G9: =D9/E9 -> 0.62633116 | H9: =C9/D9*100 -> 87.625682 | I9: =Observations!$Q$7 -> 586.8976 | J9: =Observations!$O$27 -> 5.2113
A10: 2019/20 | B10: Principale (oct.-mars) | C10: =Observations!$S$8 -> 825 | D10: =Observations!$S$28 -> 904.56829 | E10: =Observations!$X$8 -> 1490.121 | F10: =C10/E10 -> 0.5536463 | G10: =D10/E10 -> 0.6070435 | H10: =C10/D10*100 -> 91.203728 | I10: =Observations!$Q$8 -> 593.77663 | J10: =Observations!$O$28 -> 5.4089
A11: 2019/20 | B11: Intermédiaire (avr.-sept.) | C11: =Observations!$S$9 -> 825 | D11: =Observations!$S$29 -> 846.06943 | E11: =Observations!$X$9 -> 1323.3272 | F11: =C11/E11 -> 0.6234286 | G11: =D11/E11 -> 0.63935015 | H11: =C11/D11*100 -> 97.509728 | I11: =Observations!$Q$9 -> 578.5804 | J11: =Observations!$O$29 -> 5.6348833
A12: 2020/21 | B12: Principale (oct.-mars) | C12: =Observations!$S$10 -> 1000 | D12: =Observations!$S$30 -> 1008.2278 | E12: =Observations!$X$10 -> 1305.3537 | F12: =C12/E12 -> 0.76607588 | G12: =D12/E12 -> 0.77237904 | H12: =C12/D12*100 -> 99.18393 | I12: =Observations!$Q$10 -> 547.10364 | J12: =Observations!$O$30 -> 5.7302667
A13: 2020/21 | B13: Intermédiaire (avr.-sept.) | C13: =Observations!$S$11 -> 750 | D13: =Observations!$S$31 -> 1005.1123 | E13: =Observations!$X$11 -> 1331.3374 | F13: =C13/E13 -> 0.56334328 | G13: =D13/E13 -> 0.75496435 | H13: =C13/D13*100 -> 74.618527 | I13: =Observations!$Q$11 -> 550.25616 | J13: =Observations!$O$31 -> 5.78115
A14: 2021/22 | B14: Principale (oct.-mars) | C14: =Observations!$S$12 -> 825 | D14: =Observations!$S$32 -> 988.66664 | E14: =Observations!$X$12 -> 1430.1041 | F14: =C14/E14 -> 0.5768811 | G14: =D14/E14 -> 0.69132497 | H14: =C14/D14*100 -> 83.44572 | I14: =Observations!$Q$12 -> 578.96606 | J14: =Observations!$O$32 -> 6.1839667
A15: 2021/22 | B15: Intermédiaire (avr.-sept.) | C15: =Observations!$S$13 -> 825 | D15: =Observations!$S$33 -> 879.87725 | E15: =Observations!$X$13 -> 1478.9463 | F15: =C15/E15 -> 0.55782959 | G15: =D15/E15 -> 0.59493524 | H15: =C15/D15*100 -> 93.763078 | I15: =Observations!$Q$13 -> 633.60467 | J15: =Observations!$O$33 -> 7.6043167
A16: 2022/23 | B16: Principale (oct.-mars) | C16: =Observations!$S$14 -> 900 | D16: =Observations!$S$34 -> 729.32611 | E16: =Observations!$X$14 -> 1595.3908 | F16: =C16/E16 -> 0.5641251 | G16: =D16/E16 -> 0.45714573 | H16: =C16/D16*100 -> 123.40159 | I16: =Observations!$Q$14 -> 627.3496 | J16: =Observations!$O$34 -> 11.010267
A17: 2022/23 | B17: Intermédiaire (avr.-sept.) | C17: =Observations!$S$15 -> 900 | D17: =Observations!$S$35 -> 701.96683 | E17: =Observations!$X$15 -> 1955.8891 | F17: =C17/E17 -> 0.46014879 | G17: =D17/E17 -> 0.3588991 | H17: =C17/D17*100 -> 128.21119 | I17: =Observations!$Q$15 -> 602.54621 | J17: =Observations!$O$35 -> 10.987117
A18: 2023/24 | B18: Principale (oct.-mars) | C18: =Observations!$S$16 -> 1000 | D18: =Observations!$S$36 -> 1068.012 | E18: =Observations!$X$16 -> 2924.6742 | F18: =C18/E18 -> 0.34191843 | G18: =D18/E18 -> 0.36517299 | H18: =C18/D18*100 -> 93.631907 | I18: =Observations!$Q$16 -> 607.0108 | J18: =Observations!$O$36 -> 11.89455
A19: 2023/24 | B19: Intermédiaire (avr.-sept.) | C19: =Observations!$S$17 -> 1500 | D19: =Observations!$S$37 -> 1384.1081 | E19: =Observations!$X$17 -> 4628.3983 | F19: =C19/E19 -> 0.3240862 | G19: =D19/E19 -> 0.29904689 | H19: =C19/D19*100 -> 108.37304 | I19: =Observations!$Q$17 -> 603.1694 | J19: =Observations!$O$37 -> 14.4331
A20: 2024/25 | B20: Principale (oct.-mars) | C20: =Observations!$S$18 -> 1800 | D20: =Observations!$S$38 -> 1922.8063 | E20: =Observations!$X$18 -> 5527.0204 | F20: =C20/E20 -> 0.32567276 | G20: =D20/E20 -> 0.34789202 | H20: =C20/D20*100 -> 93.613175 | I20: =Observations!$Q$18 -> 619.18635 | J20: =Observations!$O$38 -> 15.457067
A21: 2024/25 | B21: Intermédiaire (avr.-sept.) | C21: =Observations!$S$19 -> 2200 | D21: =Observations!$S$39 -> 2392.2446 | E21: =Observations!$X$19 -> 4517.8031 | F21: =C21/E21 -> 0.48696235 | G21: =D21/E21 -> 0.52951501 | H21: =C21/D21*100 -> 91.963841 | I21: =Observations!$Q$19 -> 570.16368 | J21: =Observations!$O$39 -> 11.821583
A22: 2025/26 | B22: Principale (oct.-mars) | C22: =Observations!$S$20 -> 2800 | D22: =Observations!$S$40 -> 2964.4546 | E22: =Observations!$X$20 -> 2731.1039 | F22: =C22/E22 -> 1.0252265 | G22: =D22/E22 -> 1.0854419 | H22: =C22/D22*100 -> 94.452451 | I22: =Observations!$Q$20 -> 562.12788 | J22: =Observations!$O$40 -> 10.998117
A23: 2025/26 | B23: Intermédiaire (avr.-sept.) | C23: =Observations!$S$21 -> 1200 | D23: =Observations!$S$41 -> 2059.1954 | E23: =Observations!$X$21 -> 2666.3546 | F23: =C23/E23 -> 0.45005266 | G23: =D23/E23 -> 0.77228865 | H23: =C23/D23*100 -> 58.275187 | I23: =Observations!$Q$21 -> 566.22402 | J23: =Observations!$O$41 -> 11.3817
A24: 2026/27 | B24: Ouverture (cours d'août 2026) | C24: =Observations!$S$42 -> 1200 | D24: =Observations!$S$43 -> 2085.7803 | E24: =Observations!$X$42 -> 3387.5448 | F24: =C24/E24 -> 0.35423886 | G24: =D24/E24 -> 0.61572037 | H24: =C24/D24*100 -> 57.532425 | I24: =Observations!$Q$42 -> 565.22679 | J24: =Observations!$O$43 -> 11.49
A26: Moyenne 10 campagnes (2016/17-2025/26) | C26: =AVERAGE(C4:C23) -> 1102.5 | D26: =AVERAGE(D4:D23) -> 1229.8488 | E26: =AVERAGE(E4:E23) -> 2129.625 | F26: =AVERAGE(F4:F23) -> 0.56393904 | G26: =AVERAGE(G4:G23) -> 0.63923028 | H26: =AVERAGE(H4:H23) -> 91.060797
A27: Moyenne 3 dernières campagnes (2023/24-2025/26) | C27: =AVERAGE(C18:C23) -> 1750 | D27: =AVERAGE(D18:D23) -> 1965.1368 | E27: =AVERAGE(E18:E23) -> 3832.5591 | F27: =AVERAGE(F18:F23) -> 0.49231981 | G27: =AVERAGE(G18:G23) -> 0.56655957 | H27: =AVERAGE(H18:H23) -> 90.0516
A28: Coefficient de variation 10 campagnes | C28: =STDEV(C4:C23)/AVERAGE(C4:C23) -> 0.51012584 | D28: =STDEV(D4:D23)/AVERAGE(D4:D23) -> 0.49809602 | E28: =STDEV(E4:E23)/AVERAGE(E4:E23) -> 0.61653871
A30: Lecture : la transmission rapporte le prix bord champ au cours mondial moyen de la même demi-campagne (méthode identique pour les deux pays). Les prix ivoiriens reposent sur des ventes anticipées conclues plusieurs mois avant la campagne (mars-juin 2026 pour 2026/27, source CI_CAC_VENTES) : un décalage est structurel. Demi-campagne intermédiaire 2025/26 : cours moyen avr.-août 2026 (septembre non encore publié).

Sheet Series_CI
A1: Prix officiels ivoiriens : 10 campagnes, nominal et réel (FCFA constants 2025)
A3: Année d'ouverture | B3: Inflation CI (%) | C3: Indice des prix (2015 = 100) | D3: Source inflation | E3: Cacao principale | F3: Cacao intermédiaire | G3: Café | H3: Anacarde | I3: Coton graine | J3: Cacao princ. (FCFA 2025) | K3: Café (FCFA 2025) | L3: Anacarde (FCFA 2025) | M3: Coton (FCFA 2025) | N3: Cours cacao (FCFA/kg, princ.) | O3: Cours robusta (FCFA/kg, camp.)
A4: 2015 | C4: 100
A5: 2016 | B5: 0.72 | C5: =C4*(1+B5/100) -> 100.72 | D5: Banque mondiale (WDI, d'après INS) | E5: =Observations!$S$2 -> 1100 | F5: =Observations!$S$3 -> 700 | G5: =Observations!$S$51 -> 750 | H5: =Observations!$S$64 -> 350 | I5: n.d. | J5: =IF(ISNUMBER(E5),E5*$C$14/C5,"n.d.") -> 1360.3893 | K5: =IF(ISNUMBER(G5),G5*$C$14/C5,"n.d.") -> 927.53815 | L5: =IF(ISNUMBER(H5),H5*$C$14/C5,"n.d.") -> 432.85114 | M5: =IF(ISNUMBER(I5),I5*$C$14/C5,"n.d.") -> n.d. | N5: =Observations!$X$2 -> 1405.57 | O5: =Observations!$X$51 -> 1358.6634
A6: 2017 | B6: 0.69 | C6: =C5*(1+B6/100) -> 101.41497 | D6: Banque mondiale (WDI, d'après INS) | E6: =Observations!$S$4 -> 700 | F6: =Observations!$S$5 -> 700 | G6: =Observations!$S$52 -> 750 | H6: =Observations!$S$65 -> 440 | I6: =Observations!$S$85 -> 265 | J6: =IF(ISNUMBER(E6),E6*$C$14/C6,"n.d.") -> 859.76986 | K6: =IF(ISNUMBER(G6),G6*$C$14/C6,"n.d.") -> 921.18199 | L6: =IF(ISNUMBER(H6),H6*$C$14/C6,"n.d.") -> 540.42677 | M6: =IF(ISNUMBER(I6),I6*$C$14/C6,"n.d.") -> 325.4843 | N6: =Observations!$X$4 -> 1156.0999 | O6: =Observations!$X$52 -> 1061.7159
A7: 2018 | B7: 0.4 | C7: =C6*(1+B7/100) -> 101.82063 | D7: Banque mondiale (WDI, d'après INS) | E7: =Observations!$S$6 -> 750 | F7: =Observations!$S$7 -> 750 | G7: =Observations!$S$53 -> 700 | H7: =Observations!$S$66 -> 500 | I7: =Observations!$S$86 -> 265 | J7: =IF(ISNUMBER(E7),E7*$C$14/C7,"n.d.") -> 917.51195 | K7: =IF(ISNUMBER(G7),G7*$C$14/C7,"n.d.") -> 856.34448 | L7: =IF(ISNUMBER(H7),H7*$C$14/C7,"n.d.") -> 611.67463 | M7: =IF(ISNUMBER(I7),I7*$C$14/C7,"n.d.") -> 324.18755 | N7: =Observations!$X$6 -> 1272.2114 | O7: =Observations!$X$53 -> 976.56168
A8: 2019 | B8: 0.79 | C8: =C7*(1+B8/100) -> 102.62501 | D8: Banque mondiale (WDI, d'après INS) | E8: =Observations!$S$8 -> 825 | F8: =Observations!$S$9 -> 825 | G8: =Observations!$S$54 -> 700 | H8: =Observations!$S$67 -> 375 | I8: =Observations!$S$87 -> 300 | J8: =IF(ISNUMBER(E8),E8*$C$14/C8,"n.d.") -> 1001.3525 | K8: =IF(ISNUMBER(G8),G8*$C$14/C8,"n.d.") -> 849.63239 | L8: =IF(ISNUMBER(H8),H8*$C$14/C8,"n.d.") -> 455.16021 | M8: =IF(ISNUMBER(I8),I8*$C$14/C8,"n.d.") -> 364.12817 | N8: =Observations!$X$8 -> 1490.121 | O8: =Observations!$X$54 -> 891.11683
A9: 2020 | B9: 2.41 | C9: =C8*(1+B9/100) -> 105.09827 | D9: Banque mondiale (WDI, d'après INS) | E9: =Observations!$S$10 -> 1000 | F9: =Observations!$S$11 -> 750 | G9: =Observations!$S$55 -> 550 | H9: =Observations!$S$68 -> 400 | I9: =Observations!$S$88 -> 300 | J9: =IF(ISNUMBER(E9),E9*$C$14/C9,"n.d.") -> 1185.1973 | K9: =IF(ISNUMBER(G9),G9*$C$14/C9,"n.d.") -> 651.85851 | L9: =IF(ISNUMBER(H9),H9*$C$14/C9,"n.d.") -> 474.07892 | M9: =IF(ISNUMBER(I9),I9*$C$14/C9,"n.d.") -> 355.55919 | N9: =Observations!$X$10 -> 1305.3537 | O9: =Observations!$X$55 -> 971.59551
A10: 2021 | B10: 4.16 | C10: =C9*(1+B10/100) -> 109.47036 | D10: Banque mondiale (WDI) ; BCEAO 4,2 % | E10: =Observations!$S$12 -> 825 | F10: =Observations!$S$13 -> 825 | G10: =Observations!$S$56 -> 700 | H10: =Observations!$S$69 -> 305 | I10: =Observations!$S$89 -> 300 | J10: =IF(ISNUMBER(E10),E10*$C$14/C10,"n.d.") -> 938.73634 | K10: =IF(ISNUMBER(G10),G10*$C$14/C10,"n.d.") -> 796.50356 | L10: =IF(ISNUMBER(H10),H10*$C$14/C10,"n.d.") -> 347.04798 | M10: =IF(ISNUMBER(I10),I10*$C$14/C10,"n.d.") -> 341.35867 | N10: =Observations!$X$12 -> 1430.1041 | O10: =Observations!$X$56 -> 1428.7782
A11: 2022 | B11: 5.23 | C11: =C10*(1+B11/100) -> 115.19566 | D11: Banque mondiale (WDI) ; BCEAO 5,2 % | E11: =Observations!$S$14 -> 900 | F11: =Observations!$S$15 -> 900 | G11: =Observations!$S$57 -> 750 | H11: =Observations!$S$70 -> 305 | I11: =Observations!$S$90 -> 310 | J11: =IF(ISNUMBER(E11),E11*$C$14/C11,"n.d.") -> 973.17876 | K11: =IF(ISNUMBER(G11),G11*$C$14/C11,"n.d.") -> 810.9823 | L11: =IF(ISNUMBER(H11),H11*$C$14/C11,"n.d.") -> 329.79947 | M11: =IF(ISNUMBER(I11),I11*$C$14/C11,"n.d.") -> 335.20602 | N11: =Observations!$X$14 -> 1595.3908 | O11: =Observations!$X$57 -> 1515.3067
A12: 2023 | B12: 4.37 | C12: =C11*(1+B12/100) -> 120.22971 | D12: Banque mondiale (WDI) ; BCEAO 4,4 % | E12: =Observations!$S$16 -> 1000 | F12: =Observations!$S$17 -> 1500 | G12: =Observations!$S$58 -> 900 | H12: =Observations!$S$71 -> 315 | I12: =Observations!$S$91 -> 310 | J12: =IF(ISNUMBER(E12),E12*$C$14/C12,"n.d.") -> 1036.035 | K12: =IF(ISNUMBER(G12),G12*$C$14/C12,"n.d.") -> 932.4315 | L12: =IF(ISNUMBER(H12),H12*$C$14/C12,"n.d.") -> 326.35102 | M12: =IF(ISNUMBER(I12),I12*$C$14/C12,"n.d.") -> 321.17085 | N12: =Observations!$X$16 -> 2924.6742 | O12: =Observations!$X$58 -> 2328.864
A13: 2024 | B13: 3.5 | C13: =C12*(1+B13/100) -> 124.43775 | D13: BCEAO, Rapport annuel sur l'inflation 2024 | E13: =Observations!$S$18 -> 1800 | F13: =Observations!$S$19 -> 2200 | G13: =Observations!$S$59 -> 1500 | H13: =Observations!$S$72 -> 275 | I13: =Observations!$S$92 -> 310 | J13: =IF(ISNUMBER(E13),E13*$C$14/C13,"n.d.") -> 1801.8 | K13: =IF(ISNUMBER(G13),G13*$C$14/C13,"n.d.") -> 1501.5 | L13: =IF(ISNUMBER(H13),H13*$C$14/C13,"n.d.") -> 275.275 | M13: =IF(ISNUMBER(I13),I13*$C$14/C13,"n.d.") -> 310.31 | N13: =Observations!$X$18 -> 5527.0204 | O13: =Observations!$X$59 -> 2960.0927
A14: 2025 | B14: 0.1 | C14: =C13*(1+B14/100) -> 124.56219 | D14: DG Trésor / BCEAO (rapport annuel prix UEMOA 2025) | E14: =Observations!$S$20 -> 2800 | F14: =Observations!$S$21 -> 1200 | G14: =Observations!$S$60 -> 1700 | H14: =Observations!$S$73 -> 425 | I14: =Observations!$S$93 -> 310 | J14: =IF(ISNUMBER(E14),E14*$C$14/C14,"n.d.") -> 2800 | K14: =IF(ISNUMBER(G14),G14*$C$14/C14,"n.d.") -> 1700 | L14: =IF(ISNUMBER(H14),H14*$C$14/C14,"n.d.") -> 425 | M14: =IF(ISNUMBER(I14),I14*$C$14/C14,"n.d.") -> 310 | N14: =Observations!$X$20 -> 2731.1039 | O14: =Observations!$X$60 -> 2301.7138
A15: 2026 | B15: n.d. | C15: =C14 -> 124.56219 | D15: IPC 2026 non publié : niveau 2025 conservé | E15: =Observations!$S$42 -> 1200 | F15: n.d. | G15: =Observations!$S$61 -> 1300 | H15: =Observations!$S$74 -> 400 | I15: n.d. | J15: =IF(ISNUMBER(E15),E15*$C$14/C15,"n.d.") -> 1200 | K15: =IF(ISNUMBER(G15),G15*$C$14/C15,"n.d.") -> 1300 | L15: =IF(ISNUMBER(H15),H15*$C$14/C15,"n.d.") -> 400 | M15: =IF(ISNUMBER(I15),I15*$C$14/C15,"n.d.") -> n.d. | N15: =Observations!$X$42 -> 3387.5448 | O15: =Observations!$X$61 -> 2253.1983
A17: Variation 2016→2025 (nominal) | E17: =IFERROR(E14/E5-1,"") -> 1.5454545 | G17: =IFERROR(G14/G5-1,"") -> 1.2666667 | H17: =IFERROR(H14/H5-1,"") -> 0.21428571 | I17: =IFERROR(I14/I6-1,"") -> 0.16981132
A18: Variation 2016→2025 (réel) | J18: =IFERROR(J14/J5-1,"") -> 1.0582344 | K18: =IFERROR(K14/K5-1,"") -> 0.83280871 | L18: =IFERROR(L14/L5-1,"") -> -0.01813819 | M18: =IFERROR(M14/M6-1,"") -> -0.047573121
A19: Variation 2016→2026 (dernier prix connu, nominal) | E19: =IFERROR(E15/E5-1,"") -> 0.090909091 | G19: =IFERROR(G15/G5-1,"") -> 0.73333333 | H19: =IFERROR(H15/H5-1,"") -> 0.14285714
A20: Variation 2016→2026 (dernier prix connu, réel) | J20: =IFERROR(J15/J5-1,"") -> -0.11789955 | K20: =IFERROR(K15/K5-1,"") -> 0.4015596 | L20: =IFERROR(L15/L5-1,"") -> -0.075894767
A21: Coefficient de variation 2016-2025 | E21: =STDEV(E5:E14)/AVERAGE(E5:E14) -> 0.55717858 | G21: =STDEV(G5:G14)/AVERAGE(G5:G14) -> 0.42390826 | H21: =STDEV(H5:H14)/AVERAGE(H5:H14) -> 0.19508849 | I21: =STDEV(I6:I14)/AVERAGE(I6:I14) -> 0.062496055 | N21: =STDEV(N5:N14)/AVERAGE(N5:N14) -> 0.65146851 | O21: =STDEV(O5:O14)/AVERAGE(O5:O14) -> 0.4496716
A23: Notes : prix d'ouverture de campagne (le prix intermédiaire du cacao est en colonne F). Déflateur : IPC Côte d'Ivoire de l'année d'ouverture. Coton : série disponible à partir de 2017/18. Café 2016/17 déduit du maintien à 750 FCFA en 2017/18.

Sheet Decomposition
A1: Décomposition de la valeur : du prix international au prix producteur
A3: Cacao – structure du prix CAF (règle de partage) | B3: % du CAF | C3: FCFA/kg (2026/27, si part = 60 %) | D3: USD/kg | E3: Source / note
A4: Prix CAF de référence implicite (prix bord champ ÷ 60 %) | B4: =1 -> 1 | C4: =Observations!$S$42/B5 -> 2000 | D4: =C4/Observations!$Q$42 -> 3.5384027 | E4: Calcul : 1 200 FCFA/kg ÷ 60 % (plancher réglementaire). Majorant du CAF si la part producteur dépasse 60 %.
A5: Producteur (prix bord champ garanti) | B5: =0.6 -> 0.6 | C5: =$C$4*B5 -> 1200 | D5: =C5/Observations!$Q$42 -> 2.1230416 | E5: Règle de partage ≥60 % du CAF (Banque mondiale 2019 ; Agence Ecofin 2026)
A6: Droit unique de sortie (DUS) | B6: =0.146 -> 0.146 | C6: =$C$4*B6 -> 292 | D6: =C6/Observations!$Q$42 -> 0.51660679 | E6: 14,6 % du CAF depuis le 16/11/2012 (OMC TPR 2017 ; Banque mondiale 2019)
A7: Autres prélèvements fiscaux et parafiscaux | B7: =0.22-0.146 -> 0.074 | C7: =$C$4*B7 -> 148 | D7: =C7/Observations!$Q$42 -> 0.2618418 | E7: Plafond global ≈22 % du CAF (Banque mondiale 2019) ; 23,2 % observé en 2016/17 (OMC)
A8: Coûts de commercialisation, transport, conditionnement, marges, fret et assurance (résidu) | B8: =1-B5-B6-B7 -> 0.18 | C8: =$C$4*B8 -> 360 | D8: =C8/Observations!$Q$42 -> 0.63691248 | E8: Résidu calculé (dont ≈225 FCFA/kg de marges privées selon la Banque mondiale 2019)
A9: Pour mémoire : cours mondial ICCO, août 2026 (FCFA/kg) | C9: =Observations!$S$144 -> 3387.5448 | D9: =Observations!$R$144 -> 5.987 | E9: Le CAF implicite des ventes anticipées est très inférieur au cours de marché d'août 2026 : décalage dû au calendrier des ventes (mars-juin 2026).
A11: Anacarde 2026 – du bord champ au CFR Asie | B11: FCFA/kg | C11: % du CFR | D11: USD/kg | E11: Source / note
A12: Prix plancher bord champ | B12: =400 -> 400 | C12: =B12/$B$18 -> 0.45694742 | D12: =B12/Observations!$Q$83 -> 0.71283797 | E12: Barème 2026 (CCAK)
A13: Collecte → magasin intérieur | B13: =425-400 -> 25 | C13: =B13/$B$18 -> 0.028559214 | D13: =B13/Observations!$Q$83 -> 0.044552373 | E13: Plancher magasin intérieur 425
A14: Magasin intérieur → magasin usine | B14: =454-425 -> 29 | C14: =B14/$B$18 -> 0.033128688 | D14: =B14/Observations!$Q$83 -> 0.051680753 | E14: Plancher magasin usine 454
A15: Magasin usine → magasin portuaire | B15: =484-454 -> 30 | C15: =B15/$B$18 -> 0.034271056 | D15: =B15/Observations!$Q$83 -> 0.053462848 | E15: Plancher magasin portuaire 484
A16: Droit unique de sortie (5 % de la valeur CAF de référence) | B16: =0.05*Observations!$S$83 -> 43.768712 | C16: =B16/$B$18 -> 0.05 | D16: =B16/Observations!$Q$83 -> 0.078 | E16: DUS 5 % depuis le 20/11/2024 (assiette approximée par le CFR)
A17: Fret maritime, frais portuaires, conditionnement, financement, freinte et marge exportateur (résidu) | B17: =Observations!$S$83-SUM(B12:B16) -> 347.60553 | C17: =B17/$B$18 -> 0.39709362 | D17: =B17/Observations!$Q$83 -> 0.61946605 | E17: Résidu calculé ; non décomposable faute de données publiques sur les coûts d'exportation
A18: Prix CFR Vietnam/Inde, noix ivoirienne (avr.-mai 2026) | B18: =Observations!$S$83 -> 875.37424 | C18: =B18/$B$18 -> 1 | D18: =B18/Observations!$Q$83 -> 1.56 | E18: Cotation de négoce (fiabilité C) ; valeur unitaire Vietnam toutes origines janv.-avr. 2026 : voir Observations
A20: Caoutchouc – part du cours mondial (base kg sec) | B20: Valeur | E20: Source / note
A21: Part du prix de référence revenant au producteur (règle 2026) | B21: =0.66 -> 0.66 | E21: 63 % jusqu'en 2025 ; 66 % à partir de 2026 (Agence Ecofin)
A22: Moyenne observée : prix bord champ (sec, DRC 60 %) ÷ TSR20 du mois précédent | B22: =AVERAGE(Observations!$Y$101,Observations!$Y$102,Observations!$Y$103,Observations!$Y$104,Observations!$Y$105) -> 0.59875527 | E22: 5 couples mois/TSR20 vérifiés (janv. et avr. 2025 ; janv., févr. et avr. 2026)
A23: Même calcul si le DRC réel est de 66 % (milieu de 65-68 %) | B23: =B22*Parametres!$C$6/0.66 -> 0.54432297 | E23: Un DRC réel supérieur à la convention réduit la rémunération effective par kg sec
A24: Thaïlande : prix cup lump 100 % DRC ÷ TSR20 (mai 2025) | B24: =Observations!$Y$109 -> 1.0060933
A26: Palmier à huile – partage huile/régime | B26: Ratio | E26: Source / note
A27: CI : prix du régime ÷ prix intérieur de l'huile brute (janv. 2026) | B27: =Observations!$S$111/Observations!$S$112 -> 0.12903226
A28: CI : prix du régime ÷ prix mondial de l'huile brute (janv. 2026) | B28: =Observations!$Y$111 -> 0.14347142
A29: Indonésie (Riau) : prix du régime ÷ prix mondial de l'huile brute (janv. 2026) | B29: =Observations!$Y$114 -> 0.20596614
A30: Malaisie : prix du régime (MPOB) ÷ prix mondial de l'huile brute (2025) | B30: =Observations!$Y$115 -> 0.21688915
A31: CI : prix intérieur de l'huile brute ÷ prix mondial (janv. 2026) | B31: =Observations!$Y$112 -> 1.1119035 | E31: Un ratio >100 % signale un marché intérieur protégé (prix de l'huile supérieur au prix mondial)
A33: Coton – soutien budgétaire 2025/26 | B33: Valeur | E33: Source / note
A34: Subvention exceptionnelle 2025/26 (FCFA) | B34: 25300000000 | E34: Agence Ecofin (0108-130586) : 25,3 Mds FCFA contre 11,9 Mds en 2024/25
A35: Production de coton graine de référence (t, campagne 2024/25) | B35: =Volumes_Rendements!B7 -> 351764
A36: Subvention rapportée au kg de coton graine (FCFA/kg) | B36: =B34/(B35*1000) -> 71.923221 | E36: Ordre de grandeur : la production 2025/26 n'étant pas encore publiée, la production 2024/25 sert de dénominateur
A37: En % du prix d'achat (310 FCFA/kg) | B37: =B36/Observations!$S$93 -> 0.23201039

Sheet Positionnement
A1: Positionnement des filières (graphique 1 de la note)
A3: Filière | B3: X : rémunération relative (indice CI, médiane comparateurs = 100) | C3: Y : taux de transmission (prix CI / référence internationale) | D3: Taille : valeur brute au producteur (Mds FCFA) | E3: Note
A4: Cacao | B4: =Indicateurs!I32 -> 57.532425 | C4: =Indicateurs!J32 -> 0.35423886 | D4: =Volumes_Rendements!F4 -> 2400 | E4: Ouverture 2026/27 ; transmission vs cours d'août 2026
A5: Café | B5: =Indicateurs!I33 -> 67.827094 | C5: =Indicateurs!J33 -> 0.57695765 | D5: =Volumes_Rendements!F8 -> 32.2816 | E5: 2026/27 ; transmission vs robusta d'août 2026
A6: Anacarde | B6: =Indicateurs!I34 -> 97.560976 | C6: =Indicateurs!J34 -> 0.45694742 | D6: =Volumes_Rendements!F5 -> 619.6884 | E6: Campagne 2026 ; transmission vs CFR Asie avr.-mai 2026
A7: Coton | B7: =Indicateurs!I35 -> 103.33333 | C7: =Indicateurs!J35 -> 0.72795032 | D7: =Volumes_Rendements!F7 -> 109.04684 | E7: 2025/26 ; transmission en équivalent fibre vs indice A
A8: Caoutchouc | B8: =Indicateurs!I36 -> 70.508729 | C8: =Decomposition!B22 -> 0.59875527 | D8: =Volumes_Rendements!F6 -> 774.4 | E8: Sept. 2026 (base sèche) ; transmission = moyenne des couples vérifiés

Sheet Volumes_Rendements
A1: Importance économique (valeur brute au producteur) et revenu brut à l'hectare
A3: Filière | B3: Volume (t) | C3: Libellé | D3: ID prix | E3: Prix FCFA/kg | F3: Valeur brute producteur (Mds FCFA) | G3: Source | H3: URL | I3: Remarque
A4: Cacao | B4: 2000000 | C4: Production 2025/26 (prévision CCC 2,0-2,1 Mt) | D4: CAC-CI-2026/27-P | E4: =Observations!$S$42 -> 1200 | F4: =B4*1000*E4/1000000000 -> 2400 | G4: CCC (via CNBC Africa/Reuters) – La Côte d'Ivoire anticipe 2,0-2,1 Mt de cacao en 2025/26 (+10,5 %) | H4: https://www.cnbcafrica.com/2026/ivory-coast-expects-cocoa-output-to-rise-10-5-in-2025-26-season-regulator-says | I4: Borne basse de la prévision
A5: Anacarde | B5: 1549221 | C5: Production commercialisée 2025 | D5: ANA-CI-2026 | E5: =Observations!$S$74 -> 400 | F5: =B5*1000*E5/1000000000 -> 619.6884 | G5: MINADERPV (via AIP) – Production historique de 1 549 221 t de noix de cajou en 2025 | H5: https://www.aip.ci/316955/aip-la-cote-divoire-atteint-une-production-historique-de-1-549-221-tonnes-de-noix-de-cajou-au-titre-de-la-campagne-2025/
A6: Caoutchouc | B6: 1600000 | C6: Production ≈1,6 Mt (2023) | D6: CAO-CI-2026-09 | E6: =Observations!$S$108 -> 484 | F6: =B6*1000*E6/1000000000 -> 774.4 | G6: Financial Afrik – Numéro trois mondial du caoutchouc (≈1,6 Mt en 2023) | H6: https://www.financialafrik.com/2026/01/15/numero-trois-mondial-du-caoutchouc-la-cote-divoire-veut-capter-davantage-de-valeur/ | I6: Base humide supposée (non précisée par la source)
A7: Coton | B7: 351764 | C7: Coton graine 2024/25 | D7: COT-CI-2025/26 | E7: =Observations!$S$93 -> 310 | F7: =B7*1000*E7/1000000000 -> 109.04684 | G7: Agence Ecofin – Croissance modeste de la production cotonnière 2024/2025 : 351 764 t, 984 kg/ha, 357 267 ha | H7: https://www.agenceecofin.com/actualites-agro/1501-124919-cote-d-ivoire-croissance-modeste-de-la-production-cotonniere-en-2024/2025
A8: Café | B8: 24832 | C8: Achats oct. 2024-juin 2025 (effondrement de la production) | D8: CAF-CI-2026/27 | E8: =Observations!$S$61 -> 1300 | F8: =B8*1000*E8/1000000000 -> 32.2816 | G8: AIP – Filière café-cacao : production de café 24 832 t d'octobre 2024 à juin 2025 (-69,7 %) | H8: https://www.aip.ci/257515/cote-divoire-aip-la-filiere-cafe-cacao-moteur-de-croissance-economique-face-aux-defis-sociaux-et-environnementaux-feature/
A10: Filière | B10: Pays | C10: Rendement (kg/ha) | D10: ID prix | E10: Prix FCFA/kg | F10: Revenu brut (FCFA/ha) | G10: Source | H10: URL
A11: Cacao | B11: Côte d'Ivoire | C11: 500 | D11: CAC-CI-2026/27-P | E11: =Observations!$S$42 -> 1200 | F11: =C11*E11 -> 600000 | G11: Wessel & Quist-Wessel (2015), NJAS – Cocoa production in West Africa, a review ; KIT (2018) – Rendements moyens : Côte d'Ivoire ≈500-600 kg/ha ; Ghana ≈400 kg/ha | H11: https://www.sciencedirect.com/science/article/pii/S1573521415000160
A12: Cacao | B12: Ghana | C12: 400 | D12: CAC-GH-2026/27-P | E12: =Observations!$S$43 -> 2085.7803 | F12: =C12*E12 -> 834312.14 | G12: Wessel & Quist-Wessel (2015), NJAS – Cocoa production in West Africa, a review ; KIT (2018) – Rendements moyens : Côte d'Ivoire ≈500-600 kg/ha ; Ghana ≈400 kg/ha | H12: https://www.sciencedirect.com/science/article/pii/S1573521415000160
A13: Coton | B13: Côte d'Ivoire | C13: 984 | D13: COT-CI-2025/26 | E13: =Observations!$S$93 -> 310 | F13: =C13*E13 -> 305040 | G13: Agence Ecofin – Croissance modeste de la production cotonnière 2024/2025 : 351 764 t, 984 kg/ha, 357 267 ha | H13: https://www.agenceecofin.com/actualites-agro/1501-124919-cote-d-ivoire-croissance-modeste-de-la-production-cotonniere-en-2024/2025
A14: Coton | B14: Burkina Faso | C14: 865 | D14: COT-BF-2025/26 | E14: =Observations!$S$94 -> 325 | F14: =C14*E14 -> 281125 | G14: Agence Ecofin – Burkina Faso : production 2024/2025 (300 000 t ; 865 kg/ha) | H14: https://www.agenceecofin.com/actualites-agro/2002-126013-au-burkina-faso-la-production-cotonniere-2024/2025-s-annonce-plus-faible-que-prevu
A15: Coton | B15: Mali | C15: 914 | D15: COT-ML-2025/26 | E15: =Observations!$S$95 -> 300 | F15: =C15*E15 -> 274200 | G15: La Marina (Bénin) – Campagne 2024-2025 : rendements Bénin 1 248 kg/ha, Mali 914 kg/ha | H15: https://lamarinabj.com/index.php/2025/02/05/campagne-cotonniere-2024-2025-en-afrique-le-benin-peut-il-reprendre-sa-place-de-leader/
A16: Coton | B16: Bénin | C16: 1248 | D16: COT-BJ-2025/26 | E16: =Observations!$S$96 -> 300 | F16: =C16*E16 -> 374400 | G16: La Marina (Bénin) – Campagne 2024-2025 : rendements Bénin 1 248 kg/ha, Mali 914 kg/ha | H16: https://lamarinabj.com/index.php/2025/02/05/campagne-cotonniere-2024-2025-en-afrique-le-benin-peut-il-reprendre-sa-place-de-leader/

Sheet Audit_QC
A1: Audit de cohérence (section 18 du cahier des charges)
A3: Comparaison | B3: Période | C3: Produit | D3: Qualité | E3: Stade | F3: Unité | G3: Monnaie | H3: Référence internationale | I3: Source primaire | J3: Politique publique (soutien) | K3: Fiscalité | L3: Verdict
A4: Cacao CI vs Ghana (2016/17-2026/27) | B4: OK (même demi-campagne) | C4: OK | D4: OK (grade marchand) | E4: OK (bord champ) | F4: OK (GH¢/t → kg) | G4: OK (BRI/BoG mensuel) | H4: OK (ICCO, même période) | I4: Partiel (presse relayant CCC/COCOBOD) | J4: Ghana : 70 % FOB légal ; CI : ventes anticipées, rachat de stocks 2026 | K4: CI : DUS 14,6 % + ≈7 % ; Ghana : non documenté | L4: Comparaison directe
A5: Cacao CI vs Cameroun / Nigeria / Équateur | B5: Partiel (points de marché) | C5: OK | D5: Différente (Équateur) | E5: OK | F5: OK (quintal → kg) | G5: OK | H5: OK | I5: Non (presse/secondaire) | J5: Marchés libéralisés | K5: Non documentée | L5: Indicative
A6: Café CI vs Vietnam / Ouganda | B6: Proche (juil.-sept. 2026) | C6: OK (café vert) | D6: OK (FAQ) | E6: OK | F6: OK | G6: Partiel (UGX source C) | H6: OK (OIC) | I6: Ouganda : UCDA (A) | J6: CI : prix administré (subvention 2019/20) | K6: Non documentée | L6: Directe (Vietnam) / directe-prudente (Ouganda)
A7: Anacarde CI vs UEMOA / Ghana | B7: OK (campagne 2026) | C7: OK (noix brute) | D7: Partiel (KOR Ghana spécifié) | E7: OK (bord champ) | F7: OK | G7: OK | H7: Partiel (cotation de négoce) | I7: Ghana TCDA (A) | J7: Prix planchers non toujours respectés | K7: CI : DUS 5 % | L7: Comparaison directe
A8: Anacarde CI vs Tanzanie | B8: Décalée (oct.-janv.) | C8: OK | D8: Différente (KOR élevé) | E8: Différent (magasin primaire) | F8: OK | G8: Approx. (C) | H8: Partiel | I8: Non | J8: Système d'enchères | K8: Non documentée | L8: Indicative
A9: Coton CI vs UEMOA | B9: OK (2025/26) | C9: OK (coton graine 1er choix) | D9: OK | E9: OK | F9: OK | G9: OK (même devise) | H9: OK (indice A, éq. fibre) | I9: Partiel (Sofitex A ; autres B/C) | J9: CI : subvention 25,3 Mds FCFA | K9: Non documentée | L9: Comparaison directe
A10: Caoutchouc CI vs Thaïlande / Indonésie | B10: Décalée (mai 2025 / août 2026) | C10: OK | D10: Converti en base sèche (DRC 60 %) | E10: Proche | F10: OK (kg sec) | G10: OK (BCE) | H10: Partiel (TSR20 2026 incomplet) | I10: Non (presse) | J10: Thaïlande : soutiens ponctuels | K10: Non documentée | L10: Indicative
A11: Palmier CI vs Indonésie / Malaisie | B11: Proche (janv. 2026 / 2025) | C11: OK (régimes) | D11: Partiel (OER différents) | E11: Différent (bord champ / usine) | F11: OK | G11: OK (BCE) | H11: OK (CIF Rotterdam) | I11: Malaisie MPOB (A) | J11: Prix administré CI ; prélèvements export Indonésie | K11: Taxes export Indonésie non retraitées | L11: Indicative
A12: Riz CI vs Sénégal / Vietnam / parité FOB (riz thaï) | B12: OK (2025) | C12: OK (paddy) | D12: Partiel (paddy frais VN) | E12: OK | F12: OK | G12: OK | H12: Partiel (FOB Bangkok, hors fret) | I12: USDA (A) | J12: Sénégal : subvention 30 FCFA/kg | K12: Droits à l'importation non retraités | L12: Directe (Sénégal) / indicative (Vietnam)
A13: Banane, mangue, ananas, vivriers | B13: — | C13: — | D13: — | E13: — | F13: — | G13: — | H13: — | I13: — | J13: — | K13: — | L13: Données insuffisantes

Sheet Sources
A1: Clé | B1: Institution | C1: Titre / contenu utilisé | D1: URL | E1: Type | F1: Fiabilité | G1: Date de consultation
A2: BCE_FX | B2: Banque centrale européenne | C2: Taux de référence quotidiens (eurofxref-hist), parité fixe 655,957 FCFA/EUR | D2: https://www.ecb.europa.eu/stats/policy_and_exchange_rates/euro_reference_exchange_rates/html/index.en.html | E2: Banque centrale | F2: A | G2: 2026-10-01
A3: BF_ANA_2026 | B3: Gouvernement du Burkina Faso (via Sika Finance) | C3: Prix bord champ de la noix de cajou maintenu à 385 FCFA/kg (2026) | D3: https://www.sikafinance.com/marches/burkina-le-prix-bord-champ-de-la-noix-de-cajou-maintenu-a-385-fcfakg-pour-soutenir-la-transformation-locale_60008 | E3: Presse (annonce officielle) | F3: B | G3: 2026-10-01
A4: BF_COT_2526 | B4: SOFITEX (Burkina Faso) | C4: Campagne 2025-2026 : engrais 17 500 FCFA, kg de coton 325 FCFA | D4: https://www.sofitex.bf/2025/04/10/campagne-cotonniere-2025-2026-les-engrais-a-17-500-f-cfa-les-insecticides-a-5-200-f-cfa-et-le-kg-de-coton-a-325-f-cfa/ | E4: Officielle (société cotonnière) | F4: A | G4: 2026-10-01
A5: BF_COT_PROD | B5: Agence Ecofin | C5: Burkina Faso : production 2024/2025 (300 000 t ; 865 kg/ha) | D5: https://www.agenceecofin.com/actualites-agro/2002-126013-au-burkina-faso-la-production-cotonniere-2024/2025-s-annonce-plus-faible-que-prevu | E5: Presse | F5: B | G5: 2026-10-01
A6: BF_MAN_2026 | B6: Gouvernement du Burkina Faso (via leFaso.net) | C6: Campagne fruitière 2026 : anacarde 385 FCFA, mangue 95 FCFA le kg | D6: https://lefaso.net/spip.php?article144610 | E6: Presse (annonce officielle) | F6: B | G6: 2026-10-01
A7: BJ_COT_2526 | B7: Gouvernement du Bénin (via La Nation) | C7: Campagne cotonnière 2025-2026 : prix des insecticides et du coton graine homologués (300 FCFA) | D7: https://lanation.bj/actualites/campagne-cotonniere-2025-2026-les-prix-des-insecticides-et-du-coton-graine-homologues | E7: Presse publique (annonce officielle) | F7: B | G7: 2026-10-01
A8: BJ_COT_2627 | B8: Gouvernement du Bénin (via Le Matinal) | C8: Campagne 2026-2027 : coton conventionnel 300 FCFA (1er choix), biologique 360 FCFA (CM du 13/05/2026) | D8: https://lematinal.bj/campagne-cotonniere-2026-2027-le-prix-de-cession-des-intrants-et-dachat-de-coton-graine-homologue/ | E8: Presse (annonce officielle) | F8: B | G8: 2026-10-01
A9: BM_CACAO_2019 | B9: Banque mondiale | C9: Situation économique en Côte d'Ivoire : au pays du cacao (2019) – part producteur ≥60 % CAF, prélèvements ≈22 % CAF | D9: https://documents1.worldbank.org/curated/en/277191561741906355/pdf/Cote-dIvoire-Economic-Update.pdf | E9: Institution internationale | F9: A | G9: 2026-10-01
A10: BM_PINK | B10: Banque mondiale | C10: Commodity Price Data (Pink Sheet), CMO-Historical-Data-Monthly.xlsx, mise à jour 3 février 2026 | D10: https://www.worldbank.org/en/research/commodity-markets | E10: Institution internationale | F10: A | G10: 2026-10-01
A11: BOG_FX | B11: Banque du Ghana | C11: Taux interbancaires moyens mensuels 2026 | D11: https://www.bog.gov.gh/economic-data/exchange-rate/ | E11: Banque centrale | F11: A | G11: 2026-10-01
A12: BRI_FX | B12: Banque des règlements internationaux | C12: US dollar exchange rates (WS_XRU), moyennes mensuelles | D12: https://data.bis.org/topics/XRU | E12: Institution internationale | F12: A | G12: 2026-10-01
... A128: VN_RIZ | B128: SGGP News | C128: Paddy frais du delta du Mékong : IR 50404 5 400-5 500 ; OM 5451 5 600-5 700 VND/kg (2025) | D128: https://en.sggp.org.vn/rice-farmers-in-mekong-delta-struggle-as-prices-plunge-yields-decline-post120063.html | E128: Presse | F128: B | G128: 2026-10-01

Sheet Cours_mensuels
A1: Mois | B1: Cacao ICCO (USD/kg) | C1: Source | D1: Café robusta (USD/kg) | E1: Source | F1: Coton indice A (USD/kg) | G1: Source | H1: Caoutchouc TSR20 (USD/kg) | I1: Source | J1: Huile de palme (USD/t) | K1: Source | L1: Riz Thaï 5 % (USD/t) | M1: Source
A2: 2014-01 | B2: 2.81943 | C2: BM | D2: 1.934113 | E2: BM | F2: 2.005322 | G2: BM | H2: 2.1442 | I2: BM | J2: 862.63 | K2: BM | L2: 450 | M2: BM
A3: 2014-02 | B3: 2.99284 | C3: BM | D3: 2.114231 | E3: BM | F3: 2.073445 | G3: BM | H3: 1.9011 | I3: BM | J3: 904.34 | K3: BM | L3: 459 | M3: BM
A4: 2014-03 | B4: 3.04167 | C4: BM | D4: 2.323008 | E4: BM | F4: 2.137379 | G4: BM | H4: 1.929 | I4: BM | J4: 953.81 | K4: BM | L4: 422 | M4: BM
A5: 2014-04 | B5: 3.05061 | C5: BM | D5: 2.326976 | E5: BM | F5: 2.076752 | G5: BM | H5: 1.7757 | I5: BM | J5: 926.63 | K5: BM | L5: 395 | M5: BM
A6: 2014-05 | B6: 3.02999 | C6: BM | D6: 2.270538 | E6: BM | F6: 2.043903 | G6: BM | H6: 1.6931 | I6: BM | J6: 898.42 | K6: BM | L6: 388 | M6: BM
A7: 2014-06 | B7: 3.17433 | C7: BM | D7: 2.18059 | E7: BM | F7: 2.004 | G7: BM | H7: 1.7113 | I7: BM | J7: 861.88 | K7: BM | L7: 397 | M7: BM
A8: 2014-07 | B8: 3.19604 | C8: BM | D8: 2.244083 | E8: BM | F8: 1.848353 | G8: BM | H8: 1.7004 | I8: BM | J8: 853.69 | K8: BM | L8: 422 | M8: BM
A9: 2014-08 | B9: 3.27027 | C9: BM | D9: 2.210132 | E9: BM | F9: 1.631419 | G9: BM | H9: 1.6661 | I9: BM | J9: 778.69 | K9: BM | L9: 445 | M9: BM
A10: 2014-09 | B10: 3.21483 | C10: BM | D10: 2.216084 | E10: BM | F10: 1.61775 | G10: BM | H10: 1.5319 | I10: BM | J10: 760.75 | K10: BM | L10: 432 | M10: BM
A11: 2014-10 | B11: 3.10083 | C11: BM | D11: 2.308237 | E11: BM | F11: 1.55073 | G11: BM | H11: 1.5061 | I11: BM | J11: 764.4 | K11: BM | L11: 428 | M11: BM
